Workbook

Sheet Things To Address
A1: Type | B1: Description
A2: PPC Cost | B2: You have paid clicks (CampaignAdjusted=Capterra,SplitAdjusted=capterra,KeyWord=GetApp) that have not been allocated a cost. Use the Tools menu to update costs.
A3: PPC Cost | B3: You have paid clicks (CampaignAdjusted=Capterra,SplitAdjusted=capterra,KeyWord=FreeTrial) that have not been allocated a cost. However, this looks invalid, as it came from a blank Referrer.
A4: PPC Cost | B4: You have paid clicks (CampaignAdjusted=Capterra,SplitAdjusted=Capterra_destinationURL,KeyWord=trial) that have not been allocated a cost. However, this looks invalid, as it came from a blank Referrer.
A5: PPC Cost | B5: You have paid clicks (CampaignAdjusted=Capterra,SplitAdjusted=Capterra_freetrial,KeyWord=CS) that have not been allocated a cost. However, this looks invalid, as it came from a blank Referrer.
A6: PPC Cost | B6: You have paid clicks (CampaignAdjusted=Capterra,SplitAdjusted=,KeyWord=crm-software) that have not been allocated a cost. However, this looks invalid, as it came from a blank Referrer.
A7: PPC Cost | B7: You have paid clicks (CampaignAdjusted=Capterra,SplitAdjusted=Proposals,KeyWord=LP) that have not been allocated a cost. Use the Tools menu to update costs.
A8: PPC Cost | B8: You have paid clicks (CampaignAdjusted=Capterra,SplitAdjusted=Capterra_destinationURL,KeyWord=capterra) that have not been allocated a cost. Use the Tools menu to update costs.
A9: PPC Cost | B9: You have paid clicks (CampaignAdjusted=Capterra,SplitAdjusted=ME,KeyWord=LP) that have not been allocated a cost. Use the Tools menu to update costs.
A10: PPC Cost | B10: You have paid clicks (CampaignAdjusted=Capterra,SplitAdjusted=Capterra_destinationURL,KeyWord=capterra) that have not been allocated a cost. However, this looks invalid, as it came from a blank Referrer.
A11: PPC Cost | B11: You have paid clicks (CampaignAdjusted=Capterra,SplitAdjusted=ME,KeyWord=LP) that have not been allocated a cost. However, this looks invalid, as it came from a blank Referrer.
A12: PPC Cost | B12: You have paid clicks (CampaignAdjusted=Capterra,SplitAdjusted=Proposals,KeyWord=LP) that have not been allocated a cost. However, this looks invalid, as it came from a blank Referrer.
... A469: PPC Cost | B469: You have paid clicks (CampaignAdjusted=Twitter X Ad,SplitAdjusted=Video-views,KeyWord=Desktop) that have not been allocated a cost. However, this looks invalid, as it came from a blank Referrer.

Sheet Accounts
A1: RecordID | B1: AccountName | C1: SignUpDate | D1: CancellationDate | E1: ConvertPayDate | F1: IsActive | G1: IsConversionException | H1: IsCountedAsChurn | I1: IsTrialConverted | J1: PayType | K1: AppName | L1: AccountingPlatform | M1: PlatformToggle | N1: CustDatSaaSAmountToDate | O1: CustDatLastSaaSAmount | P1: CustDatPSAmountToDate | Q1: CustDatPSLastMonth | R1: ExpectedLifetime | S1: MethodDiscount | T1: Channel | U1: PartnerName | V1: CookieID | W1: Att_Direct_SEO_Referrer | X1: Att_Direct | Y1: Att_SEO | Z1: Att_OPN_Other_Peoples_Networks | AA1: Att_Pay_Per_Click | AB1: Att_Partners | AC1: Att_Email | AD1: Att_Remarketing | AE1: Att_Social | AF1: Att_Help_Center | AG1: Att_Online_Chat_Tool | AH1: Att_Content | AI1: Att_Banner_Ads | AJ1: Att_Seminar_Conference | AK1: Att_Referral_Program | AL1: Att_Referral_Link | AM1: Att_Backlinks | AN1: Att_Other | AO1: Att_Webinar | AP1: Att_None | AQ1: SyncTypeRegion | AR1: Vertical | AS1: Sector | AT1: CustDatIndustry | AU1: CustDatFirstSyncCompleted | AV1: CustDatLastRefreshed | AW1: CustDatCountOfEmployees | AX1: CustDatAnnualSales | AY1: CustDatCountOfCustomers | AZ1: LicenseCount | BA1: CountOfCustomScreens | BB1: CountOfCustomScreensMN | BC1: Day | BD1: Week | BE1: Month | BF1: Year | BG1: SignUpCountry | BH1: URL | BI1: Category | BJ1: Media Type
A2: 153108 | B2: multdoor | C2: 45991.991 | F2: TRUE | G2: FALSE | H2: FALSE | I2: FALSE | J2: Monthly | K2: Method:CRM For QBO | L2: QBO | M2: New | N2: 0 | O2: 63.75 | P2: 0 | Q2: 0 | R2: 0 | S2: US-3 Month Promo(25% off) | T2: Direct | V2: 7217712 | W2: https://www.google.com/ | X2: 0 | Y2: 1 | Z2: 0 | AA2: 0 | AB2: 0 | AC2: 0 | AD2: 0 | AE2: 0 | AF2: 0 | AG2: 0 | AH2: 0 | AI2: 0 | AJ2: 0 | AK2: 0 | AL2: 0 | AM2: 0 | AN2: 0 | AO2: 0 | AP2: =1-SUM(X2:AN2) -> 0 | AQ2: CA | AR2: Other | AS2: other | AT2: Industrial building construction | AU2: 45991 | AV2: 46024.034 | AW2: 0 | AX2: 318369.12 | AY2: 13 | AZ2: 1 | BA2: 0 | BB2: 0 | BC2: 45991 | BD2: 47 | BE2: Nov | BF2: 2025 | BG2: Canada | BH2: =VLOOKUP(B2,CookieClicks!D:O,12,FALSE) -> https://www.method.me/ | BI2: =IFERROR(__xludf.DUMMYFUNCTION("VLOOKUP(REGEXREPLACE(BH2,""[?].*"",""""),ContentBuckets!A:C,2,FALSE)"),"Homepage") -> Homepage | BJ2: =IFERROR(__xludf.DUMMYFUNCTION("VLOOKUP(REGEXREPLACE(BH2,""[?].*"",""""),ContentBuckets!A:C,3,FALSE)"),"Other page") -> Other page
A3: 153109 | B3: alromanimechanicalworkshop6 | C3: 45992.129 | F3: TRUE | G3: FALSE | H3: FALSE | I3: FALSE | J3: Monthly | K3: Method:CRM For QBO | L3: QBO | M3: New | N3: 0 | O3: 53.25 | P3: 0 | Q3: 0 | R3: 28 | S3: US-3 Month Promo(25% off) | T3: Direct | V3: 7218180 | W3: https://www.google.com/ | X3: 0 | Y3: 1 | Z3: 0 | AA3: 0 | AB3: 0 | AC3: 0 | AD3: 0 | AE3: 0 | AF3: 0 | AG3: 0 | AH3: 0 | AI3: 0 | AJ3: 0 | AK3: 0 | AL3: 0 | AM3: 0 | AN3: 0 | AO3: 0 | AP3: =1-SUM(X3:AN3) -> 0 | AQ3: KW | AR3: Repair and maintenance | AV3: 46023.982 | AW3: 9 | AX3: 0 | AY3: 214 | AZ3: 1 | BA3: 0 | BB3: 0 | BC3: 45992 | BD3: 48 | BE3: Dec | BF3: 2025 | BG3: Kuwait | BH3: =VLOOKUP(B3,CookieClicks!D:O,12,FALSE) -> https://www.method.me/ | BI3: =IFERROR(__xludf.DUMMYFUNCTION("VLOOKUP(REGEXREPLACE(BH3,""[?].*"",""""),ContentBuckets!A:C,2,FALSE)"),"Homepage") -> Homepage | BJ3: =IFERROR(__xludf.DUMMYFUNCTION("VLOOKUP(REGEXREPLACE(BH3,""[?].*"",""""),ContentBuckets!A:C,3,FALSE)"),"Other page") -> Other page
A4: 153110 | B4: student26 | C4: 45992.176 | F4: TRUE | G4: FALSE | H4: FALSE | I4: FALSE | J4: Monthly | K4: Method:CRM | L4: QuickBooks | M4: New | N4: 0 | O4: 44.25 | P4: 0 | Q4: 0 | R4: 0 | S4: US-3 Month Promo(25% off) | T4: Direct | V4: 7218307 | X4: 0 | Y4: 0 | Z4: 0 | AA4: 0 | AB4: 0 | AC4: 0 | AD4: 0 | AE4: 0 | AF4: 0 | AG4: 0 | AH4: 0 | AI4: 0 | AJ4: 0 | AK4: 0 | AL4: 0 | AM4: 0 | AN4: 1 | AO4: 0 | AP4: =1-SUM(X4:AN4) -> 0 | AV4: 46024.028 | AW4: 0 | AX4: 0 | AY4: 0 | AZ4: 1 | BA4: 0 | BB4: 0 | BC4: 45992 | BD4: 48 | BE4: Dec | BF4: 2025 | BG4: Indonesia | BH4: =VLOOKUP(B4,CookieClicks!D:O,12,FALSE) -> https://www.method.me/blog/construction-project-success-crm-solution/ | BI4: =IFERROR(__xludf.DUMMYFUNCTION("VLOOKUP(REGEXREPLACE(BH4,""[?].*"",""""),ContentBuckets!A:C,2,FALSE)"),"CRM") -> CRM | BJ4: =IFERROR(__xludf.DUMMYFUNCTION("VLOOKUP(REGEXREPLACE(BH4,""[?].*"",""""),ContentBuckets!A:C,3,FALSE)"),"Blog") -> Blog
A5: 153111 | B5: healthcaremaintenanceservices | C5: 45992.326 | E5: 46006.688 | F5: TRUE | G5: FALSE | H5: FALSE | I5: FALSE | J5: Monthly | K5: Method:CRM For QBO | L5: QBO | M5: New | N5: 88.5 | O5: 70.5 | P5: 0 | Q5: 0 | R5: 28 | S5: US-3 Month Promo(25% off) | T5: Direct | V5: 7204189 | W5: https://www.google.com/ | X5: 0 | Y5: 1 | Z5: 0 | AA5: 0 | AB5: 0 | AC5: 0 | AD5: 0 | AE5: 0 | AF5: 0 | AG5: 0 | AH5: 0 | AI5: 0 | AJ5: 0 | AK5: 0 | AL5: 0 | AM5: 0 | AN5: 0 | AO5: 0 | AP5: =1-SUM(X5:AN5) -> 0 | AQ5: US | AR5: Repair and maintenance | AU5: 45992 | AV5: 46024.001 | AW5: 6 | AX5: 4570973.8 | AY5: 441 | AZ5: 2 | BA5: 0 | BB5: 0 | BC5: 45992 | BD5: 48 | BE5: Dec | BF5: 2025 | BG5: United States | BH5: =VLOOKUP(B5,CookieClicks!D:O,12,FALSE) -> https://www.method.me/blog/quickbooks-customer-portal/ | BI5: =IFERROR(__xludf.DUMMYFUNCTION("VLOOKUP(REGEXREPLACE(BH5,""[?].*"",""""),ContentBuckets!A:C,2,FALSE)"),"Listicle - General") -> Listicle - General | BJ5: =IFERROR(__xludf.DUMMYFUNCTION("VLOOKUP(REGEXREPLACE(BH5,""[?].*"",""""),ContentBuckets!A:C,3,FALSE)"),"Blog") -> Blog
A6: 153112 | B6: customoutdoorkitchens | C6: 45992.336 | F6: TRUE | G6: FALSE | H6: FALSE | I6: FALSE | J6: Monthly | K6: Method:CRM For QBO | L6: QBO | M6: New | N6: 0 | O6: 44.25 | P6: 0 | Q6: 0 | R6: 28 | S6: US-3 Month Promo(25% off) | T6: Direct | V6: 7171808 | W6: https://www.google.com/ | X6: 0 | Y6: 1 | Z6: 0 | AA6: 0 | AB6: 0 | AC6: 0 | AD6: 0 | AE6: 0 | AF6: 0 | AG6: 0 | AH6: 0 | AI6: 0 | AJ6: 0 | AK6: 0 | AL6: 0 | AM6: 0 | AN6: 0 | AO6: 0 | AP6: =1-SUM(X6:AN6) -> 0 | AQ6: US | AR6: Construction | AT6: Outdoor Kitchen Design / Build | AU6: 45992 | AV6: 46023.99 | AW6: 0 | AX6: 0 | AY6: 403 | AZ6: 1 | BA6: 0 | BB6: 0 | BC6: 45992 | BD6: 48 | BE6: Dec | BF6: 2025 | BG6: United States | BH6: =VLOOKUP(B6,CookieClicks!D:O,12,FALSE) -> https://www.method.me/ | BI6: =IFERROR(__xludf.DUMMYFUNCTION("VLOOKUP(REGEXREPLACE(BH6,""[?].*"",""""),ContentBuckets!A:C,2,FALSE)"),"Homepage") -> Homepage | BJ6: =IFERROR(__xludf.DUMMYFUNCTION("VLOOKUP(REGEXREPLACE(BH6,""[?].*"",""""),ContentBuckets!A:C,3,FALSE)"),"Other page") -> Other page
A7: 153113 | B7: manexusa | C7: 45992.342 | D7: 45992.365 | F7: FALSE | G7: TRUE | H7: FALSE | I7: FALSE | J7: Monthly | K7: Method:CRM | L7: QuickBooks | M7: New | N7: 0 | O7: 0 | P7: 0 | Q7: 0 | R7: 0 | S7: US-3 Month Promo(25% off) | T7: Direct | V7: 7168930 | X7: 1 | Y7: 0 | Z7: 0 | AA7: 0 | AB7: 0 | AC7: 0 | AD7: 0 | AE7: 0 | AF7: 0 | AG7: 0 | AH7: 0 | AI7: 0 | AJ7: 0 | AK7: 0 | AL7: 0 | AM7: 0 | AN7: 0 | AO7: 0 | AP7: =1-SUM(X7:AN7) -> 0 | AW7: 0 | AX7: 0 | AY7: 0 | AZ7: 1 | BA7: 0 | BB7: 0 | BC7: 45992 | BD7: 48 | BE7: Dec | BF7: 2025 | BG7: United States | BH7: =VLOOKUP(B7,CookieClicks!D:O,12,FALSE) -> http://signup.method.me/methodcrm | BI7: =IFERROR(__xludf.DUMMYFUNCTION("VLOOKUP(REGEXREPLACE(BH7,""[?].*"",""""),ContentBuckets!A:C,2,FALSE)"),"#N/A") -> #N/A | BJ7: =IFERROR(__xludf.DUMMYFUNCTION("VLOOKUP(REGEXREPLACE(BH7,""[?].*"",""""),ContentBuckets!A:C,3,FALSE)"),"#N/A") -> #N/A
A8: 153114 | B8: reddoorpestcontrol2 | C8: 45992.347 | F8: TRUE | G8: FALSE | H8: FALSE | I8: FALSE | J8: Monthly | K8: Method:CRM For QBO | L8: QBO | M8: New | N8: 0 | O8: 44.25 | P8: 0 | Q8: 0 | R8: 28 | S8: US-3 Month Promo(25% off) | T8: Direct | V8: 7218855 | X8: 1 | Y8: 0 | Z8: 0 | AA8: 0 | AB8: 0 | AC8: 0 | AD8: 0 | AE8: 0 | AF8: 0 | AG8: 0 | AH8: 0 | AI8: 0 | AJ8: 0 | AK8: 0 | AL8: 0 | AM8: 0 | AN8: 0 | AO8: 0 | AP8: =1-SUM(X8:AN8) -> 0 | AQ8: US | AR8: Field Services | AU8: 45992 | AV8: 46024.028 | AW8: 0 | AX8: 44332.44 | AY8: 564 | AZ8: 1 | BA8: 0 | BB8: 0 | BC8: 45992 | BD8: 48 | BE8: Dec | BF8: 2025 | BG8: United States | BH8: =VLOOKUP(B8,CookieClicks!D:O,12,FALSE) -> https://signin.method.me/Password/Reset?rpcode=-nZQ0G03B%2bIuTre9Gdsw3ggkv!rw%3du%3dJPbRgJ7a-UmqVNiskXhWYwfMQB8a5 | BI8: =IFERROR(__xludf.DUMMYFUNCTION("VLOOKUP(REGEXREPLACE(BH8,""[?].*"",""""),ContentBuckets!A:C,2,FALSE)"),"#N/A") -> #N/A | BJ8: =IFERROR(__xludf.DUMMYFUNCTION("VLOOKUP(REGEXREPLACE(BH8,""[?].*"",""""),ContentBuckets!A:C,3,FALSE)"),"#N/A") -> #N/A
A9: 153115 | B9: manexusa2 | C9: 45992.362 | D9: 46000.378 | F9: FALSE | G9: TRUE | H9: FALSE | I9: FALSE | J9: Monthly | K9: Method:CRM for QBD | L9: QBDT | M9: New | N9: 0 | O9: 63.75 | P9: 0 | Q9: 0 | R9: 28 | S9: US-3 Month Promo(25% off) | T9: Direct | V9: 7168930 | X9: 1 | Y9: 0 | Z9: 0 | AA9: 0 | AB9: 0 | AC9: 0 | AD9: 0 | AE9: 0 | AF9: 0 | AG9: 0 | AH9: 0 | AI9: 0 | AJ9: 0 | AK9: 0 | AL9: 0 | AM9: 0 | AN9: 0 | AO9: 0 | AP9: =1-SUM(X9:AN9) -> 0 | AQ9: US | AR9: Manufacturing (MWD) | AU9: 45992 | AV9: 46000.018 | AW9: 15 | AX9: 933479.16 | AY9: 3208 | AZ9: 1 | BA9: 0 | BB9: 0 | BC9: 45992 | BD9: 48 | BE9: Dec | BF9: 2025 | BG9: United States | BH9: =VLOOKUP(B9,CookieClicks!D:O,12,FALSE) -> http://signup.method.me/methodcrm | BI9: =IFERROR(__xludf.DUMMYFUNCTION("VLOOKUP(REGEXREPLACE(BH9,""[?].*"",""""),ContentBuckets!A:C,2,FALSE)"),"#N/A") -> #N/A | BJ9: =IFERROR(__xludf.DUMMYFUNCTION("VLOOKUP(REGEXREPLACE(BH9,""[?].*"",""""),ContentBuckets!A:C,3,FALSE)"),"#N/A") -> #N/A
A10: 153116 | B10: jlbcompanies | C10: 45992.416 | E10: 46009.496 | F10: TRUE | G10: FALSE | H10: FALSE | I10: FALSE | J10: Monthly | K10: Method:CRM For QBO | L10: QBO | M10: New | N10: 72.75 | O10: 72.75 | P10: 0 | Q10: 0 | R10: 28 | S10: US-3 Month Promo(25% off) | T10: Direct | V10: 7210242 | W10: https://www.google.com/ | X10: 0 | Y10: 1 | Z10: 0 | AA10: 0 | AB10: 0 | AC10: 0 | AD10: 0 | AE10: 0 | AF10: 0 | AG10: 0 | AH10: 0 | AI10: 0 | AJ10: 0 | AK10: 0 | AL10: 0 | AM10: 0 | AN10: 0 | AO10: 0 | AP10: =1-SUM(X10:AN10) -> 0 | AQ10: US | AR10: Other | AU10: 45992 | AV10: 46024.003 | AW10: 56 | AX10: 2704501.3 | AY10: 1178 | AZ10: 1 | BA10: 0 | BB10: 1 | BC10: 45992 | BD10: 48 | BE10: Dec | BF10: 2025 | BG10: United States | BH10: =VLOOKUP(B10,CookieClicks!D:O,12,FALSE) -> https://www.method.me/ | BI10: =IFERROR(__xludf.DUMMYFUNCTION("VLOOKUP(REGEXREPLACE(BH10,""[?].*"",""""),ContentBuckets!A:C,2,FALSE)"),"Homepage") -> Homepage | BJ10: =IFERROR(__xludf.DUMMYFUNCTION("VLOOKUP(REGEXREPLACE(BH10,""[?].*"",""""),ContentBuckets!A:C,3,FALSE)"),"Other page") -> Other page
A11: 153119 | B11: ssisanitary | C11: 45992.461 | E11: 46006.461 | F11: TRUE | G11: FALSE | H11: FALSE | I11: FALSE | J11: Monthly | K11: Method:CRM For QBO | L11: QBO | M11: New | N11: 452.5 | O11: 127.5 | P11: 558 | Q11: 558 | R11: 28 | S11: US-3 Month Promo(25% off) | T11: Direct | V11: 7191321 | W11: https://www.google.com/ | X11: 0 | Y11: 1 | Z11: 0 | AA11: 0 | AB11: 0 | AC11: 0 | AD11: 0 | AE11: 0 | AF11: 0 | AG11: 0 | AH11: 0 | AI11: 0 | AJ11: 0 | AK11: 0 | AL11: 0 | AM11: 0 | AN11: 0 | AO11: 0 | AP11: =1-SUM(X11:AN11) -> 0 | AQ11: US | AR11: Wholesale and distribution services (MWD) | AU11: 45992 | AV11: 46024.027 | AW11: 0 | AX11: 2002376.5 | AY11: 1130 | AZ11: 2 | BA11: 0 | BB11: 12 | BC11: 45992 | BD11: 48 | BE11: Dec | BF11: 2025 | BG11: United States | BH11: =VLOOKUP(B11,CookieClicks!D:O,12,FALSE) -> https://www.method.me/ | BI11: =IFERROR(__xludf.DUMMYFUNCTION("VLOOKUP(REGEXREPLACE(BH11,""[?].*"",""""),ContentBuckets!A:C,2,FALSE)"),"Homepage") -> Homepage | BJ11: =IFERROR(__xludf.DUMMYFUNCTION("VLOOKUP(REGEXREPLACE(BH11,""[?].*"",""""),ContentBuckets!A:C,3,FALSE)"),"Other page") -> Other page
A12: 153120 | B12: highendcompaniesllc | C12: 45992.476 | E12: 46006.486 | F12: TRUE | G12: FALSE | H12: FALSE | I12: FALSE | J12: Monthly | K12: Method:CRM For QBO | L12: QBO | M12: New | N12: 88.5 | O12: 116 | P12: 0 | Q12: 0 | R12: 28 | S12: US-3 Month Promo(25% off) | T12: Direct | V12: 7219935 | W12: https://www.google.com/ | X12: 0 | Y12: 1 | Z12: 0 | AA12: 0 | AB12: 0 | AC12: 0 | AD12: 0 | AE12: 0 | AF12: 0 | AG12: 0 | AH12: 0 | AI12: 0 | AJ12: 0 | AK12: 0 | AL12: 0 | AM12: 0 | AN12: 0 | AO12: 0 | AP12: =1-SUM(X12:AN12) -> 0 | AQ12: US | AR12: Other | AU12: 45992 | AV12: 46024.012 | AW12: 0 | AX12: 877018.8 | AY12: 117 | AZ12: 2 | BA12: 0 | BB12: 1 | BC12: 45992 | BD12: 48 | BE12: Dec | BF12: 2025 | BG12: United States | BH12: =VLOOKUP(B12,CookieClicks!D:O,12,FALSE) -> https://www.method.me/ | BI12: =IFERROR(__xludf.DUMMYFUNCTION("VLOOKUP(REGEXREPLACE(BH12,""[?].*"",""""),ContentBuckets!A:C,2,FALSE)"),"Homepage") -> Homepage | BJ12: =IFERROR(__xludf.DUMMYFUNCTION("VLOOKUP(REGEXREPLACE(BH12,""[?].*"",""""),ContentBuckets!A:C,3,FALSE)"),"Other page") -> Other page
A13: 153121 | B13: jirehtransmissionsllc | C13: 45992.497 | D13: 45992.503 | F13: FALSE | G13: FALSE | H13: FALSE | I13: FALSE | J13: Monthly | K13: Method:CRM For QBO | L13: QBO | M13: New | N13: 0 | O13: 0 | P13: 0 | Q13: 0 | R13: 0 | S13: US-3 Month Promo(25% off) | T13: Direct | V13: 7220141 | X13: 0 | Y13: 0 | Z13: 0 | AA13: 1 | AB13: 0 | AC13: 0 | AD13: 0 | AE13: 0 | AF13: 0 | AG13: 0 | AH13: 0 | AI13: 0 | AJ13: 0 | AK13: 0 | AL13: 0 | AM13: 0 | AN13: 0 | AO13: 0 | AP13: =1-SUM(X13:AN13) -> 0 | AQ13: US | AW13: 0 | AX13: 0 | AY13: 0 | AZ13: 1 | BA13: 0 | BB13: 0 | BC13: 45992 | BD13: 48 | BE13: Dec | BF13: 2025 | BG13: United States | BH13: =VLOOKUP(B13,CookieClicks!D:O,12,FALSE) -> https://grow.method.me/crm-quickbooks/?trc=86&trk=how to add signature in quickbooks online&trs=USA-G-QB-Bing&msclkid=557a0cff02eb14d3c64065d2caeb7896&utm_source=bing&utm_medium=cpc&utm_campaign=US - Generic 2020&utm_term=how to add signature in quickbooks online&utm_content=Generic | BI13: =IFERROR(__xludf.DUMMYFUNCTION("VLOOKUP(REGEXREPLACE(BH13,""[?].*"",""""),ContentBuckets!A:C,2,FALSE)"),"#N/A") -> #N/A | BJ13: =IFERROR(__xludf.DUMMYFUNCTION("VLOOKUP(REGEXREPLACE(BH13,""[?].*"",""""),ContentBuckets!A:C,3,FALSE)"),"#N/A") -> #N/A
A14: 153122 | B14: waycosalesinc | C14: 45992.517 | E14: 46007.597 | F14: TRUE | G14: FALSE | H14: FALSE | I14: FALSE | J14: Monthly | K14: Method:CRM For QBO | L14: QBO | M14: New | N14: 165 | O14: 186 | P14: 0 | Q14: 0 | R14: 0 | S14: US-3 Month Promo(25% off) | T14: Direct | V14: 6659644 | X14: 0 | Y14: 0 | Z14: 0 | AA14: 1 | AB14: 0 | AC14: 0 | AD14: 0 | AE14: 0 | AF14: 0 | AG14: 0 | AH14: 0 | AI14: 0 | AJ14: 0 | AK14: 0 | AL14: 0 | AM14: 0 | AN14: 0 | AO14: 0 | AP14: =1-SUM(X14:AN14) -> 0 | AQ14: US | AT14: Other | AU14: 45992 | AV14: 46024.035 | AW14: 13 | AX14: 8098044.1 | AY14: 1917 | AZ14: 4 | BA14: 0 | BB14: 10 | BC14: 45992 | BD14: 48 | BE14: Dec | BF14: 2025 | BG14: United States | BH14: =VLOOKUP(B14,CookieClicks!D:O,12,FALSE) -> https://grow.method.me/crm-quickbooks/?trc=81&trk=crm integrates with quickbooks&trs=US-QBInt&campaignid=1543381580&adgroupid=100383660218&adid=424373886646&gad_source=1&gad_campaignid=1543381580&gclid=Cj0KCQjw64jDBhDXARIsABkk8J7ukkus1kvinzQTfDBa9T3cwLPvsAUFxay55glRRXyqwvQ1Qif88XkaAgwwEALw_wcB | BI14: =IFERROR(__xludf.DUMMYFUNCTION("VLOOKUP(REGEXREPLACE(BH14,""[?].*"",""""),ContentBuckets!A:C,2,FALSE)"),"#N/A") -> #N/A | BJ14: =IFERROR(__xludf.DUMMYFUNCTION("VLOOKUP(REGEXREPLACE(BH14,""[?].*"",""""),ContentBuckets!A:C,3,FALSE)"),"#N/A") -> #N/A
A15: 153124 | B15: aeromarinebiotechllc | C15: 45992.532 | F15: TRUE | G15: FALSE | H15: FALSE | I15: FALSE | J15: Monthly | K15: Method:CRM For QBO | L15: QBO | M15: New | N15: 0 | O15: 63.75 | P15: 0 | Q15: 0 | R15: 28 | S15: US-3 Month Promo(25% off) | T15: Direct | V15: 7220412 | X15: 0 | Y15: 0 | Z15: 1 | AA15: 0 | AB15: 0 | AC15: 0 | AD15: 0 | AE15: 0 | AF15: 0 | AG15: 0 | AH15: 0 | AI15: 0 | AJ15: 0 | AK15: 0 | AL15: 0 | AM15: 0 | AN15: 0 | AO15: 0 | AP15: =1-SUM(X15:AN15) -> 0 | AQ15: US | AR15: Manufacturing (MWD) | AU15: 45992 | AV15: 46023.982 | AW15: 0 | AX15: 610920 | AY15: 47 | AZ15: 1 | BA15: 0 | BB15: 0 | BC15: 45992 | BD15: 48 | BE15: Dec | BF15: 2025 | BG15: United States | BH15: =VLOOKUP(B15,CookieClicks!D:O,12,FALSE) -> https://signup.method.me/QBOAppstoreSignup?offering=methodcrm | BI15: =IFERROR(__xludf.DUMMYFUNCTION("VLOOKUP(REGEXREPLACE(BH15,""[?].*"",""""),ContentBuckets!A:C,2,FALSE)"),"#N/A") -> #N/A | BJ15: =IFERROR(__xludf.DUMMYFUNCTION("VLOOKUP(REGEXREPLACE(BH15,""[?].*"",""""),ContentBuckets!A:C,3,FALSE)"),"#N/A") -> #N/A
A16: 153126 | B16: whitingdesignandelectric | C16: 45992.56 | F16: TRUE | G16: FALSE | H16: FALSE | I16: FALSE | J16: Monthly | K16: Method:CRM For QBO | L16: QBO | M16: New | N16: 0 | O16: 44.25 | P16: 0 | Q16: 0 | R16: 0 | S16: US-3 Month Promo(25% off) | T16: Direct | V16: 7220589 | X16: 0 | Y16: 0 | Z16: 0 | AA16: 1 | AB16: 0 | AC16: 0 | AD16: 0 | AE16: 0 | AF16: 0 | AG16: 0 | AH16: 0 | AI16: 0 | AJ16: 0 | AK16: 0 | AL16: 0 | AM16: 0 | AN16: 0 | AO16: 0 | AP16: =1-SUM(X16:AN16) -> 0 | AU16: 45992 | AV16: 46024.037 | AW16: 1 | AX16: 117120 | AY16: 331 | AZ16: 1 | BA16: 0 | BB16: 0 | BC16: 45992 | BD16: 48 | BE16: Dec | BF16: 2025 | BG16: United States | BH16: =VLOOKUP(B16,CookieClicks!D:O,12,FALSE) -> https://grow.method.me/crm-quickbooks/?trc=81&trk=quickbooks crm&trs=USA-QB-G_Ex&campaignid=22265826203&adgroupid=176758613473&adid=734012603510&gad_source=1&gad_campaignid=22265826203&gbraid=0AAAAAD3ItnbQ-scslMn1OtVxbVSWxN2mJ&gclid=CjwKCAiAlrXJBhBAEiwA-5pgwvitKEc_ApMEwccMJJ-0vo8UrY40YDAv2UXM6GNodmORrMYKZy6gOhoC3A0QAvD_BwE | BI16: =IFERROR(__xludf.DUMMYFUNCTION("VLOOKUP(REGEXREPLACE(BH16,""[?].*"",""""),ContentBuckets!A:C,2,FALSE)"),"#N/A") -> #N/A | BJ16: =IFERROR(__xludf.DUMMYFUNCTION("VLOOKUP(REGEXREPLACE(BH16,""[?].*"",""""),ContentBuckets!A:C,3,FALSE)"),"#N/A") -> #N/A
A17: 153127 | B17: mastercraneandhoist | C17: 45992.584 | E17: 46006.663 | F17: TRUE | G17: FALSE | H17: FALSE | I17: FALSE | J17: Monthly | K17: Method:CRM For QBO | L17: QBO | M17: New | N17: 59 | O17: 59 | P17: 0 | Q17: 0 | R17: 28 | T17: Direct | V17: 7158239 | X17: 0 | Y17: 0 | Z17: 0 | AA17: 0 | AB17: 0 | AC17: 0 | AD17: 0 | AE17: 0 | AF17: 0 | AG17: 0 | AH17: 0 | AI17: 0 | AJ17: 0 | AK17: 0 | AL17: 0 | AM17: 0 | AN17: 0 | AO17: 0 | AP17: =1-SUM(X17:AN17) -> 1 | AQ17: US | AR17: Consulting and Professional Services | AT17: All other professional, scientific, and technical services | AU17: 45992 | AV17: 46024.01 | AW17: 1 | AX17: 0 | AY17: 24 | AZ17: 1 | BA17: 0 | BB17: 6 | BC17: 45992 | BD17: 48 | BE17: Dec | BF17: 2025 | BG17: United States | BH17: =VLOOKUP(B17,CookieClicks!D:O,12,FALSE) -> https://signin.method.me/error?errorCode=165&returnUrl=https%3A%2F%2Fcandhcraneservices.method.me%2Fapps%2FDefault.aspx%23%2Ff71e8a16-2653-4e1e-89d3-37753dce28a2 | BI17: =IFERROR(__xludf.DUMMYFUNCTION("VLOOKUP(REGEXREPLACE(BH17,""[?].*"",""""),ContentBuckets!A:C,2,FALSE)"),"#N/A") -> #N/A | BJ17: =IFERROR(__xludf.DUMMYFUNCTION("VLOOKUP(REGEXREPLACE(BH17,""[?].*"",""""),ContentBuckets!A:C,3,FALSE)"),"#N/A") -> #N/A
A18: 153128 | B18: grety | C18: 45992.584 | D18: 45999.674 | F18: FALSE | G18: TRUE | H18: FALSE | I18: FALSE | J18: Monthly | K18: Method:CRM for QBD | L18: QBDT | M18: New | N18: 0 | O18: 44.25 | P18: 0 | Q18: 0 | R18: 0 | S18: US-3 Month Promo(25% off) | T18: Direct | V18: 7220805 | X18: 1 | Y18: 0 | Z18: 0 | AA18: 0 | AB18: 0 | AC18: 0 | AD18: 0 | AE18: 0 | AF18: 0 | AG18: 0 | AH18: 0 | AI18: 0 | AJ18: 0 | AK18: 0 | AL18: 0 | AM18: 0 | AN18: 0 | AO18: 0 | AP18: =1-SUM(X18:AN18) -> 0 | AV18: 45999.006 | AW18: 0 | AX18: 0 | AY18: 0 | AZ18: 1 | BA18: 0 | BB18: 0 | BC18: 45992 | BD18: 48 | BE18: Dec | BF18: 2025 | BG18: Canada | BH18: =VLOOKUP(B18,CookieClicks!D:O,12,FALSE) -> http://signup.method.me/methodcrm?_gl=1*16dqon3*_gcl_au*NjAzNTg3NTQzLjE3NjQ2MDk3Mjc.*_ga*MjEyOTUxMjU4MC4xNzY0NjA5NzM0*_ga_L2HEZNW53E*czE3NjQ2MDk3MzQkbzEkZzAkdDE3NjQ2MDk3MzUkajU5JGwwJGgxNjczNjM2NjYx&_ga=2.54480033.848033626.1764609734-2129512580.1764609734 | BI18: =IFERROR(__xludf.DUMMYFUNCTION("VLOOKUP(REGEXREPLACE(BH18,""[?].*"",""""),ContentBuckets!A:C,2,FALSE)"),"#N/A") -> #N/A | BJ18: =IFERROR(__xludf.DUMMYFUNCTION("VLOOKUP(REGEXREPLACE(BH18,""[?].*"",""""),ContentBuckets!A:C,3,FALSE)"),"#N/A") -> #N/A
A19: 153129 | B19: danielaziz | C19: 45992.613 | F19: TRUE | G19: FALSE | H19: FALSE | I19: FALSE | J19: Monthly | K19: Method:CRM | L19: QuickBooks | M19: New | N19: 0 | O19: 44.25 | P19: 0 | Q19: 0 | R19: 0 | S19: US-3 Month Promo(25% off) | T19: Direct | V19: 7221061 | X19: 1 | Y19: 0 | Z19: 0 | AA19: 0 | AB19: 0 | AC19: 0 | AD19: 0 | AE19: 0 | AF19: 0 | AG19: 0 | AH19: 0 | AI19: 0 | AJ19: 0 | AK19: 0 | AL19: 0 | AM19: 0 | AN19: 0 | AO19: 0 | AP19: =1-SUM(X19:AN19) -> 0 | AV19: 46023.993 | AW19: 0 | AX19: 0 | AY19: 0 | AZ19: 1 | BA19: 0 | BB19: 0 | BC19: 45992 | BD19: 48 | BE19: Dec | BF19: 2025 | BG19: United States | BH19: =VLOOKUP(B19,CookieClicks!D:O,12,FALSE) -> https://signin.method.me/?returnUrl=https%3A%2F%2Fumjca.methodportal.com%2Fapps%2F | BI19: =IFERROR(__xludf.DUMMYFUNCTION("VLOOKUP(REGEXREPLACE(BH19,""[?].*"",""""),ContentBuckets!A:C,2,FALSE)"),"#N/A") -> #N/A | BJ19: =IFERROR(__xludf.DUMMYFUNCTION("VLOOKUP(REGEXREPLACE(BH19,""[?].*"",""""),ContentBuckets!A:C,3,FALSE)"),"#N/A") -> #N/A
A20: 153130 | B20: knightinsurancesolutions | C20: 45992.629 | D20: 46000.424 | F20: FALSE | G20: TRUE | H20: FALSE | I20: FALSE | J20: Monthly | K20: Method:CRM | L20: QuickBooks | M20: New | N20: 0 | O20: 44.25 | P20: 0 | Q20: 0 | R20: 0 | S20: US-3 Month Promo(25% off) | T20: Direct | V20: 7155332 | W20: https://www.google.com/ | X20: 0 | Y20: 0.6 | Z20: 0 | AA20: 0.4 | AB20: 0 | AC20: 0 | AD20: 0 | AE20: 0 | AF20: 0 | AG20: 0 | AH20: 0 | AI20: 0 | AJ20: 0 | AK20: 0 | AL20: 0 | AM20: 0 | AN20: 0 | AO20: 0 | AP20: =1-SUM(X20:AN20) -> 0 | AV20: 46000.015 | AW20: 0 | AX20: 0 | AY20: 0 | AZ20: 1 | BA20: 0 | BB20: 0 | BC20: 45992 | BD20: 48 | BE20: Dec | BF20: 2025 | BG20: United States | BH20: =VLOOKUP(B20,CookieClicks!D:O,12,FALSE) -> https://grow.method.me/multi-entity/?trc=81&trk=multi-account crm&trs=US-Multi-entity&campaignid=22836319657&adgroupid=183992915458&adid=765768443211&gad_source=1&gad_campaignid=22836319657&gbraid=0AAAAAD3ItnZcCORda2sETHQ4nib78uZ3B&gclid=Cj0KCQiArOvIBhDLARIsAPwJXOaKqhQhO0cz3xMBJwlL3cEyFuApzdc6oy79yWcGj6HiTsVqGqWRzxkaAhctEALw_wcB | BI20: =IFERROR(__xludf.DUMMYFUNCTION("VLOOKUP(REGEXREPLACE(BH20,""[?].*"",""""),ContentBuckets!A:C,2,FALSE)"),"#N/A") -> #N/A | BJ20: =IFERROR(__xludf.DUMMYFUNCTION("VLOOKUP(REGEXREPLACE(BH20,""[?].*"",""""),ContentBuckets!A:C,3,FALSE)"),"#N/A") -> #N/A
A21: 153131 | B21: joeythecoffeeguy | C21: 45992.64 | F21: TRUE | G21: FALSE | H21: FALSE | I21: FALSE | J21: Monthly | K21: Method:CRM For QBO | L21: QBO | M21: New | N21: 0 | O21: 63.75 | P21: 0 | Q21: 0 | R21: 0 | S21: US-3 Month Promo(25% off) | T21: Direct | V21: 7221267 | X21: 0 | Y21: 0 | Z21: 0 | AA21: 1 | AB21: 0 | AC21: 0 | AD21: 0 | AE21: 0 | AF21: 0 | AG21: 0 | AH21: 0 | AI21: 0 | AJ21: 0 | AK21: 0 | AL21: 0 | AM21: 0 | AN21: 0 | AO21: 0 | AP21: =1-SUM(X21:AN21) -> 0 | AQ21: US | AT21: Coffee and tea manufacturing | AU21: 45992 | AV21: 46024.017 | AW21: 1 | AX21: 4891.68 | AY21: 89 | AZ21: 1 | BA21: 0 | BB21: 0 | BC21: 45992 | BD21: 48 | BE21: Dec | BF21: 2025 | BG21: United States | BH21: =VLOOKUP(B21,CookieClicks!D:O,12,FALSE) -> https://grow.method.me/qb-payment/?trc=81&trk=quickbooks online payment processing&trs=US-payment&campaignid=19733246298&adgroupid=146278163933&adid=649435146420&gad_source=1&gad_campaignid=19733246298&gbraid=0AAAAAD3ItnZi9CFAjVhQFCFOFcYmyOWup&gclid=CjwKCAiAlrXJBhBAEiwA-5pgwvgqW2qm5b78Drd4wf59_QQVxH1WepiBjaJvI-eC_MsZ_LDbnGVEVxoC8okQAvD_BwE | BI21: =IFERROR(__xludf.DUMMYFUNCTION("VLOOKUP(REGEXREPLACE(BH21,""[?].*"",""""),ContentBuckets!A:C,2,FALSE)"),"#N/A") -> #N/A | BJ21: =IFERROR(__xludf.DUMMYFUNCTION("VLOOKUP(REGEXREPLACE(BH21,""[?].*"",""""),ContentBuckets!A:C,3,FALSE)"),"#N/A") -> #N/A
A22: 153132 | B22: octopusgdn | C22: 45992.687 | E22: 46007.792 | F22: TRUE | G22: FALSE | H22: FALSE | I22: FALSE | J22: Monthly | K22: Method:CRM For QBO | L22: QBO | M22: New | N22: 44.25 | O22: 44.25 | P22: 0 | Q22: 0 | R22: 28 | S22: US-3 Month Promo(25% off) | T22: Direct | V22: 7034286 | W22: https://www.google.com/ | X22: 0 | Y22: 1 | Z22: 0 | AA22: 0 | AB22: 0 | AC22: 0 | AD22: 0 | AE22: 0 | AF22: 0 | AG22: 0 | AH22: 0 | AI22: 0 | AJ22: 0 | AK22: 0 | AL22: 0 | AM22: 0 | AN22: 0 | AO22: 0 | AP22: =1-SUM(X22:AN22) -> 0 | AQ22: US | AR22: Wholesale and distribution services (MWD) | AT22: Fish and seafood merchant wholesalers | AU22: 45992 | AV22: 46024.037 | AW22: 3 | AX22: 996361.8 | AY22: 89 | AZ22: 1 | BA22: 0 | BB22: 0 | BC22: 45992 | BD22: 48 | BE22: Dec | BF22: 2025 | BG22: United States | BH22: =VLOOKUP(B22,CookieClicks!D:O,12,FALSE) -> https://www.method.me/crm-quickbooks/pricing/ | BI22: =IFERROR(__xludf.DUMMYFUNCTION("VLOOKUP(REGEXREPLACE(BH22,""[?].*"",""""),ContentBuckets!A:C,2,FALSE)"),"/crm-quickbooks/") -> /crm-quickbooks/ | BJ22: =IFERROR(__xludf.DUMMYFUNCTION("VLOOKUP(REGEXREPLACE(BH22,""[?].*"",""""),ContentBuckets!A:C,3,FALSE)"),"Other page") -> Other page
A23: 153134 | B23: cravenscoffee | C23: 45992.769 | F23: TRUE | G23: FALSE | H23: FALSE | I23: FALSE | J23: Monthly | K23: Method:CRM for QBD | L23: QBDT | M23: New | N23: 0 | O23: 109.5 | P23: 0 | Q23: 0 | R23: 28 | S23: US-3 Month Promo(25% off) | T23: Direct | V23: 7012113 | W23: https://chatgpt.com/ | X23: 0 | Y23: 0.4 | Z23: 0 | AA23: 0 | AB23: 0 | AC23: 0.6002 | AD23: 0 | AE23: 0 | AF23: 0 | AG23: 0 | AH23: 0 | AI23: 0 | AJ23: 0 | AK23: 0 | AL23: 0 | AM23: 0 | AN23: 0 | AO23: 0 | AP23: =1-SUM(X23:AN23) -> -0.0002 | AQ23: US | AR23: Wholesale and distribution services (MWD) | AT23: OtherNone | AU23: 45993 | AV23: 46023.995 | AW23: 25 | AX23: 404158.8 | AY23: 732 | AZ23: 2 | BA23: 0 | BB23: 0 | BC23: 45992 | BD23: 48 | BE23: Dec | BF23: 2025 | BG23: United States | BH23: =VLOOKUP(B23,CookieClicks!D:O,12,FALSE) -> https://www.method.me/ | BI23: =IFERROR(__xludf.DUMMYFUNCTION("VLOOKUP(REGEXREPLACE(BH23,""[?].*"",""""),ContentBuckets!A:C,2,FALSE)"),"Homepage") -> Homepage | BJ23: =IFERROR(__xludf.DUMMYFUNCTION("VLOOKUP(REGEXREPLACE(BH23,""[?].*"",""""),ContentBuckets!A:C,3,FALSE)"),"Other page") -> Other page
A24: 153135 | B24: cosmicvisionairesllc | C24: 45992.803 | F24: TRUE | G24: FALSE | H24: FALSE | I24: FALSE | J24: Monthly | K24: Method:CRM For QBO | L24: QBO | M24: New | N24: 0 | O24: 62.25 | P24: 0 | Q24: 0 | R24: 28 | S24: US-3 Month Promo(25% off) | T24: Direct | V24: 7203163 | W24: https://www.google.com/ | X24: 0 | Y24: 0.5 | Z24: 0 | AA24: 0.5 | AB24: 0 | AC24: 0 | AD24: 0 | AE24: 0 | AF24: 0 | AG24: 0 | AH24: 0 | AI24: 0 | AJ24: 0 | AK24: 0 | AL24: 0 | AM24: 0 | AN24: 0 | AO24: 0 | AP24: =1-SUM(X24:AN24) -> 0 | AQ24: US | AR24: IT and computer related | AT24: Software publishers | AU24: 45992 | AV24: 46023.994 | AW24: 0 | AX24: 0 | AY24: 0 | AZ24: 1 | BA24: 0 | BB24: 0 | BC24: 45992 | BD24: 48 | BE24: Dec | BF24: 2025 | BG24: United States | BH24: =VLOOKUP(B24,CookieClicks!D:O,12,FALSE) -> https://www.method.me/ | BI24: =IFERROR(__xludf.DUMMYFUNCTION("VLOOKUP(REGEXREPLACE(BH24,""[?].*"",""""),ContentBuckets!A:C,2,FALSE)"),"Homepage") -> Homepage | BJ24: =IFERROR(__xludf.DUMMYFUNCTION("VLOOKUP(REGEXREPLACE(BH24,""[?].*"",""""),ContentBuckets!A:C,3,FALSE)"),"Other page") -> Other page
A25: 153136 | B25: khshopapp | C25: 45992.827 | F25: TRUE | G25: FALSE | H25: FALSE | I25: FALSE | J25: Monthly | K25: Method:CRM | L25: QuickBooks | M25: New | N25: 0 | O25: 26.25 | P25: 0 | Q25: 0 | R25: 0 | S25: US-3 Month Promo(25% off) | T25: Direct | V25: 7222319 | W25: https://www.google.com/ | X25: 0 | Y25: 1 | Z25: 0 | AA25: 0 | AB25: 0 | AC25: 0 | AD25: 0 | AE25: 0 | AF25: 0 | AG25: 0 | AH25: 0 | AI25: 0 | AJ25: 0 | AK25: 0 | AL25: 0 | AM25: 0 | AN25: 0 | AO25: 0 | AP25: =1-SUM(X25:AN25) -> 0 | AV25: 46024.007 | AW25: 0 | AX25: 0 | AY25: 0 | AZ25: 1 | BA25: 0 | BB25: 0 | BC25: 45992 | BD25: 48 | BE25: Dec | BF25: 2025 | BG25: Egypt | BH25: =VLOOKUP(B25,CookieClicks!D:O,12,FALSE) -> http://signup.method.me/donor/ | BI25: =IFERROR(__xludf.DUMMYFUNCTION("VLOOKUP(REGEXREPLACE(BH25,""[?].*"",""""),ContentBuckets!A:C,2,FALSE)"),"#N/A") -> #N/A | BJ25: =IFERROR(__xludf.DUMMYFUNCTION("VLOOKUP(REGEXREPLACE(BH25,""[?].*"",""""),ContentBuckets!A:C,3,FALSE)"),"#N/A") -> #N/A
A26: 153138 | B26: servicerankprocommateiucwebcompaniesllc | C26: 45992.931 | F26: TRUE | G26: FALSE | H26: FALSE | I26: FALSE | J26: Monthly | K26: Method:CRM For QBO | L26: QBO | M26: New | N26: 0 | O26: 81 | P26: 0 | Q26: 0 | R26: 28 | S26: US-3 Month Promo(25% off) | T26: Direct | V26: 7222778 | X26: 0 | Y26: 0 | Z26: 0 | AA26: 0 | AB26: 0 | AC26: 0 | AD26: 0 | AE26: 0 | AF26: 0 | AG26: 0 | AH26: 0 | AI26: 0 | AJ26: 0 | AK26: 0 | AL26: 0 | AM26: 0 | AN26: 0 | AO26: 0 | AP26: =1-SUM(X26:AN26) -> 1 | AQ26: US | AR26: Consulting and Professional Services | AU26: 45992 | AV26: 46024.026 | AW26: 0 | AX26: 6600 | AY26: 26 | AZ26: 2 | BA26: 0 | BB26: 0 | BC26: 45992 | BD26: 48 | BE26: Dec | BF26: 2025 | BG26: United States | BH26: =VLOOKUP(B26,CookieClicks!D:O,12,FALSE) -> http://signup.method.me/methodcrm?_gl=1*35xga*_gcl_au*OTA4NzE2NzI5LjE3NjQ2NDU2NTg.*_ga*MTI1ODgwNDgzOS4xNzY0NjQ1NjU4*_ga_L2HEZNW53E*czE3NjQ2NDU2NTgkbzEkZzAkdDE3NjQ2NDU2NTgkajYwJGwwJGgzNDc2MjkzNDg.&_ga=2.76960469.1538964529.1764645658-1258804839.1764645658 | BI26: =IFERROR(__xludf.DUMMYFUNCTION("VLOOKUP(REGEXREPLACE(BH26,""[?].*"",""""),ContentBuckets!A:C,2,FALSE)"),"#N/A") -> #N/A | BJ26: =IFERROR(__xludf.DUMMYFUNCTION("VLOOKUP(REGEXREPLACE(BH26,""[?].*"",""""),ContentBuckets!A:C,3,FALSE)"),"#N/A") -> #N/A
A27: 153139 | B27: test212 | C27: 45992.956 | F27: TRUE | G27: FALSE | H27: FALSE | I27: FALSE | J27: Monthly | K27: Method:CRM for QBD | L27: QBDT | M27: New | N27: 0 | O27: 44.25 | P27: 0 | Q27: 0 | R27: 28 | S27: US-3 Month Promo(25% off) | T27: Direct | V27: 7222681 | X27: 0 | Y27: 0 | Z27: 0 | AA27: 0 | AB27: 0 | AC27: 1 | AD27: 0 | AE27: 0 | AF27: 0 | AG27: 0 | AH27: 0 | AI27: 0 | AJ27: 0 | AK27: 0 | AL27: 0 | AM27: 0 | AN27: 0 | AO27: 0 | AP27: =1-SUM(X27:AN27) -> 0 | AQ27: US | AR27: Wholesale and distribution services (MWD) | AT27: WholesaleDistributionandSales | AU27: 45992 | AV27: 46024.03 | AW27: 0 | AX27: 1943.4 | AY27: 3 | AZ27: 1 | BA27: 0 | BB27: 0 | BC27: 45992 | BD27: 48 | BE27: Dec | BF27: 2025 | BG27: United States | BH27: =VLOOKUP(B27,CookieClicks!D:O,12,FALSE) -> https://www.method.me/ | BI27: =IFERROR(__xludf.DUMMYFUNCTION("VLOOKUP(REGEXREPLACE(BH27,""[?].*"",""""),ContentBuckets!A:C,2,FALSE)"),"Homepage") -> Homepage | BJ27: =IFERROR(__xludf.DUMMYFUNCTION("VLOOKUP(REGEXREPLACE(BH27,""[?].*"",""""),ContentBuckets!A:C,3,FALSE)"),"Other page") -> Other page
A28: 153140 | B28: butleragway | C28: 45992.958 | F28: TRUE | G28: FALSE | H28: FALSE | I28: FALSE | J28: Monthly | K28: Method:CRM | L28: None | M28: New | N28: 0 | O28: 44.25 | P28: 0 | Q28: 0 | R28: 0 | S28: US-3 Month Promo(25% off) | T28: Direct | V28: 7222912 | X28: 0 | Y28: 0 | Z28: 0 | AA28: 1 | AB28: 0 | AC28: 0 | AD28: 0 | AE28: 0 | AF28: 0 | AG28: 0 | AH28: 0 | AI28: 0 | AJ28: 0 | AK28: 0 | AL28: 0 | AM28: 0 | AN28: 0 | AO28: 0 | AP28: =1-SUM(X28:AN28) -> 0 | AV28: 46023.981 | AW28: 0 | AX28: 0 | AY28: 0 | AZ28: 1 | BA28: 0 | BB28: 0 | BC28: 45992 | BD28: 48 | BE28: Dec | BF28: 2025 | BG28: United States | BH28: =VLOOKUP(B28,CookieClicks!D:O,12,FALSE) -> https://www.method.me/?trc=81&trk=PMax&trs=PMax-FS&campaignid=21074820200&adgroupid&adid&gad_source=5&gad_campaignid=21077580125 | BI28: =IFERROR(__xludf.DUMMYFUNCTION("VLOOKUP(REGEXREPLACE(BH28,""[?].*"",""""),ContentBuckets!A:C,2,FALSE)"),"Homepage") -> Homepage | BJ28: =IFERROR(__xludf.DUMMYFUNCTION("VLOOKUP(REGEXREPLACE(BH28,""[?].*"",""""),ContentBuckets!A:C,3,FALSE)"),"Other page") -> Other page
A29: 153141 | B29: westernheatingandairllc | C29: 45992.972 | E29: 46006.532 | F29: TRUE | G29: FALSE | H29: FALSE | I29: FALSE | J29: Prepay | K29: Method:CRM For QBO | L29: QBO | M29: New | N29: 53.1 | O29: 59 | P29: 0 | Q29: 0 | R29: 28 | T29: Direct | V29: 7222975 | X29: 1 | Y29: 0 | Z29: 0 | AA29: 0 | AB29: 0 | AC29: 0 | AD29: 0 | AE29: 0 | AF29: 0 | AG29: 0 | AH29: 0 | AI29: 0 | AJ29: 0 | AK29: 0 | AL29: 0 | AM29: 0 | AN29: 0 | AO29: 0 | AP29: =1-SUM(X29:AN29) -> 0 | AQ29: US | AR29: Field Services | AU29: 45993 | AV29: 46024.042 | AW29: 2 | AX29: 1592809.9 | AY29: 843 | AZ29: 1 | BA29: 0 | BB29: 5 | BC29: 45992 | BD29: 48 | BE29: Dec | BF29: 2025 | BG29: United States | BH29: =VLOOKUP(B29,CookieClicks!D:O,12,FALSE) -> http://signup.method.me/methodcrm/ | BI29: =IFERROR(__xludf.DUMMYFUNCTION("VLOOKUP(REGEXREPLACE(BH29,""[?].*"",""""),ContentBuckets!A:C,2,FALSE)"),"#N/A") -> #N/A | BJ29: =IFERROR(__xludf.DUMMYFUNCTION("VLOOKUP(REGEXREPLACE(BH29,""[?].*"",""""),ContentBuckets!A:C,3,FALSE)"),"#N/A") -> #N/A
A30: 153142 | B30: makeready | C30: 45993.035 | F30: TRUE | G30: FALSE | H30: FALSE | I30: FALSE | J30: Monthly | K30: Method:CRM For QBO | L30: QBO | M30: New | N30: 0 | O30: 53.25 | P30: 0 | Q30: 0 | R30: 0 | S30: US-3 Month Promo(25% off) | T30: Direct | V30: 7223248 | X30: 0 | Y30: 0 | Z30: 0 | AA30: 1 | AB30: 0 | AC30: 0 | AD30: 0 | AE30: 0 | AF30: 0 | AG30: 0 | AH30: 0 | AI30: 0 | AJ30: 0 | AK30: 0 | AL30: 0 | AM30: 0 | AN30: 0 | AO30: 0 | AP30: =1-SUM(X30:AN30) -> 0 | AV30: 46024.01 | AW30: 0 | AX30: 0 | AY30: 0 | AZ30: 1 | BA30: 0 | BB30: 0 | BC30: 45993 | BD30: 48 | BE30: Dec | BF30: 2025 | BG30: United States | BH30: =VLOOKUP(B30,CookieClicks!D:O,12,FALSE) -> https://grow.method.me/crm-quickbooks/?trc=86&trk=quickbook estimate&trs=USA-G-QB-Bing&msclkid=9d5a77cb2b2b167e1c921ee5569f174b&utm_source=bing&utm_medium=cpc&utm_campaign=US - Generic 2020&utm_term=quickbook estimate&utm_content=Generic | BI30: =IFERROR(__xludf.DUMMYFUNCTION("VLOOKUP(REGEXREPLACE(BH30,""[?].*"",""""),ContentBuckets!A:C,2,FALSE)"),"#N/A") -> #N/A | BJ30: =IFERROR(__xludf.DUMMYFUNCTION("VLOOKUP(REGEXREPLACE(BH30,""[?].*"",""""),ContentBuckets!A:C,3,FALSE)"),"#N/A") -> #N/A
A31: 153143 | B31: cloudheroes2 | C31: 45993.297 | F31: TRUE | G31: FALSE | H31: FALSE | I31: FALSE | J31: Monthly | K31: Method:CRM For QBO | L31: QBO | M31: New | N31: 0 | O31: 236.25 | P31: 0 | Q31: 0 | R31: 28 | S31: US-3 Month Promo(25% off) | T31: Direct | V31: 7224530 | W31: https://www.google.com/ | X31: 0 | Y31: 1 | Z31: 0 | AA31: 0 | AB31: 0 | AC31: 0 | AD31: 0 | AE31: 0 | AF31: 0 | AG31: 0 | AH31: 0 | AI31: 0 | AJ31: 0 | AK31: 0 | AL31: 0 | AM31: 0 | AN31: 0 | AO31: 0 | AP31: =1-SUM(X31:AN31) -> 0 | AQ31: GB | AR31: IT and computer related | AU31: 45993 | AV31: 46023.993 | AW31: 4 | AX31: 154369.32 | AY31: 1305 | AZ31: 2 | BA31: 0 | BB31: 1 | BC31: 45993 | BD31: 48 | BE31: Dec | BF31: 2025 | BG31: United Kingdom | BH31: =VLOOKUP(B31,CookieClicks!D:O,12,FALSE) -> https://www.method.me/ | BI31: =IFERROR(__xludf.DUMMYFUNCTION("VLOOKUP(REGEXREPLACE(BH31,""[?].*"",""""),ContentBuckets!A:C,2,FALSE)"),"Homepage") -> Homepage | BJ31: =IFERROR(__xludf.DUMMYFUNCTION("VLOOKUP(REGEXREPLACE(BH31,""[?].*"",""""),ContentBuckets!A:C,3,FALSE)"),"Other page") -> Other page
A32: 153144 | B32: umjca2 | C32: 45993.306 | D32: 46000.642 | F32: FALSE | G32: FALSE | H32: FALSE | I32: FALSE | J32: Monthly | K32: Method:CRM For QBO | L32: QBO | M32: New | N32: 0 | O32: 44.25 | P32: 0 | Q32: 0 | R32: 0 | S32: US-3 Month Promo(25% off) | T32: Direct | V32: 7224570 | X32: 1 | Y32: 0 | Z32: 0 | AA32: 0 | AB32: 0 | AC32: 0 | AD32: 0 | AE32: 0 | AF32: 0 | AG32: 0 | AH32: 0 | AI32: 0 | AJ32: 0 | AK32: 0 | AL32: 0 | AM32: 0 | AN32: 0 | AO32: 0 | AP32: =1-SUM(X32:AN32) -> 0 | AV32: 46000.042 | AW32: 0 | AX32: 0 | AY32: 0 | AZ32: 1 | BA32: 0 | BB32: 0 | BC32: 45993 | BD32: 48 | BE32: Dec | BF32: 2025 | BG32: United States | BH32: =VLOOKUP(B32,CookieClicks!D:O,12,FALSE) -> https://signin.method.me/?returnUrl=https%3A%2F%2Fumjca.methodportal.com%2Fapps%2F | BI32: =IFERROR(__xludf.DUMMYFUNCTION("VLOOKUP(REGEXREPLACE(BH32,""[?].*"",""""),ContentBuckets!A:C,2,FALSE)"),"#N/A") -> #N/A | BJ32: =IFERROR(__xludf.DUMMYFUNCTION("VLOOKUP(REGEXREPLACE(BH32,""[?].*"",""""),ContentBuckets!A:C,3,FALSE)"),"#N/A") -> #N/A
A33: 153145 | B33: fetzerfinancial8 | C33: 45993.333 | F33: TRUE | G33: FALSE | H33: FALSE | I33: FALSE | J33: Monthly | K33: Method:CRM For QBO | L33: QBO | M33: New | N33: 0 | O33: 54.75 | P33: 0 | Q33: 0 | R33: 28 | S33: US-3 Month Promo(25% off) | T33: Direct | V33: 7224692 | X33: 0 | Y33: 0 | Z33: 1 | AA33: 0 | AB33: 0 | AC33: 0 | AD33: 0 | AE33: 0 | AF33: 0 | AG33: 0 | AH33: 0 | AI33: 0 | AJ33: 0 | AK33: 0 | AL33: 0 | AM33: 0 | AN33: 0 | AO33: 0 | AP33: =1-SUM(X33:AN33) -> 0 | AQ33: US | AR33: Accounting and Bookkeeping | AU33: 45993 | AV33: 46023.999 | AW33: 2 | AX33: 0 | AY33: 1550 | AZ33: 1 | BA33: 0 | BB33: 0 | BC33: 45993 | BD33: 48 | BE33: Dec | BF33: 2025 | BG33: United States | BH33: =VLOOKUP(B33,CookieClicks!D:O,12,FALSE) -> https://signup.method.me/QBOAppstoreSignup?offering=methodcrm | BI33: =IFERROR(__xludf.DUMMYFUNCTION("VLOOKUP(REGEXREPLACE(BH33,""[?].*"",""""),ContentBuckets!A:C,2,FALSE)"),"#N/A") -> #N/A | BJ33: =IFERROR(__xludf.DUMMYFUNCTION("VLOOKUP(REGEXREPLACE(BH33,""[?].*"",""""),ContentBuckets!A:C,3,FALSE)"),"#N/A") -> #N/A
A34: 153146 | B34: platinumplaygrounds | C34: 45993.335 | F34: TRUE | G34: FALSE | H34: FALSE | I34: FALSE | J34: Monthly | K34: Method:CRM For QBO | L34: QBO | M34: New | N34: 0 | O34: 150.75 | P34: 0 | Q34: 0 | R34: 28 | S34: US-3 Month Promo(25% off) | T34: Direct | V34: 7148020 | X34: 1 | Y34: 0 | Z34: 0 | AA34: 0 | AB34: 0 | AC34: 0 | AD34: 0 | AE34: 0 | AF34: 0 | AG34: 0 | AH34: 0 | AI34: 0 | AJ34: 0 | AK34: 0 | AL34: 0 | AM34: 0 | AN34: 0 | AO34: 0 | AP34: =1-SUM(X34:AN34) -> 0 | AQ34: US | AR34: Other | AT34: 21 | AU34: 45993 | AV34: 46024.038 | AW34: 30 | AX34: 183336 | AY34: 1068 | AZ34: 3 | BA34: 0 | BB34: 0 | BC34: 45993 | BD34: 48 | BE34: Dec | BF34: 2025 | BG34: United States | BH34: =VLOOKUP(B34,CookieClicks!D:O,12,FALSE) -> https://www.method.me/industries/field-service-management-software/?utm_source=chatgpt.com | BI34: =IFERROR(__xludf.DUMMYFUNCTION("VLOOKUP(REGEXREPLACE(BH34,""[?].*"",""""),ContentBuckets!A:C,2,FALSE)"),"Industries page") -> Industries page | BJ34: =IFERROR(__xludf.DUMMYFUNCTION("VLOOKUP(REGEXREPLACE(BH34,""[?].*"",""""),ContentBuckets!A:C,3,FALSE)"),"Other page") -> Other page
A35: 153147 | B35: rvrepairnearmellc | C35: 45993.36 | F35: TRUE | G35: FALSE | H35: FALSE | I35: FALSE | J35: Monthly | K35: Method:FieldServices for QBD | L35: QBDT | M35: New | N35: 0 | O35: 44.25 | P35: 0 | Q35: 0 | R35: 28 | S35: US-3 Month Promo(25% off) | T35: Direct | V35: 7224805 | X35: 0 | Y35: 0 | Z35: 0 | AA35: 1 | AB35: 0 | AC35: 0 | AD35: 0 | AE35: 0 | AF35: 0 | AG35: 0 | AH35: 0 | AI35: 0 | AJ35: 0 | AK35: 0 | AL35: 0 | AM35: 0 | AN35: 0 | AO35: 0 | AP35: =1-SUM(X35:AN35) -> 0 | AR35: Field Services | AV35: 46024.023 | AW35: 0 | AX35: 0 | AY35: 0 | AZ35: 1 | BA35: 0 | BB35: 0 | BC35: 45993 | BD35: 48 | BE35: Dec | BF35: 2025 | BG35: United States | BH35: =VLOOKUP(B35,CookieClicks!D:O,12,FALSE) -> https://grow.method.me/quickbooks-fsm/?trc=81&trk=quickbooks work order management&trs=US-WorkOrder&campaignid=12406628869&adgroupid=118144098877&adid=500417359916&gad_source=1&gad_campaignid=12406628869&gbraid=0AAAAAD3Itnbb-v0p7Dw7Bhdk7OpsQaId8&gclid=Cj0KCQiAubrJBhCbARIsAHIdxD9PhuzgzFx4d3Oeatq_oulj9ZdbZgTzuwu80IJCqEK0UFsHKWmAAL4aAnntEALw_wcB | BI35: =IFERROR(__xludf.DUMMYFUNCTION("VLOOKUP(REGEXREPLACE(BH35,""[?].*"",""""),ContentBuckets!A:C,2,FALSE)"),"#N/A") -> #N/A | BJ35: =IFERROR(__xludf.DUMMYFUNCTION("VLOOKUP(REGEXREPLACE(BH35,""[?].*"",""""),ContentBuckets!A:C,3,FALSE)"),"#N/A") -> #N/A
A36: 153157 | B36: individual6 | C36: 45993.44 | F36: TRUE | G36: FALSE | H36: FALSE | I36: FALSE | J36: Monthly | K36: Method:CRM For QBO | L36: QBO | M36: New | N36: 0 | O36: 62.25 | P36: 0 | Q36: 0 | R36: 28 | S36: US-3 Month Promo(25% off) | T36: Direct | V36: 7225423 | X36: 0 | Y36: 0 | Z36: 0 | AA36: 1 | AB36: 0 | AC36: 0 | AD36: 0 | AE36: 0 | AF36: 0 | AG36: 0 | AH36: 0 | AI36: 0 | AJ36: 0 | AK36: 0 | AL36: 0 | AM36: 0 | AN36: 0 | AO36: 0 | AP36: =1-SUM(X36:AN36) -> 0 | AQ36: US | AR36: Other | AU36: 45995 | AV36: 46024.006 | AW36: 0 | AX36: 0 | AY36: 583 | AZ36: 1 | BA36: 0 | BB36: 0 | BC36: 45993 | BD36: 48 | BE36: Dec | BF36: 2025 | BG36: United States | BH36: =VLOOKUP(B36,CookieClicks!D:O,12,FALSE) -> https://grow.method.me/crm-quickbooks/?trc=81&trk=quickbooks crm&trs=USA-QB-G_Ex&campaignid=22265826203&adgroupid=176758613473&adid=734012603510&gad_source=1&gad_campaignid=22265826203&gbraid=0AAAAAD3ItnbZS3z8l6nzYVFFMJ1qRT6ol&gclid=Cj0KCQiAubrJBhCbARIsAHIdxD91Aj2WQqPOZpBBh09mY5kWzXBsLLrHYQVGPGApxr6fWSq1XW-0KsgaAk0GEALw_wcB | BI36: =IFERROR(__xludf.DUMMYFUNCTION("VLOOKUP(REGEXREPLACE(BH36,""[?].*"",""""),ContentBuckets!A:C,2,FALSE)"),"#N/A") -> #N/A | BJ36: =IFERROR(__xludf.DUMMYFUNCTION("VLOOKUP(REGEXREPLACE(BH36,""[?].*"",""""),ContentBuckets!A:C,3,FALSE)"),"#N/A") -> #N/A
A37: 153158 | B37: thenesthomeimprovementcentreinc | C37: 45993.447 | F37: TRUE | G37: FALSE | H37: FALSE | I37: FALSE | J37: Monthly | K37: Method:CRM For QBO | L37: QBO | M37: New | N37: 0 | O37: 54.75 | P37: 0 | Q37: 0 | R37: 28 | S37: US-3 Month Promo(25% off) | T37: Direct | V37: 7225452 | W37: https://www.google.com/ | X37: 0 | Y37: 1 | Z37: 0 | AA37: 0 | AB37: 0 | AC37: 0 | AD37: 0 | AE37: 0 | AF37: 0 | AG37: 0 | AH37: 0 | AI37: 0 | AJ37: 0 | AK37: 0 | AL37: 0 | AM37: 0 | AN37: 0 | AO37: 0 | AP37: =1-SUM(X37:AN37) -> 0 | AQ37: CA | AR37: Other | AU37: 45993 | AV37: 46024.03 | AW37: 0 | AX37: 93603.72 | AY37: 241 | AZ37: 1 | BA37: 0 | BB37: 0 | BC37: 45993 | BD37: 48 | BE37: Dec | BF37: 2025 | BG37: Canada | BH37: =VLOOKUP(B37,CookieClicks!D:O,12,FALSE) -> https://www.method.me/ | BI37: =IFERROR(__xludf.DUMMYFUNCTION("VLOOKUP(REGEXREPLACE(BH37,""[?].*"",""""),ContentBuckets!A:C,2,FALSE)"),"Homepage") -> Homepage | BJ37: =IFERROR(__xludf.DUMMYFUNCTION("VLOOKUP(REGEXREPLACE(BH37,""[?].*"",""""),ContentBuckets!A:C,3,FALSE)"),"Other page") -> Other page
A38: 153159 | B38: garcyusa | C38: 45993.463 | F38: TRUE | G38: FALSE | H38: FALSE | I38: FALSE | J38: Monthly | K38: Method:FieldServices for QBD | L38: QBDT | M38: New | N38: 0 | O38: 54.75 | P38: 0 | Q38: 0 | R38: 28 | S38: US-3 Month Promo(25% off) | T38: Direct | V38: 7225548 | W38: https://www.google.com/ | X38: 0 | Y38: 1 | Z38: 0 | AA38: 0 | AB38: 0 | AC38: 0 | AD38: 0 | AE38: 0 | AF38: 0 | AG38: 0 | AH38: 0 | AI38: 0 | AJ38: 0 | AK38: 0 | AL38: 0 | AM38: 0 | AN38: 0 | AO38: 0 | AP38: =1-SUM(X38:AN38) -> 0 | AQ38: US | AR38: Manufacturing (MWD) | AT38: Manufacturing | AU38: 45993 | AV38: 46023.999 | AW38: 0 | AX38: 0 | AY38: 1 | AZ38: 1 | BA38: 0 | BB38: 0 | BC38: 45993 | BD38: 48 | BE38: Dec | BF38: 2025 | BG38: United States | BH38: =VLOOKUP(B38,CookieClicks!D:O,12,FALSE) -> https://www.method.me/ | BI38: =IFERROR(__xludf.DUMMYFUNCTION("VLOOKUP(REGEXREPLACE(BH38,""[?].*"",""""),ContentBuckets!A:C,2,FALSE)"),"Homepage") -> Homepage | BJ38: =IFERROR(__xludf.DUMMYFUNCTION("VLOOKUP(REGEXREPLACE(BH38,""[?].*"",""""),ContentBuckets!A:C,3,FALSE)"),"Other page") -> Other page
A39: 153160 | B39: vandalenindustries | C39: 45993.469 | E39: 46010.613 | F39: TRUE | G39: FALSE | H39: FALSE | I39: FALSE | J39: Monthly | K39: Method:CRM for QBD | L39: QBDT | M39: New | N39: 318.75 | O39: 318.75 | P39: 0 | Q39: 0 | R39: 28 | S39: US-3 Month Promo(25% off) | T39: Direct | V39: 7224722 | X39: 0 | Y39: 0 | Z39: 0 | AA39: 1 | AB39: 0 | AC39: 0 | AD39: 0 | AE39: 0 | AF39: 0 | AG39: 0 | AH39: 0 | AI39: 0 | AJ39: 0 | AK39: 0 | AL39: 0 | AM39: 0 | AN39: 0 | AO39: 0 | AP39: =1-SUM(X39:AN39) -> 0 | AQ39: US | AR39: Construction | AT39: retail | AU39: 45996 | AV39: 46024.04 | AW39: 36 | AX39: 3509037 | AY39: 2882 | AZ39: 5 | BA39: 0 | BB39: 3 | BC39: 45993 | BD39: 48 | BE39: Dec | BF39: 2025 | BG39: United States | BH39: =VLOOKUP(B39,CookieClicks!D:O,12,FALSE) -> https://grow.method.me/crm-quickbooks/?trc=81&trk=quickbooks crm&trs=USA-QB-G_Ex&campaignid=22265826203&adgroupid=176758613473&adid=734012603510&gad_source=1&gad_campaignid=22265826203&gbraid=0AAAAAD3ItnbZS3z8l6nzYVFFMJ1qRT6ol&gclid=Cj0KCQiAubrJBhCbARIsAHIdxD9TJfHqIbvGNWgRIlJBUeVw2pz6Co67n1sZyTh7dICR2olwrmUWYYYaAty5EALw_wcB | BI39: =IFERROR(__xludf.DUMMYFUNCTION("VLOOKUP(REGEXREPLACE(BH39,""[?].*"",""""),ContentBuckets!A:C,2,FALSE)"),"#N/A") -> #N/A | BJ39: =IFERROR(__xludf.DUMMYFUNCTION("VLOOKUP(REGEXREPLACE(BH39,""[?].*"",""""),ContentBuckets!A:C,3,FALSE)"),"#N/A") -> #N/A
A40: 153161 | B40: pizzahurt | C40: 45993.474 | F40: TRUE | G40: FALSE | H40: FALSE | I40: FALSE | J40: Monthly | K40: Method:CRM | L40: QuickBooks | M40: New | N40: 0 | O40: 44.25 | P40: 0 | Q40: 0 | R40: 0 | S40: US-3 Month Promo(25% off) | T40: Direct | V40: 7225705 | X40: 0 | Y40: 0 | Z40: 0 | AA40: 1 | AB40: 0 | AC40: 0 | AD40: 0 | AE40: 0 | AF40: 0 | AG40: 0 | AH40: 0 | AI40: 0 | AJ40: 0 | AK40: 0 | AL40: 0 | AM40: 0 | AN40: 0 | AO40: 0 | AP40: =1-SUM(X40:AN40) -> 0 | AV40: 46024.02 | AW40: 0 | AX40: 0 | AY40: 0 | AZ40: 1 | BA40: 0 | BB40: 0 | BC40: 45993 | BD40: 48 | BE40: Dec | BF40: 2025 | BG40: United States | BH40: =VLOOKUP(B40,CookieClicks!D:O,12,FALSE) -> https://grow.method.me/crm-quickbooks/?trk=capterra&trc=78&trs=Capterra_destinationURL&utm_source=capterra&utm_medium=cpc&utm_campaign=destinationURL&gdmcid=c29c73e3-2013-4457-9593-8e7a2867d847 | BI40: =IFERROR(__xludf.DUMMYFUNCTION("VLOOKUP(REGEXREPLACE(BH40,""[?].*"",""""),ContentBuckets!A:C,2,FALSE)"),"#N/A") -> #N/A | BJ40: =IFERROR(__xludf.DUMMYFUNCTION("VLOOKUP(REGEXREPLACE(BH40,""[?].*"",""""),ContentBuckets!A:C,3,FALSE)"),"#N/A") -> #N/A
A41: 153162 | B41: sbc2 | C41: 45993.484 | F41: TRUE | G41: FALSE | H41: FALSE | I41: FALSE | J41: Monthly | K41: Method:CRM For QBO | L41: QBO | M41: New | N41: 0 | O41: 63.75 | P41: 0 | Q41: 0 | R41: 0 | S41: US-3 Month Promo(25% off) | T41: Direct | V41: 7168038 | W41: https://www.google.com/ | X41: 0 | Y41: 1 | Z41: 0 | AA41: 0 | AB41: 0 | AC41: 0 | AD41: 0 | AE41: 0 | AF41: 0 | AG41: 0 | AH41: 0 | AI41: 0 | AJ41: 0 | AK41: 0 | AL41: 0 | AM41: 0 | AN41: 0 | AO41: 0 | AP41: =1-SUM(X41:AN41) -> 0 | AV41: 46024.03 | AW41: 0 | AX41: 0 | AY41: 0 | AZ41: 1 | BA41: 0 | BB41: 0 | BC41: 45993 | BD41: 48 | BE41: Dec | BF41: 2025 | BG41: Canada | BH41: =VLOOKUP(B41,CookieClicks!D:O,12,FALSE) -> https://www.method.me/ | BI41: =IFERROR(__xludf.DUMMYFUNCTION("VLOOKUP(REGEXREPLACE(BH41,""[?].*"",""""),ContentBuckets!A:C,2,FALSE)"),"Homepage") -> Homepage | BJ41: =IFERROR(__xludf.DUMMYFUNCTION("VLOOKUP(REGEXREPLACE(BH41,""[?].*"",""""),ContentBuckets!A:C,3,FALSE)"),"Other page") -> Other page
A42: 153163 | B42: ashram | C42: 45993.491 | F42: TRUE | G42: FALSE | H42: FALSE | I42: FALSE | J42: Monthly | K42: Method:CRM for Xero | L42: Xero | M42: New | N42: 0 | O42: 44.25 | P42: 0 | Q42: 0 | R42: 0 | S42: US-3 Month Promo(25% off) | T42: Direct | V42: 7225592 | W42: https://www.google.com/ | X42: 0 | Y42: 1 | Z42: 0 | AA42: 0 | AB42: 0 | AC42: 0 | AD42: 0 | AE42: 0 | AF42: 0 | AG42: 0 | AH42: 0 | AI42: 0 | AJ42: 0 | AK42: 0 | AL42: 0 | AM42: 0 | AN42: 0 | AO42: 0 | AP42: =1-SUM(X42:AN42) -> 0 | AV42: 46023.987 | AW42: 0 | AX42: 0 | AY42: 0 | AZ42: 1 | BA42: 0 | BB42: 0 | BC42: 45993 | BD42: 48 | BE42: Dec | BF42: 2025 | BG42: India | BH42: =VLOOKUP(B42,CookieClicks!D:O,12,FALSE) -> https://www.method.me/ | BI42: =IFERROR(__xludf.DUMMYFUNCTION("VLOOKUP(REGEXREPLACE(BH42,""[?].*"",""""),ContentBuckets!A:C,2,FALSE)"),"Homepage") -> Homepage | BJ42: =IFERROR(__xludf.DUMMYFUNCTION("VLOOKUP(REGEXREPLACE(BH42,""[?].*"",""""),ContentBuckets!A:C,3,FALSE)"),"Other page") -> Other page
A43: 153164 | B43: gestioncobe | C43: 45993.504 | F43: TRUE | G43: FALSE | H43: FALSE | I43: FALSE | J43: Monthly | K43: Method:CRM For QBO | L43: QBO | M43: New | N43: 0 | O43: 44.25 | P43: 0 | Q43: 0 | R43: 0 | S43: US-3 Month Promo(25% off) | T43: Direct | V43: 7225967 | X43: 0 | Y43: 0 | Z43: 1 | AA43: 0 | AB43: 0 | AC43: 0 | AD43: 0 | AE43: 0 | AF43: 0 | AG43: 0 | AH43: 0 | AI43: 0 | AJ43: 0 | AK43: 0 | AL43: 0 | AM43: 0 | AN43: 0 | AO43: 0 | AP43: =1-SUM(X43:AN43) -> 0 | AQ43: CA | AU43: 45993 | AV43: 46023.998 | AW43: 13 | AX43: 621726.72 | AY43: 178 | AZ43: 1 | BA43: 0 | BB43: 0 | BC43: 45993 | BD43: 48 | BE43: Dec | BF43: 2025 | BG43: Canada | BH43: =VLOOKUP(B43,CookieClicks!D:O,12,FALSE) -> https://signup.method.me/QBOAppstoreSignup?offering=methodcrm | BI43: =IFERROR(__xludf.DUMMYFUNCTION("VLOOKUP(REGEXREPLACE(BH43,""[?].*"",""""),ContentBuckets!A:C,2,FALSE)"),"#N/A") -> #N/A | BJ43: =IFERROR(__xludf.DUMMYFUNCTION("VLOOKUP(REGEXREPLACE(BH43,""[?].*"",""""),ContentBuckets!A:C,3,FALSE)"),"#N/A") -> #N/A
A44: 153165 | B44: cotektheamericas | C44: 45993.528 | F44: TRUE | G44: FALSE | H44: FALSE | I44: FALSE | J44: Monthly | K44: Method:CRM For QBO | L44: QBO | M44: New | N44: 0 | O44: 145.5 | P44: 0 | Q44: 0 | R44: 28 | S44: US-3 Month Promo(25% off) | T44: Direct | V44: 7226145 | W44: https://www.google.com/ | X44: 0 | Y44: 1 | Z44: 0 | AA44: 0 | AB44: 0 | AC44: 0 | AD44: 0 | AE44: 0 | AF44: 0 | AG44: 0 | AH44: 0 | AI44: 0 | AJ44: 0 | AK44: 0 | AL44: 0 | AM44: 0 | AN44: 0 | AO44: 0 | AP44: =1-SUM(X44:AN44) -> 0 | AQ44: CA | AR44: Wholesale and distribution services (MWD) | AU44: 45993 | AV44: 46023.989 | AW44: 6 | AX44: 920222.76 | AY44: 405 | AZ44: 2 | BA44: 0 | BB44: 0 | BC44: 45993 | BD44: 48 | BE44: Dec | BF44: 2025 | BG44: Canada | BH44: =VLOOKUP(B44,CookieClicks!D:O,12,FALSE) -> https://www.method.me/ | BI44: =IFERROR(__xludf.DUMMYFUNCTION("VLOOKUP(REGEXREPLACE(BH44,""[?].*"",""""),ContentBuckets!A:C,2,FALSE)"),"Homepage") -> Homepage | BJ44: =IFERROR(__xludf.DUMMYFUNCTION("VLOOKUP(REGEXREPLACE(BH44,""[?].*"",""""),ContentBuckets!A:C,3,FALSE)"),"Other page") -> Other page
A45: 153166 | B45: brontebaycpaprofessionalcorporation2 | C45: 45993.537 | E45: 45994.544 | F45: TRUE | G45: FALSE | H45: FALSE | I45: FALSE | J45: Prepay | K45: Method:CRM For QBO | L45: QBO | M45: New | N45: 54.45 | O45: 63.75 | P45: 387.5 | Q45: 387.5 | R45: 28 | S45: US-3 Month Promo(25% off) | T45: Direct | V45: 7033836 | W45: https://www.google.com/ | X45: 0 | Y45: 0.4 | Z45: 0 | AA45: 0 | AB45: 0 | AC45: 0.15 | AD45: 0 | AE45: 0 | AF45: 0 | AG45: 0 | AH45: 0.45 | AI45: 0 | AJ45: 0 | AK45: 0 | AL45: 0 | AM45: 0 | AN45: 0 | AO45: 0 | AP45: =1-SUM(X45:AN45) -> 0 | AQ45: CA | AR45: Accounting and Bookkeeping | AU45: 45993 | AV45: 46023.987 | AW45: 22 | AX45: 0 | AY45: 429 | AZ45: 1 | BA45: 0 | BB45: 6 | BC45: 45993 | BD45: 48 | BE45: Dec | BF45: 2025 | BG45: Canada | BH45: =VLOOKUP(B45,CookieClicks!D:O,12,FALSE) -> https://www.method.me/crm-quickbooks/pricing/ | BI45: =IFERROR(__xludf.DUMMYFUNCTION("VLOOKUP(REGEXREPLACE(BH45,""[?].*"",""""),ContentBuckets!A:C,2,FALSE)"),"/crm-quickbooks/") -> /crm-quickbooks/ | BJ45: =IFERROR(__xludf.DUMMYFUNCTION("VLOOKUP(REGEXREPLACE(BH45,""[?].*"",""""),ContentBuckets!A:C,3,FALSE)"),"Other page") -> Other page
A46: 153167 | B46: growtrax2 | C46: 45993.539 | F46: TRUE | G46: FALSE | H46: FALSE | I46: FALSE | J46: Monthly | K46: Method:CRM | L46: QuickBooks | M46: New | N46: 0 | O46: 44.25 | P46: 0 | Q46: 0 | R46: 0 | S46: US-3 Month Promo(25% off) | T46: Direct | V46: 7171683 | W46: https://www.google.com/ | X46: 0 | Y46: 1 | Z46: 0 | AA46: 0 | AB46: 0 | AC46: 0 | AD46: 0 | AE46: 0 | AF46: 0 | AG46: 0 | AH46: 0 | AI46: 0 | AJ46: 0 | AK46: 0 | AL46: 0 | AM46: 0 | AN46: 0 | AO46: 0 | AP46: =1-SUM(X46:AN46) -> 0 | AV46: 46023.999 | AW46: 0 | AX46: 0 | AY46: 0 | AZ46: 1 | BA46: 0 | BB46: 0 | BC46: 45993 | BD46: 48 | BE46: Dec | BF46: 2025 | BG46: Switzerland | BH46: =VLOOKUP(B46,CookieClicks!D:O,12,FALSE) -> https://www.method.me/crm-quickbooks/integrations/ | BI46: =IFERROR(__xludf.DUMMYFUNCTION("VLOOKUP(REGEXREPLACE(BH46,""[?].*"",""""),ContentBuckets!A:C,2,FALSE)"),"/crm-quickbooks/") -> /crm-quickbooks/ | BJ46: =IFERROR(__xludf.DUMMYFUNCTION("VLOOKUP(REGEXREPLACE(BH46,""[?].*"",""""),ContentBuckets!A:C,3,FALSE)"),"Other page") -> Other page
A47: 153169 | B47: bluewatercas2 | C47: 45993.618 | E47: 45993.627 | F47: TRUE | G47: FALSE | H47: FALSE | I47: FALSE | J47: Monthly | K47: Method:CRM For QBO | L47: QBO | M47: New | N47: 164.25 | O47: 164.25 | P47: 0 | Q47: 0 | R47: 28 | S47: US-3 Month Promo(25% off) | T47: Direct | V47: 7226908 | X47: 1 | Y47: 0 | Z47: 0 | AA47: 0 | AB47: 0 | AC47: 0 | AD47: 0 | AE47: 0 | AF47: 0 | AG47: 0 | AH47: 0 | AI47: 0 | AJ47: 0 | AK47: 0 | AL47: 0 | AM47: 0 | AN47: 0 | AO47: 0 | AP47: =1-SUM(X47:AN47) -> 0 | AQ47: US | AR47: Other | AT47: Other chemical and allied products merchant wholesalers | AU47: 45993 | AV47: 46023.988 | AW47: 8 | AX47: 1757076 | AY47: 176 | AZ47: 3 | BA47: 0 | BB47: 1 | BC47: 45993 | BD47: 48 | BE47: Dec | BF47: 2025 | BG47: United States | BH47: =VLOOKUP(B47,CookieClicks!D:O,12,FALSE) -> https://signin.method.me/ | BI47: =IFERROR(__xludf.DUMMYFUNCTION("VLOOKUP(REGEXREPLACE(BH47,""[?].*"",""""),ContentBuckets!A:C,2,FALSE)"),"#N/A") -> #N/A | BJ47: =IFERROR(__xludf.DUMMYFUNCTION("VLOOKUP(REGEXREPLACE(BH47,""[?].*"",""""),ContentBuckets!A:C,3,FALSE)"),"#N/A") -> #N/A
A48: 153170 | B48: method113 | C48: 45993.624 | F48: TRUE | G48: TRUE | H48: FALSE | I48: FALSE | J48: Monthly | K48: Method:CRM For QBO | L48: QBO | M48: New | N48: 0 | O48: 44.25 | P48: 0 | Q48: 0 | R48: 0 | S48: US-3 Month Promo(25% off) | T48: Direct | V48: 7200361 | W48: https://www.google.com/ | X48: 0 | Y48: 1 | Z48: 0 | AA48: 0 | AB48: 0 | AC48: 0 | AD48: 0 | AE48: 0 | AF48: 0 | AG48: 0 | AH48: 0 | AI48: 0 | AJ48: 0 | AK48: 0 | AL48: 0 | AM48: 0 | AN48: 0 | AO48: 0 | AP48: =1-SUM(X48:AN48) -> 0 | AV48: 46024.011 | AW48: 0 | AX48: 0 | AY48: 0 | AZ48: 1 | BA48: 0 | BB48: 0 | BC48: 45993 | BD48: 48 | BE48: Dec | BF48: 2025 | BG48: Canada | BH48: =VLOOKUP(B48,CookieClicks!D:O,12,FALSE) -> https://www.method.me/ | BI48: =IFERROR(__xludf.DUMMYFUNCTION("VLOOKUP(REGEXREPLACE(BH48,""[?].*"",""""),ContentBuckets!A:C,2,FALSE)"),"Homepage") -> Homepage | BJ48: =IFERROR(__xludf.DUMMYFUNCTION("VLOOKUP(REGEXREPLACE(BH48,""[?].*"",""""),ContentBuckets!A:C,3,FALSE)"),"Other page") -> Other page
A49: 153172 | B49: ecoofficewerks | C49: 45993.666 | F49: TRUE | G49: FALSE | H49: FALSE | I49: FALSE | J49: Monthly | K49: Method:CRM For QBO | L49: QBO | M49: New | N49: 0 | O49: 44.25 | P49: 0 | Q49: 0 | R49: 0 | S49: US-3 Month Promo(25% off) | T49: Direct | V49: 7227287 | X49: 0 | Y49: 0 | Z49: 0 | AA49: 1 | AB49: 0 | AC49: 0 | AD49: 0 | AE49: 0 | AF49: 0 | AG49: 0 | AH49: 0 | AI49: 0 | AJ49: 0 | AK49: 0 | AL49: 0 | AM49: 0 | AN49: 0 | AO49: 0 | AP49: =1-SUM(X49:AN49) -> 0 | AT49: Professional Consulting | AU49: 45993 | AV49: 46023.992 | AW49: 5 | AX49: 0 | AY49: 26 | AZ49: 1 | BA49: 0 | BB49: 0 | BC49: 45993 | BD49: 48 | BE49: Dec | BF49: 2025 | BG49: United States | BH49: =VLOOKUP(B49,CookieClicks!D:O,12,FALSE) -> https://grow.method.me/best-quickbooks-crm/?trc=86&trk=grow.method.me&trs=Bing-PMax&msclkid=9f4239fb50c21fa5297050d40275a688&utm_source=bing&utm_medium=cpc&utm_campaign=Bing - PMAX&utm_term=grow.method.me&utm_content=US - retargeting | BI49: =IFERROR(__xludf.DUMMYFUNCTION("VLOOKUP(REGEXREPLACE(BH49,""[?].*"",""""),ContentBuckets!A:C,2,FALSE)"),"#N/A") -> #N/A | BJ49: =IFERROR(__xludf.DUMMYFUNCTION("VLOOKUP(REGEXREPLACE(BH49,""[?].*"",""""),ContentBuckets!A:C,3,FALSE)"),"#N/A") -> #N/A
A50: 153173 | B50: wanderwood | C50: 45993.676 | F50: TRUE | G50: FALSE | H50: FALSE | I50: FALSE | J50: Monthly | K50: Method:CRM For QBO | L50: QBO | M50: New | N50: 0 | O50: 44.25 | P50: 0 | Q50: 0 | R50: 28 | S50: US-3 Month Promo(25% off) | T50: Direct | V50: 7227385 | W50: https://www.google.com/ | X50: 0 | Y50: 1 | Z50: 0 | AA50: 0 | AB50: 0 | AC50: 0 | AD50: 0 | AE50: 0 | AF50: 0 | AG50: 0 | AH50: 0 | AI50: 0 | AJ50: 0 | AK50: 0 | AL50: 0 | AM50: 0 | AN50: 0 | AO50: 0 | AP50: =1-SUM(X50:AN50) -> 0 | AQ50: US | AR50: Other | AU50: 45993 | AV50: 46024.036 | AW50: 22 | AX50: 953108.28 | AY50: 398 | AZ50: 1 | BA50: 0 | BB50: 0 | BC50: 45993 | BD50: 48 | BE50: Dec | BF50: 2025 | BG50: United States | BH50: =VLOOKUP(B50,CookieClicks!D:O,12,FALSE) -> https://www.method.me/ | BI50: =IFERROR(__xludf.DUMMYFUNCTION("VLOOKUP(REGEXREPLACE(BH50,""[?].*"",""""),ContentBuckets!A:C,2,FALSE)"),"Homepage") -> Homepage | BJ50: =IFERROR(__xludf.DUMMYFUNCTION("VLOOKUP(REGEXREPLACE(BH50,""[?].*"",""""),ContentBuckets!A:C,3,FALSE)"),"Other page") -> Other page
A51: 153174 | B51: gflsystems | C51: 45993.69 | F51: TRUE | G51: FALSE | H51: FALSE | I51: FALSE | J51: Monthly | K51: Method:CRM For QBO | L51: QBO | M51: New | N51: 0 | O51: 63.75 | P51: 0 | Q51: 0 | R51: 28 | S51: US-3 Month Promo(25% off) | T51: Direct | V51: 7227482 | W51: https://www.google.com/ | X51: 0 | Y51: 1 | Z51: 0 | AA51: 0 | AB51: 0 | AC51: 0 | AD51: 0 | AE51: 0 | AF51: 0 | AG51: 0 | AH51: 0 | AI51: 0 | AJ51: 0 | AK51: 0 | AL51: 0 | AM51: 0 | AN51: 0 | AO51: 0 | AP51: =1-SUM(X51:AN51) -> 0 | AR51: Field Services | AV51: 46024.01 | AW51: 0 | AX51: 0 | AY51: 0 | AZ51: 1 | BA51: 0 | BB51: 0 | BC51: 45993 | BD51: 48 | BE51: Dec | BF51: 2025 | BG51: United States | BH51: =VLOOKUP(B51,CookieClicks!D:O,12,FALSE) -> https://www.method.me/ | BI51: =IFERROR(__xludf.DUMMYFUNCTION("VLOOKUP(REGEXREPLACE(BH51,""[?].*"",""""),ContentBuckets!A:C,2,FALSE)"),"Homepage") -> Homepage | BJ51: =IFERROR(__xludf.DUMMYFUNCTION("VLOOKUP(REGEXREPLACE(BH51,""[?].*"",""""),ContentBuckets!A:C,3,FALSE)"),"Other page") -> Other page
A52: 153175 | B52: mammothlive2 | C52: 45993.691 | F52: TRUE | G52: FALSE | H52: FALSE | I52: FALSE | J52: Monthly | K52: Method:CRM for QBD | L52: QBDT | M52: New | N52: 0 | O52: 132.75 | P52: 0 | Q52: 0 | R52: 0 | S52: US-3 Month Promo(25% off) | T52: Direct | V52: 7227496 | X52: 1 | Y52: 0 | Z52: 0 | AA52: 0 | AB52: 0 | AC52: 0 | AD52: 0 | AE52: 0 | AF52: 0 | AG52: 0 | AH52: 0 | AI52: 0 | AJ52: 0 | AK52: 0 | AL52: 0 | AM52: 0 | AN52: 0 | AO52: 0 | AP52: =1-SUM(X52:AN52) -> 0 | AQ52: US | AT52: GeneralServicebasedBusiness | AU52: 45993 | AV52: 46024.009 | AW52: 1 | AX52: 0 | AY52: 92 | AZ52: 3 | BA52: 0 | BB52: 0 | BC52: 45993 | BD52: 48 | BE52: Dec | BF52: 2025 | BG52: United States | BH52: =VLOOKUP(B52,CookieClicks!D:O,12,FALSE) -> http://signup.method.me/?offering=methodcrm | BI52: =IFERROR(__xludf.DUMMYFUNCTION("VLOOKUP(REGEXREPLACE(BH52,""[?].*"",""""),ContentBuckets!A:C,2,FALSE)"),"#N/A") -> #N/A | BJ52: =IFERROR(__xludf.DUMMYFUNCTION("VLOOKUP(REGEXREPLACE(BH52,""[?].*"",""""),ContentBuckets!A:C,3,FALSE)"),"#N/A") -> #N/A
A53: 153176 | B53: kovarwoodwork | C53: 45993.72 | F53: TRUE | G53: FALSE | H53: FALSE | I53: FALSE | J53: Monthly | K53: Method:CRM | L53: QuickBooks | M53: New | N53: 0 | O53: 44.25 | P53: 0 | Q53: 0 | R53: 0 | S53: US-3 Month Promo(25% off) | T53: Direct | V53: 7227716 | X53: 0 | Y53: 0 | Z53: 0 | AA53: 1 | AB53: 0 | AC53: 0 | AD53: 0 | AE53: 0 | AF53: 0 | AG53: 0 | AH53: 0 | AI53: 0 | AJ53: 0 | AK53: 0 | AL53: 0 | AM53: 0 | AN53: 0 | AO53: 0 | AP53: =1-SUM(X53:AN53) -> 0 | AV53: 46024.008 | AW53: 0 | AX53: 0 | AY53: 0 | AZ53: 1 | BA53: 0 | BB53: 0 | BC53: 45993 | BD53: 48 | BE53: Dec | BF53: 2025 | BG53: United States | BH53: =VLOOKUP(B53,CookieClicks!D:O,12,FALSE) -> https://grow.method.me/crm-quickbooks/?trc=86&trk=custom invoice quickbooks&trs=USA-G-QB-Bing&msclkid=6baba474e41013e1c2edcd5b81029a7c&utm_source=bing&utm_medium=cpc&utm_campaign=US - Generic 2020&utm_term=custom invoice quickbooks&utm_content=Generic | BI53: =IFERROR(__xludf.DUMMYFUNCTION("VLOOKUP(REGEXREPLACE(BH53,""[?].*"",""""),ContentBuckets!A:C,2,FALSE)"),"#N/A") -> #N/A | BJ53: =IFERROR(__xludf.DUMMYFUNCTION("VLOOKUP(REGEXREPLACE(BH53,""[?].*"",""""),ContentBuckets!A:C,3,FALSE)"),"#N/A") -> #N/A
A54: 153177 | B54: ogleheatingandcoolgin | C54: 45993.726 | F54: TRUE | G54: FALSE | H54: FALSE | I54: FALSE | J54: Monthly | K54: Method:CRM for QBD | L54: QBDT | M54: New | N54: 0 | O54: 44.25 | P54: 0 | Q54: 0 | R54: 28 | S54: US-3 Month Promo(25% off) | T54: Direct | V54: 7226948 | W54: https://www.google.com/ | X54: 0 | Y54: 0.5 | Z54: 0 | AA54: 0.5 | AB54: 0 | AC54: 0 | AD54: 0 | AE54: 0 | AF54: 0 | AG54: 0 | AH54: 0 | AI54: 0 | AJ54: 0 | AK54: 0 | AL54: 0 | AM54: 0 | AN54: 0 | AO54: 0 | AP54: =1-SUM(X54:AN54) -> 0 | AR54: Construction | AV54: 46024.018 | AW54: 0 | AX54: 0 | AY54: 0 | AZ54: 1 | BA54: 0 | BB54: 0 | BC54: 45993 | BD54: 48 | BE54: Dec | BF54: 2025 | BG54: United States | BH54: =VLOOKUP(B54,CookieClicks!D:O,12,FALSE) -> https://www.method.me/ | BI54: =IFERROR(__xludf.DUMMYFUNCTION("VLOOKUP(REGEXREPLACE(BH54,""[?].*"",""""),ContentBuckets!A:C,2,FALSE)"),"Homepage") -> Homepage | BJ54: =IFERROR(__xludf.DUMMYFUNCTION("VLOOKUP(REGEXREPLACE(BH54,""[?].*"",""""),ContentBuckets!A:C,3,FALSE)"),"Other page") -> Other page
A55: 153178 | B55: westernslopefire | C55: 45993.735 | E55: 45995.601 | F55: TRUE | G55: FALSE | H55: FALSE | I55: FALSE | J55: Monthly | K55: Method:CRM For QBO | L55: QBO | M55: New | N55: 44.25 | O55: 44.25 | P55: 0 | Q55: 0 | R55: 28 | S55: US-3 Month Promo(25% off) | T55: Direct | V55: 7227818 | W55: https://www.google.com/ | X55: 0 | Y55: 1 | Z55: 0 | AA55: 0 | AB55: 0 | AC55: 0 | AD55: 0 | AE55: 0 | AF55: 0 | AG55: 0 | AH55: 0 | AI55: 0 | AJ55: 0 | AK55: 0 | AL55: 0 | AM55: 0 | AN55: 0 | AO55: 0 | AP55: =1-SUM(X55:AN55) -> 0 | AQ55: US | AR55: Field Services | AU55: 45993 | AV55: 46024.041 | AW55: 2 | AX55: 457119 | AY55: 690 | AZ55: 1 | BA55: 0 | BB55: 1 | BC55: 45993 | BD55: 48 | BE55: Dec | BF55: 2025 | BG55: United States | BH55: =VLOOKUP(B55,CookieClicks!D:O,12,FALSE) -> https://www.method.me/ | BI55: =IFERROR(__xludf.DUMMYFUNCTION("VLOOKUP(REGEXREPLACE(BH55,""[?].*"",""""),ContentBuckets!A:C,2,FALSE)"),"Homepage") -> Homepage | BJ55: =IFERROR(__xludf.DUMMYFUNCTION("VLOOKUP(REGEXREPLACE(BH55,""[?].*"",""""),ContentBuckets!A:C,3,FALSE)"),"Other page") -> Other page
A56: 153179 | B56: hybridelectronics5 | C56: 45993.748 | D56: 46014.422 | E56: 45994.663 | F56: FALSE | G56: TRUE | H56: FALSE | I56: FALSE | J56: Monthly | K56: Method:CRM For QBO | L56: QBO | M56: New | N56: 0 | O56: 63.75 | P56: 0 | Q56: 0 | R56: 0 | S56: US-3 Month Promo(25% off) | T56: Direct | V56: 6729572 | X56: 0 | Y56: 0 | Z56: 0 | AA56: 1 | AB56: 0 | AC56: 0 | AD56: 0 | AE56: 0 | AF56: 0 | AG56: 0 | AH56: 0 | AI56: 0 | AJ56: 0 | AK56: 0 | AL56: 0 | AM56: 0 | AN56: 0 | AO56: 0 | AP56: =1-SUM(X56:AN56) -> 0 | AV56: 46014.012 | AW56: 0 | AX56: 0 | AY56: 0 | AZ56: 1 | BA56: 0 | BB56: 0 | BC56: 45993 | BD56: 48 | BE56: Dec | BF56: 2025 | BG56: United States | BH56: =VLOOKUP(B56,CookieClicks!D:O,12,FALSE) -> https://grow.method.me/crm-quickbooks/?trc=81&trk=crm works with quickbooks&trs=USA-QB-G_Ex&campaignid=22265826203&adgroupid=176758613473&adid=734012603510&gad_source=1&gad_campaignid=22265826203&gbraid=0AAAAAD3ItnY8dYj6EgtzuDGCW8YS03VZf&gclid=CjwKCAjwp_LDBhBCEiwAK7FnkurcoCbN_VHZKoD3F3-xeGHISK-ND6ZLXrhGH384yLRCm7EqUXDdVBoCtFYQAvD_BwE | BI56: =IFERROR(__xludf.DUMMYFUNCTION("VLOOKUP(REGEXREPLACE(BH56,""[?].*"",""""),ContentBuckets!A:C,2,FALSE)"),"#N/A") -> #N/A | BJ56: =IFERROR(__xludf.DUMMYFUNCTION("VLOOKUP(REGEXREPLACE(BH56,""[?].*"",""""),ContentBuckets!A:C,3,FALSE)"),"#N/A") -> #N/A
A57: 153180 | B57: threepillarsconsulting | C57: 45993.803 | F57: TRUE | G57: FALSE | H57: FALSE | I57: FALSE | J57: Monthly | K57: Method:CRM For QBO | L57: QBO | M57: New | N57: 0 | O57: 53.25 | P57: 0 | Q57: 0 | R57: 28 | S57: US-3 Month Promo(25% off) | T57: Direct | V57: 7228093 | X57: 0 | Y57: 0 | Z57: 0 | AA57: 1 | AB57: 0 | AC57: 0 | AD57: 0 | AE57: 0 | AF57: 0 | AG57: 0 | AH57: 0 | AI57: 0 | AJ57: 0 | AK57: 0 | AL57: 0 | AM57: 0 | AN57: 0 | AO57: 0 | AP57: =1-SUM(X57:AN57) -> 0 | AQ57: US | AR57: Consulting and Professional Services | AU57: 45993 | AV57: 46024.043 | AW57: 0 | AX57: 0 | AY57: 0 | AZ57: 1 | BA57: 0 | BB57: 0 | BC57: 45993 | BD57: 48 | BE57: Dec | BF57: 2025 | BG57: United States | BH57: =VLOOKUP(B57,CookieClicks!D:O,12,FALSE) -> https://grow.method.me/crm-quickbooks/?trc=81&trk=crm integrates with quickbooks&trs=US-QBInt-Ex&campaignid=22265826203&adgroupid=186545727779&adid=777091446185&gad_source=1&gad_campaignid=22265826203&gbraid=0AAAAAD3Itnam2j5nHWVuXmJuoGB4QHUV1&gclid=Cj0KCQiAubrJBhCbARIsAHIdxD8sT4zpzABpZFGx3n1JzaoHNFaaUsR3ntg8deFRNjmBN_2jm3OixmsaApvvEALw_wcB | BI57: =IFERROR(__xludf.DUMMYFUNCTION("VLOOKUP(REGEXREPLACE(BH57,""[?].*"",""""),ContentBuckets!A:C,2,FALSE)"),"#N/A") -> #N/A | BJ57: =IFERROR(__xludf.DUMMYFUNCTION("VLOOKUP(REGEXREPLACE(BH57,""[?].*"",""""),ContentBuckets!A:C,3,FALSE)"),"#N/A") -> #N/A
A58: 153181 | B58: saniclean2 | C58: 45993.835 | F58: TRUE | G58: FALSE | H58: FALSE | I58: FALSE | J58: Monthly | K58: Method:CRM For QBO | L58: QBO | M58: New | N58: 0 | O58: 53.25 | P58: 0 | Q58: 0 | R58: 28 | S58: US-3 Month Promo(25% off) | T58: Direct | V58: 7228190 | W58: https://www.google.com/ | X58: 0 | Y58: 1 | Z58: 0 | AA58: 0 | AB58: 0 | AC58: 0 | AD58: 0 | AE58: 0 | AF58: 0 | AG58: 0 | AH58: 0 | AI58: 0 | AJ58: 0 | AK58: 0 | AL58: 0 | AM58: 0 | AN58: 0 | AO58: 0 | AP58: =1-SUM(X58:AN58) -> 0 | AQ58: US | AR58: Other | AU58: 45993 | AV58: 46024.039 | AW58: 1 | AX58: 315672.96 | AY58: 67 | AZ58: 1 | BA58: 0 | BB58: 0 | BC58: 45993 | BD58: 48 | BE58: Dec | BF58: 2025 | BG58: United States | BH58: =VLOOKUP(B58,CookieClicks!D:O,12,FALSE) -> https://www.method.me/ | BI58: =IFERROR(__xludf.DUMMYFUNCTION("VLOOKUP(REGEXREPLACE(BH58,""[?].*"",""""),ContentBuckets!A:C,2,FALSE)"),"Homepage") -> Homepage | BJ58: =IFERROR(__xludf.DUMMYFUNCTION("VLOOKUP(REGEXREPLACE(BH58,""[?].*"",""""),ContentBuckets!A:C,3,FALSE)"),"Other page") -> Other page
A59: 153182 | B59: agoradistributioninc | C59: 45993.866 | F59: TRUE | G59: FALSE | H59: FALSE | I59: FALSE | J59: Monthly | K59: Method:CRM For QBO | L59: QBO | M59: New | N59: 0 | O59: 105.75 | P59: 0 | Q59: 0 | R59: 28 | S59: US-3 Month Promo(25% off) | T59: Direct | V59: 7225937 | X59: 1 | Y59: 0 | Z59: 0 | AA59: 0 | AB59: 0 | AC59: 0 | AD59: 0 | AE59: 0 | AF59: 0 | AG59: 0 | AH59: 0 | AI59: 0 | AJ59: 0 | AK59: 0 | AL59: 0 | AM59: 0 | AN59: 0 | AO59: 0 | AP59: =1-SUM(X59:AN59) -> 0 | AQ59: CA | AR59: Manufacturing (MWD) | AT59: Solution Promotionnelle | AU59: 45993 | AV59: 46023.981 | AW59: 15 | AX59: 1404293 | AY59: 1030 | AZ59: 3 | BA59: 0 | BB59: 0 | BC59: 45993 | BD59: 48 | BE59: Dec | BF59: 2025 | BG59: Canada | BH59: =VLOOKUP(B59,CookieClicks!D:O,12,FALSE) -> https://www.method.me/ | BI59: =IFERROR(__xludf.DUMMYFUNCTION("VLOOKUP(REGEXREPLACE(BH59,""[?].*"",""""),ContentBuckets!A:C,2,FALSE)"),"Homepage") -> Homepage | BJ59: =IFERROR(__xludf.DUMMYFUNCTION("VLOOKUP(REGEXREPLACE(BH59,""[?].*"",""""),ContentBuckets!A:C,3,FALSE)"),"Other page") -> Other page
A60: 153183 | B60: joni | C60: 45993.879 | F60: TRUE | G60: FALSE | H60: FALSE | I60: FALSE | J60: Monthly | K60: Method:CRM For QBO | L60: QBO | M60: New | N60: 0 | O60: 44.25 | P60: 0 | Q60: 0 | R60: 0 | S60: US-3 Month Promo(25% off) | T60: Direct | V60: 7228418 | W60: https://www.google.com/ | X60: 0 | Y60: 1 | Z60: 0 | AA60: 0 | AB60: 0 | AC60: 0 | AD60: 0 | AE60: 0 | AF60: 0 | AG60: 0 | AH60: 0 | AI60: 0 | AJ60: 0 | AK60: 0 | AL60: 0 | AM60: 0 | AN60: 0 | AO60: 0 | AP60: =1-SUM(X60:AN60) -> 0 | AV60: 46024.003 | AW60: 0 | AX60: 0 | AY60: 0 | AZ60: 1 | BA60: 0 | BB60: 0 | BC60: 45993 | BD60: 48 | BE60: Dec | BF60: 2025 | BG60: India | BH60: =VLOOKUP(B60,CookieClicks!D:O,12,FALSE) -> https://signin.method.me/ | BI60: =IFERROR(__xludf.DUMMYFUNCTION("VLOOKUP(REGEXREPLACE(BH60,""[?].*"",""""),ContentBuckets!A:C,2,FALSE)"),"#N/A") -> #N/A | BJ60: =IFERROR(__xludf.DUMMYFUNCTION("VLOOKUP(REGEXREPLACE(BH60,""[?].*"",""""),ContentBuckets!A:C,3,FALSE)"),"#N/A") -> #N/A
A61: 153184 | B61: clearwaterpoolcare | C61: 45993.915 | D61: 46008.752 | F61: FALSE | G61: FALSE | H61: FALSE | I61: FALSE | J61: Monthly | K61: Method:CRM for Xero | L61: Xero | M61: New | N61: 0 | O61: 53.25 | P61: 0 | Q61: 0 | R61: 28 | S61: US-3 Month Promo(25% off) | T61: Direct | V61: 7214453 | W61: https://www.google.com/ | X61: 0 | Y61: 1 | Z61: 0 | AA61: 0 | AB61: 0 | AC61: 0 | AD61: 0 | AE61: 0 | AF61: 0 | AG61: 0 | AH61: 0 | AI61: 0 | AJ61: 0 | AK61: 0 | AL61: 0 | AM61: 0 | AN61: 0 | AO61: 0 | AP61: =1-SUM(X61:AN61) -> 0 | AR61: Field Services | AV61: 46007.996 | AW61: 0 | AX61: 0 | AY61: 0 | AZ61: 1 | BA61: 0 | BB61: 0 | BC61: 45993 | BD61: 48 | BE61: Dec | BF61: 2025 | BG61: Australia | BH61: =VLOOKUP(B61,CookieClicks!D:O,12,FALSE) -> https://www.method.me/ | BI61: =IFERROR(__xludf.DUMMYFUNCTION("VLOOKUP(REGEXREPLACE(BH61,""[?].*"",""""),ContentBuckets!A:C,2,FALSE)"),"Homepage") -> Homepage | BJ61: =IFERROR(__xludf.DUMMYFUNCTION("VLOOKUP(REGEXREPLACE(BH61,""[?].*"",""""),ContentBuckets!A:C,3,FALSE)"),"Other page") -> Other page
A62: 153185 | B62: verticalelectric4 | C62: 45993.944 | D62: 46000.501 | F62: FALSE | G62: FALSE | H62: FALSE | I62: FALSE | J62: Monthly | K62: Method:CRM For QBO | L62: QBO | M62: New | N62: 0 | O62: 44.25 | P62: 0 | Q62: 0 | R62: 28 | S62: US-3 Month Promo(25% off) | T62: Direct | V62: 7228602 | W62: https://www.google.com/ | X62: 0 | Y62: 1 | Z62: 0 | AA62: 0 | AB62: 0 | AC62: 0 | AD62: 0 | AE62: 0 | AF62: 0 | AG62: 0 | AH62: 0 | AI62: 0 | AJ62: 0 | AK62: 0 | AL62: 0 | AM62: 0 | AN62: 0 | AO62: 0 | AP62: =1-SUM(X62:AN62) -> 0 | AQ62: US | AR62: Construction | AT62: Electrical contractor | AU62: 45993 | AV62: 46000.047 | AW62: 0 | AX62: 307515.12 | AY62: 1308 | AZ62: 1 | BA62: 0 | BB62: 0 | BC62: 45993 | BD62: 48 | BE62: Dec | BF62: 2025 | BG62: United States | BH62: =VLOOKUP(B62,CookieClicks!D:O,12,FALSE) -> https://www.method.me/ | BI62: =IFERROR(__xludf.DUMMYFUNCTION("VLOOKUP(REGEXREPLACE(BH62,""[?].*"",""""),ContentBuckets!A:C,2,FALSE)"),"Homepage") -> Homepage | BJ62: =IFERROR(__xludf.DUMMYFUNCTION("VLOOKUP(REGEXREPLACE(BH62,""[?].*"",""""),ContentBuckets!A:C,3,FALSE)"),"Other page") -> Other page
A63: 153186 | B63: commercialconsultingservicesllc | C63: 45994.019 | D63: 46023.482 | F63: FALSE | G63: FALSE | H63: FALSE | I63: FALSE | J63: Monthly | K63: Method:CRM For QBO | L63: QBO | M63: New | N63: 0 | O63: 186.75 | P63: 0 | Q63: 0 | R63: 0 | S63: US-3 Month Promo(25% off) | T63: Direct | V63: 7228836 | W63: https://www.bing.com/ | X63: 0 | Y63: 1 | Z63: 0 | AA63: 0 | AB63: 0 | AC63: 0 | AD63: 0 | AE63: 0 | AF63: 0 | AG63: 0 | AH63: 0 | AI63: 0 | AJ63: 0 | AK63: 0 | AL63: 0 | AM63: 0 | AN63: 0 | AO63: 0 | AP63: =1-SUM(X63:AN63) -> 0 | AQ63: US | AU63: 45994 | AV63: 46022.992 | AW63: 1 | AX63: 76824 | AY63: 16 | AZ63: 3 | BA63: 0 | BB63: 0 | BC63: 45994 | BD63: 48 | BE63: Dec | BF63: 2025 | BG63: United States | BH63: =VLOOKUP(B63,CookieClicks!D:O,12,FALSE) -> https://www.method.me/ | BI63: =IFERROR(__xludf.DUMMYFUNCTION("VLOOKUP(REGEXREPLACE(BH63,""[?].*"",""""),ContentBuckets!A:C,2,FALSE)"),"Homepage") -> Homepage | BJ63: =IFERROR(__xludf.DUMMYFUNCTION("VLOOKUP(REGEXREPLACE(BH63,""[?].*"",""""),ContentBuckets!A:C,3,FALSE)"),"Other page") -> Other page
A64: 153187 | B64: tauruscorp | C64: 45994.047 | D64: 46020.431 | F64: FALSE | G64: FALSE | H64: FALSE | I64: FALSE | J64: Monthly | K64: Method:CRM for QBD | L64: QBDT | M64: New | N64: 0 | O64: 53.25 | P64: 0 | Q64: 0 | R64: 28 | S64: US-3 Month Promo(25% off) | T64: Direct | V64: 7228931 | W64: https://www.bing.com/ | X64: 0 | Y64: 1 | Z64: 0 | AA64: 0 | AB64: 0 | AC64: 0 | AD64: 0 | AE64: 0 | AF64: 0 | AG64: 0 | AH64: 0 | AI64: 0 | AJ64: 0 | AK64: 0 | AL64: 0 | AM64: 0 | AN64: 0 | AO64: 0 | AP64: =1-SUM(X64:AN64) -> 0 | AR64: Consulting and Professional Services | AV64: 46020.034 | AW64: 0 | AX64: 0 | AY64: 0 | AZ64: 1 | BA64: 0 | BB64: 0 | BC64: 45994 | BD64: 48 | BE64: Dec | BF64: 2025 | BG64: United Arab Emirates | BH64: =VLOOKUP(B64,CookieClicks!D:O,12,FALSE) -> https://www.method.me/ | BI64: =IFERROR(__xludf.DUMMYFUNCTION("VLOOKUP(REGEXREPLACE(BH64,""[?].*"",""""),ContentBuckets!A:C,2,FALSE)"),"Homepage") -> Homepage | BJ64: =IFERROR(__xludf.DUMMYFUNCTION("VLOOKUP(REGEXREPLACE(BH64,""[?].*"",""""),ContentBuckets!A:C,3,FALSE)"),"Other page") -> Other page
A65: 153188 | B65: nanh | C65: 45994.054 | F65: TRUE | G65: FALSE | H65: FALSE | I65: FALSE | J65: Monthly | K65: Method:CRM for QBD | L65: QBDT | M65: New | N65: 0 | O65: 44.25 | P65: 0 | Q65: 0 | R65: 0 | S65: US-3 Month Promo(25% off) | T65: Direct | V65: 7228947 | W65: https://www.google.com/ | X65: 0 | Y65: 1 | Z65: 0 | AA65: 0 | AB65: 0 | AC65: 0 | AD65: 0 | AE65: 0 | AF65: 0 | AG65: 0 | AH65: 0 | AI65: 0 | AJ65: 0 | AK65: 0 | AL65: 0 | AM65: 0 | AN65: 0 | AO65: 0 | AP65: =1-SUM(X65:AN65) -> 0 | AV65: 46024.02 | AW65: 0 | AX65: 0 | AY65: 0 | AZ65: 1 | BA65: 0 | BB65: 0 | BC65: 45994 | BD65: 48 | BE65: Dec | BF65: 2025 | BG65: Vietnam | BH65: =VLOOKUP(B65,CookieClicks!D:O,12,FALSE) -> https://signin.method.me/ | BI65: =IFERROR(__xludf.DUMMYFUNCTION("VLOOKUP(REGEXREPLACE(BH65,""[?].*"",""""),ContentBuckets!A:C,2,FALSE)"),"#N/A") -> #N/A | BJ65: =IFERROR(__xludf.DUMMYFUNCTION("VLOOKUP(REGEXREPLACE(BH65,""[?].*"",""""),ContentBuckets!A:C,3,FALSE)"),"#N/A") -> #N/A
A66: 153189 | B66: zennohintl | C66: 45994.161 | D66: 46008.829 | F66: FALSE | G66: FALSE | H66: FALSE | I66: FALSE | J66: Monthly | K66: Method:CRM For QBO | L66: QBO | M66: New | N66: 0 | O66: 54.75 | P66: 0 | Q66: 0 | R66: 0 | S66: US-3 Month Promo(25% off) | T66: Direct | V66: 7229263 | X66: 1 | Y66: 0 | Z66: 0 | AA66: 0 | AB66: 0 | AC66: 0 | AD66: 0 | AE66: 0 | AF66: 0 | AG66: 0 | AH66: 0 | AI66: 0 | AJ66: 0 | AK66: 0 | AL66: 0 | AM66: 0 | AN66: 0 | AO66: 0 | AP66: =1-SUM(X66:AN66) -> 0 | AQ66: HK | AU66: 45994 | AV66: 46008.051 | AW66: 0 | AX66: 3298800 | AY66: 448 | AZ66: 1 | BA66: 0 | BB66: 0 | BC66: 45994 | BD66: 48 | BE66: Dec | BF66: 2025 | BG66: Hong Kong | BH66: =VLOOKUP(B66,CookieClicks!D:O,12,FALSE) -> http://signup.method.me/methodcrm/ | BI66: =IFERROR(__xludf.DUMMYFUNCTION("VLOOKUP(REGEXREPLACE(BH66,""[?].*"",""""),ContentBuckets!A:C,2,FALSE)"),"#N/A") -> #N/A | BJ66: =IFERROR(__xludf.DUMMYFUNCTION("VLOOKUP(REGEXREPLACE(BH66,""[?].*"",""""),ContentBuckets!A:C,3,FALSE)"),"#N/A") -> #N/A
A67: 153190 | B67: wasangshow | C67: 45994.24 | F67: TRUE | G67: FALSE | H67: FALSE | I67: FALSE | J67: Monthly | K67: Method:CRM for QBD | L67: QBDT | M67: New | N67: 0 | O67: 44.25 | P67: 0 | Q67: 0 | R67: 0 | S67: US-3 Month Promo(25% off) | T67: Direct | V67: 7229509 | X67: 1 | Y67: 0 | Z67: 0 | AA67: 0 | AB67: 0 | AC67: 0 | AD67: 0 | AE67: 0 | AF67: 0 | AG67: 0 | AH67: 0 | AI67: 0 | AJ67: 0 | AK67: 0 | AL67: 0 | AM67: 0 | AN67: 0 | AO67: 0 | AP67: =1-SUM(X67:AN67) -> 0 | AV67: 46024.041 | AW67: 0 | AX67: 0 | AY67: 0 | AZ67: 1 | BA67: 0 | BB67: 0 | BC67: 45994 | BD67: 48 | BE67: Dec | BF67: 2025 | BG67: Taiwan | BH67: =VLOOKUP(B67,CookieClicks!D:O,12,FALSE) -> https://www.method.me/ | BI67: =IFERROR(__xludf.DUMMYFUNCTION("VLOOKUP(REGEXREPLACE(BH67,""[?].*"",""""),ContentBuckets!A:C,2,FALSE)"),"Homepage") -> Homepage | BJ67: =IFERROR(__xludf.DUMMYFUNCTION("VLOOKUP(REGEXREPLACE(BH67,""[?].*"",""""),ContentBuckets!A:C,3,FALSE)"),"Other page") -> Other page
A68: 153191 | B68: db4 | C68: 45994.287 | F68: TRUE | G68: FALSE | H68: FALSE | I68: FALSE | J68: Monthly | K68: Method:CRM For QBO | L68: QBO | M68: New | N68: 0 | O68: 54.75 | P68: 0 | Q68: 0 | R68: 28 | S68: US-3 Month Promo(25% off) | T68: Direct | V68: 7229653 | X68: 0 | Y68: 0 | Z68: 0 | AA68: 1 | AB68: 0 | AC68: 0 | AD68: 0 | AE68: 0 | AF68: 0 | AG68: 0 | AH68: 0 | AI68: 0 | AJ68: 0 | AK68: 0 | AL68: 0 | AM68: 0 | AN68: 0 | AO68: 0 | AP68: =1-SUM(X68:AN68) -> 0 | AR68: Accounting and Bookkeeping | AV68: 46023.994 | AW68: 0 | AX68: 0 | AY68: 0 | AZ68: 1 | BA68: 0 | BB68: 0 | BC68: 45994 | BD68: 48 | BE68: Dec | BF68: 2025 | BG68: United States | BH68: =VLOOKUP(B68,CookieClicks!D:O,12,FALSE) -> https://grow.method.me/quickbooks-crm-fb/?trc=517&trk=BOF&trs=FB-Lookalike&utm_source=Facebook&utm_medium=PPC&utm_campaign=Banner_trial&utm_id=120213444289450307&utm_content=120215433569050307&utm_term=120215433408020307&fbclid=IwY2xjawOdA8ZleHRuA2FlbQEwAGFkaWQBqykbuk3ag3NydGMGYXBwX2lkEDIyMjAzOTE3ODgyMDA4OTIAAR5hGI96W_1h-NzXKvyCvL68GkcHGJA2cqXPhAZWGhdtTeaKDSdhk36cRrgImg_aem_H2VsKu2fQVsISvAguSn5BA&campaign_id=120213444289450307&ad_id=120215433569050307 | BI68: =IFERROR(__xludf.DUMMYFUNCTION("VLOOKUP(REGEXREPLACE(BH68,""[?].*"",""""),ContentBuckets!A:C,2,FALSE)"),"#N/A") -> #N/A | BJ68: =IFERROR(__xludf.DUMMYFUNCTION("VLOOKUP(REGEXREPLACE(BH68,""[?].*"",""""),ContentBuckets!A:C,3,FALSE)"),"#N/A") -> #N/A
A69: 153192 | B69: bandbshowroom | C69: 45994.31 | E69: 46001.674 | F69: TRUE | G69: FALSE | H69: FALSE | I69: FALSE | J69: Monthly | K69: Method:CRM For QBO | L69: QBO | M69: New | N69: 132.75 | O69: 132.75 | P69: 0 | Q69: 0 | R69: 28 | S69: US-3 Month Promo(25% off) | T69: Direct | V69: 7225658 | X69: 0 | Y69: 0 | Z69: 0 | AA69: 1 | AB69: 0 | AC69: 0 | AD69: 0 | AE69: 0 | AF69: 0 | AG69: 0 | AH69: 0 | AI69: 0 | AJ69: 0 | AK69: 0 | AL69: 0 | AM69: 0 | AN69: 0 | AO69: 0 | AP69: =1-SUM(X69:AN69) -> 0 | AQ69: CA | AR69: Other | AU69: 45994 | AV69: 46023.985 | AW69: 1 | AX69: 1832474.2 | AY69: 177 | AZ69: 3 | BA69: 0 | BB69: 0 | BC69: 45994 | BD69: 48 | BE69: Dec | BF69: 2025 | BG69: Canada | BH69: =VLOOKUP(B69,CookieClicks!D:O,12,FALSE) -> https://grow.method.me/quickbooks-method-cad/?trc=81&trk=crm with quickbooks&trs=CAN-QB-G&campaignid=1543604353&adgroupid=61438895000&adid=704657828091&gad_source=1&gad_campaignid=1543604353&gbraid=0AAAAAD3ItnaMundn4Up-tYMPWfU3dxz9g&gclid=Cj0KCQiAubrJBhCbARIsAHIdxD-glMYsYOyvG25S4CG0ZiIQTwVJ7RjEV29E7JMM3sIvI1E_Ch4_c9kaAswBEALw_wcB | BI69: =IFERROR(__xludf.DUMMYFUNCTION("VLOOKUP(REGEXREPLACE(BH69,""[?].*"",""""),ContentBuckets!A:C,2,FALSE)"),"#N/A") -> #N/A | BJ69: =IFERROR(__xludf.DUMMYFUNCTION("VLOOKUP(REGEXREPLACE(BH69,""[?].*"",""""),ContentBuckets!A:C,3,FALSE)"),"#N/A") -> #N/A
A70: 153193 | B70: medpipe2 | C70: 45994.315 | F70: TRUE | G70: FALSE | H70: FALSE | I70: FALSE | J70: Monthly | K70: Method:CRM for QBD | L70: QBDT | M70: New | N70: 0 | O70: 62.25 | P70: 0 | Q70: 0 | R70: 28 | S70: US-3 Month Promo(25% off) | T70: Direct | V70: 7189860 | W70: https://www.google.com/ | X70: 0 | Y70: 1 | Z70: 0 | AA70: 0 | AB70: 0 | AC70: 0 | AD70: 0 | AE70: 0 | AF70: 0 | AG70: 0 | AH70: 0 | AI70: 0 | AJ70: 0 | AK70: 0 | AL70: 0 | AM70: 0 | AN70: 0 | AO70: 0 | AP70: =1-SUM(X70:AN70) -> 0 | AR70: Other | AV70: 46024.016 | AW70: 0 | AX70: 0 | AY70: 0 | AZ70: 1 | BA70: 0 | BB70: 0 | BC70: 45994 | BD70: 48 | BE70: Dec | BF70: 2025 | BG70: United States | BH70: =VLOOKUP(B70,CookieClicks!D:O,12,FALSE) -> https://www.method.me/contact-us/?trc=180&trk=contact-us&trs=gmb-profile&utm_source=seo&utm_medium=google&utm_campaign=my-business-profile | BI70: =IFERROR(__xludf.DUMMYFUNCTION("VLOOKUP(REGEXREPLACE(BH70,""[?].*"",""""),ContentBuckets!A:C,2,FALSE)"),"Other page") -> Other page | BJ70: =IFERROR(__xludf.DUMMYFUNCTION("VLOOKUP(REGEXREPLACE(BH70,""[?].*"",""""),ContentBuckets!A:C,3,FALSE)"),"Other page") -> Other page
A71: 153196 | B71: up2codesystems | C71: 45994.39 | F71: TRUE | G71: FALSE | H71: FALSE | I71: FALSE | J71: Monthly | K71: Method:CRM For QBO | L71: QBO | M71: New | N71: 0 | O71: 63.75 | P71: 0 | Q71: 0 | R71: 28 | S71: US-3 Month Promo(25% off) | T71: Direct | V71: 7230330 | X71: 1 | Y71: 0 | Z71: 0 | AA71: 0 | AB71: 0 | AC71: 0 | AD71: 0 | AE71: 0 | AF71: 0 | AG71: 0 | AH71: 0 | AI71: 0 | AJ71: 0 | AK71: 0 | AL71: 0 | AM71: 0 | AN71: 0 | AO71: 0 | AP71: =1-SUM(X71:AN71) -> 0 | AQ71: US | AR71: Field Services | AU71: 45994 | AV71: 46024.043 | AW71: 49 | AX71: 12000 | AY71: 676 | AZ71: 1 | BA71: 0 | BB71: 0 | BC71: 45994 | BD71: 48 | BE71: Dec | BF71: 2025 | BG71: United States | BH71: =VLOOKUP(B71,CookieClicks!D:O,12,FALSE) -> https://www.method.me/ | BI71: =IFERROR(__xludf.DUMMYFUNCTION("VLOOKUP(REGEXREPLACE(BH71,""[?].*"",""""),ContentBuckets!A:C,2,FALSE)"),"Homepage") -> Homepage | BJ71: =IFERROR(__xludf.DUMMYFUNCTION("VLOOKUP(REGEXREPLACE(BH71,""[?].*"",""""),ContentBuckets!A:C,3,FALSE)"),"Other page") -> Other page
A72: 153198 | B72: indeed | C72: 45994.404 | F72: TRUE | G72: FALSE | H72: FALSE | I72: FALSE | J72: Monthly | K72: Method:CRM For QBO | L72: QBO | M72: New | N72: 0 | O72: 44.25 | P72: 0 | Q72: 0 | R72: 28 | S72: US-3 Month Promo(25% off) | T72: Direct | V72: 7230452 | X72: 0 | Y72: 0 | Z72: 0 | AA72: 0 | AB72: 0 | AC72: 0 | AD72: 0 | AE72: 0 | AF72: 0 | AG72: 0 | AH72: 0 | AI72: 0 | AJ72: 0 | AK72: 0 | AL72: 0 | AM72: 0 | AN72: 0 | AO72: 0 | AP72: =1-SUM(X72:AN72) -> 1 | AR72: Accounting and Bookkeeping | AV72: 46024.007 | AW72: 0 | AX72: 0 | AY72: 0 | AZ72: 1 | BA72: 0 | BB72: 0 | BC72: 45994 | BD72: 48 | BE72: Dec | BF72: 2025 | BG72: Serbia | BH72: =VLOOKUP(B72,CookieClicks!D:O,12,FALSE) -> http://signup.method.me/methodcrm?_gl=1*a0vgwo*_gcl_au*MTgzNzE4NjA2MS4xNzY0NzcyOTQ1*_ga*MTkyNjc2OTE3MS4xNzY0NzcyOTQ1*_ga_L2HEZNW53E*czE3NjQ3NzI5NDQkbzEkZzAkdDE3NjQ3NzI5NDUkajU5JGwwJGg4NzA4NjEyMDk.&_ga=2.145381616.577777304.1764772945-1926769171.1764772945 | BI72: =IFERROR(__xludf.DUMMYFUNCTION("VLOOKUP(REGEXREPLACE(BH72,""[?].*"",""""),ContentBuckets!A:C,2,FALSE)"),"#N/A") -> #N/A | BJ72: =IFERROR(__xludf.DUMMYFUNCTION("VLOOKUP(REGEXREPLACE(BH72,""[?].*"",""""),ContentBuckets!A:C,3,FALSE)"),"#N/A") -> #N/A
A73: 153199 | B73: remmgroup | C73: 45994.41 | D73: 46008.419 | F73: FALSE | G73: FALSE | H73: FALSE | I73: FALSE | J73: Monthly | K73: Method:CRM For QBO | L73: QBO | M73: New | N73: 0 | O73: 298.5 | P73: 0 | Q73: 0 | R73: 28 | S73: US-3 Month Promo(25% off) | T73: Direct | V73: 7196123 | W73: https://www.google.com/ | X73: 0 | Y73: 1 | Z73: 0 | AA73: 0 | AB73: 0 | AC73: 0 | AD73: 0 | AE73: 0 | AF73: 0 | AG73: 0 | AH73: 0 | AI73: 0 | AJ73: 0 | AK73: 0 | AL73: 0 | AM73: 0 | AN73: 0 | AO73: 0 | AP73: =1-SUM(X73:AN73) -> 0 | AQ73: CA | AR73: Consulting and Professional Services | AT73: Recycling | AU73: 45994 | AV73: 46008.037 | AW73: 0 | AX73: 4173.72 | AY73: 42 | AZ73: 10 | BA73: 0 | BB73: 0 | BC73: 45994 | BD73: 48 | BE73: Dec | BF73: 2025 | BG73: Canada | BH73: =VLOOKUP(B73,CookieClicks!D:O,12,FALSE) -> https://www.method.me/ | BI73: =IFERROR(__xludf.DUMMYFUNCTION("VLOOKUP(REGEXREPLACE(BH73,""[?].*"",""""),ContentBuckets!A:C,2,FALSE)"),"Homepage") -> Homepage | BJ73: =IFERROR(__xludf.DUMMYFUNCTION("VLOOKUP(REGEXREPLACE(BH73,""[?].*"",""""),ContentBuckets!A:C,3,FALSE)"),"Other page") -> Other page
A74: 153202 | B74: redtoothimageryllc | C74: 45994.429 | F74: TRUE | G74: FALSE | H74: FALSE | I74: FALSE | J74: Monthly | K74: Method:CRM For QBO | L74: QBO | M74: New | N74: 0 | O74: 44.25 | P74: 0 | Q74: 0 | R74: 28 | S74: US-3 Month Promo(25% off) | T74: Direct | V74: 7230630 | X74: 0 | Y74: 0 | Z74: 1 | AA74: 0 | AB74: 0 | AC74: 0 | AD74: 0 | AE74: 0 | AF74: 0 | AG74: 0 | AH74: 0 | AI74: 0 | AJ74: 0 | AK74: 0 | AL74: 0 | AM74: 0 | AN74: 0 | AO74: 0 | AP74: =1-SUM(X74:AN74) -> 0 | AQ74: US | AR74: Other | AU74: 45994 | AV74: 46024.022 | AW74: 6 | AX74: 62268 | AY74: 948 | AZ74: 1 | BA74: 0 | BB74: 0 | BC74: 45994 | BD74: 48 | BE74: Dec | BF74: 2025 | BG74: United States | BH74: =VLOOKUP(B74,CookieClicks!D:O,12,FALSE) -> https://signup.method.me/QBOAppstoreSignup?offering=methodcrm | BI74: =IFERROR(__xludf.DUMMYFUNCTION("VLOOKUP(REGEXREPLACE(BH74,""[?].*"",""""),ContentBuckets!A:C,2,FALSE)"),"#N/A") -> #N/A | BJ74: =IFERROR(__xludf.DUMMYFUNCTION("VLOOKUP(REGEXREPLACE(BH74,""[?].*"",""""),ContentBuckets!A:C,3,FALSE)"),"#N/A") -> #N/A
A75: 153203 | B75: emk | C75: 45994.44 | D75: 46015.41 | F75: FALSE | G75: TRUE | H75: FALSE | I75: FALSE | J75: Monthly | K75: Method:CRM | L75: None | M75: New | N75: 0 | O75: 44.25 | P75: 0 | Q75: 0 | R75: 0 | S75: US-3 Month Promo(25% off) | T75: Direct | V75: 7229842 | W75: https://www.google.com/ | X75: 0 | Y75: 1 | Z75: 0 | AA75: 0 | AB75: 0 | AC75: 0 | AD75: 0 | AE75: 0 | AF75: 0 | AG75: 0 | AH75: 0 | AI75: 0 | AJ75: 0 | AK75: 0 | AL75: 0 | AM75: 0 | AN75: 0 | AO75: 0 | AP75: =1-SUM(X75:AN75) -> 0 | AV75: 46014.998 | AW75: 0 | AX75: 0 | AY75: 0 | AZ75: 1 | BA75: 0 | BB75: 0 | BC75: 45994 | BD75: 48 | BE75: Dec | BF75: 2025 | BG75: Morocco | BH75: =VLOOKUP(B75,CookieClicks!D:O,12,FALSE) -> http://signup.method.me/methodcrm | BI75: =IFERROR(__xludf.DUMMYFUNCTION("VLOOKUP(REGEXREPLACE(BH75,""[?].*"",""""),ContentBuckets!A:C,2,FALSE)"),"#N/A") -> #N/A | BJ75: =IFERROR(__xludf.DUMMYFUNCTION("VLOOKUP(REGEXREPLACE(BH75,""[?].*"",""""),ContentBuckets!A:C,3,FALSE)"),"#N/A") -> #N/A
A76: 153205 | B76: dragonpowerpromo | C76: 45994.463 | E76: 46021.764 | F76: TRUE | G76: FALSE | H76: FALSE | I76: FALSE | J76: Monthly | K76: Method:CRM For QBO | L76: QBO | M76: New | N76: 63.75 | O76: 63.75 | P76: 0 | Q76: 0 | R76: 28 | S76: US-3 Month Promo(25% off) | T76: Direct | V76: 7220470 | X76: 0 | Y76: 0 | Z76: 0 | AA76: 1 | AB76: 0 | AC76: 0 | AD76: 0 | AE76: 0 | AF76: 0 | AG76: 0 | AH76: 0 | AI76: 0 | AJ76: 0 | AK76: 0 | AL76: 0 | AM76: 0 | AN76: 0 | AO76: 0 | AP76: =1-SUM(X76:AN76) -> 0 | AQ76: US | AR76: Wholesale and distribution services (MWD) | AU76: 45994 | AV76: 46023.989 | AW76: 0 | AX76: 217711.56 | AY76: 1497 | AZ76: 1 | BA76: 0 | BB76: 0 | BC76: 45994 | BD76: 48 | BE76: Dec | BF76: 2025 | BG76: United States | BH76: =VLOOKUP(B76,CookieClicks!D:O,12,FALSE) -> https://grow.method.me/crm-quickbooks/?trc=81&trk=quickbooks crm&trs=USA-QB-G_Ex&campaignid=22265826203&adgroupid=176758613473&adid=734012603510&gad_source=1&gad_campaignid=22265826203&gbraid=0AAAAAD3ItnbQ-scslMn1OtVxbVSWxN2mJ&gclid=CjwKCAiAlrXJBhBAEiwA-5pgwnLR64YdpwU2sV9YesE_12PLfc5YAT_XruCnd4kJ7DgaBfFYBL8wkxoCFP8QAvD_BwE | BI76: =IFERROR(__xludf.DUMMYFUNCTION("VLOOKUP(REGEXREPLACE(BH76,""[?].*"",""""),ContentBuckets!A:C,2,FALSE)"),"#N/A") -> #N/A | BJ76: =IFERROR(__xludf.DUMMYFUNCTION("VLOOKUP(REGEXREPLACE(BH76,""[?].*"",""""),ContentBuckets!A:C,3,FALSE)"),"#N/A") -> #N/A
A77: 153207 | B77: bluegrasspoolmanagement | C77: 45994.47 | E77: 46008.532 | F77: TRUE | G77: FALSE | H77: FALSE | I77: FALSE | J77: Monthly | K77: Method:CRM For QBO | L77: QBO | M77: New | N77: 44.25 | O77: 44.25 | P77: 0 | Q77: 0 | R77: 28 | S77: US-3 Month Promo(25% off) | T77: Direct | V77: 7230971 | W77: https://www.google.com/ | X77: 0 | Y77: 1 | Z77: 0 | AA77: 0 | AB77: 0 | AC77: 0 | AD77: 0 | AE77: 0 | AF77: 0 | AG77: 0 | AH77: 0 | AI77: 0 | AJ77: 0 | AK77: 0 | AL77: 0 | AM77: 0 | AN77: 0 | AO77: 0 | AP77: =1-SUM(X77:AN77) -> 0 | AQ77: US | AR77: Repair and maintenance | AT77: Pool Management | AU77: 45994 | AV77: 46023.987 | AW77: 0 | AX77: 1135141.4 | AY77: 40 | AZ77: 1 | BA77: 0 | BB77: 2 | BC77: 45994 | BD77: 48 | BE77: Dec | BF77: 2025 | BG77: United States | BH77: =VLOOKUP(B77,CookieClicks!D:O,12,FALSE) -> https://www.method.me/ | BI77: =IFERROR(__xludf.DUMMYFUNCTION("VLOOKUP(REGEXREPLACE(BH77,""[?].*"",""""),ContentBuckets!A:C,2,FALSE)"),"Homepage") -> Homepage | BJ77: =IFERROR(__xludf.DUMMYFUNCTION("VLOOKUP(REGEXREPLACE(BH77,""[?].*"",""""),ContentBuckets!A:C,3,FALSE)"),"Other page") -> Other page
A78: 153209 | B78: cornerstoneirrigationservicesinc | C78: 45994.483 | D78: 46010.666 | F78: FALSE | G78: FALSE | H78: FALSE | I78: FALSE | J78: Monthly | K78: Method:CRM For QBO | L78: QBO | M78: New | N78: 0 | O78: 53.25 | P78: 0 | Q78: 0 | R78: 0 | S78: US-3 Month Promo(25% off) | T78: Direct | V78: 7231141 | X78: 0 | Y78: 0 | Z78: 0 | AA78: 1 | AB78: 0 | AC78: 0 | AD78: 0 | AE78: 0 | AF78: 0 | AG78: 0 | AH78: 0 | AI78: 0 | AJ78: 0 | AK78: 0 | AL78: 0 | AM78: 0 | AN78: 0 | AO78: 0 | AP78: =1-SUM(X78:AN78) -> 0 | AV78: 46009.99 | AW78: 0 | AX78: 0 | AY78: 0 | AZ78: 1 | BA78: 0 | BB78: 0 | BC78: 45994 | BD78: 48 | BE78: Dec | BF78: 2025 | BG78: United States | BH78: =VLOOKUP(B78,CookieClicks!D:O,12,FALSE) -> https://grow.method.me/best-quickbooks-crm/?trc=86&trk=grow.method.me&trs=Bing-PMax&msclkid=06d9e66ac1db136da9858f5aa7a5a1e8&utm_source=bing&utm_medium=cpc&utm_campaign=Bing - PMAX&utm_term=grow.method.me&utm_content=US - retargeting | BI78: =IFERROR(__xludf.DUMMYFUNCTION("VLOOKUP(REGEXREPLACE(BH78,""[?].*"",""""),ContentBuckets!A:C,2,FALSE)"),"#N/A") -> #N/A | BJ78: =IFERROR(__xludf.DUMMYFUNCTION("VLOOKUP(REGEXREPLACE(BH78,""[?].*"",""""),ContentBuckets!A:C,3,FALSE)"),"#N/A") -> #N/A
A79: 153210 | B79: duttonarchitecturepllc | C79: 45994.499 | E79: 46014.467 | F79: TRUE | G79: FALSE | H79: FALSE | I79: FALSE | J79: Monthly | K79: Method:CRM For QBO | L79: QBO | M79: New | N79: 36.75 | O79: 36.75 | P79: 0 | Q79: 0 | R79: 28 | S79: US-3 Month Promo(25% off) | T79: Direct | V79: 7129479 | W79: https://www.google.com/ | X79: 0 | Y79: 1 | Z79: 0 | AA79: 0 | AB79: 0 | AC79: 0 | AD79: 0 | AE79: 0 | AF79: 0 | AG79: 0 | AH79: 0 | AI79: 0 | AJ79: 0 | AK79: 0 | AL79: 0 | AM79: 0 | AN79: 0 | AO79: 0 | AP79: =1-SUM(X79:AN79) -> 0 | AQ79: US | AR79: Consulting and Professional Services | AT79: Architectural services | AU79: 45994 | AV79: 46023.992 | AW79: 15 | AX79: 2658050.6 | AY79: 707 | AZ79: 1 | BA79: 0 | BB79: 0 | BC79: 45994 | BD79: 48 | BE79: Dec | BF79: 2025 | BG79: United States | BH79: =VLOOKUP(B79,CookieClicks!D:O,12,FALSE) -> https://www.method.me/contact-us/?trc=180&trk=contact-us&trs=gmb-profile&utm_source=seo&utm_medium=google&utm_campaign=my-business-profile | BI79: =IFERROR(__xludf.DUMMYFUNCTION("VLOOKUP(REGEXREPLACE(BH79,""[?].*"",""""),ContentBuckets!A:C,2,FALSE)"),"Other page") -> Other page | BJ79: =IFERROR(__xludf.DUMMYFUNCTION("VLOOKUP(REGEXREPLACE(BH79,""[?].*"",""""),ContentBuckets!A:C,3,FALSE)"),"Other page") -> Other page
A80: 153211 | B80: theappliancebarnfl | C80: 45994.499 | F80: TRUE | G80: FALSE | H80: FALSE | I80: FALSE | J80: Monthly | K80: Method:CRM For QBO | L80: QBO | M80: New | N80: 0 | O80: 44.25 | P80: 0 | Q80: 0 | R80: 28 | S80: US-3 Month Promo(25% off) | T80: Direct | V80: 7231310 | W80: https://www.google.com/ | X80: 0 | Y80: 1 | Z80: 0 | AA80: 0 | AB80: 0 | AC80: 0 | AD80: 0 | AE80: 0 | AF80: 0 | AG80: 0 | AH80: 0 | AI80: 0 | AJ80: 0 | AK80: 0 | AL80: 0 | AM80: 0 | AN80: 0 | AO80: 0 | AP80: =1-SUM(X80:AN80) -> 0 | AQ80: US | AR80: Retail | AT80: Household appliance stores | AU80: 45994 | AV80: 46024.043 | AW80: 1 | AX80: 11928 | AY80: 60 | AZ80: 1 | BA80: 0 | BB80: 0 | BC80: 45994 | BD80: 48 | BE80: Dec | BF80: 2025 | BG80: United States | BH80: =VLOOKUP(B80,CookieClicks!D:O,12,FALSE) -> https://www.method.me/ | BI80: =IFERROR(__xludf.DUMMYFUNCTION("VLOOKUP(REGEXREPLACE(BH80,""[?].*"",""""),ContentBuckets!A:C,2,FALSE)"),"Homepage") -> Homepage | BJ80: =IFERROR(__xludf.DUMMYFUNCTION("VLOOKUP(REGEXREPLACE(BH80,""[?].*"",""""),ContentBuckets!A:C,3,FALSE)"),"Other page") -> Other page
A81: 153212 | B81: hudsonrestoration | C81: 45994.515 | F81: TRUE | G81: FALSE | H81: FALSE | I81: FALSE | J81: Monthly | K81: Method:CRM For QBO | L81: QBO | M81: New | N81: 0 | O81: 44.25 | P81: 0 | Q81: 0 | R81: 28 | S81: US-3 Month Promo(25% off) | T81: Direct | V81: 7231451 | W81: https://www.google.com/ | X81: 0 | Y81: 1 | Z81: 0 | AA81: 0 | AB81: 0 | AC81: 0 | AD81: 0 | AE81: 0 | AF81: 0 | AG81: 0 | AH81: 0 | AI81: 0 | AJ81: 0 | AK81: 0 | AL81: 0 | AM81: 0 | AN81: 0 | AO81: 0 | AP81: =1-SUM(X81:AN81) -> 0 | AQ81: CA | AR81: Construction | AU81: 45994 | AV81: 46024.006 | AW81: 19 | AX81: 1259388.6 | AY81: 8100 | AZ81: 1 | BA81: 0 | BB81: 1 | BC81: 45994 | BD81: 48 | BE81: Dec | BF81: 2025 | BG81: Canada | BH81: =VLOOKUP(B81,CookieClicks!D:O,12,FALSE) -> https://www.method.me/ | BI81: =IFERROR(__xludf.DUMMYFUNCTION("VLOOKUP(REGEXREPLACE(BH81,""[?].*"",""""),ContentBuckets!A:C,2,FALSE)"),"Homepage") -> Homepage | BJ81: =IFERROR(__xludf.DUMMYFUNCTION("VLOOKUP(REGEXREPLACE(BH81,""[?].*"",""""),ContentBuckets!A:C,3,FALSE)"),"Other page") -> Other page
A82: 153213 | B82: pacificmicrosystemsllc | C82: 45994.519 | E82: 46001.557 | F82: TRUE | G82: FALSE | H82: FALSE | I82: FALSE | J82: Monthly | K82: Method:CRM For QBO | L82: QBO | M82: New | N82: 63.75 | O82: 63.75 | P82: 775 | Q82: 775 | R82: 28 | S82: US-3 Month Promo(25% off) | T82: Direct | V82: 7231589 | X82: 0 | Y82: 0 | Z82: 0 | AA82: 1 | AB82: 0 | AC82: 0 | AD82: 0 | AE82: 0 | AF82: 0 | AG82: 0 | AH82: 0 | AI82: 0 | AJ82: 0 | AK82: 0 | AL82: 0 | AM82: 0 | AN82: 0 | AO82: 0 | AP82: =1-SUM(X82:AN82) -> 0 | AQ82: US | AR82: Field Services | AU82: 45994 | AV82: 46024.038 | AW82: 3 | AX82: 1269229.7 | AY82: 928 | AZ82: 1 | BA82: 0 | BB82: 8 | BC82: 45994 | BD82: 48 | BE82: Dec | BF82: 2025 | BG82: United States | BH82: =VLOOKUP(B82,CookieClicks!D:O,12,FALSE) -> http://signup.method.me/methodcrm?trc=81&trk=freetrial&trs=G2&utm_source=G2&utm_medium=cpc&utm_campaign=G2-profile | BI82: =IFERROR(__xludf.DUMMYFUNCTION("VLOOKUP(REGEXREPLACE(BH82,""[?].*"",""""),ContentBuckets!A:C,2,FALSE)"),"#N/A") -> #N/A | BJ82: =IFERROR(__xludf.DUMMYFUNCTION("VLOOKUP(REGEXREPLACE(BH82,""[?].*"",""""),ContentBuckets!A:C,3,FALSE)"),"#N/A") -> #N/A
A83: 153214 | B83: bigrodconstruction | C83: 45994.522 | F83: TRUE | G83: FALSE | H83: FALSE | I83: FALSE | J83: Monthly | K83: Method:CRM | L83: None | M83: New | N83: 0 | O83: 44.25 | P83: 0 | Q83: 0 | R83: 0 | S83: US-3 Month Promo(25% off) | T83: Direct | V83: 7231606 | X83: 1 | Y83: 0 | Z83: 0 | AA83: 0 | AB83: 0 | AC83: 0 | AD83: 0 | AE83: 0 | AF83: 0 | AG83: 0 | AH83: 0 | AI83: 0 | AJ83: 0 | AK83: 0 | AL83: 0 | AM83: 0 | AN83: 0 | AO83: 0 | AP83: =1-SUM(X83:AN83) -> 0 | AV83: 46023.988 | AW83: 0 | AX83: 0 | AY83: 0 | AZ83: 1 | BA83: 0 | BB83: 0 | BC83: 45994 | BD83: 48 | BE83: Dec | BF83: 2025 | BG83: Finland | BH83: =VLOOKUP(B83,CookieClicks!D:O,12,FALSE) -> https://www.method.me/ | BI83: =IFERROR(__xludf.DUMMYFUNCTION("VLOOKUP(REGEXREPLACE(BH83,""[?].*"",""""),ContentBuckets!A:C,2,FALSE)"),"Homepage") -> Homepage | BJ83: =IFERROR(__xludf.DUMMYFUNCTION("VLOOKUP(REGEXREPLACE(BH83,""[?].*"",""""),ContentBuckets!A:C,3,FALSE)"),"Other page") -> Other page
A84: 153215 | B84: belangerengineeringcorp | C84: 45994.531 | F84: TRUE | G84: FALSE | H84: FALSE | I84: FALSE | J84: Monthly | K84: Method:CRM For QBO | L84: QBO | M84: New | N84: 0 | O84: 177 | P84: 0 | Q84: 0 | R84: 28 | S84: US-3 Month Promo(25% off) | T84: Direct | V84: 7193888 | W84: https://www.google.com/ | X84: 0 | Y84: 1 | Z84: 0 | AA84: 0 | AB84: 0 | AC84: 0 | AD84: 0 | AE84: 0 | AF84: 0 | AG84: 0 | AH84: 0 | AI84: 0 | AJ84: 0 | AK84: 0 | AL84: 0 | AM84: 0 | AN84: 0 | AO84: 0 | AP84: =1-SUM(X84:AN84) -> 0 | AQ84: CA | AR84: Consulting and Professional Services | AU84: 45994 | AV84: 46023.987 | AW84: 33 | AX84: 0 | AY84: 5770 | AZ84: 4 | BA84: 0 | BB84: 0 | BC84: 45994 | BD84: 48 | BE84: Dec | BF84: 2025 | BG84: Canada | BH84: =VLOOKUP(B84,CookieClicks!D:O,12,FALSE) -> http://signup.method.me/methodcrm | BI84: =IFERROR(__xludf.DUMMYFUNCTION("VLOOKUP(REGEXREPLACE(BH84,""[?].*"",""""),ContentBuckets!A:C,2,FALSE)"),"#N/A") -> #N/A | BJ84: =IFERROR(__xludf.DUMMYFUNCTION("VLOOKUP(REGEXREPLACE(BH84,""[?].*"",""""),ContentBuckets!A:C,3,FALSE)"),"#N/A") -> #N/A
A85: 153216 | B85: completeplumbingservicesinc | C85: 45994.562 | E85: 46002.787 | F85: TRUE | G85: FALSE | H85: FALSE | I85: FALSE | J85: Monthly | K85: Method:CRM For QBO | L85: QBO | M85: New | N85: 88.5 | O85: 88.5 | P85: 0 | Q85: 0 | R85: 28 | S85: US-3 Month Promo(25% off) | T85: Direct | V85: 7231851 | X85: 0 | Y85: 0 | Z85: 0 | AA85: 1 | AB85: 0 | AC85: 0 | AD85: 0 | AE85: 0 | AF85: 0 | AG85: 0 | AH85: 0 | AI85: 0 | AJ85: 0 | AK85: 0 | AL85: 0 | AM85: 0 | AN85: 0 | AO85: 0 | AP85: =1-SUM(X85:AN85) -> 0 | AQ85: US | AR85: Construction | AT85: Plumbing, heating, and air-conditioning contractors | AU85: 45994 | AV85: 46023.993 | AW85: 0 | AX85: 92940 | AY85: 0 | AZ85: 2 | BA85: 0 | BB85: 0 | BC85: 45994 | BD85: 48 | BE85: Dec | BF85: 2025 | BG85: United States | BH85: =VLOOKUP(B85,CookieClicks!D:O,12,FALSE) -> https://www.method.me/quickbooks-crm/?trc=81&trk=&trs=USA-DSA-QB&campaignid=13038312612&adgroupid=128764620688&adid=776781070272&gad_source=1&gad_campaignid=13038312612&gbraid=0AAAAAD3ItnZKpzd3lODAba8pKfFEjv0PS&gclid=CjwKCAiA3L_JBhAlEiwAlcWO586sd9uwlYeuVd1KVMq1XHVUHWwm6OOs-7KHnncKPjvfxDnbUun8hhoCK3AQAvD_BwE | BI85: =IFERROR(__xludf.DUMMYFUNCTION("VLOOKUP(REGEXREPLACE(BH85,""[?].*"",""""),ContentBuckets!A:C,2,FALSE)"),"/crm-quickbooks/") -> /crm-quickbooks/ | BJ85: =IFERROR(__xludf.DUMMYFUNCTION("VLOOKUP(REGEXREPLACE(BH85,""[?].*"",""""),ContentBuckets!A:C,3,FALSE)"),"Other page") -> Other page
A86: 153217 | B86: adoninetworks | C86: 45994.565 | E86: 46008.486 | F86: TRUE | G86: FALSE | H86: FALSE | I86: FALSE | J86: Monthly | K86: Method:CRM For QBO | L86: QBO | M86: New | N86: 44.25 | O86: 44.25 | P86: 0 | Q86: 0 | R86: 28 | S86: US-3 Month Promo(25% off) | T86: Direct | V86: 7156504 | X86: 0 | Y86: 0 | Z86: 0 | AA86: 0 | AB86: 0 | AC86: 1 | AD86: 0 | AE86: 0 | AF86: 0 | AG86: 0 | AH86: 0 | AI86: 0 | AJ86: 0 | AK86: 0 | AL86: 0 | AM86: 0 | AN86: 0 | AO86: 0 | AP86: =1-SUM(X86:AN86) -> 0 | AQ86: US | AR86: IT and computer related | AU86: 45994 | AV86: 46023.981 | AW86: 36 | AX86: 880832.04 | AY86: 383 | AZ86: 1 | BA86: 0 | BB86: 0 | BC86: 45994 | BD86: 48 | BE86: Dec | BF86: 2025 | BG86: United States | BH86: =VLOOKUP(B86,CookieClicks!D:O,12,FALSE) -> https://grow.method.me/black-friday-cyber-monday-2025/?trc=711&trk=1stCTA&trs=Email1&utm_campaign=%5B6733%5D%3A 1 0 Black Friday Promo - Leads&utm_content=Get 25 off when you try Method 👀&utm_medium=email&utm_source=ActiveCampaign&vgo_ee=GNoBeZ5kARjN7xAGDE%2Bf2s86Eg9QQAE%2F3CtjXsGf5xnDFijrT18Dug%3D%3D%3A2ymmcwqtXVxwvFjkq06pmpOm7onfJhbi | BI86: =IFERROR(__xludf.DUMMYFUNCTION("VLOOKUP(REGEXREPLACE(BH86,""[?].*"",""""),ContentBuckets!A:C,2,FALSE)"),"#N/A") -> #N/A | BJ86: =IFERROR(__xludf.DUMMYFUNCTION("VLOOKUP(REGEXREPLACE(BH86,""[?].*"",""""),ContentBuckets!A:C,3,FALSE)"),"#N/A") -> #N/A
A87: 153218 | B87: testorg11 | C87: 45994.585 | F87: TRUE | G87: FALSE | H87: FALSE | I87: FALSE | J87: Monthly | K87: Method:CRM for Xero | L87: Xero | M87: New | N87: 0 | O87: 62.25 | P87: 0 | Q87: 0 | R87: 0 | S87: US-3 Month Promo(25% off) | T87: Direct | V87: 7004999 | X87: 1 | Y87: 0 | Z87: 0 | AA87: 0 | AB87: 0 | AC87: 0 | AD87: 0 | AE87: 0 | AF87: 0 | AG87: 0 | AH87: 0 | AI87: 0 | AJ87: 0 | AK87: 0 | AL87: 0 | AM87: 0 | AN87: 0 | AO87: 0 | AP87: =1-SUM(X87:AN87) -> 0 | AQ87: IN | AU87: 46008 | AV87: 46024.038 | AW87: 0 | AX87: 5130000 | AY87: 0 | AZ87: 1 | BA87: 0 | BB87: 14 | BC87: 45994 | BD87: 48 | BE87: Dec | BF87: 2025 | BG87: India | BH87: =VLOOKUP(B87,CookieClicks!D:O,12,FALSE) -> https://www.method.me/ | BI87: =IFERROR(__xludf.DUMMYFUNCTION("VLOOKUP(REGEXREPLACE(BH87,""[?].*"",""""),ContentBuckets!A:C,2,FALSE)"),"Homepage") -> Homepage | BJ87: =IFERROR(__xludf.DUMMYFUNCTION("VLOOKUP(REGEXREPLACE(BH87,""[?].*"",""""),ContentBuckets!A:C,3,FALSE)"),"Other page") -> Other page
A88: 153219 | B88: yjynjhxfyn | C88: 45994.59 | D88: 45994.624 | F88: FALSE | G88: TRUE | H88: FALSE | I88: FALSE | J88: Monthly | K88: Method:CRM For QBO | L88: QBO | M88: New | N88: 0 | O88: 0 | P88: 0 | Q88: 0 | R88: 0 | S88: US-3 Month Promo(25% off) | T88: Direct | V88: 7232226 | W88: https://www.google.com/ | X88: 0 | Y88: 1 | Z88: 0 | AA88: 0 | AB88: 0 | AC88: 0 | AD88: 0 | AE88: 0 | AF88: 0 | AG88: 0 | AH88: 0 | AI88: 0 | AJ88: 0 | AK88: 0 | AL88: 0 | AM88: 0 | AN88: 0 | AO88: 0 | AP88: =1-SUM(X88:AN88) -> 0 | AW88: 0 | AX88: 0 | AY88: 0 | AZ88: 1 | BA88: 0 | BB88: 0 | BC88: 45994 | BD88: 48 | BE88: Dec | BF88: 2025 | BG88: Algeria | BH88: =VLOOKUP(B88,CookieClicks!D:O,12,FALSE) -> https://www.method.me/features/mobile-app/ | BI88: =IFERROR(__xludf.DUMMYFUNCTION("VLOOKUP(REGEXREPLACE(BH88,""[?].*"",""""),ContentBuckets!A:C,2,FALSE)"),"Features page") -> Features page | BJ88: =IFERROR(__xludf.DUMMYFUNCTION("VLOOKUP(REGEXREPLACE(BH88,""[?].*"",""""),ContentBuckets!A:C,3,FALSE)"),"Other page") -> Other page
A89: 153220 | B89: speedyseweranddrain | C89: 45994.633 | D89: 46000.692 | F89: FALSE | G89: FALSE | H89: FALSE | I89: FALSE | J89: Monthly | K89: Method:CRM for QBD | L89: QBDT | M89: New | N89: 0 | O89: 53.25 | P89: 0 | Q89: 0 | R89: 0 | S89: US-3 Month Promo(25% off) | T89: Direct | V89: 7232539 | W89: https://www.google.com/ | X89: 0 | Y89: 1 | Z89: 0 | AA89: 0 | AB89: 0 | AC89: 0 | AD89: 0 | AE89: 0 | AF89: 0 | AG89: 0 | AH89: 0 | AI89: 0 | AJ89: 0 | AK89: 0 | AL89: 0 | AM89: 0 | AN89: 0 | AO89: 0 | AP89: =1-SUM(X89:AN89) -> 0 | AV89: 46000.028 | AW89: 0 | AX89: 0 | AY89: 0 | AZ89: 1 | BA89: 0 | BB89: 0 | BC89: 45994 | BD89: 48 | BE89: Dec | BF89: 2025 | BG89: United States | BH89: =VLOOKUP(B89,CookieClicks!D:O,12,FALSE) -> https://www.method.me/blog/how-to-build-a-crm-system/ | BI89: =IFERROR(__xludf.DUMMYFUNCTION("VLOOKUP(REGEXREPLACE(BH89,""[?].*"",""""),ContentBuckets!A:C,2,FALSE)"),"CRM") -> CRM | BJ89: =IFERROR(__xludf.DUMMYFUNCTION("VLOOKUP(REGEXREPLACE(BH89,""[?].*"",""""),ContentBuckets!A:C,3,FALSE)"),"Blog") -> Blog
A90: 153221 | B90: marlinzpharma2 | C90: 45994.638 | E90: 46013.499 | F90: TRUE | G90: FALSE | H90: FALSE | I90: FALSE | J90: Monthly | K90: Method:CRM for QBD | L90: QBDT | M90: New | N90: 106.5 | O90: 106.5 | P90: 0 | Q90: 0 | R90: 28 | S90: US-3 Month Promo(25% off) | T90: Direct | V90: 7231212 | X90: 0 | Y90: 0 | Z90: 0 | AA90: 1 | AB90: 0 | AC90: 0 | AD90: 0 | AE90: 0 | AF90: 0 | AG90: 0 | AH90: 0 | AI90: 0 | AJ90: 0 | AK90: 0 | AL90: 0 | AM90: 0 | AN90: 0 | AO90: 0 | AP90: =1-SUM(X90:AN90) -> 0 | AQ90: US | AR90: Other | AT90: WholesaleDistributionandSales | AU90: 45996 | AV90: 46024.019 | AW90: 12 | AX90: 7223409.6 | AY90: 3867 | AZ90: 2 | BA90: 0 | BB90: 6 | BC90: 45994 | BD90: 48 | BE90: Dec | BF90: 2025 | BG90: United States | BH90: =VLOOKUP(B90,CookieClicks!D:O,12,FALSE) -> https://www.method.me/quickbooks-crm/?trc=81&trk=&trs=USA-DSA-QB&campaignid=13038312612&adgroupid=128764620688&adid=776781070272&gad_source=1&gad_campaignid=13038312612&gbraid=0AAAAAD3ItnZKpzd3lODAba8pKfFEjv0PS&gclid=CjwKCAiA3L_JBhAlEiwAlcWO57IzoZ1HEwnwQhVxa17_tNYdp87cXV9u6Sf7d73T_-jvkxRHAKJ4FhoC1sUQAvD_BwE | BI90: =IFERROR(__xludf.DUMMYFUNCTION("VLOOKUP(REGEXREPLACE(BH90,""[?].*"",""""),ContentBuckets!A:C,2,FALSE)"),"/crm-quickbooks/") -> /crm-quickbooks/ | BJ90: =IFERROR(__xludf.DUMMYFUNCTION("VLOOKUP(REGEXREPLACE(BH90,""[?].*"",""""),ContentBuckets!A:C,3,FALSE)"),"Other page") -> Other page
A91: 153222 | B91: intelgest2 | C91: 45994.689 | D91: 45995.393 | F91: FALSE | G91: TRUE | H91: FALSE | I91: FALSE | J91: Monthly | K91: Method:CRM for QBD | L91: QBDT | M91: New | N91: 0 | O91: 44.25 | P91: 0 | Q91: 0 | R91: 28 | S91: US-3 Month Promo(25% off) | T91: Direct | V91: 7197435 | X91: 1 | Y91: 0 | Z91: 0 | AA91: 0 | AB91: 0 | AC91: 0 | AD91: 0 | AE91: 0 | AF91: 0 | AG91: 0 | AH91: 0 | AI91: 0 | AJ91: 0 | AK91: 0 | AL91: 0 | AM91: 0 | AN91: 0 | AO91: 0 | AP91: =1-SUM(X91:AN91) -> 0 | AR91: Field Services | AV91: 45995.004 | AW91: 0 | AX91: 0 | AY91: 0 | AZ91: 1 | BA91: 0 | BB91: 0 | BC91: 45994 | BD91: 48 | BE91: Dec | BF91: 2025 | BG91: Canada | BH91: =VLOOKUP(B91,CookieClicks!D:O,12,FALSE) -> https://www.method.me/ | BI91: =IFERROR(__xludf.DUMMYFUNCTION("VLOOKUP(REGEXREPLACE(BH91,""[?].*"",""""),ContentBuckets!A:C,2,FALSE)"),"Homepage") -> Homepage | BJ91: =IFERROR(__xludf.DUMMYFUNCTION("VLOOKUP(REGEXREPLACE(BH91,""[?].*"",""""),ContentBuckets!A:C,3,FALSE)"),"Other page") -> Other page
A92: 153223 | B92: corpcommunications | C92: 45994.724 | F92: TRUE | G92: FALSE | H92: FALSE | I92: FALSE | J92: Monthly | K92: Method:CRM | L92: QuickBooks | M92: New | N92: 0 | O92: 44.25 | P92: 0 | Q92: 0 | R92: 0 | S92: US-3 Month Promo(25% off) | T92: Direct | V92: 7233303 | W92: https://www.bing.com/ | X92: 0 | Y92: 1 | Z92: 0 | AA92: 0 | AB92: 0 | AC92: 0 | AD92: 0 | AE92: 0 | AF92: 0 | AG92: 0 | AH92: 0 | AI92: 0 | AJ92: 0 | AK92: 0 | AL92: 0 | AM92: 0 | AN92: 0 | AO92: 0 | AP92: =1-SUM(X92:AN92) -> 0 | AV92: 46023.994 | AW92: 0 | AX92: 0 | AY92: 0 | AZ92: 1 | BA92: 0 | BB92: 0 | BC92: 45994 | BD92: 48 | BE92: Dec | BF92: 2025 | BG92: Canada | BH92: =VLOOKUP(B92,CookieClicks!D:O,12,FALSE) -> https://www.method.me/blog/invoice-as-a-contractor/ | BI92: =IFERROR(__xludf.DUMMYFUNCTION("VLOOKUP(REGEXREPLACE(BH92,""[?].*"",""""),ContentBuckets!A:C,2,FALSE)"),"General how-to") -> General how-to | BJ92: =IFERROR(__xludf.DUMMYFUNCTION("VLOOKUP(REGEXREPLACE(BH92,""[?].*"",""""),ContentBuckets!A:C,3,FALSE)"),"Blog") -> Blog
A93: 153224 | B93: jetglowaviation | C93: 45994.855 | D93: 45995.686 | F93: FALSE | G93: FALSE | H93: FALSE | I93: FALSE | J93: Monthly | K93: Method:CRM For QBO | L93: QBO | M93: New | N93: 0 | O93: 62.25 | P93: 0 | Q93: 0 | R93: 28 | S93: US-3 Month Promo(25% off) | T93: Direct | V93: 7183421 | X93: 0 | Y93: 0 | Z93: 0 | AA93: 1 | AB93: 0 | AC93: 0 | AD93: 0 | AE93: 0 | AF93: 0 | AG93: 0 | AH93: 0 | AI93: 0 | AJ93: 0 | AK93: 0 | AL93: 0 | AM93: 0 | AN93: 0 | AO93: 0 | AP93: =1-SUM(X93:AN93) -> 0 | AQ93: US | AR93: Repair and maintenance | AT93: Other support activities for air transportation | AU93: 45994 | AV93: 45995.008 | AW93: 0 | AX93: 60480 | AY93: 3 | AZ93: 1 | BA93: 0 | BB93: 0 | BC93: 45994 | BD93: 48 | BE93: Dec | BF93: 2025 | BG93: United States | BH93: =VLOOKUP(B93,CookieClicks!D:O,12,FALSE) -> https://grow.method.me/direct-su/?trc=81&trk=quickbooks integration apps&trs=US-QBInt-Ex&campaignid=22265826203&adgroupid=186545727779&adid=777003326845&gad_source=1&gad_campaignid=22265826203&gbraid=0AAAAAD3ItnZgDnAgUtllny9Jaz3XIKgWf&gclid=CjwKCAiA24XJBhBXEiwAXElO30FXfKRweD8-jWimcTRSnKQskAm5a_0VOCAEX1Q96IP2isPxgq1iDBoCxusQAvD_BwE | BI93: =IFERROR(__xludf.DUMMYFUNCTION("VLOOKUP(REGEXREPLACE(BH93,""[?].*"",""""),ContentBuckets!A:C,2,FALSE)"),"#N/A") -> #N/A | BJ93: =IFERROR(__xludf.DUMMYFUNCTION("VLOOKUP(REGEXREPLACE(BH93,""[?].*"",""""),ContentBuckets!A:C,3,FALSE)"),"#N/A") -> #N/A
A94: 153225 | B94: bametalgraphics | C94: 45994.879 | D94: 46007.753 | F94: FALSE | G94: FALSE | H94: FALSE | I94: FALSE | J94: Monthly | K94: Method:CRM For QBO | L94: QBO | M94: New | N94: 0 | O94: 255 | P94: 0 | Q94: 0 | R94: 28 | S94: US-3 Month Promo(25% off) | T94: Direct | V94: 7234024 | W94: https://www.google.com/ | X94: 0 | Y94: 1 | Z94: 0 | AA94: 0 | AB94: 0 | AC94: 0 | AD94: 0 | AE94: 0 | AF94: 0 | AG94: 0 | AH94: 0 | AI94: 0 | AJ94: 0 | AK94: 0 | AL94: 0 | AM94: 0 | AN94: 0 | AO94: 0 | AP94: =1-SUM(X94:AN94) -> 0 | AQ94: US | AR94: Retail | AU94: 45994 | AV94: 46006.986 | AW94: 9 | AX94: 710630.4 | AY94: 2176 | AZ94: 4 | BA94: 0 | BB94: 4 | BC94: 45994 | BD94: 48 | BE94: Dec | BF94: 2025 | BG94: United States | BH94: =VLOOKUP(B94,CookieClicks!D:O,12,FALSE) -> https://www.method.me/ | BI94: =IFERROR(__xludf.DUMMYFUNCTION("VLOOKUP(REGEXREPLACE(BH94,""[?].*"",""""),ContentBuckets!A:C,2,FALSE)"),"Homepage") -> Homepage | BJ94: =IFERROR(__xludf.DUMMYFUNCTION("VLOOKUP(REGEXREPLACE(BH94,""[?].*"",""""),ContentBuckets!A:C,3,FALSE)"),"Other page") -> Other page
A95: 153226 | B95: resilientfireprotection | C95: 45995.029 | F95: TRUE | G95: FALSE | H95: FALSE | I95: FALSE | J95: Monthly | K95: Method:FieldServices for QBO | L95: QBO | M95: New | N95: 0 | O95: 53.25 | P95: 0 | Q95: 0 | R95: 28 | S95: US-3 Month Promo(25% off) | T95: Direct | V95: 7234633 | W95: https://www.google.com/ | X95: 0 | Y95: 1 | Z95: 0 | AA95: 0 | AB95: 0 | AC95: 0 | AD95: 0 | AE95: 0 | AF95: 0 | AG95: 0 | AH95: 0 | AI95: 0 | AJ95: 0 | AK95: 0 | AL95: 0 | AM95: 0 | AN95: 0 | AO95: 0 | AP95: =1-SUM(X95:AN95) -> 0 | AQ95: US | AR95: Field Services | AT95: Industrial building construction | AU95: 46012 | AV95: 46024.022 | AW95: 0 | AX95: 0 | AY95: 0 | AZ95: 1 | BA95: 0 | BB95: 0 | BC95: 45995 | BD95: 48 | BE95: Dec | BF95: 2025 | BG95: United States | BH95: =VLOOKUP(B95,CookieClicks!D:O,12,FALSE) -> https://www.method.me/crm-quickbooks/pricing/field-service/ | BI95: =IFERROR(__xludf.DUMMYFUNCTION("VLOOKUP(REGEXREPLACE(BH95,""[?].*"",""""),ContentBuckets!A:C,2,FALSE)"),"/crm-quickbooks/") -> /crm-quickbooks/ | BJ95: =IFERROR(__xludf.DUMMYFUNCTION("VLOOKUP(REGEXREPLACE(BH95,""[?].*"",""""),ContentBuckets!A:C,3,FALSE)"),"Other page") -> Other page
A96: 153227 | B96: httpsu | C96: 45995.248 | D96: 46000.422 | F96: FALSE | G96: TRUE | H96: FALSE | I96: FALSE | J96: Monthly | K96: Method:CRM For QBO | L96: QBO | M96: New | N96: 0 | O96: 44.25 | P96: 0 | Q96: 0 | R96: 28 | S96: US-3 Month Promo(25% off) | T96: Direct | V96: 7235439 | W96: https://www.google.com/ | X96: 0 | Y96: 1 | Z96: 0 | AA96: 0 | AB96: 0 | AC96: 0 | AD96: 0 | AE96: 0 | AF96: 0 | AG96: 0 | AH96: 0 | AI96: 0 | AJ96: 0 | AK96: 0 | AL96: 0 | AM96: 0 | AN96: 0 | AO96: 0 | AP96: =1-SUM(X96:AN96) -> 0 | AR96: Field Services | AV96: 46000.012 | AW96: 0 | AX96: 0 | AY96: 0 | AZ96: 1 | BA96: 0 | BB96: 0 | BC96: 45995 | BD96: 48 | BE96: Dec | BF96: 2025 | BG96: India | BH96: =VLOOKUP(B96,CookieClicks!D:O,12,FALSE) -> https://www.method.me/ | BI96: =IFERROR(__xludf.DUMMYFUNCTION("VLOOKUP(REGEXREPLACE(BH96,""[?].*"",""""),ContentBuckets!A:C,2,FALSE)"),"Homepage") -> Homepage | BJ96: =IFERROR(__xludf.DUMMYFUNCTION("VLOOKUP(REGEXREPLACE(BH96,""[?].*"",""""),ContentBuckets!A:C,3,FALSE)"),"Other page") -> Other page
A97: 153228 | B97: intelgest3 | C97: 45995.314 | F97: TRUE | G97: FALSE | H97: FALSE | I97: FALSE | J97: Monthly | K97: Method:CRM For QBO | L97: QBO | M97: New | N97: 0 | O97: 53.25 | P97: 0 | Q97: 0 | R97: 28 | S97: US-3 Month Promo(25% off) | T97: Direct | V97: 7197435 | X97: 1 | Y97: 0 | Z97: 0 | AA97: 0 | AB97: 0 | AC97: 0 | AD97: 0 | AE97: 0 | AF97: 0 | AG97: 0 | AH97: 0 | AI97: 0 | AJ97: 0 | AK97: 0 | AL97: 0 | AM97: 0 | AN97: 0 | AO97: 0 | AP97: =1-SUM(X97:AN97) -> 0 | AQ97: CA | AR97: Field Services | AT97: Security | AU97: 45995 | AV97: 46024.016 | AW97: 1 | AX97: 473508 | AY97: 11 | AZ97: 1 | BA97: 0 | BB97: 0 | BC97: 45995 | BD97: 48 | BE97: Dec | BF97: 2025 | BG97: Canada | BH97: =VLOOKUP(B97,CookieClicks!D:O,12,FALSE) -> https://www.method.me/ | BI97: =IFERROR(__xludf.DUMMYFUNCTION("VLOOKUP(REGEXREPLACE(BH97,""[?].*"",""""),ContentBuckets!A:C,2,FALSE)"),"Homepage") -> Homepage | BJ97: =IFERROR(__xludf.DUMMYFUNCTION("VLOOKUP(REGEXREPLACE(BH97,""[?].*"",""""),ContentBuckets!A:C,3,FALSE)"),"Other page") -> Other page
A98: 153229 | B98: manexusa3 | C98: 45995.338 | D98: 46000.379 | F98: FALSE | G98: TRUE | H98: FALSE | I98: FALSE | J98: Monthly | K98: Method:CRM for QBD | L98: QBDT | M98: New | N98: 0 | O98: 63.75 | P98: 0 | Q98: 0 | R98: 28 | S98: US-3 Month Promo(25% off) | T98: Direct | V98: 7168930 | X98: 1 | Y98: 0 | Z98: 0 | AA98: 0 | AB98: 0 | AC98: 0 | AD98: 0 | AE98: 0 | AF98: 0 | AG98: 0 | AH98: 0 | AI98: 0 | AJ98: 0 | AK98: 0 | AL98: 0 | AM98: 0 | AN98: 0 | AO98: 0 | AP98: =1-SUM(X98:AN98) -> 0 | AQ98: US | AR98: Manufacturing (MWD) | AT98: Manufacturing | AU98: 45995 | AV98: 46000.018 | AW98: 8 | AX98: 2144783.4 | AY98: 1078 | AZ98: 1 | BA98: 0 | BB98: 0 | BC98: 45995 | BD98: 48 | BE98: Dec | BF98: 2025 | BG98: United States | BH98: =VLOOKUP(B98,CookieClicks!D:O,12,FALSE) -> http://signup.method.me/methodcrm | BI98: =IFERROR(__xludf.DUMMYFUNCTION("VLOOKUP(REGEXREPLACE(BH98,""[?].*"",""""),ContentBuckets!A:C,2,FALSE)"),"#N/A") -> #N/A | BJ98: =IFERROR(__xludf.DUMMYFUNCTION("VLOOKUP(REGEXREPLACE(BH98,""[?].*"",""""),ContentBuckets!A:C,3,FALSE)"),"#N/A") -> #N/A
A99: 153230 | B99: manexusa4 | C99: 45995.35 | D99: 45995.412 | F99: FALSE | G99: TRUE | H99: FALSE | I99: FALSE | J99: Monthly | K99: Method:CRM | L99: QuickBooks | M99: New | N99: 0 | O99: 0 | P99: 0 | Q99: 0 | R99: 28 | S99: US-3 Month Promo(25% off) | T99: Direct | V99: 7168930 | X99: 1 | Y99: 0 | Z99: 0 | AA99: 0 | AB99: 0 | AC99: 0 | AD99: 0 | AE99: 0 | AF99: 0 | AG99: 0 | AH99: 0 | AI99: 0 | AJ99: 0 | AK99: 0 | AL99: 0 | AM99: 0 | AN99: 0 | AO99: 0 | AP99: =1-SUM(X99:AN99) -> 0 | AR99: Manufacturing (MWD) | AW99: 0 | AX99: 0 | AY99: 0 | AZ99: 1 | BA99: 0 | BB99: 0 | BC99: 45995 | BD99: 48 | BE99: Dec | BF99: 2025 | BG99: United States | BH99: =VLOOKUP(B99,CookieClicks!D:O,12,FALSE) -> http://signup.method.me/methodcrm | BI99: =IFERROR(__xludf.DUMMYFUNCTION("VLOOKUP(REGEXREPLACE(BH99,""[?].*"",""""),ContentBuckets!A:C,2,FALSE)"),"#N/A") -> #N/A | BJ99: =IFERROR(__xludf.DUMMYFUNCTION("VLOOKUP(REGEXREPLACE(BH99,""[?].*"",""""),ContentBuckets!A:C,3,FALSE)"),"#N/A") -> #N/A
A100: 153231 | B100: allservicessouthfloridaelevator | C100: 45995.372 | F100: TRUE | G100: FALSE | H100: FALSE | I100: FALSE | J100: Monthly | K100: Method:CRM For QBO | L100: QBO | M100: New | N100: 0 | O100: 127.5 | P100: 0 | Q100: 0 | R100: 0 | S100: US-3 Month Promo(25% off) | T100: Direct | V100: 7120535 | X100: 0 | Y100: 0 | Z100: 0 | AA100: 1 | AB100: 0 | AC100: 0 | AD100: 0 | AE100: 0 | AF100: 0 | AG100: 0 | AH100: 0 | AI100: 0 | AJ100: 0 | AK100: 0 | AL100: 0 | AM100: 0 | AN100: 0 | AO100: 0 | AP100: =1-SUM(X100:AN100) -> 0 | AQ100: US | AU100: 45995 | AV100: 46023.983 | AW100: 15 | AX100: 1435320 | AY100: 245 | AZ100: 2 | BA100: 0 | BB100: 0 | BC100: 45995 | BD100: 48 | BE100: Dec | BF100: 2025 | BG100: United States | BH100: =VLOOKUP(B100,CookieClicks!D:O,12,FALSE) -> https://grow.method.me/direct-su/?trc=81&trk=quickbooks crm integrations&trs=USA-QB-G_Ex&campaignid=22265826203&adgroupid=176758613473&adid=776774035818&gad_source=1&gad_campaignid=22265826203&gbraid=0AAAAAD3Itnb4w7dkGBMCKYB0IWq9_ilk-&gclid=CjwKCAiAt8bIBhBpEiwAzH1w6b2wVMmLrkot6f7wbE-gLM3zhJqxyaiVfdz2k8kGVqyWXddgG5u6cBoCQwoQAvD_BwE | BI100: =IFERROR(__xludf.DUMMYFUNCTION("VLOOKUP(REGEXREPLACE(BH100,""[?].*"",""""),ContentBuckets!A:C,2,FALSE)"),"#N/A") -> #N/A | BJ100: =IFERROR(__xludf.DUMMYFUNCTION("VLOOKUP(REGEXREPLACE(BH100,""[?].*"",""""),ContentBuckets!A:C,3,FALSE)"),"#N/A") -> #N/A
...

Sheet CookieClicks
A1: CookieClickID | B1: CreatedDate | C1: CookieID | D1: CompanyAccount | E1: SignUpDate | F1: AttributionAmount | G1: Cost | H1: CampaignOriginal | I1: SplitOriginal | J1: CampaignAdjusted | K1: CampaignAdjustedType | L1: SplitAdjusted | M1: Keyword | N1: Referrer | O1: URL | P1: BrowserInfo | Q1: IPAddress | R1: IsToBeIgnored | S1: AttributionType | T1: LastAdjusted | U1: Day | V1: Week | W1: Month | X1: Year | Y1: AdjustedByRule | Z1: SyncRegion | AA1: SignUpCountry | AB1: IsConversionExeption | AC1: AppName | AD1: AccountingPlatform
A2: 7989715 | B2: 45991.99 | C2: 7217712 | D2: multdoor | E2: 45991.991 | F2: 1 | G2: 0 | J2: SEO | K2: SEO | L2: Google | M2: DirectSEO | N2: https://www.google.com/ | O2: https://www.method.me/ | P2: Mozilla/5.0 (Macintosh; Intel Mac OS X 10_15_7) AppleWebKit/605.1.15 (KHTML, like Gecko) Version/18.5 Safari/605.1.15 | Q2: 104.28.133.33 | R2: FALSE | S2: U | T2: 45991.992 | U2: 45991 | V2: 47 | W2: Nov | X2: 2025 | Y2: 130-SEO: google (DirectSEO) | Z2: CA | AA2: Canada | AB2: FALSE | AC2: QBO | AD2: New
A3: 7990183 | B3: 45992.128 | C3: 7218180 | D3: alromanimechanicalworkshop6 | E3: 45992.129 | F3: 1 | G3: 0 | J3: SEO | K3: SEO | L3: Google | M3: DirectSEO | N3: https://www.google.com/ | O3: https://www.method.me/ | P3: Mozilla/5.0 (Windows NT 10.0; Win64; x64) AppleWebKit/537.36 (KHTML, like Gecko) Chrome/142.0.0.0 Safari/537.36 | Q3: 188.70.49.221 | R3: FALSE | S3: U | T3: 45992.131 | U3: 45992 | V3: 48 | W3: Dec | X3: 2025 | Y3: 130-SEO: google (DirectSEO) | Z3: KW | AA3: Kuwait | AB3: FALSE | AC3: QBO | AD3: New
A4: 7990312 | B4: 45992.175 | C4: 7218307 | D4: student26 | E4: 45992.176 | F4: 1 | G4: 0 | J4: Other - Generic | K4: Other | M4: DirectSEO | N4: https://claude.ai/ | O4: https://www.method.me/blog/construction-project-success-crm-solution/ | P4: Mozilla/5.0 (Windows NT 10.0; Win64; x64) AppleWebKit/537.36 (KHTML, like Gecko) Chrome/142.0.0.0 Safari/537.36 | Q4: 140.213.148.239 | R4: FALSE | S4: U | T4: 45992.177 | U4: 45992 | V4: 48 | W4: Dec | X4: 2025 | Y4: 500-Other: catch-all remainders (DirectSEO) | AA4: Indonesia | AB4: FALSE | AC4: QuickBooks | AD4: New
A5: 7976046 | B5: 45988.269 | C5: 7204189 | D5: healthcaremaintenanceservices | E5: 45992.326 | F5: 1 | G5: 0 | J5: SEO | K5: SEO | L5: Google | M5: DirectSEO | N5: https://www.google.com/ | O5: https://www.method.me/blog/quickbooks-customer-portal/ | P5: Mozilla/5.0 (Windows NT 10.0; Win64; x64) AppleWebKit/537.36 (KHTML, like Gecko) Chrome/142.0.0.0 Safari/537.36 Edg/142.0.0.0 | Q5: 200.12.168.23 | R5: FALSE | S5: U | T5: 45992.327 | U5: 45988 | V5: 47 | W5: Nov | X5: 2025 | Y5: 130-SEO: google (DirectSEO) | Z5: US | AA5: United States | AB5: FALSE | AC5: QBO | AD5: New
A6: 7943172 | B6: 45981.349 | C6: 7171808 | D6: customoutdoorkitchens | E6: 45992.336 | F6: 1 | G6: 0 | J6: SEO | K6: SEO | L6: Google | M6: DirectSEO | N6: https://www.google.com/ | O6: https://www.method.me/ | P6: Mozilla/5.0 (Windows NT 10.0; Win64; x64) AppleWebKit/537.36 (KHTML, like Gecko) Chrome/142.0.0.0 Safari/537.36 | Q6: 94.140.11.156 | R6: FALSE | S6: U | T6: 45992.338 | U6: 45981 | V6: 46 | W6: Nov | X6: 2025 | Y6: 130-SEO: google (DirectSEO) | Z6: US | AA6: United States | AB6: FALSE | AC6: QBO | AD6: New
A7: 7940245 | B7: 45980.624 | C7: 7168930 | D7: manexusa | E7: 45992.342 | F7: 1 | G7: 0 | J7: Direct | K7: Direct | L7: blank | M7: DirectSEO | O7: http://signup.method.me/methodcrm | P7: Mozilla/5.0 (Windows NT 10.0; Win64; x64) AppleWebKit/537.36 (KHTML, like Gecko) Chrome/142.0.0.0 Safari/537.36 Edg/142.0.0.0 | Q7: 69.202.176.104, 52.9.26.127 | R7: FALSE | S7: U | T7: 46000.338 | U7: 45980 | V7: 46 | W7: Nov | X7: 2025 | Y7: 50-Direct: Referrer Blank (Direct) | AA7: United States | AB7: TRUE | AC7: QuickBooks | AD7: New
A8: 7990876 | B8: 45992.341 | C8: 7218855 | D8: reddoorpestcontrol2 | E8: 45992.347 | F8: 1 | G8: 0 | J8: Direct | K8: Direct | L8: blank | M8: DirectSEO | O8: https://signin.method.me/Password/Reset?rpcode=-nZQ0G03B%2bIuTre9Gdsw3ggkv!rw%3du%3dJPbRgJ7a-UmqVNiskXhWYwfMQB8a5 | P8: Mozilla/5.0 (iPhone; CPU iPhone OS 18_6_2 like Mac OS X) AppleWebKit/605.1.15 (KHTML, like Gecko) CriOS/142.0.7444.148 Mobile/15E148 Safari/604.1 | Q8: 65.24.101.202 | R8: FALSE | S8: U | T8: 45992.348 | U8: 45992 | V8: 48 | W8: Dec | X8: 2025 | Y8: 50-Direct: Referrer Blank (Direct) | Z8: US | AA8: United States | AB8: FALSE | AC8: QBO | AD8: New
A9: 7940245 | B9: 45980.624 | C9: 7168930 | D9: manexusa2 | E9: 45992.362 | F9: 1 | G9: 0 | J9: Direct | K9: Direct | L9: blank | M9: DirectSEO | O9: http://signup.method.me/methodcrm | P9: Mozilla/5.0 (Windows NT 10.0; Win64; x64) AppleWebKit/537.36 (KHTML, like Gecko) Chrome/142.0.0.0 Safari/537.36 Edg/142.0.0.0 | Q9: 69.202.176.104, 52.9.26.127 | R9: FALSE | S9: U | T9: 46000.338 | U9: 45980 | V9: 46 | W9: Nov | X9: 2025 | Y9: 50-Direct: Referrer Blank (Direct) | Z9: US | AA9: United States | AB9: TRUE | AC9: QBDT | AD9: New
A10: 7982156 | B10: 45989.695 | C10: 7210242 | D10: jlbcompanies | E10: 45992.416 | F10: 1 | G10: 0 | J10: SEO | K10: SEO | L10: Google | M10: DirectSEO | N10: https://www.google.com/ | O10: https://www.method.me/ | P10: Mozilla/5.0 (Macintosh; Intel Mac OS X 10_15_7) AppleWebKit/537.36 (KHTML, like Gecko) Chrome/142.0.0.0 Safari/537.36 | Q10: 74.244.21.218 | R10: FALSE | S10: U | T10: 45992.417 | U10: 45989 | V10: 47 | W10: Nov | X10: 2025 | Y10: 130-SEO: google (DirectSEO) | Z10: US | AA10: United States | AB10: FALSE | AC10: QBO | AD10: New
A11: 7962989 | B11: 45985.632 | C11: 7191321 | D11: ssisanitary | E11: 45992.461 | F11: 1 | G11: 0 | J11: SEO | K11: SEO | L11: Google | M11: DirectSEO | N11: https://www.google.com/ | O11: https://www.method.me/ | P11: Mozilla/5.0 (Windows NT 10.0; Win64; x64) AppleWebKit/537.36 (KHTML, like Gecko) Chrome/142.0.0.0 Safari/537.36 | Q11: 66.41.215.134 | R11: FALSE | S11: U | T11: 45992.463 | U11: 45985 | V11: 47 | W11: Nov | X11: 2025 | Y11: 130-SEO: google (DirectSEO) | Z11: US | AA11: United States | AB11: FALSE | AC11: QBO | AD11: New
A12: 7992024 | B12: 45992.474 | C12: 7219935 | D12: highendcompaniesllc | E12: 45992.476 | F12: 1 | G12: 0 | J12: SEO | K12: SEO | L12: Google | M12: DirectSEO | N12: https://www.google.com/ | O12: https://www.method.me/ | P12: Mozilla/5.0 (Macintosh; Intel Mac OS X 10_15_7) AppleWebKit/605.1.15 (KHTML, like Gecko) Version/18.0.1 Safari/605.1.15 | Q12: 70.170.147.21 | R12: FALSE | S12: U | T12: 45992.478 | U12: 45992 | V12: 48 | W12: Dec | X12: 2025 | Y12: 130-SEO: google (DirectSEO) | Z12: US | AA12: United States | AB12: FALSE | AC12: QBO | AD12: New
A13: 7992242 | B13: 45992.497 | C13: 7220141 | D13: jirehtransmissionsllc | E13: 45992.497 | F13: 1 | G13: 0 | H13: Bing | I13: USA-G-QB-Bing | J13: Bing | K13: Pay Per Click | L13: USA-G-QB-Bing | M13: how_to_add_signature_in_quickbooks_online | N13: https://www.bing.com/ | O13: https://grow.method.me/crm-quickbooks/?trc=86&trk=how to add signature in quickbooks online&trs=USA-G-QB-Bing&msclkid=557a0cff02eb14d3c64065d2caeb7896&utm_source=bing&utm_medium=cpc&utm_campaign=US - Generic 2020&utm_term=how to add signature in quickbooks online&utm_content=Generic | P13: Mozilla/5.0 (Windows NT 10.0; Win64; x64) AppleWebKit/537.36 (KHTML, like Gecko) Chrome/138.0.0.0 Safari/537.36 Edg/138.0.0.0 | Q13: 142.79.74.157 | R13: FALSE | S13: U | T13: 45992.499 | U13: 45992 | V13: 48 | W13: Dec | X13: 2025 | Y13: - | Z13: US | AA13: United States | AB13: FALSE | AC13: QBO | AD13: New
A14: 7413817 | B14: 45838.512 | C14: 6659644 | D14: waycosalesinc | E14: 45992.517 | F14: 1 | G14: 0 | H14: AdWords | I14: US-QBInt | J14: AdWords | K14: Pay Per Click | L14: US-QBInt | M14: crm_integrates_with_quickbooks | N14: https://www.google.com/ | O14: https://grow.method.me/crm-quickbooks/?trc=81&trk=crm integrates with quickbooks&trs=US-QBInt&campaignid=1543381580&adgroupid=100383660218&adid=424373886646&gad_source=1&gad_campaignid=1543381580&gclid=Cj0KCQjw64jDBhDXARIsABkk8J7ukkus1kvinzQTfDBa9T3cwLPvsAUFxay55glRRXyqwvQ1Qif88XkaAgwwEALw_wcB | P14: Mozilla/5.0 (Windows NT 10.0; Win64; x64) AppleWebKit/537.36 (KHTML, like Gecko) Chrome/134.0.0.0 Safari/537.36 OPR/119.0.0.0 | Q14: 76.166.152.133 | R14: FALSE | S14: U | T14: 45992.519 | U14: 45838 | V14: 26 | W14: Jun | X14: 2025 | Y14: - | Z14: US | AA14: United States | AB14: FALSE | AC14: QBO | AD14: New
A15: 7992525 | B15: 45992.531 | C15: 7220412 | D15: aeromarinebiotechllc | E15: 45992.532 | F15: 1 | G15: 0 | J15: Intuit App Card Traffic | K15: OPN - Other Peoples Networks | L15: Intuit | M15: DirectSEO | N15: https://appcenter.intuit.com/ | O15: https://signup.method.me/QBOAppstoreSignup?offering=methodcrm | P15: Mozilla/5.0 (Windows NT 10.0; Win64; x64) AppleWebKit/537.36 (KHTML, like Gecko) Chrome/142.0.0.0 Safari/537.36 Edg/142.0.0.0 | Q15: 65.184.140.156 | R15: FALSE | S15: U | T15: 45992.533 | U15: 45992 | V15: 48 | W15: Dec | X15: 2025 | Y15: 179-ReferralLink: intuit (OPN) - App center | Z15: US | AA15: United States | AB15: FALSE | AC15: QBO | AD15: New
A16: 7992707 | B16: 45992.554 | C16: 7220589 | D16: whitingdesignandelectric | E16: 45992.56 | F16: 1 | G16: 0 | H16: AdWords | I16: USA-QB-G_Ex | J16: AdWords | K16: Pay Per Click | L16: USA-QB-G_Ex | M16: quickbooks_crm | N16: https://www.google.com/ | O16: https://grow.method.me/crm-quickbooks/?trc=81&trk=quickbooks crm&trs=USA-QB-G_Ex&campaignid=22265826203&adgroupid=176758613473&adid=734012603510&gad_source=1&gad_campaignid=22265826203&gbraid=0AAAAAD3ItnbQ-scslMn1OtVxbVSWxN2mJ&gclid=CjwKCAiAlrXJBhBAEiwA-5pgwvitKEc_ApMEwccMJJ-0vo8UrY40YDAv2UXM6GNodmORrMYKZy6gOhoC3A0QAvD_BwE | P16: Mozilla/5.0 (Macintosh; Intel Mac OS X 10_15_7) AppleWebKit/537.36 (KHTML, like Gecko) Chrome/142.0.0.0 Safari/537.36 | Q16: 174.162.141.142 | R16: FALSE | S16: U | T16: 45992.561 | U16: 45992 | V16: 48 | W16: Dec | X16: 2025 | Y16: - | AA16: United States | AB16: FALSE | AC16: QBO | AD16: New
A17: 7929360 | B17: 45978.595 | C17: 7158239 | D17: mastercraneandhoist | E17: 45992.584 | F17: 0 | G17: 0 | M17: DirectSEO | N17: https://candhcraneservices.method.me/ | O17: https://signin.method.me/error?errorCode=165&returnUrl=https%3A%2F%2Fcandhcraneservices.method.me%2Fapps%2FDefault.aspx%23%2Ff71e8a16-2653-4e1e-89d3-37753dce28a2 | P17: Mozilla/5.0 (Windows NT 10.0; Win64; x64) AppleWebKit/537.36 (KHTML, like Gecko) Chrome/142.0.0.0 Safari/537.36 Edg/142.0.0.0 | Q17: 139.94.200.69 | R17: TRUE | S17: U | T17: 45992.585 | U17: 45978 | V17: 46 | W17: Nov | X17: 2025 | Y17: 10-Ignore Referrer https method.me | Z17: US | AA17: United States | AB17: FALSE | AC17: QBO | AD17: New
A18: 7992930 | B18: 45992.583 | C18: 7220805 | D18: grety | E18: 45992.584 | F18: 1 | G18: 0 | J18: Direct | K18: Direct | L18: blank | M18: DirectSEO | O18: http://signup.method.me/methodcrm?_gl=1*16dqon3*_gcl_au*NjAzNTg3NTQzLjE3NjQ2MDk3Mjc.*_ga*MjEyOTUxMjU4MC4xNzY0NjA5NzM0*_ga_L2HEZNW53E*czE3NjQ2MDk3MzQkbzEkZzAkdDE3NjQ2MDk3MzUkajU5JGwwJGgxNjczNjM2NjYx&_ga=2.54480033.848033626.1764609734-2129512580.1764609734 | P18: Mozilla/5.0 (Windows NT 10.0; Win64; x64) AppleWebKit/537.36 (KHTML, like Gecko) Chrome/142.0.0.0 Safari/537.36 | Q18: 205.250.238.119, 52.9.26.127 | R18: FALSE | S18: U | T18: 45992.585 | U18: 45992 | V18: 48 | W18: Dec | X18: 2025 | Y18: 50-Direct: Referrer Blank (Direct) | AA18: Canada | AB18: TRUE | AC18: QBDT | AD18: New
A19: 7993203 | B19: 45992.613 | C19: 7221061 | D19: danielaziz | E19: 45992.613 | F19: 1 | G19: 0 | J19: Direct | K19: Direct | L19: blank | M19: DirectSEO | O19: https://signin.method.me/?returnUrl=https%3A%2F%2Fumjca.methodportal.com%2Fapps%2F | P19: Mozilla/5.0 (iPhone; CPU iPhone OS 18_6_2 like Mac OS X) AppleWebKit/605.1.15 (KHTML, like Gecko) Version/18.6 Mobile/15E148 Safari/604.1 | Q19: 100.2.9.141 | R19: FALSE | S19: U | T19: 45992.615 | U19: 45992 | V19: 48 | W19: Dec | X19: 2025 | Y19: 50-Direct: Referrer Blank (Direct) | AA19: United States | AB19: FALSE | AC19: QuickBooks | AD19: New
A20: 7926423 | B20: 45978.134 | C20: 7155332 | D20: knightinsurancesolutions | E20: 45992.629 | F20: 0.4 | G20: 0 | H20: AdWords | I20: US-Multi-entity | J20: AdWords | K20: Pay Per Click | L20: US-Multi-entity | M20: multi-account_crm | N20: https://www.google.com/ | O20: https://grow.method.me/multi-entity/?trc=81&trk=multi-account crm&trs=US-Multi-entity&campaignid=22836319657&adgroupid=183992915458&adid=765768443211&gad_source=1&gad_campaignid=22836319657&gbraid=0AAAAAD3ItnZcCORda2sETHQ4nib78uZ3B&gclid=Cj0KCQiArOvIBhDLARIsAPwJXOaKqhQhO0cz3xMBJwlL3cEyFuApzdc6oy79yWcGj6HiTsVqGqWRzxkaAhctEALw_wcB | P20: Mozilla/5.0 (Macintosh; Intel Mac OS X 10_15_7) AppleWebKit/537.36 (KHTML, like Gecko) Chrome/142.0.0.0 Safari/537.36 | Q20: 107.123.49.25 | R20: FALSE | S20: U | T20: 45992.631 | U20: 45978 | V20: 46 | W20: Nov | X20: 2025 | Y20: - | AA20: United States | AB20: TRUE | AC20: QuickBooks | AD20: New
A21: 7926904 | B21: 45978.292 | C21: 7155332 | D21: knightinsurancesolutions | E21: 45992.629 | F21: 0.2 | G21: 0 | H21: SEO | I21: gmb-profile | J21: SEO | K21: SEO | L21: gmb-profile | M21: contact-us | N21: https://www.google.com/ | O21: https://www.method.me/contact-us/?trc=180&trk=contact-us&trs=gmb-profile&utm_source=seo&utm_medium=google&utm_campaign=my-business-profile | P21: Mozilla/5.0 (Macintosh; Intel Mac OS X 10_15_7) AppleWebKit/537.36 (KHTML, like Gecko) Chrome/142.0.0.0 Safari/537.36 | Q21: 107.123.49.25 | R21: FALSE | S21: U | T21: 45992.631 | U21: 45978 | V21: 46 | W21: Nov | X21: 2025 | Y21: - | AA21: United States | AB21: TRUE | AC21: QuickBooks | AD21: New
A22: 7926905 | B22: 45978.293 | C22: 7155332 | D22: knightinsurancesolutions | E22: 45992.629 | F22: 0.4 | G22: 0 | H22: SEO | I22: gmb-profile | J22: SEO | K22: SEO | L22: gmb-profile | M22: contact-us | N22: https://www.google.com/ | O22: https://www.method.me/contact-us/?trc=180&trk=contact-us&trs=gmb-profile&utm_source=seo&utm_medium=google&utm_campaign=my-business-profile | P22: Mozilla/5.0 (Macintosh; Intel Mac OS X 10_15_7) AppleWebKit/537.36 (KHTML, like Gecko) Chrome/142.0.0.0 Safari/537.36 | Q22: 107.123.49.25 | R22: FALSE | S22: U | T22: 45992.631 | U22: 45978 | V22: 46 | W22: Nov | X22: 2025 | Y22: - | AA22: United States | AB22: TRUE | AC22: QuickBooks | AD22: New
A23: 7993414 | B23: 45992.64 | C23: 7221267 | D23: joeythecoffeeguy | E23: 45992.64 | F23: 1 | G23: 0 | H23: AdWords | I23: US-payment | J23: AdWords | K23: Pay Per Click | L23: US-payment | M23: quickbooks_online_payment_processing | N23: https://www.google.com/ | O23: https://grow.method.me/qb-payment/?trc=81&trk=quickbooks online payment processing&trs=US-payment&campaignid=19733246298&adgroupid=146278163933&adid=649435146420&gad_source=1&gad_campaignid=19733246298&gbraid=0AAAAAD3ItnZi9CFAjVhQFCFOFcYmyOWup&gclid=CjwKCAiAlrXJBhBAEiwA-5pgwvgqW2qm5b78Drd4wf59_QQVxH1WepiBjaJvI-eC_MsZ_LDbnGVEVxoC8okQAvD_BwE | P23: Mozilla/5.0 (Macintosh; Intel Mac OS X 10_15_7) AppleWebKit/537.36 (KHTML, like Gecko) Chrome/142.0.0.0 Safari/537.36 | Q23: 108.30.191.109 | R23: FALSE | S23: U | T23: 45992.642 | U23: 45992 | V23: 48 | W23: Dec | X23: 2025 | Y23: - | Z23: US | AA23: United States | AB23: FALSE | AC23: QBO | AD23: New
A24: 7798735 | B24: 45951.643 | C24: 7034286 | D24: octopusgdn | E24: 45992.687 | F24: 1 | G24: 0 | J24: SEO | K24: SEO | L24: Google | M24: DirectSEO | N24: https://www.google.com/ | O24: https://www.method.me/crm-quickbooks/pricing/ | P24: Mozilla/5.0 (Macintosh; Intel Mac OS X 10_15_7) AppleWebKit/537.36 (KHTML, like Gecko) Chrome/141.0.0.0 Safari/537.36 | Q24: 73.110.192.243 | R24: FALSE | S24: U | T24: 45992.688 | U24: 45951 | V24: 42 | W24: Oct | X24: 2025 | Y24: 130-SEO: google (DirectSEO) | Z24: US | AA24: United States | AB24: FALSE | AC24: QBO | AD24: New
A25: 7776004 | B25: 45946.676 | C25: 7012113 | D25: cravenscoffee | E25: 45992.769 | F25: 0.4 | G25: 0 | J25: SEO | K25: SEO | L25: ChatGPT | M25: DirectSEO | N25: https://chatgpt.com/ | O25: https://www.method.me/ | P25: Mozilla/5.0 (Macintosh; Intel Mac OS X 10_15_7) AppleWebKit/537.36 (KHTML, like Gecko) Chrome/139.0.0.0 Safari/537.36 | Q25: 73.225.249.66 | R25: FALSE | S25: U | T25: 45992.77 | U25: 45946 | V25: 41 | W25: Oct | X25: 2025 | Y25: 194-ChatGPT | Z25: US | AA25: United States | AB25: FALSE | AC25: QBDT | AD25: New
A26: 7906804 | B26: 45973.767 | C26: 7012113 | D26: cravenscoffee | E26: 45992.769 | F26: 0.0182 | G26: 0 | H26: Black Friday Promo 2025 | I26: Email1 | J26: Black Friday Promo 2025 | K26: Email | L26: Email1 | M26: 1stCTA | O26: https://grow.method.me/black-friday-cyber-monday-2025/?trc=711&trk=1stCTA&trs=Email1&utm_campaign=%5B6733%5D%3A 1 0 Black Friday Promo - Leads&utm_content=Get 25 off when you try Method 👀&utm_medium=email&utm_source=ActiveCampaign&vgo_ee=Z0ps0FPGAtFs8OHBt9PXFq5NIxcU2ckrsJ55U2pZESzV%2FXxjB6Q%3D%3Ap4Q%2FALYhLUwI%2FrUkhqoAdhSvhe%2BvXIjN | P26: Mozilla/5.0 (Macintosh; Intel Mac OS X 10_15_7) AppleWebKit/537.36 (KHTML, like Gecko) Chrome/139.0.0.0 Safari/537.36 | Q26: 73.225.249.66 | R26: FALSE | S26: U | T26: 45992.77 | U26: 45973 | V26: 45 | W26: Nov | X26: 2025 | Y26: - | Z26: US | AA26: United States | AB26: FALSE | AC26: QBDT | AD26: New
A27: 7934299 | B27: 45979.486 | C27: 7012113 | D27: cravenscoffee | E27: 45992.769 | F27: 0.0182 | G27: 0 | H27: Black Friday Promo 2025 | I27: Email2 | J27: Black Friday Promo 2025 | K27: Email | L27: Email2 | M27: CTA | O27: https://grow.method.me/black-friday-cyber-monday-2025/?trc=711&trk=CTA&trs=Email2&utm_campaign=%5B6733%5D%3A 2 0 Black Friday Promo - Leads&utm_content=Plan ahead and get 25 off Method⏳&utm_medium=email&utm_source=ActiveCampaign&vgo_ee=vk5aT1LI90B1mzMXZIu%2BWYHi9%2F9iWcf%2Bbs%2FvwFZXJx6MfSoRwms%3D%3Ae7nmmW231fLgmZmblgcOC8TtoljUInFi | P27: Mozilla/5.0 (Macintosh; Intel Mac OS X 10_15_7) AppleWebKit/537.36 (KHTML, like Gecko) Chrome/139.0.0.0 Safari/537.36 | Q27: 73.225.249.66 | R27: FALSE | S27: U | T27: 45992.77 | U27: 45979 | V27: 46 | W27: Nov | X27: 2025 | Y27: - | Z27: US | AA27: United States | AB27: FALSE | AC27: QBDT | AD27: New
A28: 7940650 | B28: 45980.685 | C28: 7012113 | D28: cravenscoffee | E28: 45992.769 | F28: 0.0182 | G28: 0 | H28: Black Friday Promo 2025 | I28: Email2 | J28: Black Friday Promo 2025 | K28: Email | L28: Email2 | M28: CTA | O28: https://grow.method.me/black-friday-cyber-monday-2025/?trc=711&trk=CTA&trs=Email2&utm_campaign=%5B6733%5D%3A 2 0 Black Friday Promo - Leads&utm_content=Plan ahead and get 25 off Method⏳&utm_medium=email&utm_source=ActiveCampaign&vgo_ee=vk5aT1LI90B1mzMXZIu%2BWYHi9%2F9iWcf%2Bbs%2FvwFZXJx6MfSoRwms%3D%3Ae7nmmW231fLgmZmblgcOC8TtoljUInFi | P28: Mozilla/5.0 (Macintosh; Intel Mac OS X 10_15_7) AppleWebKit/537.36 (KHTML, like Gecko) Chrome/139.0.0.0 Safari/537.36 | Q28: 73.225.249.66 | R28: FALSE | S28: U | T28: 45992.77 | U28: 45980 | V28: 46 | W28: Nov | X28: 2025 | Y28: - | Z28: US | AA28: United States | AB28: FALSE | AC28: QBDT | AD28: New
A29: 7943751 | B29: 45981.425 | C29: 7012113 | D29: cravenscoffee | E29: 45992.769 | F29: 0.0182 | G29: 0 | H29: Black Friday Promo 2025 | I29: Email2 | J29: Black Friday Promo 2025 | K29: Email | L29: Email2 | M29: CTA | O29: https://grow.method.me/black-friday-cyber-monday-2025/?trc=711&trk=CTA&trs=Email2&utm_campaign=%5B6733%5D%3A 2 0 Black Friday Promo - Leads&utm_content=Plan ahead and get 25 off Method⏳&utm_medium=email&utm_source=ActiveCampaign&vgo_ee=vk5aT1LI90B1mzMXZIu%2BWYHi9%2F9iWcf%2Bbs%2FvwFZXJx6MfSoRwms%3D%3Ae7nmmW231fLgmZmblgcOC8TtoljUInFi | P29: Mozilla/5.0 (Macintosh; Intel Mac OS X 10_15_7) AppleWebKit/537.36 (KHTML, like Gecko) Chrome/139.0.0.0 Safari/537.36 | Q29: 73.225.249.66 | R29: FALSE | S29: U | T29: 45992.77 | U29: 45981 | V29: 46 | W29: Nov | X29: 2025 | Y29: - | Z29: US | AA29: United States | AB29: FALSE | AC29: QBDT | AD29: New
A30: 7967284 | B30: 45986.561 | C30: 7012113 | D30: cravenscoffee | E30: 45992.769 | F30: 0.0182 | G30: 0 | H30: Black Friday Promo 2025 | I30: Email2 | J30: Black Friday Promo 2025 | K30: Email | L30: Email2 | M30: Banner | O30: https://grow.method.me/black-friday-cyber-monday-2025/?trc=711&trk=Banner&trs=Email2&utm_campaign=%5B6733%5D%3A 2 5 Black Friday Promo - Leads&utm_content=Our Black Friday Sale is HERE - 25 off First 3 Months&utm_medium=email&utm_source=ActiveCampaign&vgo_ee=hVwUn5s3L7Gp1d3V4Jx3NDFIk3TRy0MsLtjL15jSXB2NINOgM%2Fw%3D%3AMT%2FmlrhuFoilZ%2FMWLPtUoBcCec65dQlu | P30: Mozilla/5.0 (Macintosh; Intel Mac OS X 10_15_7) AppleWebKit/537.36 (KHTML, like Gecko) Chrome/142.0.0.0 Safari/537.36 | Q30: 73.225.249.66 | R30: FALSE | S30: U | T30: 45992.77 | U30: 45986 | V30: 47 | W30: Nov | X30: 2025 | Y30: - | Z30: US | AA30: United States | AB30: FALSE | AC30: QBDT | AD30: New
A31: 7971663 | B31: 45987.41 | C31: 7012113 | D31: cravenscoffee | E31: 45992.769 | F31: 0.0182 | G31: 0 | H31: Black Friday Promo 2025 | I31: Email2 | J31: Black Friday Promo 2025 | K31: Email | L31: Email2 | M31: Banner | O31: https://grow.method.me/black-friday-cyber-monday-2025/?trc=711&trk=Banner&trs=Email2&utm_campaign=%5B6733%5D%3A 2 5 Black Friday Promo - Leads&utm_content=Our Black Friday Sale is HERE - 25 off First 3 Months&utm_medium=email&utm_source=ActiveCampaign&vgo_ee=hVwUn5s3L7Gp1d3V4Jx3NDFIk3TRy0MsLtjL15jSXB2NINOgM%2Fw%3D%3AMT%2FmlrhuFoilZ%2FMWLPtUoBcCec65dQlu | P31: Mozilla/5.0 (Macintosh; Intel Mac OS X 10_15_7) AppleWebKit/537.36 (KHTML, like Gecko) Chrome/142.0.0.0 Safari/537.36 | Q31: 108.85.198.23 | R31: FALSE | S31: U | T31: 45992.77 | U31: 45987 | V31: 47 | W31: Nov | X31: 2025 | Y31: - | Z31: US | AA31: United States | AB31: FALSE | AC31: QBDT | AD31: New
A32: 7976608 | B32: 45988.436 | C32: 7012113 | D32: cravenscoffee | E32: 45992.769 | F32: 0.0182 | G32: 0 | H32: Black Friday Promo 2025 | I32: Email2 | J32: Black Friday Promo 2025 | K32: Email | L32: Email2 | M32: Banner | O32: https://grow.method.me/black-friday-cyber-monday-2025/?trc=711&trk=Banner&trs=Email2&utm_campaign=%5B6733%5D%3A 2 5 Black Friday Promo - Leads&utm_content=Our Black Friday Sale is HERE - 25 off First 3 Months&utm_medium=email&utm_source=ActiveCampaign&vgo_ee=hVwUn5s3L7Gp1d3V4Jx3NDFIk3TRy0MsLtjL15jSXB2NINOgM%2Fw%3D%3AMT%2FmlrhuFoilZ%2FMWLPtUoBcCec65dQlu | P32: Mozilla/5.0 (Macintosh; Intel Mac OS X 10_15_7) AppleWebKit/537.36 (KHTML, like Gecko) Chrome/142.0.0.0 Safari/537.36 | Q32: 108.85.198.23 | R32: FALSE | S32: U | T32: 45992.77 | U32: 45988 | V32: 47 | W32: Nov | X32: 2025 | Y32: - | Z32: US | AA32: United States | AB32: FALSE | AC32: QBDT | AD32: New
A33: 7980861 | B33: 45989.423 | C33: 7012113 | D33: cravenscoffee | E33: 45992.769 | F33: 0.0182 | G33: 0 | H33: Black Friday Promo 2025 | I33: Email2 | J33: Black Friday Promo 2025 | K33: Email | L33: Email2 | M33: Banner | O33: https://grow.method.me/black-friday-cyber-monday-2025/?trc=711&trk=Banner&trs=Email2&utm_campaign=%5B6733%5D%3A 2 5 Black Friday Promo - Leads&utm_content=Our Black Friday Sale is HERE - 25 off First 3 Months&utm_medium=email&utm_source=ActiveCampaign&vgo_ee=hVwUn5s3L7Gp1d3V4Jx3NDFIk3TRy0MsLtjL15jSXB2NINOgM%2Fw%3D%3AMT%2FmlrhuFoilZ%2FMWLPtUoBcCec65dQlu | P33: Mozilla/5.0 (Macintosh; Intel Mac OS X 10_15_7) AppleWebKit/537.36 (KHTML, like Gecko) Chrome/142.0.0.0 Safari/537.36 | Q33: 108.85.198.23 | R33: FALSE | S33: U | T33: 45992.77 | U33: 45989 | V33: 47 | W33: Nov | X33: 2025 | Y33: - | Z33: US | AA33: United States | AB33: FALSE | AC33: QBDT | AD33: New
A34: 7987701 | B34: 45991.452 | C34: 7012113 | D34: cravenscoffee | E34: 45992.769 | F34: 0.0182 | G34: 0 | H34: Black Friday Promo 2025 | I34: Email2 | J34: Black Friday Promo 2025 | K34: Email | L34: Email2 | M34: Banner | O34: https://grow.method.me/black-friday-cyber-monday-2025/?trc=711&trk=Banner&trs=Email2&utm_campaign=%5B6733%5D%3A 2 5 Black Friday Promo - Leads&utm_content=Our Black Friday Sale is HERE - 25 off First 3 Months&utm_medium=email&utm_source=ActiveCampaign&vgo_ee=hVwUn5s3L7Gp1d3V4Jx3NDFIk3TRy0MsLtjL15jSXB2NINOgM%2Fw%3D%3AMT%2FmlrhuFoilZ%2FMWLPtUoBcCec65dQlu | P34: Mozilla/5.0 (Macintosh; Intel Mac OS X 10_15_7) AppleWebKit/537.36 (KHTML, like Gecko) Chrome/142.0.0.0 Safari/537.36 | Q34: 73.225.165.140 | R34: FALSE | S34: U | T34: 45992.77 | U34: 45991 | V34: 47 | W34: Nov | X34: 2025 | Y34: - | Z34: US | AA34: United States | AB34: FALSE | AC34: QBDT | AD34: New
A35: 7989280 | B35: 45991.862 | C35: 7012113 | D35: cravenscoffee | E35: 45992.769 | F35: 0.0182 | G35: 0 | H35: Black Friday Promo 2025 | I35: Email2 | J35: Black Friday Promo 2025 | K35: Email | L35: Email2 | M35: Banner | O35: https://grow.method.me/black-friday-cyber-monday-2025/?trc=711&trk=Banner&trs=Email2&utm_campaign=%5B6733%5D%3A 2 5 Black Friday Promo - Leads&utm_content=Our Black Friday Sale is HERE - 25 off First 3 Months&utm_medium=email&utm_source=ActiveCampaign&vgo_ee=hVwUn5s3L7Gp1d3V4Jx3NDFIk3TRy0MsLtjL15jSXB2NINOgM%2Fw%3D%3AMT%2FmlrhuFoilZ%2FMWLPtUoBcCec65dQlu | P35: Mozilla/5.0 (Macintosh; Intel Mac OS X 10_15_7) AppleWebKit/537.36 (KHTML, like Gecko) Chrome/142.0.0.0 Safari/537.36 | Q35: 73.225.165.140 | R35: FALSE | S35: U | T35: 45992.77 | U35: 45991 | V35: 47 | W35: Nov | X35: 2025 | Y35: - | Z35: US | AA35: United States | AB35: FALSE | AC35: QBDT | AD35: New
A36: 7991679 | B36: 45992.44 | C36: 7012113 | D36: cravenscoffee | E36: 45992.769 | F36: 0.0182 | G36: 0 | H36: Black Friday Promo 2025 | I36: Email2 | J36: Black Friday Promo 2025 | K36: Email | L36: Email2 | M36: Banner | O36: https://grow.method.me/black-friday-cyber-monday-2025/?trc=711&trk=Banner&trs=Email2&utm_campaign=%5B6733%5D%3A 2 5 Black Friday Promo - Leads&utm_content=Our Black Friday Sale is HERE - 25 off First 3 Months&utm_medium=email&utm_source=ActiveCampaign&vgo_ee=hVwUn5s3L7Gp1d3V4Jx3NDFIk3TRy0MsLtjL15jSXB2NINOgM%2Fw%3D%3AMT%2FmlrhuFoilZ%2FMWLPtUoBcCec65dQlu | P36: Mozilla/5.0 (Macintosh; Intel Mac OS X 10_15_7) AppleWebKit/537.36 (KHTML, like Gecko) Chrome/142.0.0.0 Safari/537.36 | Q36: 73.225.249.66 | R36: FALSE | S36: U | T36: 45992.77 | U36: 45992 | V36: 48 | W36: Dec | X36: 2025 | Y36: - | Z36: US | AA36: United States | AB36: FALSE | AC36: QBDT | AD36: New
A37: 7994199 | B37: 45992.76 | C37: 7012113 | D37: cravenscoffee | E37: 45992.769 | F37: 0.4 | G37: 0 | H37: Black Friday Promo 2025 | I37: Email2 | J37: Black Friday Promo 2025 | K37: Email | L37: Email2 | M37: Banner | N37: https://grow.method.me/black-friday-cyber-monday-2025/?trc=711&trk=Banner&trs=Email2&utm_campaign=[6733]: 2 5 Black Friday Promo - Leads&utm_content=Our Black Friday Sale is HERE - 25 off First 3 Months&utm_medium=email&utm_source=ActiveCampaign&vgo_ee=hVwUn5s3L7Gp1d3V4Jx3NDFIk3TRy0MsLtjL15jSXB2NINOgM%2Fw%3D:MT%2FmlrhuFoilZ%2FMWLPtUoBcCec65dQlu | O37: http://signup.method.me/methodcrm?trc=711&trk=Banner&trs=Email2&utm_campaign=%5B6733%5D%3A 2 5 Black Friday Promo - Leads&utm_content=Our Black Friday Sale is HERE - 25 off First 3 Months&utm_medium=email&utm_source=ActiveCampaign&vgo_ee=hVwUn5s3L7Gp1d3V4Jx3NDFIk3TRy0MsLtjL15jSXB2NINOgM%2Fw%3D%3AMT%2FmlrhuFoilZ%2FMWLPtUoBcCec65dQlu | P37: Mozilla/5.0 (Macintosh; Intel Mac OS X 10_15_7) AppleWebKit/537.36 (KHTML, like Gecko) Chrome/142.0.0.0 Safari/537.36 | Q37: 73.225.249.66, 52.9.26.127 | R37: FALSE | S37: U | T37: 45992.77 | U37: 45992 | V37: 48 | W37: Dec | X37: 2025 | Y37: - | Z37: US | AA37: United States | AB37: FALSE | AC37: QBDT | AD37: New
A38: 7975016 | B38: 45987.992 | C38: 7203163 | D38: cosmicvisionairesllc | E38: 45992.803 | F38: 0.5 | G38: 0 | J38: SEO | K38: SEO | L38: Google | M38: DirectSEO | N38: https://www.google.com/ | O38: https://www.method.me/ | P38: Mozilla/5.0 (Windows NT 10.0; Win64; x64) AppleWebKit/537.36 (KHTML, like Gecko) Chrome/142.0.0.0 Safari/537.36 Edg/142.0.0.0 | Q38: 104.219.198.108 | R38: FALSE | S38: U | T38: 45992.805 | U38: 45987 | V38: 47 | W38: Nov | X38: 2025 | Y38: 130-SEO: google (DirectSEO) | Z38: US | AA38: United States | AB38: FALSE | AC38: QBO | AD38: New
A39: 7994384 | B39: 45992.803 | C39: 7203163 | D39: cosmicvisionairesllc | E39: 45992.803 | F39: 0.5 | G39: 0 | H39: AdWords | I39: US-QBInt-Ex | J39: AdWords | K39: Pay Per Click | L39: US-QBInt-Ex | M39: integrate_with_quickbooks_desktop | N39: https://www.google.com/ | O39: https://grow.method.me/crm-quickbooks/?trc=81&trk=integrate with quickbooks desktop&trs=US-QBInt-Ex&campaignid=22265826203&adgroupid=186545727779&adid=777091446185&gad_source=1&gad_campaignid=22265826203&gbraid=0AAAAAD3ItnbZS3z8l6nzYVFFMJ1qRT6ol&gclid=CjwKCAiAlrXJBhBAEiwA-5pgwg5H7_tUfZbou9Ws2xcWC0V1Nx5aBgxKaqQPG4rw9C-WDJ7SeUTnuRoCBvkQAvD_BwE | P39: Mozilla/5.0 (Windows NT 10.0; Win64; x64) AppleWebKit/537.36 (KHTML, like Gecko) Chrome/142.0.0.0 Safari/537.36 Edg/142.0.0.0 | Q39: 104.219.198.108 | R39: FALSE | S39: U | T39: 45992.805 | U39: 45992 | V39: 48 | W39: Dec | X39: 2025 | Y39: - | Z39: US | AA39: United States | AB39: FALSE | AC39: QBO | AD39: New
A40: 7994513 | B40: 45992.827 | C40: 7222319 | D40: khshopapp | E40: 45992.827 | F40: 1 | G40: 0 | J40: SEO | K40: SEO | L40: Google | M40: DirectSEO | N40: https://www.google.com/ | O40: http://signup.method.me/donor/ | P40: Mozilla/5.0 (Windows NT 10.0; Win64; x64) AppleWebKit/537.36 (KHTML, like Gecko) Chrome/141.0.0.0 Safari/537.36 | Q40: 162.120.188.234, 52.9.26.127 | R40: FALSE | S40: U | T40: 45992.828 | U40: 45992 | V40: 48 | W40: Dec | X40: 2025 | Y40: 130-SEO: google (DirectSEO) | AA40: Egypt | AB40: FALSE | AC40: QuickBooks | AD40: New
A41: 7994974 | B41: 45992.931 | C41: 7222778 | D41: servicerankprocommateiucwebcompaniesllc | E41: 45992.931 | F41: 0 | G41: 0 | M41: DirectSEO | N41: https://www.method.me/ | O41: http://signup.method.me/methodcrm?_gl=1*35xga*_gcl_au*OTA4NzE2NzI5LjE3NjQ2NDU2NTg.*_ga*MTI1ODgwNDgzOS4xNzY0NjQ1NjU4*_ga_L2HEZNW53E*czE3NjQ2NDU2NTgkbzEkZzAkdDE3NjQ2NDU2NTgkajYwJGwwJGgzNDc2MjkzNDg.&_ga=2.76960469.1538964529.1764645658-1258804839.1764645658 | P41: Mozilla/5.0 (Macintosh; Intel Mac OS X 10_15_7) AppleWebKit/537.36 (KHTML, like Gecko) Chrome/142.0.0.0 Safari/537.36 | Q41: 76.98.201.194, 52.9.26.127 | R41: TRUE | S41: U | T41: 45992.933 | U41: 45992 | V41: 48 | W41: Dec | X41: 2025 | Y41: 10-Ignore Referrer https method.me | Z41: US | AA41: United States | AB41: FALSE | AC41: QBO | AD41: New
A42: 7994876 | B42: 45992.915 | C42: 7222681 | D42: test212 | E42: 45992.956 | F42: 0 | G42: 0 | J42: Direct | K42: Direct | L42: blank | M42: DirectSEO | O42: https://www.method.me/ | P42: Mozilla/5.0 (Windows NT 10.0; Win64; x64) AppleWebKit/537.36 (KHTML, like Gecko) Chrome/142.0.0.0 Safari/537.36 | Q42: 100.14.235.70 | R42: FALSE | S42: U | T42: 45992.958 | U42: 45992 | V42: 48 | W42: Dec | X42: 2025 | Y42: 50-Direct: Referrer Blank (Direct) | Z42: US | AA42: United States | AB42: FALSE | AC42: QBDT | AD42: New
A43: 7995088 | B43: 45992.953 | C43: 7222681 | D43: test212 | E43: 45992.956 | F43: 1 | G43: 0 | H43: Black Friday Promo 2025 | I43: Email3 | J43: Black Friday Promo 2025 | K43: Email | L43: Email3 | M43: CTA | O43: https://grow.method.me/black-friday-cyber-monday-2025/?trc=711&trk=CTA&trs=Email3&utm_campaign=%5B6733%5D%3A 3 0 Black Friday Promo - Leads&utm_content=Cyber Day Sale🚨25 off with Method&utm_medium=email&utm_source=ActiveCampaign&vgo_ee=9DHzJExT2v2%2B1fvKVqgmBPyk2%2BvHpawFSje428pKXH2lllbfzV4%3D%3ATDPn6K9B6n1q%2FPnYBJI%2F4Nae7Op30XVj | P43: Mozilla/5.0 (Windows NT 10.0; Win64; x64) AppleWebKit/537.36 (KHTML, like Gecko) Chrome/142.0.0.0 Safari/537.36 | Q43: 100.14.235.70 | R43: FALSE | S43: U | T43: 45992.958 | U43: 45992 | V43: 48 | W43: Dec | X43: 2025 | Y43: - | Z43: US | AA43: United States | AB43: FALSE | AC43: QBDT | AD43: New
A44: 7995109 | B44: 45992.957 | C44: 7222912 | D44: butleragway | E44: 45992.958 | F44: 1 | G44: 0 | H44: AdWords | I44: PMax-FS | J44: AdWords | K44: Pay Per Click | L44: PMax-FS | M44: PMax | N44: https://syndicatedsearch.goog/ | O44: https://www.method.me/?trc=81&trk=PMax&trs=PMax-FS&campaignid=21074820200&adgroupid&adid&gad_source=5&gad_campaignid=21077580125 | P44: Mozilla/5.0 (Linux; Android 16; SM-S166V Build/BP2A.250605.031.A3; wv) AppleWebKit/537.36 (KHTML, like Gecko) Version/4.0 Chrome/142.0.0.0 Mobile Safari/537.36 [FB_IAB/FB4A;FBAV/540.0.0.49.148;IABMV/1;] | Q44: 66.26.67.225 | R44: FALSE | S44: U | T44: 45992.959 | U44: 45992 | V44: 48 | W44: Dec | X44: 2025 | Y44: - | AA44: United States | AB44: FALSE | AC44: None | AD44: New
A45: 7995172 | B45: 45992.97 | C45: 7222975 | D45: westernheatingandairllc | E45: 45992.972 | F45: 1 | G45: 0 | J45: Direct | K45: Direct | L45: blank | M45: DirectSEO | O45: http://signup.method.me/methodcrm/ | P45: Mozilla/5.0 (iPhone; CPU iPhone OS 17_6_1 like Mac OS X) AppleWebKit/605.1.15 (KHTML, like Gecko) Version/17.6 Mobile/15E148 Safari/604.1 | Q45: 204.153.3.52, 52.9.26.127 | R45: FALSE | S45: U | T45: 45992.974 | U45: 45992 | V45: 48 | W45: Dec | X45: 2025 | Y45: 50-Direct: Referrer Blank (Direct) | Z45: US | AA45: United States | AB45: FALSE | AC45: QBO | AD45: New
A46: 7995446 | B46: 45993.034 | C46: 7223248 | D46: makeready | E46: 45993.035 | F46: 1 | G46: 0 | H46: Bing | I46: USA-G-QB-Bing | J46: Bing | K46: Pay Per Click | L46: USA-G-QB-Bing | M46: quickbook_estimate | N46: https://www.bing.com/ | O46: https://grow.method.me/crm-quickbooks/?trc=86&trk=quickbook estimate&trs=USA-G-QB-Bing&msclkid=9d5a77cb2b2b167e1c921ee5569f174b&utm_source=bing&utm_medium=cpc&utm_campaign=US - Generic 2020&utm_term=quickbook estimate&utm_content=Generic | P46: Mozilla/5.0 (Windows NT 10.0; Win64; x64) AppleWebKit/537.36 (KHTML, like Gecko) Chrome/142.0.0.0 Safari/537.36 Edg/142.0.0.0 | Q46: 71.205.40.179 | R46: FALSE | S46: U | T46: 45993.036 | U46: 45993 | V46: 48 | W46: Dec | X46: 2025 | Y46: - | AA46: United States | AB46: FALSE | AC46: QBO | AD46: New
A47: 7996743 | B47: 45993.297 | C47: 7224530 | D47: cloudheroes2 | E47: 45993.297 | F47: 1 | G47: 0 | J47: SEO | K47: SEO | L47: Google | M47: DirectSEO | N47: https://www.google.com/ | O47: https://www.method.me/ | P47: Mozilla/5.0 (Macintosh; Intel Mac OS X 10_15_7) AppleWebKit/537.36 (KHTML, like Gecko) Chrome/142.0.0.0 Safari/537.36 | Q47: 212.113.204.34 | R47: FALSE | S47: U | T47: 45993.298 | U47: 45993 | V47: 48 | W47: Dec | X47: 2025 | Y47: 130-SEO: google (DirectSEO) | Z47: GB | AA47: United Kingdom | AB47: FALSE | AC47: QBO | AD47: New
A48: 7996783 | B48: 45993.306 | C48: 7224570 | D48: umjca2 | E48: 45993.306 | F48: 1 | G48: 0 | J48: Direct | K48: Direct | L48: blank | M48: DirectSEO | O48: https://signin.method.me/?returnUrl=https%3A%2F%2Fumjca.methodportal.com%2Fapps%2F | P48: Mozilla/5.0 (iPhone; CPU iPhone OS 18_7 like Mac OS X) AppleWebKit/605.1.15 (KHTML, like Gecko) Version/26.1 Mobile/15E148 Safari/604.1 | Q48: 108.46.49.34 | R48: FALSE | S48: U | T48: 45993.307 | U48: 45993 | V48: 48 | W48: Dec | X48: 2025 | Y48: 50-Direct: Referrer Blank (Direct) | AA48: United States | AB48: FALSE | AC48: QBO | AD48: New
A49: 7996907 | B49: 45993.334 | C49: 7224692 | D49: fetzerfinancial8 | E49: 45993.333 | F49: 1 | G49: 0 | J49: Intuit App Card Traffic | K49: OPN - Other Peoples Networks | L49: Intuit | M49: DirectSEO | N49: https://appcenter.intuit.com/ | O49: https://signup.method.me/QBOAppstoreSignup?offering=methodcrm | P49: Mozilla/5.0 (Windows NT 10.0; Win64; x64) AppleWebKit/537.36 (KHTML, like Gecko) Chrome/142.0.0.0 Safari/537.36 | Q49: 50.243.171.77 | R49: FALSE | S49: U | T49: 45993.335 | U49: 45993 | V49: 48 | W49: Dec | X49: 2025 | Y49: 179-ReferralLink: intuit (OPN) - App center | Z49: US | AA49: United States | AB49: FALSE | AC49: QBO | AD49: New
A50: 7919003 | B50: 45975.689 | C50: 7148020 | D50: platinumplaygrounds | E50: 45993.335 | F50: 1 | G50: 0 | J50: Direct | K50: Direct | L50: blank | M50: DirectSEO | O50: https://www.method.me/industries/field-service-management-software/?utm_source=chatgpt.com | P50: Mozilla/5.0 (Macintosh; Intel Mac OS X 10_15_7) AppleWebKit/537.36 (KHTML, like Gecko) Chrome/141.0.0.0 Safari/537.36 | Q50: 76.183.149.90 | R50: FALSE | S50: U | T50: 45993.336 | U50: 45975 | V50: 45 | W50: Nov | X50: 2025 | Y50: 50-Direct: Referrer Blank (Direct) | Z50: US | AA50: United States | AB50: FALSE | AC50: QBO | AD50: New
A51: 7997021 | B51: 45993.358 | C51: 7224805 | D51: rvrepairnearmellc | E51: 45993.36 | F51: 1 | G51: 0 | H51: AdWords | I51: US-WorkOrder | J51: AdWords | K51: Pay Per Click | L51: US-WorkOrder | M51: quickbooks_work_order_management | N51: https://www.google.com/ | O51: https://grow.method.me/quickbooks-fsm/?trc=81&trk=quickbooks work order management&trs=US-WorkOrder&campaignid=12406628869&adgroupid=118144098877&adid=500417359916&gad_source=1&gad_campaignid=12406628869&gbraid=0AAAAAD3Itnbb-v0p7Dw7Bhdk7OpsQaId8&gclid=Cj0KCQiAubrJBhCbARIsAHIdxD9PhuzgzFx4d3Oeatq_oulj9ZdbZgTzuwu80IJCqEK0UFsHKWmAAL4aAnntEALw_wcB | P51: Mozilla/5.0 (Windows NT 10.0; Win64; x64) AppleWebKit/537.36 (KHTML, like Gecko) Chrome/142.0.0.0 Safari/537.36 | Q51: 104.193.160.11 | R51: FALSE | S51: U | T51: 45993.361 | U51: 45993 | V51: 48 | W51: Dec | X51: 2025 | Y51: - | AA51: United States | AB51: FALSE | AC51: QBDT | AD51: New
A52: 7997649 | B52: 45993.44 | C52: 7225423 | D52: individual6 | E52: 45993.44 | F52: 1 | G52: 0 | H52: AdWords | I52: USA-QB-G_Ex | J52: AdWords | K52: Pay Per Click | L52: USA-QB-G_Ex | M52: quickbooks_crm | N52: https://www.google.com/ | O52: https://grow.method.me/crm-quickbooks/?trc=81&trk=quickbooks crm&trs=USA-QB-G_Ex&campaignid=22265826203&adgroupid=176758613473&adid=734012603510&gad_source=1&gad_campaignid=22265826203&gbraid=0AAAAAD3ItnbZS3z8l6nzYVFFMJ1qRT6ol&gclid=Cj0KCQiAubrJBhCbARIsAHIdxD91Aj2WQqPOZpBBh09mY5kWzXBsLLrHYQVGPGApxr6fWSq1XW-0KsgaAk0GEALw_wcB | P52: Mozilla/5.0 (Windows NT 10.0; Win64; x64) AppleWebKit/537.36 (KHTML, like Gecko) Chrome/142.0.0.0 Safari/537.36 | Q52: 40.134.88.182 | R52: FALSE | S52: U | T52: 45993.442 | U52: 45993 | V52: 48 | W52: Dec | X52: 2025 | Y52: - | Z52: US | AA52: United States | AB52: FALSE | AC52: QBO | AD52: New
A53: 7997679 | B53: 45993.442 | C53: 7225452 | D53: thenesthomeimprovementcentreinc | E53: 45993.447 | F53: 1 | G53: 0 | J53: SEO | K53: SEO | L53: Google | M53: DirectSEO | N53: https://www.google.com/ | O53: https://www.method.me/ | P53: Mozilla/5.0 (Windows NT 10.0; Win64; x64) AppleWebKit/537.36 (KHTML, like Gecko) Chrome/142.0.0.0 Safari/537.36 | Q53: 70.51.164.183 | R53: FALSE | S53: U | T53: 45993.448 | U53: 45993 | V53: 48 | W53: Dec | X53: 2025 | Y53: 130-SEO: google (DirectSEO) | Z53: CA | AA53: Canada | AB53: FALSE | AC53: QBO | AD53: New
A54: 7997779 | B54: 45993.454 | C54: 7225548 | D54: garcyusa | E54: 45993.463 | F54: 1 | G54: 0 | J54: SEO | K54: SEO | L54: Google | M54: DirectSEO | N54: https://www.google.com/ | O54: https://www.method.me/ | P54: Mozilla/5.0 (Windows NT 10.0; Win64; x64) AppleWebKit/537.36 (KHTML, like Gecko) Chrome/142.0.0.0 Safari/537.36 | Q54: 12.21.105.202 | R54: FALSE | S54: U | T54: 45993.465 | U54: 45993 | V54: 48 | W54: Dec | X54: 2025 | Y54: 130-SEO: google (DirectSEO) | Z54: US | AA54: United States | AB54: FALSE | AC54: QBDT | AD54: New
A55: 7996938 | B55: 45993.341 | C55: 7224722 | D55: vandalenindustries | E55: 45993.469 | F55: 1 | G55: 0 | H55: AdWords | I55: USA-QB-G_Ex | J55: AdWords | K55: Pay Per Click | L55: USA-QB-G_Ex | M55: quickbooks_crm | N55: https://www.google.com/ | O55: https://grow.method.me/crm-quickbooks/?trc=81&trk=quickbooks crm&trs=USA-QB-G_Ex&campaignid=22265826203&adgroupid=176758613473&adid=734012603510&gad_source=1&gad_campaignid=22265826203&gbraid=0AAAAAD3ItnbZS3z8l6nzYVFFMJ1qRT6ol&gclid=Cj0KCQiAubrJBhCbARIsAHIdxD9TJfHqIbvGNWgRIlJBUeVw2pz6Co67n1sZyTh7dICR2olwrmUWYYYaAty5EALw_wcB | P55: Mozilla/5.0 (Windows NT 10.0; Win64; x64) AppleWebKit/537.36 (KHTML, like Gecko) Chrome/142.0.0.0 Safari/537.36 | Q55: 97.210.22.226 | R55: FALSE | S55: U | T55: 45993.47 | U55: 45993 | V55: 48 | W55: Dec | X55: 2025 | Y55: - | Z55: US | AA55: United States | AB55: FALSE | AC55: QBDT | AD55: New
A56: 7997946 | B56: 45993.474 | C56: 7225705 | D56: pizzahurt | E56: 45993.474 | F56: 1 | G56: 0 | H56: Capterra | I56: Capterra_destinationURL | J56: Capterra | K56: Pay Per Click | L56: Capterra_destinationURL | M56: capterra | N56: https://www.capterra.com/ | O56: https://grow.method.me/crm-quickbooks/?trk=capterra&trc=78&trs=Capterra_destinationURL&utm_source=capterra&utm_medium=cpc&utm_campaign=destinationURL&gdmcid=c29c73e3-2013-4457-9593-8e7a2867d847 | P56: Mozilla/5.0 (Windows NT 10.0; Win64; x64) AppleWebKit/537.36 (KHTML, like Gecko) Chrome/142.0.0.0 Safari/537.36 Edg/142.0.0.0 | Q56: 216.213.195.61 | R56: FALSE | S56: U | T56: 45993.476 | U56: 45993 | V56: 48 | W56: Dec | X56: 2025 | Y56: - | AA56: United States | AB56: FALSE | AC56: QuickBooks | AD56: New
A57: 7939341 | B57: 45980.512 | C57: 7168038 | D57: sbc2 | E57: 45993.484 | F57: 1 | G57: 0 | J57: SEO | K57: SEO | L57: Google | M57: DirectSEO | N57: https://www.google.com/ | O57: https://www.method.me/ | P57: Mozilla/5.0 (Macintosh; Intel Mac OS X 10_15_7) AppleWebKit/537.36 (KHTML, like Gecko) Chrome/141.0.0.0 Safari/537.36 | Q57: 130.15.33.200 | R57: FALSE | S57: U | T57: 45993.485 | U57: 45980 | V57: 46 | W57: Nov | X57: 2025 | Y57: 130-SEO: google (DirectSEO) | AA57: Canada | AB57: FALSE | AC57: QBO | AD57: New
A58: 7997825 | B58: 45993.46 | C58: 7225592 | D58: ashram | E58: 45993.491 | F58: 1 | G58: 0 | J58: SEO | K58: SEO | L58: Google | M58: DirectSEO | N58: https://www.google.com/ | O58: https://www.method.me/ | P58: Mozilla/5.0 (Windows NT 10.0; Win64; x64; rv:145.0) Gecko/20100101 Firefox/145.0 | Q58: 42.110.173.75 | R58: FALSE | S58: U | T58: 45993.492 | U58: 45993 | V58: 48 | W58: Dec | X58: 2025 | Y58: 130-SEO: google (DirectSEO) | AA58: India | AB58: FALSE | AC58: Xero | AD58: New
A59: 7998208 | B59: 45993.505 | C59: 7225967 | D59: gestioncobe | E59: 45993.504 | F59: 1 | G59: 0 | J59: Intuit App Card Traffic | K59: OPN - Other Peoples Networks | L59: Intuit | M59: DirectSEO | N59: https://appcenter.intuit.com/ | O59: https://signup.method.me/QBOAppstoreSignup?offering=methodcrm | P59: Mozilla/5.0 (Windows NT 10.0; Win64; x64) AppleWebKit/537.36 (KHTML, like Gecko) Chrome/142.0.0.0 Safari/537.36 | Q59: 24.122.128.241 | R59: FALSE | S59: U | T59: 45993.506 | U59: 45993 | V59: 48 | W59: Dec | X59: 2025 | Y59: 179-ReferralLink: intuit (OPN) - App center | Z59: CA | AA59: Canada | AB59: FALSE | AC59: QBO | AD59: New
A60: 7998387 | B60: 45993.527 | C60: 7226145 | D60: cotektheamericas | E60: 45993.528 | F60: 1 | G60: 0 | J60: SEO | K60: SEO | L60: Google | M60: DirectSEO | N60: https://www.google.com/ | O60: https://www.method.me/ | P60: Mozilla/5.0 (Windows NT 10.0; Win64; x64) AppleWebKit/537.36 (KHTML, like Gecko) Chrome/142.0.0.0 Safari/537.36 | Q60: 207.102.105.104 | R60: FALSE | S60: U | T60: 45993.529 | U60: 45993 | V60: 48 | W60: Dec | X60: 2025 | Y60: 130-SEO: google (DirectSEO) | Z60: CA | AA60: Canada | AB60: FALSE | AC60: QBO | AD60: New
A61: 7798272 | B61: 45951.603 | C61: 7033836 | D61: brontebaycpaprofessionalcorporation2 | E61: 45993.537 | F61: 0.4 | G61: 0 | J61: SEO | K61: SEO | L61: Google | M61: DirectSEO | N61: https://www.google.com/ | O61: https://www.method.me/crm-quickbooks/pricing/ | P61: Mozilla/5.0 (Windows NT 10.0; Win64; x64) AppleWebKit/537.36 (KHTML, like Gecko) Chrome/141.0.0.0 Safari/537.36 | Q61: 64.180.251.212 | R61: FALSE | S61: U | T61: 45993.539 | U61: 45951 | V61: 42 | W61: Oct | X61: 2025 | Y61: 130-SEO: google (DirectSEO) | Z61: CA | AA61: Canada | AB61: FALSE | AC61: QBO | AD61: New
A62: 7906291 | B62: 45973.692 | C62: 7033836 | D62: brontebaycpaprofessionalcorporation2 | E62: 45993.537 | F62: 0.05 | G62: 0 | H62: Black Friday Promo 2025 | I62: Email1 | J62: Black Friday Promo 2025 | K62: Email | L62: Email1 | M62: 1stCTA | O62: https://grow.method.me/black-friday-cyber-monday-2025/?trc=711&trk=1stCTA&trs=Email1&utm_campaign=%5B6733%5D%3A 1 0 Black Friday Promo - Leads&utm_content=Get 25 off when you try Method 👀&utm_medium=email&utm_source=ActiveCampaign&vgo_ee=gxt4z3o9pqZEg%2BIRMqgChfnzMnF21ZGi%2F6DRsGdfHGPs81A2fg%3D%3D%3ApUCm0ECfZZsqtJneIsnk9OFfEZ98T0Fq | P62: Mozilla/5.0 (Windows NT 10.0; Win64; x64) AppleWebKit/537.36 (KHTML, like Gecko) Chrome/142.0.0.0 Safari/537.36 | Q62: 64.180.251.212 | R62: FALSE | S62: U | T62: 45993.539 | U62: 45973 | V62: 45 | W62: Nov | X62: 2025 | Y62: - | Z62: CA | AA62: Canada | AB62: FALSE | AC62: QBO | AD62: New
A63: 7936434 | B63: 45979.785 | C63: 7033836 | D63: brontebaycpaprofessionalcorporation2 | E63: 45993.537 | F63: 0.05 | G63: 0 | H63: Black Friday Promo 2025 | I63: Email2 | J63: Black Friday Promo 2025 | K63: Email | L63: Email2 | M63: CTA | O63: https://grow.method.me/black-friday-cyber-monday-2025/?trc=711&trk=CTA&trs=Email2&utm_campaign=%5B6733%5D%3A 2 0 Black Friday Promo - Leads&utm_content=Plan ahead and get 25 off Method⏳&utm_medium=email&utm_source=ActiveCampaign&vgo_ee=%2BBHYfDULsEzC0PyInKFQms9g%2FnC2w9PPnsetVzaqvdazsP%2FGSw%3D%3D%3Aao%2B7qsSeem0PlSdj3jJB4FliIdk52cou | P63: Mozilla/5.0 (Windows NT 10.0; Win64; x64) AppleWebKit/537.36 (KHTML, like Gecko) Chrome/142.0.0.0 Safari/537.36 | Q63: 64.180.251.212 | R63: FALSE | S63: U | T63: 45993.539 | U63: 45979 | V63: 46 | W63: Nov | X63: 2025 | Y63: - | Z63: CA | AA63: Canada | AB63: FALSE | AC63: QBO | AD63: New
A64: 7967168 | B64: 45986.546 | C64: 7033836 | D64: brontebaycpaprofessionalcorporation2 | E64: 45993.537 | F64: 0.05 | G64: 0 | H64: Black Friday Promo 2025 | I64: Email2 | J64: Black Friday Promo 2025 | K64: Email | L64: Email2 | M64: CTA | O64: https://grow.method.me/black-friday-cyber-monday-2025/?trc=711&trk=CTA&trs=Email2&utm_campaign=%5B6733%5D%3A 2 5 Black Friday Promo - Leads&utm_content=Our Black Friday Sale is HERE - 25 off First 3 Months&utm_medium=email&utm_source=ActiveCampaign&vgo_ee=PQnjYH%2Bw0pQfypkJL9MipMYi9EbG37nRZnaCAirLf9o7VVZI5Q%3D%3D%3A%2B%2FxGO1t9%2BY68Ps%2BfRG94qGDBip6Xu5b4 | P64: Mozilla/5.0 (Windows NT 10.0; Win64; x64) AppleWebKit/537.36 (KHTML, like Gecko) Chrome/143.0.0.0 Safari/537.36 | Q64: 64.180.251.212 | R64: FALSE | S64: U | T64: 45993.539 | U64: 45986 | V64: 47 | W64: Nov | X64: 2025 | Y64: - | Z64: CA | AA64: Canada | AB64: FALSE | AC64: QBO | AD64: New
A65: 7991812 | B65: 45992.455 | C65: 7033836 | D65: brontebaycpaprofessionalcorporation2 | E65: 45993.537 | F65: 0.05 | G65: 0 | H65: Newsletter | I65: customization-awards | J65: Newsletter | K65: Content | L65: customization-awards | M65: DirectSEO | O65: https://grow.method.me/2025-customization-awards-register/?trc=699&&trs=customization-awards&utm_source=ActiveCampaign&utm_medium=email&utm_content=📆 Best Method CRM customizations of 2025 %28Webinar%29&utm_campaign=Customization Awards - Email %231 %28Copy%29&vgo_ee=KW%2F%2Byyk%2Bqpqsz46SHqydUN918uLSZ7FIaqKEGEEvFu5Pxg%3D%3D%3AM4f8C6WOYMl4Yo593bil9CsIW6N8px3W | P65: Mozilla/5.0 (Windows NT 10.0; Win64; x64) AppleWebKit/537.36 (KHTML, like Gecko) Chrome/143.0.0.0 Safari/537.36 | Q65: 64.180.251.212 | R65: FALSE | S65: U | T65: 45993.539 | U65: 45992 | V65: 48 | W65: Dec | X65: 2025 | Y65: - | Z65: CA | AA65: Canada | AB65: FALSE | AC65: QBO | AD65: New
A66: 7991824 | B66: 45992.456 | C66: 7033836 | D66: brontebaycpaprofessionalcorporation2 | E66: 45993.537 | F66: 0.4 | G66: 0 | H66: Newsletter | I66: customization-awards | J66: Newsletter | K66: Content | L66: customization-awards | M66: DirectSEO | N66: https://grow.method.me/2025-customization-awards-register/?trc=699&&trs=customization-awards&utm_source=ActiveCampaign&utm_medium=email&utm_content=%F0%9F%93%86%20Best%20Method%20CRM%20customizations%20of%202025%20%28Webinar%29&utm_campaign=Customization%20Awards%20-%20Email%20%231%20%28Copy%29&vgo_ee=KW%2F%2Byyk%2Bqpqsz46SHqydUN918uLSZ7FIaqKEGEEvFu5Pxg%3D%3D%3AM4f8C6WOYMl4Yo593bil9CsIW6N8px3W | O66: https://grow.method.me/2025-customization-awards-confirmation/?first_name=Subhash&last_name=Sharma&work_email=info%40brontebay.com&country=Canada&accounting_software=Xero&phone_number=4163158635&utm_source=ActiveCampaign&utm_medium=email&utm_campaign=Customization Awards - Email %231 (Copy)&trc=699&trs=customization-awards | P66: Mozilla/5.0 (Windows NT 10.0; Win64; x64) AppleWebKit/537.36 (KHTML, like Gecko) Chrome/143.0.0.0 Safari/537.36 | Q66: 64.180.251.212 | R66: FALSE | S66: U | T66: 45993.539 | U66: 45992 | V66: 48 | W66: Dec | X66: 2025 | Y66: - | Z66: CA | AA66: Canada | AB66: FALSE | AC66: QBO | AD66: New
A67: 7943045 | B67: 45981.319 | C67: 7171683 | D67: growtrax2 | E67: 45993.539 | F67: 1 | G67: 0 | J67: SEO | K67: SEO | L67: Google | M67: DirectSEO | N67: https://www.google.com/ | O67: https://www.method.me/crm-quickbooks/integrations/ | P67: Mozilla/5.0 (Macintosh; Intel Mac OS X 10_15_7) AppleWebKit/537.36 (KHTML, like Gecko) Chrome/141.0.0.0 Safari/537.36 | Q67: 83.77.122.88 | R67: FALSE | S67: U | T67: 45993.54 | U67: 45981 | V67: 46 | W67: Nov | X67: 2025 | Y67: 130-SEO: google (DirectSEO) | AA67: Switzerland | AB67: FALSE | AC67: QuickBooks | AD67: New
A68: 7999158 | B68: 45993.616 | C68: 7226908 | D68: bluewatercas2 | E68: 45993.618 | F68: 1 | G68: 0 | J68: Direct | K68: Direct | L68: blank | M68: DirectSEO | O68: https://signin.method.me/ | P68: Mozilla/5.0 (Macintosh; Intel Mac OS X 10_15_7) AppleWebKit/605.1.15 (KHTML, like Gecko) Version/18.6 Safari/605.1.15 | Q68: 104.188.123.30 | R68: FALSE | S68: U | T68: 45993.619 | U68: 45993 | V68: 48 | W68: Dec | X68: 2025 | Y68: 50-Direct: Referrer Blank (Direct) | Z68: US | AA68: United States | AB68: FALSE | AC68: QBO | AD68: New
A69: 7972169 | B69: 45987.479 | C69: 7200361 | D69: method113 | E69: 45993.624 | F69: 1 | G69: 0 | J69: SEO | K69: SEO | L69: Google | M69: DirectSEO | N69: https://www.google.com/ | O69: https://www.method.me/ | P69: Mozilla/5.0 (Windows NT 10.0; Win64; x64) AppleWebKit/537.36 (KHTML, like Gecko) Chrome/142.0.0.0 Safari/537.36 | Q69: 66.207.210.42 | R69: FALSE | S69: U | T69: 45987.486 | U69: 45987 | V69: 47 | W69: Nov | X69: 2025 | Y69: 130-SEO: google (DirectSEO) | AA69: Canada | AB69: TRUE | AC69: QBO | AD69: New
A70: 7999538 | B70: 45993.665 | C70: 7227287 | D70: ecoofficewerks | E70: 45993.666 | F70: 1 | G70: 0 | H70: Bing | I70: Bing-PMax | J70: Bing | K70: Pay Per Click | L70: Bing-PMax | M70: growmethodme | N70: https://www.bing.com/ | O70: https://grow.method.me/best-quickbooks-crm/?trc=86&trk=grow.method.me&trs=Bing-PMax&msclkid=9f4239fb50c21fa5297050d40275a688&utm_source=bing&utm_medium=cpc&utm_campaign=Bing - PMAX&utm_term=grow.method.me&utm_content=US - retargeting | P70: Mozilla/5.0 (Windows NT 10.0; Win64; x64) AppleWebKit/537.36 (KHTML, like Gecko) Chrome/142.0.0.0 Safari/537.36 Edg/142.0.0.0 | Q70: 108.94.23.4 | R70: FALSE | S70: U | T70: 45993.667 | U70: 45993 | V70: 48 | W70: Dec | X70: 2025 | Y70: - | AA70: United States | AB70: FALSE | AC70: QBO | AD70: New
A71: 7999637 | B71: 45993.676 | C71: 7227385 | D71: wanderwood | E71: 45993.676 | F71: 1 | G71: 0 | J71: SEO | K71: SEO | L71: Google | M71: DirectSEO | N71: https://www.google.com/ | O71: https://www.method.me/ | P71: Mozilla/5.0 (Windows NT 10.0; Win64; x64) AppleWebKit/537.36 (KHTML, like Gecko) Chrome/142.0.0.0 Safari/537.36 | Q71: 192.80.186.170 | R71: FALSE | S71: U | T71: 45993.678 | U71: 45993 | V71: 48 | W71: Dec | X71: 2025 | Y71: 130-SEO: google (DirectSEO) | Z71: US | AA71: United States | AB71: FALSE | AC71: QBO | AD71: New
A72: 7999736 | B72: 45993.69 | C72: 7227482 | D72: gflsystems | E72: 45993.69 | F72: 1 | G72: 0 | J72: SEO | K72: SEO | L72: Google | M72: DirectSEO | N72: https://www.google.com/ | O72: https://www.method.me/ | P72: Mozilla/5.0 (Macintosh; Intel Mac OS X 10_15_7) AppleWebKit/537.36 (KHTML, like Gecko) Chrome/142.0.0.0 Safari/537.36 | Q72: 184.75.16.122 | R72: FALSE | S72: U | T72: 45993.692 | U72: 45993 | V72: 48 | W72: Dec | X72: 2025 | Y72: 130-SEO: google (DirectSEO) | AA72: United States | AB72: FALSE | AC72: QBO | AD72: New
A73: 7999751 | B73: 45993.691 | C73: 7227496 | D73: mammothlive2 | E73: 45993.691 | F73: 1 | G73: 0 | J73: Direct | K73: Direct | L73: blank | M73: DirectSEO | O73: http://signup.method.me/?offering=methodcrm | P73: Mozilla/5.0 (Windows NT 10.0; Win64; x64) AppleWebKit/537.36 (KHTML, like Gecko) Chrome/130.0.0.0 Safari/537.36 | Q73: 74.179.67.143, 52.9.26.127 | R73: FALSE | S73: U | T73: 45993.692 | U73: 45993 | V73: 48 | W73: Dec | X73: 2025 | Y73: 50-Direct: Referrer Blank (Direct) | Z73: US | AA73: United States | AB73: FALSE | AC73: QBDT | AD73: New
A74: 7999975 | B74: 45993.72 | C74: 7227716 | D74: kovarwoodwork | E74: 45993.72 | F74: 1 | G74: 0 | H74: Bing | I74: USA-G-QB-Bing | J74: Bing | K74: Pay Per Click | L74: USA-G-QB-Bing | M74: custom_invoice_quickbooks | N74: https://duckduckgo.com/ | O74: https://grow.method.me/crm-quickbooks/?trc=86&trk=custom invoice quickbooks&trs=USA-G-QB-Bing&msclkid=6baba474e41013e1c2edcd5b81029a7c&utm_source=bing&utm_medium=cpc&utm_campaign=US - Generic 2020&utm_term=custom invoice quickbooks&utm_content=Generic | P74: Mozilla/5.0 (Macintosh; Intel Mac OS X 10_15_7) AppleWebKit/605.1.15 (KHTML, like Gecko) Version/18.6 Safari/605.1.15 | Q74: 98.97.84.36 | R74: FALSE | S74: U | T74: 45993.722 | U74: 45993 | V74: 48 | W74: Dec | X74: 2025 | Y74: - | AA74: United States | AB74: FALSE | AC74: QuickBooks | AD74: New
A75: 7999198 | B75: 45993.619 | C75: 7226948 | D75: ogleheatingandcoolgin | E75: 45993.726 | F75: 0.5 | G75: 0 | J75: SEO | K75: SEO | L75: Google | M75: DirectSEO | N75: https://www.google.com/ | O75: https://www.method.me/ | P75: Mozilla/5.0 (Windows NT 10.0; Win64; x64) AppleWebKit/537.36 (KHTML, like Gecko) Chrome/142.0.0.0 Safari/537.36 | Q75: 216.24.59.41 | R75: FALSE | S75: U | T75: 45993.727 | U75: 45993 | V75: 48 | W75: Dec | X75: 2025 | Y75: 130-SEO: google (DirectSEO) | AA75: United States | AB75: FALSE | AC75: QBDT | AD75: New
A76: 7999968 | B76: 45993.719 | C76: 7226948 | D76: ogleheatingandcoolgin | E76: 45993.726 | F76: 0.5 | G76: 0 | H76: AdWords | I76: US-New-Proposal | J76: AdWords | K76: Pay Per Click | L76: US-New-Proposal | M76: does_quickbooks_have_electronic_signature | N76: https://www.google.com/ | O76: https://grow.method.me/method-proposals/?trc=81&trk=does quickbooks have electronic signature&trs=US-New-Proposal&campaignid=19733246298&adgroupid=156304156777&adid=689695736138&gad_source=1&gad_campaignid=19733246298&gbraid=0AAAAAD3ItnZXkcsk3X30-UxERaLriQVb0&gclid=Cj0KCQiAubrJBhCbARIsAHIdxD8mdMJmjJVbZ_BWxW7YMo9ODVTBFR4STHKB7z1Cck3QDYhPCahKr-gaAtk4EALw_wcB | P76: Mozilla/5.0 (Windows NT 10.0; Win64; x64) AppleWebKit/537.36 (KHTML, like Gecko) Chrome/142.0.0.0 Safari/537.36 | Q76: 216.24.59.41 | R76: FALSE | S76: U | T76: 45993.727 | U76: 45993 | V76: 48 | W76: Dec | X76: 2025 | Y76: - | AA76: United States | AB76: FALSE | AC76: QBDT | AD76: New
A77: 8000078 | B77: 45993.734 | C77: 7227818 | D77: westernslopefire | E77: 45993.735 | F77: 1 | G77: 0 | J77: SEO | K77: SEO | L77: Google | M77: DirectSEO | N77: https://www.google.com/ | O77: https://www.method.me/ | P77: Mozilla/5.0 (Windows NT 10.0; Win64; x64) AppleWebKit/537.36 (KHTML, like Gecko) Chrome/142.0.0.0 Safari/537.36 | Q77: 170.151.146.174 | R77: FALSE | S77: U | T77: 45993.737 | U77: 45993 | V77: 48 | W77: Dec | X77: 2025 | Y77: 130-SEO: google (DirectSEO) | Z77: US | AA77: United States | AB77: FALSE | AC77: QBO | AD77: New
A78: 7485030 | B78: 45858.417 | C78: 6729572 | D78: hybridelectronics5 | E78: 45993.748 | F78: 1 | G78: 0 | H78: AdWords | I78: USA-QB-G_Ex | J78: AdWords | K78: Pay Per Click | L78: USA-QB-G_Ex | M78: crm_works_with_quickbooks | N78: https://www.google.com/ | O78: https://grow.method.me/crm-quickbooks/?trc=81&trk=crm works with quickbooks&trs=USA-QB-G_Ex&campaignid=22265826203&adgroupid=176758613473&adid=734012603510&gad_source=1&gad_campaignid=22265826203&gbraid=0AAAAAD3ItnY8dYj6EgtzuDGCW8YS03VZf&gclid=CjwKCAjwp_LDBhBCEiwAK7FnkurcoCbN_VHZKoD3F3-xeGHISK-ND6ZLXrhGH384yLRCm7EqUXDdVBoCtFYQAvD_BwE | P78: Mozilla/5.0 (Windows NT 10.0; Win64; x64) AppleWebKit/537.36 (KHTML, like Gecko) Chrome/138.0.0.0 Safari/537.36 Edg/138.0.0.0 | Q78: 104.136.164.24 | R78: FALSE | S78: U | T78: 45993.749 | U78: 45858 | V78: 28 | W78: Jul | X78: 2025 | Y78: - | AA78: United States | AB78: TRUE | AC78: QBO | AD78: New
A79: 8000368 | B79: 45993.799 | C79: 7228093 | D79: threepillarsconsulting | E79: 45993.803 | F79: 1 | G79: 0 | H79: AdWords | I79: US-QBInt-Ex | J79: AdWords | K79: Pay Per Click | L79: US-QBInt-Ex | M79: crm_integrates_with_quickbooks | N79: https://www.google.com/ | O79: https://grow.method.me/crm-quickbooks/?trc=81&trk=crm integrates with quickbooks&trs=US-QBInt-Ex&campaignid=22265826203&adgroupid=186545727779&adid=777091446185&gad_source=1&gad_campaignid=22265826203&gbraid=0AAAAAD3Itnam2j5nHWVuXmJuoGB4QHUV1&gclid=Cj0KCQiAubrJBhCbARIsAHIdxD8sT4zpzABpZFGx3n1JzaoHNFaaUsR3ntg8deFRNjmBN_2jm3OixmsaApvvEALw_wcB | P79: Mozilla/5.0 (iPhone; CPU iPhone OS 18_7_1 like Mac OS X) AppleWebKit/605.1.15 (KHTML, like Gecko) Version/18.7 Mobile/15E148 Safari/604.1 | Q79: 24.101.237.23 | R79: FALSE | S79: U | T79: 45993.804 | U79: 45993 | V79: 48 | W79: Dec | X79: 2025 | Y79: - | Z79: US | AA79: United States | AB79: FALSE | AC79: QBO | AD79: New
A80: 8000467 | B80: 45993.823 | C80: 7228190 | D80: saniclean2 | E80: 45993.835 | F80: 1 | G80: 0 | J80: SEO | K80: SEO | L80: Google | M80: DirectSEO | N80: https://www.google.com/ | O80: https://www.method.me/ | P80: Mozilla/5.0 (Windows NT 10.0; Win64; x64) AppleWebKit/537.36 (KHTML, like Gecko) Chrome/142.0.0.0 Safari/537.36 | Q80: 131.241.101.55 | R80: FALSE | S80: U | T80: 45993.836 | U80: 45993 | V80: 48 | W80: Dec | X80: 2025 | Y80: 130-SEO: google (DirectSEO) | Z80: US | AA80: United States | AB80: FALSE | AC80: QBO | AD80: New
A81: 7998178 | B81: 45993.501 | C81: 7225937 | D81: agoradistributioninc | E81: 45993.866 | F81: 1 | G81: 0 | J81: Direct | K81: Direct | L81: blank | M81: DirectSEO | O81: https://www.method.me/ | P81: Mozilla/5.0 (Macintosh; Intel Mac OS X 10_15_7) AppleWebKit/537.36 (KHTML, like Gecko) Chrome/142.0.0.0 Safari/537.36 | Q81: 184.148.207.31 | R81: FALSE | S81: U | T81: 45993.867 | U81: 45993 | V81: 48 | W81: Dec | X81: 2025 | Y81: 50-Direct: Referrer Blank (Direct) | Z81: CA | AA81: Canada | AB81: FALSE | AC81: QBO | AD81: New
A82: 8000699 | B82: 45993.878 | C82: 7228418 | D82: joni | E82: 45993.879 | F82: 1 | G82: 0 | J82: SEO | K82: SEO | L82: Google | M82: DirectSEO | N82: https://www.google.com/ | O82: https://signin.method.me/ | P82: Mozilla/5.0 (Linux; Android 10; K) AppleWebKit/537.36 (KHTML, like Gecko) Chrome/142.0.0.0 Mobile Safari/537.36 | Q82: 223.184.133.232 | R82: FALSE | S82: U | T82: 45993.881 | U82: 45993 | V82: 48 | W82: Dec | X82: 2025 | Y82: 130-SEO: google (DirectSEO) | AA82: India | AB82: FALSE | AC82: QBO | AD82: New
A83: 7986423 | B83: 45990.899 | C83: 7214453 | D83: clearwaterpoolcare | E83: 45993.915 | F83: 1 | G83: 0 | J83: SEO | K83: SEO | L83: Google | M83: DirectSEO | N83: https://www.google.com/ | O83: https://www.method.me/ | P83: Mozilla/5.0 (Windows NT 10.0; Win64; x64) AppleWebKit/537.36 (KHTML, like Gecko) Chrome/142.0.0.0 Safari/537.36 | Q83: 117.20.68.255 | R83: FALSE | S83: U | T83: 45993.916 | U83: 45990 | V83: 47 | W83: Nov | X83: 2025 | Y83: 130-SEO: google (DirectSEO) | AA83: Australia | AB83: FALSE | AC83: Xero | AD83: New
A84: 8000887 | B84: 45993.938 | C84: 7228602 | D84: verticalelectric4 | E84: 45993.944 | F84: 1 | G84: 0 | J84: SEO | K84: SEO | L84: Google | M84: DirectSEO | N84: https://www.google.com/ | O84: https://www.method.me/ | P84: Mozilla/5.0 (Macintosh; Intel Mac OS X 10_15_7) AppleWebKit/537.36 (KHTML, like Gecko) Chrome/142.0.0.0 Safari/537.36 | Q84: 107.133.215.248 | R84: FALSE | S84: U | T84: 45993.946 | U84: 45993 | V84: 48 | W84: Dec | X84: 2025 | Y84: 130-SEO: google (DirectSEO) | Z84: US | AA84: United States | AB84: FALSE | AC84: QBO | AD84: New
A85: 8001127 | B85: 45994.017 | C85: 7228836 | D85: commercialconsultingservicesllc | E85: 45994.019 | F85: 1 | G85: 0 | J85: SEO | K85: SEO | L85: Bing | M85: DirectSEO | N85: https://www.bing.com/ | O85: https://www.method.me/ | P85: Mozilla/5.0 (iPhone; CPU iPhone OS 26_1_0 like Mac OS X) AppleWebKit/605.1.15 (KHTML, like Gecko) EdgiOS/142.0.3595.95 Version/26.0 Mobile/15E148 Safari/604.1 | Q85: 74.70.251.222 | R85: FALSE | S85: U | T85: 45994.021 | U85: 45994 | V85: 48 | W85: Dec | X85: 2025 | Y85: 120-SEO: bing (DirectSEO) | Z85: US | AA85: United States | AB85: FALSE | AC85: QBO | AD85: New
A86: 8001222 | B86: 45994.046 | C86: 7228931 | D86: tauruscorp | E86: 45994.047 | F86: 1 | G86: 0 | J86: SEO | K86: SEO | L86: Bing | M86: DirectSEO | N86: https://www.bing.com/ | O86: https://www.method.me/ | P86: Mozilla/5.0 (Windows NT 10.0; Win64; x64) AppleWebKit/537.36 (KHTML, like Gecko) Chrome/142.0.0.0 Safari/537.36 Edg/142.0.0.0 | Q86: 217.165.17.226 | R86: FALSE | S86: U | T86: 45994.048 | U86: 45994 | V86: 48 | W86: Dec | X86: 2025 | Y86: 120-SEO: bing (DirectSEO) | AA86: United Arab Emirates | AB86: FALSE | AC86: QBDT | AD86: New
A87: 8001238 | B87: 45994.053 | C87: 7228947 | D87: nanh | E87: 45994.054 | F87: 1 | G87: 0 | J87: SEO | K87: SEO | L87: Google | M87: DirectSEO | N87: https://www.google.com/ | O87: https://signin.method.me/ | P87: Mozilla/5.0 (Windows NT 10.0; Win64; x64) AppleWebKit/537.36 (KHTML, like Gecko) Chrome/142.0.0.0 Safari/537.36 | Q87: 171.224.51.29 | R87: FALSE | S87: U | T87: 45994.056 | U87: 45994 | V87: 48 | W87: Dec | X87: 2025 | Y87: 130-SEO: google (DirectSEO) | AA87: Vietnam | AB87: FALSE | AC87: QBDT | AD87: New
A88: 8001558 | B88: 45994.162 | C88: 7229263 | D88: zennohintl | E88: 45994.161 | F88: 1 | G88: 0 | J88: Direct | K88: Direct | L88: blank | M88: DirectSEO | O88: http://signup.method.me/methodcrm/ | P88: Mozilla/5.0 (Windows NT 10.0; Win64; x64) AppleWebKit/537.36 (KHTML, like Gecko) Chrome/142.0.0.0 Safari/537.36 | Q88: 42.200.69.157, 52.9.26.127 | R88: FALSE | S88: U | T88: 45994.162 | U88: 45994 | V88: 48 | W88: Dec | X88: 2025 | Y88: 50-Direct: Referrer Blank (Direct) | Z88: HK | AA88: Hong Kong | AB88: FALSE | AC88: QBO | AD88: New
A89: 8001804 | B89: 45994.239 | C89: 7229509 | D89: wasangshow | E89: 45994.24 | F89: 1 | G89: 0 | J89: Direct | K89: Direct | L89: blank | M89: DirectSEO | O89: https://www.method.me/ | P89: Mozilla/5.0 (Macintosh; Intel Mac OS X 10_15_7) AppleWebKit/537.36 (KHTML, like Gecko) Chrome/142.0.0.0 Safari/537.36 | Q89: 118.160.192.126 | R89: FALSE | S89: U | T89: 45994.241 | U89: 45994 | V89: 48 | W89: Dec | X89: 2025 | Y89: 50-Direct: Referrer Blank (Direct) | AA89: Taiwan | AB89: FALSE | AC89: QBDT | AD89: New
A90: 8001948 | B90: 45994.286 | C90: 7229653 | D90: db4 | E90: 45994.287 | F90: 1 | G90: 0 | H90: Facebook Ads | I90: FB-Lookalike | J90: Facebook Ads | K90: Pay Per Click | L90: FB-Lookalike | M90: BOF | N90: https://l.facebook.com/ | O90: https://grow.method.me/quickbooks-crm-fb/?trc=517&trk=BOF&trs=FB-Lookalike&utm_source=Facebook&utm_medium=PPC&utm_campaign=Banner_trial&utm_id=120213444289450307&utm_content=120215433569050307&utm_term=120215433408020307&fbclid=IwY2xjawOdA8ZleHRuA2FlbQEwAGFkaWQBqykbuk3ag3NydGMGYXBwX2lkEDIyMjAzOTE3ODgyMDA4OTIAAR5hGI96W_1h-NzXKvyCvL68GkcHGJA2cqXPhAZWGhdtTeaKDSdhk36cRrgImg_aem_H2VsKu2fQVsISvAguSn5BA&campaign_id=120213444289450307&ad_id=120215433569050307 | P90: Mozilla/5.0 (Windows NT 10.0; Win64; x64) AppleWebKit/537.36 (KHTML, like Gecko) Chrome/142.0.0.0 Safari/537.36 | Q90: 172.59.216.34 | R90: FALSE | S90: U | T90: 45994.288 | U90: 45994 | V90: 48 | W90: Dec | X90: 2025 | Y90: - | AA90: United States | AB90: FALSE | AC90: QBO | AD90: New
A91: 7997897 | B91: 45993.469 | C91: 7225658 | D91: bandbshowroom | E91: 45994.31 | F91: 1 | G91: 0 | H91: AdWords | I91: CAN-QB-G | J91: AdWords | K91: Pay Per Click | L91: CAN-QB-G | M91: crm_with_quickbooks | N91: https://www.google.com/ | O91: https://grow.method.me/quickbooks-method-cad/?trc=81&trk=crm with quickbooks&trs=CAN-QB-G&campaignid=1543604353&adgroupid=61438895000&adid=704657828091&gad_source=1&gad_campaignid=1543604353&gbraid=0AAAAAD3ItnaMundn4Up-tYMPWfU3dxz9g&gclid=Cj0KCQiAubrJBhCbARIsAHIdxD-glMYsYOyvG25S4CG0ZiIQTwVJ7RjEV29E7JMM3sIvI1E_Ch4_c9kaAswBEALw_wcB | P91: Mozilla/5.0 (Windows NT 10.0; Win64; x64) AppleWebKit/537.36 (KHTML, like Gecko) Chrome/142.0.0.0 Safari/537.36 | Q91: 174.0.17.156 | R91: FALSE | S91: U | T91: 45994.312 | U91: 45993 | V91: 48 | W91: Dec | X91: 2025 | Y91: - | Z91: CA | AA91: Canada | AB91: FALSE | AC91: QBO | AD91: New
A92: 7961504 | B92: 45985.46 | C92: 7189860 | D92: medpipe2 | E92: 45994.315 | F92: 0.5 | G92: 0 | H92: SEO | I92: gmb-profile | J92: SEO | K92: SEO | L92: gmb-profile | M92: contact-us | N92: https://www.google.com/ | O92: https://www.method.me/contact-us/?trc=180&trk=contact-us&trs=gmb-profile&utm_source=seo&utm_medium=google&utm_campaign=my-business-profile | P92: Mozilla/5.0 (Windows NT 10.0; Win64; x64) AppleWebKit/537.36 (KHTML, like Gecko) Chrome/142.0.0.0 Safari/537.36 | Q92: 50.254.198.41 | R92: FALSE | S92: U | T92: 45994.316 | U92: 45985 | V92: 47 | W92: Nov | X92: 2025 | Y92: - | AA92: United States | AB92: FALSE | AC92: QBDT | AD92: New
A93: 8002065 | B93: 45994.314 | C93: 7189860 | D93: medpipe2 | E93: 45994.315 | F93: 0.5 | G93: 0 | H93: SEO | I93: gmb-profile | J93: SEO | K93: SEO | L93: gmb-profile | M93: contact-us | N93: https://www.google.com/ | O93: https://www.method.me/contact-us/?trc=180&trk=contact-us&trs=gmb-profile&utm_source=seo&utm_medium=google&utm_campaign=my-business-profile | P93: Mozilla/5.0 (Windows NT 10.0; Win64; x64) AppleWebKit/537.36 (KHTML, like Gecko) Chrome/142.0.0.0 Safari/537.36 | Q93: 50.254.198.41 | R93: FALSE | S93: U | T93: 45994.316 | U93: 45994 | V93: 48 | W93: Dec | X93: 2025 | Y93: - | AA93: United States | AB93: FALSE | AC93: QBDT | AD93: New
A94: 8002633 | B94: 45994.388 | C94: 7230330 | D94: up2codesystems | E94: 45994.39 | F94: 1 | G94: 0 | J94: Direct | K94: Direct | L94: blank | M94: DirectSEO | O94: https://www.method.me/ | P94: Mozilla/5.0 (Windows NT 10.0; Win64; x64) AppleWebKit/537.36 (KHTML, like Gecko) Chrome/142.0.0.0 Safari/537.36 Edg/142.0.0.0 | Q94: 50.89.36.184 | R94: FALSE | S94: U | T94: 45994.391 | U94: 45994 | V94: 48 | W94: Dec | X94: 2025 | Y94: 50-Direct: Referrer Blank (Direct) | Z94: US | AA94: United States | AB94: FALSE | AC94: QBO | AD94: New
A95: 8002757 | B95: 45994.404 | C95: 7230452 | D95: indeed | E95: 45994.404 | F95: 0 | G95: 0 | M95: DirectSEO | N95: https://www.method.me/ | O95: http://signup.method.me/methodcrm?_gl=1*a0vgwo*_gcl_au*MTgzNzE4NjA2MS4xNzY0NzcyOTQ1*_ga*MTkyNjc2OTE3MS4xNzY0NzcyOTQ1*_ga_L2HEZNW53E*czE3NjQ3NzI5NDQkbzEkZzAkdDE3NjQ3NzI5NDUkajU5JGwwJGg4NzA4NjEyMDk.&_ga=2.145381616.577777304.1764772945-1926769171.1764772945 | P95: Mozilla/5.0 (Macintosh; Intel Mac OS X 10_15_7) AppleWebKit/537.36 (KHTML, like Gecko) Chrome/142.0.0.0 Safari/537.36 | Q95: 185.67.177.77, 52.9.26.127 | R95: TRUE | S95: U | T95: 45994.406 | U95: 45994 | V95: 48 | W95: Dec | X95: 2025 | Y95: 10-Ignore Referrer https method.me | AA95: Serbia | AB95: FALSE | AC95: QBO | AD95: New
A96: 7967895 | B96: 45986.636 | C96: 7196123 | D96: remmgroup | E96: 45994.41 | F96: 1 | G96: 0 | J96: SEO | K96: SEO | L96: Google | M96: DirectSEO | N96: https://www.google.com/ | O96: https://www.method.me/ | P96: Mozilla/5.0 (Windows NT 10.0; Win64; x64) AppleWebKit/537.36 (KHTML, like Gecko) Chrome/142.0.0.0 Safari/537.36 | Q96: 99.243.57.158 | R96: FALSE | S96: U | T96: 45994.411 | U96: 45986 | V96: 47 | W96: Nov | X96: 2025 | Y96: 130-SEO: google (DirectSEO) | Z96: CA | AA96: Canada | AB96: FALSE | AC96: QBO | AD96: New
A97: 8002938 | B97: 45994.429 | C97: 7230630 | D97: redtoothimageryllc | E97: 45994.429 | F97: 1 | G97: 0 | J97: Intuit App Card Traffic | K97: OPN - Other Peoples Networks | L97: Intuit | M97: DirectSEO | N97: https://appcenter.intuit.com/ | O97: https://signup.method.me/QBOAppstoreSignup?offering=methodcrm | P97: Mozilla/5.0 (Macintosh; Intel Mac OS X 10_15_7) AppleWebKit/537.36 (KHTML, like Gecko) Chrome/142.0.0.0 Safari/537.36 | Q97: 174.16.148.240 | R97: FALSE | S97: U | T97: 45994.431 | U97: 45994 | V97: 48 | W97: Dec | X97: 2025 | Y97: 179-ReferralLink: intuit (OPN) - App center | Z97: US | AA97: United States | AB97: FALSE | AC97: QBO | AD97: New
A98: 8002139 | B98: 45994.329 | C98: 7229842 | D98: emk | E98: 45994.44 | F98: 1 | G98: 0 | J98: SEO | K98: SEO | L98: Google | M98: DirectSEO | N98: https://www.google.com/ | O98: http://signup.method.me/methodcrm | P98: Mozilla/5.0 (Windows NT 10.0; Win64; x64) AppleWebKit/537.36 (KHTML, like Gecko) Chrome/142.0.0.0 Safari/537.36 | Q98: 105.155.255.126, 52.9.26.127 | R98: FALSE | S98: U | T98: 45994.441 | U98: 45994 | V98: 48 | W98: Dec | X98: 2025 | Y98: 130-SEO: google (DirectSEO) | AA98: Morocco | AB98: TRUE | AC98: None | AD98: New
A99: 7992587 | B99: 45992.54 | C99: 7220470 | D99: dragonpowerpromo | E99: 45994.463 | F99: 1 | G99: 0 | H99: AdWords | I99: USA-QB-G_Ex | J99: AdWords | K99: Pay Per Click | L99: USA-QB-G_Ex | M99: quickbooks_crm | N99: https://www.google.com/ | O99: https://grow.method.me/crm-quickbooks/?trc=81&trk=quickbooks crm&trs=USA-QB-G_Ex&campaignid=22265826203&adgroupid=176758613473&adid=734012603510&gad_source=1&gad_campaignid=22265826203&gbraid=0AAAAAD3ItnbQ-scslMn1OtVxbVSWxN2mJ&gclid=CjwKCAiAlrXJBhBAEiwA-5pgwnLR64YdpwU2sV9YesE_12PLfc5YAT_XruCnd4kJ7DgaBfFYBL8wkxoCFP8QAvD_BwE | P99: Mozilla/5.0 (Windows NT 10.0; Win64; x64) AppleWebKit/537.36 (KHTML, like Gecko) Chrome/142.0.0.0 Safari/537.36 | Q99: 75.82.219.166 | R99: FALSE | S99: U | T99: 45994.465 | U99: 45992 | V99: 48 | W99: Dec | X99: 2025 | Y99: - | Z99: US | AA99: United States | AB99: FALSE | AC99: QBO | AD99: New
A100: 8003280 | B100: 45994.466 | C100: 7230971 | D100: bluegrasspoolmanagement | E100: 45994.47 | F100: 1 | G100: 0 | J100: SEO | K100: SEO | L100: Google | M100: DirectSEO | N100: https://www.google.com/ | O100: https://www.method.me/ | P100: Mozilla/5.0 (Macintosh; Intel Mac OS X 10_15_7) AppleWebKit/605.1.15 (KHTML, like Gecko) Version/18.5 Safari/605.1.15 | Q100: 46.110.130.21 | R100: FALSE | S100: U | T100: 45994.472 | U100: 45994 | V100: 48 | W100: Dec | X100: 2025 | Y100: 130-SEO: google (DirectSEO) | Z100: US | AA100: United States | AB100: FALSE | AC100: QBO | AD100: New
...

Sheet Day

Sheet Week

Sheet Month

Sheet ContentBuckets
A1: =IFERROR(__xludf.DUMMYFUNCTION("IMPORTRANGE(""1jPFsXIFRQiCdRdldhjwYkNm2AR-ir-VjjUEf0GzFFjY"", ""All content!A:E"")"),"URL") -> URL | B1: =IFERROR(__xludf.DUMMYFUNCTION("""COMPUTED_VALUE"""),"URL Category") -> URL Category | C1: =IFERROR(__xludf.DUMMYFUNCTION("""COMPUTED_VALUE"""),"Media type") -> Media type | D1: =IFERROR(__xludf.DUMMYFUNCTION("""COMPUTED_VALUE"""),"Title") -> Title | E1: =IFERROR(__xludf.DUMMYFUNCTION("""COMPUTED_VALUE"""),"Publish Date") -> Publish Date
A2: =IFERROR(__xludf.DUMMYFUNCTION("""COMPUTED_VALUE"""),"https://www.method.me/blog/method-makes-pwc-s-top-10-up-and-coming-technology-companies/") -> https://www.method.me/blog/method-makes-pwc-s-top-10-up-and-coming-technology-companies/ | B2: =IFERROR(__xludf.DUMMYFUNCTION("""COMPUTED_VALUE"""),"Method - Product Updates") -> Method - Product Updates | C2: =IFERROR(__xludf.DUMMYFUNCTION("""COMPUTED_VALUE"""),"Blog") -> Blog | D2: =IFERROR(__xludf.DUMMYFUNCTION("""COMPUTED_VALUE"""),"Innovating to Disrupt: Method Makes PwC’s Top 10 Up-and-Coming Technology Companies") -> Innovating to Disrupt: Method Makes PwC’s Top 10 Up-and-Coming Technology Companies | E2: =IFERROR(__xludf.DUMMYFUNCTION("""COMPUTED_VALUE"""),41596.644849537035) -> 41596.645
A3: =IFERROR(__xludf.DUMMYFUNCTION("""COMPUTED_VALUE"""),"https://www.method.me/blog/quickbooks-faq-creating-an-invoice-in-quickbooks/") -> https://www.method.me/blog/quickbooks-faq-creating-an-invoice-in-quickbooks/ | B3: =IFERROR(__xludf.DUMMYFUNCTION("""COMPUTED_VALUE"""),"QuickBooks - How-to") -> QuickBooks - How-to | C3: =IFERROR(__xludf.DUMMYFUNCTION("""COMPUTED_VALUE"""),"Blog") -> Blog | D3: =IFERROR(__xludf.DUMMYFUNCTION("""COMPUTED_VALUE"""),"How to create an invoice in QuickBooks") -> How to create an invoice in QuickBooks | E3: =IFERROR(__xludf.DUMMYFUNCTION("""COMPUTED_VALUE"""),41669.55892361111) -> 41669.559
A4: =IFERROR(__xludf.DUMMYFUNCTION("""COMPUTED_VALUE"""),"https://www.method.me/blog/new-methodcrm-report-designer-tutorial-videos/") -> https://www.method.me/blog/new-methodcrm-report-designer-tutorial-videos/ | B4: =IFERROR(__xludf.DUMMYFUNCTION("""COMPUTED_VALUE"""),"Method - Product Updates") -> Method - Product Updates | C4: =IFERROR(__xludf.DUMMYFUNCTION("""COMPUTED_VALUE"""),"Blog") -> Blog | D4: =IFERROR(__xludf.DUMMYFUNCTION("""COMPUTED_VALUE"""),"New! Method:CRM Report Designer Tutorial Videos") -> New! Method:CRM Report Designer Tutorial Videos | E4: =IFERROR(__xludf.DUMMYFUNCTION("""COMPUTED_VALUE"""),41822.63182870371) -> 41822.632
A5: =IFERROR(__xludf.DUMMYFUNCTION("""COMPUTED_VALUE"""),"https://www.method.me/blog/rejoice-methodcrm-report-designer-documentation-videos/") -> https://www.method.me/blog/rejoice-methodcrm-report-designer-documentation-videos/ | B5: =IFERROR(__xludf.DUMMYFUNCTION("""COMPUTED_VALUE"""),"Method - Product Updates") -> Method - Product Updates | C5: =IFERROR(__xludf.DUMMYFUNCTION("""COMPUTED_VALUE"""),"Blog") -> Blog | D5: =IFERROR(__xludf.DUMMYFUNCTION("""COMPUTED_VALUE"""),"Rejoice! Method:CRM Report Designer documentation and videos!") -> Rejoice! Method:CRM Report Designer documentation and videos! | E5: =IFERROR(__xludf.DUMMYFUNCTION("""COMPUTED_VALUE"""),41843.62170138889) -> 41843.622
A6: =IFERROR(__xludf.DUMMYFUNCTION("""COMPUTED_VALUE"""),"https://www.method.me/blog/small-businesses-are-kicking-butt-with-mobile-access-to-quickbooks-desktop/") -> https://www.method.me/blog/small-businesses-are-kicking-butt-with-mobile-access-to-quickbooks-desktop/ | B6: =IFERROR(__xludf.DUMMYFUNCTION("""COMPUTED_VALUE"""),"Listicle - QuickBooks") -> Listicle - QuickBooks | C6: =IFERROR(__xludf.DUMMYFUNCTION("""COMPUTED_VALUE"""),"Blog") -> Blog | D6: =IFERROR(__xludf.DUMMYFUNCTION("""COMPUTED_VALUE"""),"3 ways you win with QuickBooks mobile access") -> 3 ways you win with QuickBooks mobile access | E6: =IFERROR(__xludf.DUMMYFUNCTION("""COMPUTED_VALUE"""),41876.625497685185) -> 41876.626
A7: =IFERROR(__xludf.DUMMYFUNCTION("""COMPUTED_VALUE"""),"https://www.method.me/blog/performance-update-30-enhancements-improvements/") -> https://www.method.me/blog/performance-update-30-enhancements-improvements/ | B7: =IFERROR(__xludf.DUMMYFUNCTION("""COMPUTED_VALUE"""),"Method - Product Updates") -> Method - Product Updates | C7: =IFERROR(__xludf.DUMMYFUNCTION("""COMPUTED_VALUE"""),"Blog") -> Blog | D7: =IFERROR(__xludf.DUMMYFUNCTION("""COMPUTED_VALUE"""),"Performance Update: 30+ Enhancements & Improvements") -> Performance Update: 30+ Enhancements & Improvements | E7: =IFERROR(__xludf.DUMMYFUNCTION("""COMPUTED_VALUE"""),41885.622881944444) -> 41885.623
A8: =IFERROR(__xludf.DUMMYFUNCTION("""COMPUTED_VALUE"""),"https://www.method.me/blog/intuit-discontinues-salesforce-for-quickbooks/") -> https://www.method.me/blog/intuit-discontinues-salesforce-for-quickbooks/ | B8: =IFERROR(__xludf.DUMMYFUNCTION("""COMPUTED_VALUE"""),"QuickBooks - General") -> QuickBooks - General | C8: =IFERROR(__xludf.DUMMYFUNCTION("""COMPUTED_VALUE"""),"Blog") -> Blog | D8: =IFERROR(__xludf.DUMMYFUNCTION("""COMPUTED_VALUE"""),"Intuit discontinues Salesforce for QuickBooks: Breaking Up is Hard to Do…Or is It?") -> Intuit discontinues Salesforce for QuickBooks: Breaking Up is Hard to Do…Or is It? | E8: =IFERROR(__xludf.DUMMYFUNCTION("""COMPUTED_VALUE"""),41891.61424768518) -> 41891.614
A9: =IFERROR(__xludf.DUMMYFUNCTION("""COMPUTED_VALUE"""),"https://www.method.me/blog/how-a-pooper-scooper-went-national-with-method/") -> https://www.method.me/blog/how-a-pooper-scooper-went-national-with-method/ | B9: =IFERROR(__xludf.DUMMYFUNCTION("""COMPUTED_VALUE"""),"Method - Customer / Partner Success") -> Method - Customer / Partner Success | C9: =IFERROR(__xludf.DUMMYFUNCTION("""COMPUTED_VALUE"""),"Blog") -> Blog | D9: =IFERROR(__xludf.DUMMYFUNCTION("""COMPUTED_VALUE"""),"How a pooper scooper went national with Method") -> How a pooper scooper went national with Method | E9: =IFERROR(__xludf.DUMMYFUNCTION("""COMPUTED_VALUE"""),41900.614270833335) -> 41900.614
A10: =IFERROR(__xludf.DUMMYFUNCTION("""COMPUTED_VALUE"""),"https://www.method.me/blog/were-cooking-up-a-storm-at-quickbooks-connect/") -> https://www.method.me/blog/were-cooking-up-a-storm-at-quickbooks-connect/ | B10: =IFERROR(__xludf.DUMMYFUNCTION("""COMPUTED_VALUE"""),"Conference / Event") -> Conference / Event | C10: =IFERROR(__xludf.DUMMYFUNCTION("""COMPUTED_VALUE"""),"Blog") -> Blog | D10: =IFERROR(__xludf.DUMMYFUNCTION("""COMPUTED_VALUE"""),"We’re Cooking Up a Storm at QuickBooks Connect!") -> We’re Cooking Up a Storm at QuickBooks Connect! | E10: =IFERROR(__xludf.DUMMYFUNCTION("""COMPUTED_VALUE"""),41904.614282407405) -> 41904.614
A11: =IFERROR(__xludf.DUMMYFUNCTION("""COMPUTED_VALUE"""),"https://www.method.me/blog/stop-managing-your-leads-in-excel-your-bottom-line-will-thank-you/") -> https://www.method.me/blog/stop-managing-your-leads-in-excel-your-bottom-line-will-thank-you/ | B11: =IFERROR(__xludf.DUMMYFUNCTION("""COMPUTED_VALUE"""),"Listicle - General") -> Listicle - General | C11: =IFERROR(__xludf.DUMMYFUNCTION("""COMPUTED_VALUE"""),"Blog") -> Blog | D11: =IFERROR(__xludf.DUMMYFUNCTION("""COMPUTED_VALUE"""),"3 Benefits of Switching From Excel to Lead Management Software") -> 3 Benefits of Switching From Excel to Lead Management Software | E11: =IFERROR(__xludf.DUMMYFUNCTION("""COMPUTED_VALUE"""),41912.54216435185) -> 41912.542
A12: =IFERROR(__xludf.DUMMYFUNCTION("""COMPUTED_VALUE"""),"https://www.method.me/blog/create-workplace-harmony-with-quickbooks-integrated-workflows/") -> https://www.method.me/blog/create-workplace-harmony-with-quickbooks-integrated-workflows/ | B12: =IFERROR(__xludf.DUMMYFUNCTION("""COMPUTED_VALUE"""),"QuickBooks - General") -> QuickBooks - General | C12: =IFERROR(__xludf.DUMMYFUNCTION("""COMPUTED_VALUE"""),"Blog") -> Blog | D12: =IFERROR(__xludf.DUMMYFUNCTION("""COMPUTED_VALUE"""),"Create Workplace Harmony with QuickBooks-Integrated Workflows") -> Create Workplace Harmony with QuickBooks-Integrated Workflows | E12: =IFERROR(__xludf.DUMMYFUNCTION("""COMPUTED_VALUE"""),41920.60538194444) -> 41920.605
A13: =IFERROR(__xludf.DUMMYFUNCTION("""COMPUTED_VALUE"""),"https://www.method.me/blog/quit-using-quickbooks-as-your-lead-management-software/") -> https://www.method.me/blog/quit-using-quickbooks-as-your-lead-management-software/ | B13: =IFERROR(__xludf.DUMMYFUNCTION("""COMPUTED_VALUE"""),"QuickBooks - General") -> QuickBooks - General | C13: =IFERROR(__xludf.DUMMYFUNCTION("""COMPUTED_VALUE"""),"Blog") -> Blog | D13: =IFERROR(__xludf.DUMMYFUNCTION("""COMPUTED_VALUE"""),"Quit Using QuickBooks as Your Lead Management Software") -> Quit Using QuickBooks as Your Lead Management Software | E13: =IFERROR(__xludf.DUMMYFUNCTION("""COMPUTED_VALUE"""),41922.60539351852) -> 41922.605
A14: =IFERROR(__xludf.DUMMYFUNCTION("""COMPUTED_VALUE"""),"https://www.method.me/blog/quickbooks-online-or-quickbooks-desktop/") -> https://www.method.me/blog/quickbooks-online-or-quickbooks-desktop/ | B14: =IFERROR(__xludf.DUMMYFUNCTION("""COMPUTED_VALUE"""),"QuickBooks - General") -> QuickBooks - General | C14: =IFERROR(__xludf.DUMMYFUNCTION("""COMPUTED_VALUE"""),"Blog") -> Blog | D14: =IFERROR(__xludf.DUMMYFUNCTION("""COMPUTED_VALUE"""),"QuickBooks Online or QuickBooks Desktop: Comparison (2024)") -> QuickBooks Online or QuickBooks Desktop: Comparison (2024) | E14: =IFERROR(__xludf.DUMMYFUNCTION("""COMPUTED_VALUE"""),41928.605416666665) -> 41928.605
A15: =IFERROR(__xludf.DUMMYFUNCTION("""COMPUTED_VALUE"""),"https://www.method.me/blog/method-heads-to-quickbooks-connect/") -> https://www.method.me/blog/method-heads-to-quickbooks-connect/ | B15: =IFERROR(__xludf.DUMMYFUNCTION("""COMPUTED_VALUE"""),"Conference / Event") -> Conference / Event | C15: =IFERROR(__xludf.DUMMYFUNCTION("""COMPUTED_VALUE"""),"Blog") -> Blog | D15: =IFERROR(__xludf.DUMMYFUNCTION("""COMPUTED_VALUE"""),"On our Way to San Jose: Method heads to QuickBooks Connect!") -> On our Way to San Jose: Method heads to QuickBooks Connect! | E15: =IFERROR(__xludf.DUMMYFUNCTION("""COMPUTED_VALUE"""),41929.59675925926) -> 41929.597
A16: =IFERROR(__xludf.DUMMYFUNCTION("""COMPUTED_VALUE"""),"https://www.method.me/blog/new-method-enters-beta-at-quickbooks-connect/") -> https://www.method.me/blog/new-method-enters-beta-at-quickbooks-connect/ | B16: =IFERROR(__xludf.DUMMYFUNCTION("""COMPUTED_VALUE"""),"Method - Product Updates") -> Method - Product Updates | C16: =IFERROR(__xludf.DUMMYFUNCTION("""COMPUTED_VALUE"""),"Blog") -> Blog | D16: =IFERROR(__xludf.DUMMYFUNCTION("""COMPUTED_VALUE"""),"New Method Enters Beta at QuickBooks Connect") -> New Method Enters Beta at QuickBooks Connect | E16: =IFERROR(__xludf.DUMMYFUNCTION("""COMPUTED_VALUE"""),41939.595) -> 41939.595
A17: =IFERROR(__xludf.DUMMYFUNCTION("""COMPUTED_VALUE"""),"https://www.method.me/blog/conference-travel-tips-to-get-you-there-energized/") -> https://www.method.me/blog/conference-travel-tips-to-get-you-there-energized/ | B17: =IFERROR(__xludf.DUMMYFUNCTION("""COMPUTED_VALUE"""),"Conference / Event") -> Conference / Event | C17: =IFERROR(__xludf.DUMMYFUNCTION("""COMPUTED_VALUE"""),"Blog") -> Blog | D17: =IFERROR(__xludf.DUMMYFUNCTION("""COMPUTED_VALUE"""),"Conference Travel Tips to Get You There Energized") -> Conference Travel Tips to Get You There Energized | E17: =IFERROR(__xludf.DUMMYFUNCTION("""COMPUTED_VALUE"""),41951.58892361111) -> 41951.589
A18: =IFERROR(__xludf.DUMMYFUNCTION("""COMPUTED_VALUE"""),"https://www.method.me/blog/7-apps-to-organize-your-small-business/") -> https://www.method.me/blog/7-apps-to-organize-your-small-business/ | B18: =IFERROR(__xludf.DUMMYFUNCTION("""COMPUTED_VALUE"""),"Listicle - Software / Software overview") -> Listicle - Software / Software overview | C18: =IFERROR(__xludf.DUMMYFUNCTION("""COMPUTED_VALUE"""),"Blog") -> Blog | D18: =IFERROR(__xludf.DUMMYFUNCTION("""COMPUTED_VALUE"""),"7 Apps to Organize Your Small Business") -> 7 Apps to Organize Your Small Business | E18: =IFERROR(__xludf.DUMMYFUNCTION("""COMPUTED_VALUE"""),42011.659733796296) -> 42011.66
A19: =IFERROR(__xludf.DUMMYFUNCTION("""COMPUTED_VALUE"""),"https://www.method.me/blog/ways-to-generate-leads-online-for-your-small-business/") -> https://www.method.me/blog/ways-to-generate-leads-online-for-your-small-business/ | B19: =IFERROR(__xludf.DUMMYFUNCTION("""COMPUTED_VALUE"""),"Listicle - General") -> Listicle - General | C19: =IFERROR(__xludf.DUMMYFUNCTION("""COMPUTED_VALUE"""),"Blog") -> Blog | D19: =IFERROR(__xludf.DUMMYFUNCTION("""COMPUTED_VALUE"""),"5 Ways to Generate Leads Online for Your Small Business") -> 5 Ways to Generate Leads Online for Your Small Business | E19: =IFERROR(__xludf.DUMMYFUNCTION("""COMPUTED_VALUE"""),42025.779965277776) -> 42025.78
A20: =IFERROR(__xludf.DUMMYFUNCTION("""COMPUTED_VALUE"""),"https://www.method.me/blog/productivity-hacks-for-the-brave-small-business-owner/") -> https://www.method.me/blog/productivity-hacks-for-the-brave-small-business-owner/ | B20: =IFERROR(__xludf.DUMMYFUNCTION("""COMPUTED_VALUE"""),"Listicle - General") -> Listicle - General | C20: =IFERROR(__xludf.DUMMYFUNCTION("""COMPUTED_VALUE"""),"Blog") -> Blog | D20: =IFERROR(__xludf.DUMMYFUNCTION("""COMPUTED_VALUE"""),"10 productivity tips for small business owners") -> 10 productivity tips for small business owners | E20: =IFERROR(__xludf.DUMMYFUNCTION("""COMPUTED_VALUE"""),42034.72574074074) -> 42034.726
A21: =IFERROR(__xludf.DUMMYFUNCTION("""COMPUTED_VALUE"""),"https://www.method.me/blog/weve-arrived-methodcrm-now-available-for-australian-quickbooks-customers/") -> https://www.method.me/blog/weve-arrived-methodcrm-now-available-for-australian-quickbooks-customers/ | B21: =IFERROR(__xludf.DUMMYFUNCTION("""COMPUTED_VALUE"""),"Method - Product Updates") -> Method - Product Updates | C21: =IFERROR(__xludf.DUMMYFUNCTION("""COMPUTED_VALUE"""),"Blog") -> Blog | D21: =IFERROR(__xludf.DUMMYFUNCTION("""COMPUTED_VALUE"""),"Method:CRM Now Available for Australian QuickBooks Customers") -> Method:CRM Now Available for Australian QuickBooks Customers | E21: =IFERROR(__xludf.DUMMYFUNCTION("""COMPUTED_VALUE"""),42053.70921296296) -> 42053.709
