Workbook

Sheet AccountSummary (New)
A1: SyncType | B1: All | C1: QBDT | D1: QBDT | E1: QBO | F1: QBO | G1: Xero | H1: none | I1: All | J1: QBDT | K1: QBDT | L1: QBO | M1: QBO | N1: Xero | O1: none | P1: All | Q1: QBDT | R1: QBDT | S1: QBO | T1: QBO | U1: Xero | V1: none | W1: All
A2: Platform | B2: All | C2: Classic | D2: New | E2: Classic | F2: New | G2: New | H2: New | I2: All | J2: Classic | K2: New | L2: Classic | M2: New | N2: New | O2: New | P2: All | Q2: Classic | R2: New | S2: Classic | T2: New | U2: New | V2: New | W2: All
A3: Channel | B3: All | C3: Referred | D3: Referred | E3: Referred | F3: Referred | G3: Referred | H3: Referred | I3: Referred | J3: Managed | K3: Managed | L3: Managed | M3: Managed | N3: Managed | O3: Managed | P3: Managed | Q3: Direct | R3: Direct | S3: Direct | T3: Direct | U3: Direct | V3: Direct | W3: Direct
A4: *Trialers*
A5: Trials started this month | B5: =I5+P5+W5 -> 0 | C5: =COUNTIFS(Accounts!$E:$E,'AccountSummary (New)'!C$1,Accounts!$G:$G,'AccountSummary (New)'!C$2,Accounts!$F:$F,'AccountSummary (New)'!C$3,Accounts!$B:$B,"none",Accounts!$BF:$BF,FALSE) -> 0 | D5: =COUNTIFS(Accounts!$E:$E,'AccountSummary (New)'!D$1,Accounts!$G:$G,'AccountSummary (New)'!D$2,Accounts!$F:$F,'AccountSummary (New)'!D$3,Accounts!$B:$B,"none",Accounts!$BF:$BF,FALSE) -> 0 | E5: =COUNTIFS(Accounts!$E:$E,'AccountSummary (New)'!E$1,Accounts!$G:$G,'AccountSummary (New)'!E$2,Accounts!$F:$F,'AccountSummary (New)'!E$3,Accounts!$B:$B,"none",Accounts!$BF:$BF,FALSE) -> 0 | F5: =COUNTIFS(Accounts!$E:$E,'AccountSummary (New)'!F$1,Accounts!$G:$G,'AccountSummary (New)'!F$2,Accounts!$F:$F,'AccountSummary (New)'!F$3,Accounts!$B:$B,"none",Accounts!$BF:$BF,FALSE) -> 0 | G5: =COUNTIFS(Accounts!$E:$E,'AccountSummary (New)'!G$1,Accounts!$G:$G,'AccountSummary (New)'!G$2,Accounts!$F:$F,'AccountSummary (New)'!G$3,Accounts!$B:$B,"none",Accounts!$BF:$BF,FALSE) -> 0 | H5: =COUNTIFS(Accounts!$E:$E,'AccountSummary (New)'!H$1,Accounts!$G:$G,'AccountSummary (New)'!H$2,Accounts!$F:$F,'AccountSummary (New)'!H$3,Accounts!$B:$B,"none",Accounts!$BF:$BF,FALSE)+COUNTIFS(Accounts!$E:$E,"QuickBooks",Accounts!$G:$G,'AccountSummary (New)'!H$2,Accounts!$F:$F,'AccountSummary (New)'!H$3,Accounts!$B:$B,"none",Accounts!$BF:$BF,FALSE) -> 0 | I5: =SUM(C5:H5) -> 0 | J5: =COUNTIFS(Accounts!$E:$E,'AccountSummary (New)'!J$1,Accounts!$G:$G,'AccountSummary (New)'!J$2,Accounts!$F:$F,'AccountSummary (New)'!J$3,Accounts!$B:$B,"none",Accounts!$BF:$BF,FALSE) -> 0 | K5: =COUNTIFS(Accounts!$E:$E,'AccountSummary (New)'!K$1,Accounts!$G:$G,'AccountSummary (New)'!K$2,Accounts!$F:$F,'AccountSummary (New)'!K$3,Accounts!$B:$B,"none",Accounts!$BF:$BF,FALSE) -> 0 | L5: =COUNTIFS(Accounts!$E:$E,'AccountSummary (New)'!L$1,Accounts!$G:$G,'AccountSummary (New)'!L$2,Accounts!$F:$F,'AccountSummary (New)'!L$3,Accounts!$B:$B,"none",Accounts!$BF:$BF,FALSE) -> 0 | M5: =COUNTIFS(Accounts!$E:$E,'AccountSummary (New)'!M$1,Accounts!$G:$G,'AccountSummary (New)'!M$2,Accounts!$F:$F,'AccountSummary (New)'!M$3,Accounts!$B:$B,"none",Accounts!$BF:$BF,FALSE) -> 0 | N5: =COUNTIFS(Accounts!$E:$E,'AccountSummary (New)'!N$1,Accounts!$G:$G,'AccountSummary (New)'!N$2,Accounts!$F:$F,'AccountSummary (New)'!N$3,Accounts!$B:$B,"none",Accounts!$BF:$BF,FALSE) -> 0 | O5: =COUNTIFS(Accounts!$E:$E,'AccountSummary (New)'!O$1,Accounts!$G:$G,'AccountSummary (New)'!O$2,Accounts!$F:$F,'AccountSummary (New)'!O$3,Accounts!$B:$B,"none",Accounts!$BF:$BF,FALSE)+COUNTIFS(Accounts!$E:$E,"QuickBooks",Accounts!$G:$G,'AccountSummary (New)'!O$2,Accounts!$F:$F,'AccountSummary (New)'!O$3,Accounts!$B:$B,"none",Accounts!$BF:$BF,FALSE) -> 0 | P5: =SUM(J5:O5) -> 0 | Q5: =COUNTIFS(Accounts!$E:$E,'AccountSummary (New)'!Q$1,Accounts!$G:$G,'AccountSummary (New)'!Q$2,Accounts!$F:$F,'AccountSummary (New)'!Q$3,Accounts!$B:$B,"none",Accounts!$BF:$BF,FALSE) -> 0 | R5: =COUNTIFS(Accounts!$E:$E,'AccountSummary (New)'!R$1,Accounts!$G:$G,'AccountSummary (New)'!R$2,Accounts!$F:$F,'AccountSummary (New)'!R$3,Accounts!$B:$B,"none",Accounts!$BF:$BF,FALSE) -> 0 | S5: =COUNTIFS(Accounts!$E:$E,'AccountSummary (New)'!S$1,Accounts!$G:$G,'AccountSummary (New)'!S$2,Accounts!$F:$F,'AccountSummary (New)'!S$3,Accounts!$B:$B,"none",Accounts!$BF:$BF,FALSE) -> 0 | T5: =COUNTIFS(Accounts!$E:$E,'AccountSummary (New)'!T$1,Accounts!$G:$G,'AccountSummary (New)'!T$2,Accounts!$F:$F,'AccountSummary (New)'!T$3,Accounts!$B:$B,"none",Accounts!$BF:$BF,FALSE) -> 0 | U5: =COUNTIFS(Accounts!$E:$E,'AccountSummary (New)'!U$1,Accounts!$G:$G,'AccountSummary (New)'!U$2,Accounts!$F:$F,'AccountSummary (New)'!U$3,Accounts!$B:$B,"none",Accounts!$BF:$BF,FALSE) -> 0 | V5: =COUNTIFS(Accounts!$E:$E,'AccountSummary (New)'!V$1,Accounts!$G:$G,'AccountSummary (New)'!V$2,Accounts!$F:$F,'AccountSummary (New)'!V$3,Accounts!$B:$B,"none",Accounts!$BF:$BF,FALSE)+COUNTIFS(Accounts!$E:$E,"QuickBooks",Accounts!$G:$G,'AccountSummary (New)'!V$2,Accounts!$F:$F,'AccountSummary (New)'!V$3,Accounts!$B:$B,"none",Accounts!$BF:$BF,FALSE) -> 0 | W5: =SUM(Q5:V5) -> 0
A7: Made their first payment | B7: =I7+P7+W7 -> 0 | C7: =COUNTIFS(Accounts!$E:$E,'AccountSummary (New)'!C$1,Accounts!$G:$G,'AccountSummary (New)'!C$2,Accounts!$F:$F,'AccountSummary (New)'!C$3,Accounts!$W:$W,1) -> 0 | D7: =COUNTIFS(Accounts!$E:$E,'AccountSummary (New)'!D$1,Accounts!$G:$G,'AccountSummary (New)'!D$2,Accounts!$F:$F,'AccountSummary (New)'!D$3,Accounts!$W:$W,1) -> 0 | E7: =COUNTIFS(Accounts!$E:$E,'AccountSummary (New)'!E$1,Accounts!$G:$G,'AccountSummary (New)'!E$2,Accounts!$F:$F,'AccountSummary (New)'!E$3,Accounts!$W:$W,1) -> 0 | F7: =COUNTIFS(Accounts!$E:$E,'AccountSummary (New)'!F$1,Accounts!$G:$G,'AccountSummary (New)'!F$2,Accounts!$F:$F,'AccountSummary (New)'!F$3,Accounts!$W:$W,1) -> 0 | G7: =COUNTIFS(Accounts!$E:$E,'AccountSummary (New)'!G$1,Accounts!$G:$G,'AccountSummary (New)'!G$2,Accounts!$F:$F,'AccountSummary (New)'!G$3,Accounts!$W:$W,1) -> 0 | H7: =COUNTIFS(Accounts!$E:$E,'AccountSummary (New)'!H$1,Accounts!$G:$G,'AccountSummary (New)'!H$2,Accounts!$F:$F,'AccountSummary (New)'!H$3,Accounts!$W:$W,1) -> 0 | I7: =SUM(C7:H7) -> 0 | J7: =COUNTIFS(Accounts!$E:$E,'AccountSummary (New)'!J$1,Accounts!$G:$G,'AccountSummary (New)'!J$2,Accounts!$F:$F,'AccountSummary (New)'!J$3,Accounts!$W:$W,1) -> 0 | K7: =COUNTIFS(Accounts!$E:$E,'AccountSummary (New)'!K$1,Accounts!$G:$G,'AccountSummary (New)'!K$2,Accounts!$F:$F,'AccountSummary (New)'!K$3,Accounts!$W:$W,1) -> 0 | L7: =COUNTIFS(Accounts!$E:$E,'AccountSummary (New)'!L$1,Accounts!$G:$G,'AccountSummary (New)'!L$2,Accounts!$F:$F,'AccountSummary (New)'!L$3,Accounts!$W:$W,1) -> 0 | M7: =COUNTIFS(Accounts!$E:$E,'AccountSummary (New)'!M$1,Accounts!$G:$G,'AccountSummary (New)'!M$2,Accounts!$F:$F,'AccountSummary (New)'!M$3,Accounts!$W:$W,1) -> 0 | N7: =COUNTIFS(Accounts!$E:$E,'AccountSummary (New)'!N$1,Accounts!$G:$G,'AccountSummary (New)'!N$2,Accounts!$F:$F,'AccountSummary (New)'!N$3,Accounts!$W:$W,1) -> 0 | O7: =COUNTIFS(Accounts!$E:$E,'AccountSummary (New)'!O$1,Accounts!$G:$G,'AccountSummary (New)'!O$2,Accounts!$F:$F,'AccountSummary (New)'!O$3,Accounts!$W:$W,1) -> 0 | P7: =SUM(J7:O7) -> 0 | Q7: =COUNTIFS(Accounts!$E:$E,'AccountSummary (New)'!Q$1,Accounts!$G:$G,'AccountSummary (New)'!Q$2,Accounts!$F:$F,'AccountSummary (New)'!Q$3,Accounts!$W:$W,1) -> 0 | R7: =COUNTIFS(Accounts!$E:$E,'AccountSummary (New)'!R$1,Accounts!$G:$G,'AccountSummary (New)'!R$2,Accounts!$F:$F,'AccountSummary (New)'!R$3,Accounts!$W:$W,1) -> 0 | S7: =COUNTIFS(Accounts!$E:$E,'AccountSummary (New)'!S$1,Accounts!$G:$G,'AccountSummary (New)'!S$2,Accounts!$F:$F,'AccountSummary (New)'!S$3,Accounts!$W:$W,1) -> 0 | T7: =COUNTIFS(Accounts!$E:$E,'AccountSummary (New)'!T$1,Accounts!$G:$G,'AccountSummary (New)'!T$2,Accounts!$F:$F,'AccountSummary (New)'!T$3,Accounts!$W:$W,1) -> 0 | U7: =COUNTIFS(Accounts!$E:$E,'AccountSummary (New)'!U$1,Accounts!$G:$G,'AccountSummary (New)'!U$2,Accounts!$F:$F,'AccountSummary (New)'!U$3,Accounts!$W:$W,1) -> 0 | V7: =COUNTIFS(Accounts!$E:$E,'AccountSummary (New)'!V$1,Accounts!$G:$G,'AccountSummary (New)'!V$2,Accounts!$F:$F,'AccountSummary (New)'!V$3,Accounts!$W:$W,1) -> 0 | W7: =SUM(Q7:V7) -> 0
A8: Packs per Account | B8: =IF(B7=0,0,SUMIFS(Accounts!$L:$L,Accounts!$W:$W,1)/B7) -> 0 | C8: =IF(C7=0,0,SUMIFS(Accounts!$L:$L,Accounts!$E:$E,'AccountSummary (New)'!C$1,Accounts!$G:$G,'AccountSummary (New)'!C$2,Accounts!$F:$F,'AccountSummary (New)'!C$3,Accounts!$W:$W,1)/C7) -> 0 | D8: =IF(D7=0,0,SUMIFS(Accounts!$L:$L,Accounts!$E:$E,'AccountSummary (New)'!D$1,Accounts!$G:$G,'AccountSummary (New)'!D$2,Accounts!$F:$F,'AccountSummary (New)'!D$3,Accounts!$W:$W,1)/D7) -> 0 | E8: =IF(E7=0,0,SUMIFS(Accounts!$L:$L,Accounts!$E:$E,'AccountSummary (New)'!E$1,Accounts!$G:$G,'AccountSummary (New)'!E$2,Accounts!$F:$F,'AccountSummary (New)'!E$3,Accounts!$W:$W,1)/E7) -> 0 | F8: =IF(F7=0,0,SUMIFS(Accounts!$L:$L,Accounts!$E:$E,'AccountSummary (New)'!F$1,Accounts!$G:$G,'AccountSummary (New)'!F$2,Accounts!$F:$F,'AccountSummary (New)'!F$3,Accounts!$W:$W,1)/F7) -> 0 | G8: =IF(G7=0,0,SUMIFS(Accounts!$L:$L,Accounts!$E:$E,'AccountSummary (New)'!G$1,Accounts!$G:$G,'AccountSummary (New)'!G$2,Accounts!$F:$F,'AccountSummary (New)'!G$3,Accounts!$W:$W,1)/G7) -> 0 | H8: =IF(H7=0,0,SUMIFS(Accounts!$L:$L,Accounts!$E:$E,'AccountSummary (New)'!H$1,Accounts!$G:$G,'AccountSummary (New)'!H$2,Accounts!$F:$F,'AccountSummary (New)'!H$3,Accounts!$W:$W,1)/H7) -> 0 | I8: =IF(I7=0,0,SUMIFS(Accounts!$L:$L,Accounts!$F:$F,'AccountSummary (New)'!I$3,Accounts!$W:$W,1)/I7) -> 0 | J8: =IF(J7=0,0,SUMIFS(Accounts!$L:$L,Accounts!$E:$E,'AccountSummary (New)'!J$1,Accounts!$G:$G,'AccountSummary (New)'!J$2,Accounts!$F:$F,'AccountSummary (New)'!J$3,Accounts!$W:$W,1)/J7) -> 0 | K8: =IF(K7=0,0,SUMIFS(Accounts!$L:$L,Accounts!$E:$E,'AccountSummary (New)'!K$1,Accounts!$G:$G,'AccountSummary (New)'!K$2,Accounts!$F:$F,'AccountSummary (New)'!K$3,Accounts!$W:$W,1)/K7) -> 0 | L8: =IF(L7=0,0,SUMIFS(Accounts!$L:$L,Accounts!$E:$E,'AccountSummary (New)'!L$1,Accounts!$G:$G,'AccountSummary (New)'!L$2,Accounts!$F:$F,'AccountSummary (New)'!L$3,Accounts!$W:$W,1)/L7) -> 0 | M8: =IF(M7=0,0,SUMIFS(Accounts!$L:$L,Accounts!$E:$E,'AccountSummary (New)'!M$1,Accounts!$G:$G,'AccountSummary (New)'!M$2,Accounts!$F:$F,'AccountSummary (New)'!M$3,Accounts!$W:$W,1)/M7) -> 0 | N8: =IF(N7=0,0,SUMIFS(Accounts!$L:$L,Accounts!$E:$E,'AccountSummary (New)'!N$1,Accounts!$G:$G,'AccountSummary (New)'!N$2,Accounts!$F:$F,'AccountSummary (New)'!N$3,Accounts!$W:$W,1)/N7) -> 0 | O8: =IF(O7=0,0,SUMIFS(Accounts!$L:$L,Accounts!$E:$E,'AccountSummary (New)'!O$1,Accounts!$G:$G,'AccountSummary (New)'!O$2,Accounts!$F:$F,'AccountSummary (New)'!O$3,Accounts!$W:$W,1)/O7) -> 0 | P8: =IF(P7=0,0,SUMIFS(Accounts!$L:$L,Accounts!$F:$F,'AccountSummary (New)'!P$3,Accounts!$W:$W,1)/P7) -> 0 | Q8: =IF(Q7=0,0,SUMIFS(Accounts!$L:$L,Accounts!$E:$E,'AccountSummary (New)'!Q$1,Accounts!$G:$G,'AccountSummary (New)'!Q$2,Accounts!$F:$F,'AccountSummary (New)'!Q$3,Accounts!$W:$W,1)/Q7) -> 0 | R8: =IF(R7=0,0,SUMIFS(Accounts!$L:$L,Accounts!$E:$E,'AccountSummary (New)'!R$1,Accounts!$G:$G,'AccountSummary (New)'!R$2,Accounts!$F:$F,'AccountSummary (New)'!R$3,Accounts!$W:$W,1)/R7) -> 0 | S8: =IF(S7=0,0,SUMIFS(Accounts!$L:$L,Accounts!$E:$E,'AccountSummary (New)'!S$1,Accounts!$G:$G,'AccountSummary (New)'!S$2,Accounts!$F:$F,'AccountSummary (New)'!S$3,Accounts!$W:$W,1)/S7) -> 0 | T8: =IF(T7=0,0,SUMIFS(Accounts!$L:$L,Accounts!$E:$E,'AccountSummary (New)'!T$1,Accounts!$G:$G,'AccountSummary (New)'!T$2,Accounts!$F:$F,'AccountSummary (New)'!T$3,Accounts!$W:$W,1)/T7) -> 0 | U8: =IF(U7=0,0,SUMIFS(Accounts!$L:$L,Accounts!$E:$E,'AccountSummary (New)'!U$1,Accounts!$G:$G,'AccountSummary (New)'!U$2,Accounts!$F:$F,'AccountSummary (New)'!U$3,Accounts!$W:$W,1)/U7) -> 0 | V8: =IF(V7=0,0,SUMIFS(Accounts!$L:$L,Accounts!$E:$E,'AccountSummary (New)'!V$1,Accounts!$G:$G,'AccountSummary (New)'!V$2,Accounts!$F:$F,'AccountSummary (New)'!V$3,Accounts!$W:$W,1)/V7) -> 0 | W8: =IF(W7=0,0,SUMIFS(Accounts!$L:$L,Accounts!$F:$F,'AccountSummary (New)'!W$3,Accounts!$W:$W,1)/W7) -> 0
A9: Users per Account | B9: =IF(B7=0,0,SUMIFS(Accounts!$M:$M,Accounts!$W:$W,1)/B7) -> 0 | C9: =IF(C7=0,0,SUMIFS(Accounts!$M:$M,Accounts!$E:$E,'AccountSummary (New)'!C$1,Accounts!$G:$G,'AccountSummary (New)'!C$2,Accounts!$F:$F,'AccountSummary (New)'!C$3,Accounts!$W:$W,1)/C7) -> 0 | D9: =IF(D7=0,0,SUMIFS(Accounts!$M:$M,Accounts!$E:$E,'AccountSummary (New)'!D$1,Accounts!$G:$G,'AccountSummary (New)'!D$2,Accounts!$F:$F,'AccountSummary (New)'!D$3,Accounts!$W:$W,1)/D7) -> 0 | E9: =IF(E7=0,0,SUMIFS(Accounts!$M:$M,Accounts!$E:$E,'AccountSummary (New)'!E$1,Accounts!$G:$G,'AccountSummary (New)'!E$2,Accounts!$F:$F,'AccountSummary (New)'!E$3,Accounts!$W:$W,1)/E7) -> 0 | F9: =IF(F7=0,0,SUMIFS(Accounts!$M:$M,Accounts!$E:$E,'AccountSummary (New)'!F$1,Accounts!$G:$G,'AccountSummary (New)'!F$2,Accounts!$F:$F,'AccountSummary (New)'!F$3,Accounts!$W:$W,1)/F7) -> 0 | G9: =IF(G7=0,0,SUMIFS(Accounts!$M:$M,Accounts!$E:$E,'AccountSummary (New)'!G$1,Accounts!$G:$G,'AccountSummary (New)'!G$2,Accounts!$F:$F,'AccountSummary (New)'!G$3,Accounts!$W:$W,1)/G7) -> 0 | H9: =IF(H7=0,0,SUMIFS(Accounts!$M:$M,Accounts!$E:$E,'AccountSummary (New)'!H$1,Accounts!$G:$G,'AccountSummary (New)'!H$2,Accounts!$F:$F,'AccountSummary (New)'!H$3,Accounts!$W:$W,1)/H7) -> 0 | I9: =IF(I7=0,0,SUMIFS(Accounts!$M:$M,Accounts!$F:$F,'AccountSummary (New)'!I$3,Accounts!$W:$W,1)/I7) -> 0 | J9: =IF(J7=0,0,SUMIFS(Accounts!$M:$M,Accounts!$E:$E,'AccountSummary (New)'!J$1,Accounts!$G:$G,'AccountSummary (New)'!J$2,Accounts!$F:$F,'AccountSummary (New)'!J$3,Accounts!$W:$W,1)/J7) -> 0 | K9: =IF(K7=0,0,SUMIFS(Accounts!$M:$M,Accounts!$E:$E,'AccountSummary (New)'!K$1,Accounts!$G:$G,'AccountSummary (New)'!K$2,Accounts!$F:$F,'AccountSummary (New)'!K$3,Accounts!$W:$W,1)/K7) -> 0 | L9: =IF(L7=0,0,SUMIFS(Accounts!$M:$M,Accounts!$E:$E,'AccountSummary (New)'!L$1,Accounts!$G:$G,'AccountSummary (New)'!L$2,Accounts!$F:$F,'AccountSummary (New)'!L$3,Accounts!$W:$W,1)/L7) -> 0 | M9: =IF(M7=0,0,SUMIFS(Accounts!$M:$M,Accounts!$E:$E,'AccountSummary (New)'!M$1,Accounts!$G:$G,'AccountSummary (New)'!M$2,Accounts!$F:$F,'AccountSummary (New)'!M$3,Accounts!$W:$W,1)/M7) -> 0 | N9: =IF(N7=0,0,SUMIFS(Accounts!$M:$M,Accounts!$E:$E,'AccountSummary (New)'!N$1,Accounts!$G:$G,'AccountSummary (New)'!N$2,Accounts!$F:$F,'AccountSummary (New)'!N$3,Accounts!$W:$W,1)/N7) -> 0 | O9: =IF(O7=0,0,SUMIFS(Accounts!$M:$M,Accounts!$E:$E,'AccountSummary (New)'!O$1,Accounts!$G:$G,'AccountSummary (New)'!O$2,Accounts!$F:$F,'AccountSummary (New)'!O$3,Accounts!$W:$W,1)/O7) -> 0 | P9: =IF(P7=0,0,SUMIFS(Accounts!$M:$M,Accounts!$F:$F,'AccountSummary (New)'!P$3,Accounts!$W:$W,1)/P7) -> 0 | Q9: =IF(Q7=0,0,SUMIFS(Accounts!$M:$M,Accounts!$E:$E,'AccountSummary (New)'!Q$1,Accounts!$G:$G,'AccountSummary (New)'!Q$2,Accounts!$F:$F,'AccountSummary (New)'!Q$3,Accounts!$W:$W,1)/Q7) -> 0 | R9: =IF(R7=0,0,SUMIFS(Accounts!$M:$M,Accounts!$E:$E,'AccountSummary (New)'!R$1,Accounts!$G:$G,'AccountSummary (New)'!R$2,Accounts!$F:$F,'AccountSummary (New)'!R$3,Accounts!$W:$W,1)/R7) -> 0 | S9: =IF(S7=0,0,SUMIFS(Accounts!$M:$M,Accounts!$E:$E,'AccountSummary (New)'!S$1,Accounts!$G:$G,'AccountSummary (New)'!S$2,Accounts!$F:$F,'AccountSummary (New)'!S$3,Accounts!$W:$W,1)/S7) -> 0 | T9: =IF(T7=0,0,SUMIFS(Accounts!$M:$M,Accounts!$E:$E,'AccountSummary (New)'!T$1,Accounts!$G:$G,'AccountSummary (New)'!T$2,Accounts!$F:$F,'AccountSummary (New)'!T$3,Accounts!$W:$W,1)/T7) -> 0 | U9: =IF(U7=0,0,SUMIFS(Accounts!$M:$M,Accounts!$E:$E,'AccountSummary (New)'!U$1,Accounts!$G:$G,'AccountSummary (New)'!U$2,Accounts!$F:$F,'AccountSummary (New)'!U$3,Accounts!$W:$W,1)/U7) -> 0 | V9: =IF(V7=0,0,SUMIFS(Accounts!$M:$M,Accounts!$E:$E,'AccountSummary (New)'!V$1,Accounts!$G:$G,'AccountSummary (New)'!V$2,Accounts!$F:$F,'AccountSummary (New)'!V$3,Accounts!$W:$W,1)/V7) -> 0 | W9: =IF(W7=0,0,SUMIFS(Accounts!$M:$M,Accounts!$F:$F,'AccountSummary (New)'!W$3,Accounts!$W:$W,1)/W7) -> 0
A10: ARPC First Invoice | B10: =IF(B7=0,0,B11/B7) -> 0 | C10: =IF(C7=0,0,C11/C7) -> 0 | D10: =IF(D7=0,0,D11/D7) -> 0 | E10: =IF(E7=0,0,E11/E7) -> 0 | F10: =IF(F7=0,0,F11/F7) -> 0 | G10: =IF(G7=0,0,G11/G7) -> 0 | H10: =IF(H7=0,0,H11/H7) -> 0 | I10: =IF(I7=0,0,I11/I7) -> 0 | ... W10: =IF(W7=0,0,W11/W7) -> 0
A11: Total SaaS from Trialers | B11: =I11+P11+W11 -> 0 | C11: =SUMIFS(Accounts!$I:$I,Accounts!$E:$E,'AccountSummary (New)'!C$1,Accounts!$G:$G,'AccountSummary (New)'!C$2,Accounts!$F:$F,'AccountSummary (New)'!C$3,Accounts!$W:$W,1) -> 0 | D11: =SUMIFS(Accounts!$I:$I,Accounts!$E:$E,'AccountSummary (New)'!D$1,Accounts!$G:$G,'AccountSummary (New)'!D$2,Accounts!$F:$F,'AccountSummary (New)'!D$3,Accounts!$W:$W,1) -> 0 | E11: =SUMIFS(Accounts!$I:$I,Accounts!$E:$E,'AccountSummary (New)'!E$1,Accounts!$G:$G,'AccountSummary (New)'!E$2,Accounts!$F:$F,'AccountSummary (New)'!E$3,Accounts!$W:$W,1) -> 0 | F11: =SUMIFS(Accounts!$I:$I,Accounts!$E:$E,'AccountSummary (New)'!F$1,Accounts!$G:$G,'AccountSummary (New)'!F$2,Accounts!$F:$F,'AccountSummary (New)'!F$3,Accounts!$W:$W,1) -> 0 | G11: =SUMIFS(Accounts!$I:$I,Accounts!$E:$E,'AccountSummary (New)'!G$1,Accounts!$G:$G,'AccountSummary (New)'!G$2,Accounts!$F:$F,'AccountSummary (New)'!G$3,Accounts!$W:$W,1) -> 0 | H11: =SUMIFS(Accounts!$I:$I,Accounts!$E:$E,'AccountSummary (New)'!H$1,Accounts!$G:$G,'AccountSummary (New)'!H$2,Accounts!$F:$F,'AccountSummary (New)'!H$3,Accounts!$W:$W,1) -> 0 | I11: =SUM(C11:F11) -> 0 | J11: =SUMIFS(Accounts!$I:$I,Accounts!$E:$E,'AccountSummary (New)'!J$1,Accounts!$G:$G,'AccountSummary (New)'!J$2,Accounts!$F:$F,'AccountSummary (New)'!J$3,Accounts!$W:$W,1) -> 0 | K11: =SUMIFS(Accounts!$I:$I,Accounts!$E:$E,'AccountSummary (New)'!K$1,Accounts!$G:$G,'AccountSummary (New)'!K$2,Accounts!$F:$F,'AccountSummary (New)'!K$3,Accounts!$W:$W,1) -> 0 | L11: =SUMIFS(Accounts!$I:$I,Accounts!$E:$E,'AccountSummary (New)'!L$1,Accounts!$G:$G,'AccountSummary (New)'!L$2,Accounts!$F:$F,'AccountSummary (New)'!L$3,Accounts!$W:$W,1) -> 0 | M11: =SUMIFS(Accounts!$I:$I,Accounts!$E:$E,'AccountSummary (New)'!M$1,Accounts!$G:$G,'AccountSummary (New)'!M$2,Accounts!$F:$F,'AccountSummary (New)'!M$3,Accounts!$W:$W,1) -> 0 | N11: =SUMIFS(Accounts!$I:$I,Accounts!$E:$E,'AccountSummary (New)'!N$1,Accounts!$G:$G,'AccountSummary (New)'!N$2,Accounts!$F:$F,'AccountSummary (New)'!N$3,Accounts!$W:$W,1) -> 0 | O11: =SUMIFS(Accounts!$I:$I,Accounts!$E:$E,'AccountSummary (New)'!O$1,Accounts!$G:$G,'AccountSummary (New)'!O$2,Accounts!$F:$F,'AccountSummary (New)'!O$3,Accounts!$W:$W,1) -> 0 | P11: =SUM(J11:M11) -> 0 | Q11: =SUMIFS(Accounts!$I:$I,Accounts!$E:$E,'AccountSummary (New)'!Q$1,Accounts!$G:$G,'AccountSummary (New)'!Q$2,Accounts!$F:$F,'AccountSummary (New)'!Q$3,Accounts!$W:$W,1) -> 0 | R11: =SUMIFS(Accounts!$I:$I,Accounts!$E:$E,'AccountSummary (New)'!R$1,Accounts!$G:$G,'AccountSummary (New)'!R$2,Accounts!$F:$F,'AccountSummary (New)'!R$3,Accounts!$W:$W,1) -> 0 | S11: =SUMIFS(Accounts!$I:$I,Accounts!$E:$E,'AccountSummary (New)'!S$1,Accounts!$G:$G,'AccountSummary (New)'!S$2,Accounts!$F:$F,'AccountSummary (New)'!S$3,Accounts!$W:$W,1) -> 0 | T11: =SUMIFS(Accounts!$I:$I,Accounts!$E:$E,'AccountSummary (New)'!T$1,Accounts!$G:$G,'AccountSummary (New)'!T$2,Accounts!$F:$F,'AccountSummary (New)'!T$3,Accounts!$W:$W,1) -> 0 | U11: =SUMIFS(Accounts!$I:$I,Accounts!$E:$E,'AccountSummary (New)'!U$1,Accounts!$G:$G,'AccountSummary (New)'!U$2,Accounts!$F:$F,'AccountSummary (New)'!U$3,Accounts!$W:$W,1) -> 0 | V11: =SUMIFS(Accounts!$I:$I,Accounts!$E:$E,'AccountSummary (New)'!V$1,Accounts!$G:$G,'AccountSummary (New)'!V$2,Accounts!$F:$F,'AccountSummary (New)'!V$3,Accounts!$W:$W,1) -> 0 | W11: =SUM(Q11:V11) -> 0
A13: Trialers Lost in month they paid
A14: % who cancel | B14: =IF(B7=0,0,B15/B7) -> 0 | C14: =IF(C7=0,0,C15/C7) -> 0 | D14: =IF(D7=0,0,D15/D7) -> 0 | E14: =IF(E7=0,0,E15/E7) -> 0 | F14: =IF(F7=0,0,F15/F7) -> 0 | G14: =IF(G7=0,0,G15/G7) -> 0 | H14: =IF(H7=0,0,H15/H7) -> 0 | I14: =IF(I7=0,0,I15/I7) -> 0 | ... W14: =IF(W7=0,0,W15/W7) -> 0
A15: Paid but cancelled before EOM | B15: =I15+P15+W15 -> 0 | C15: =COUNTIFS(Accounts!$E:$E,'AccountSummary (New)'!C$1,Accounts!$G:$G,'AccountSummary (New)'!C$2,Accounts!$F:$F,'AccountSummary (New)'!C$3,Accounts!$W:$W,1,Accounts!$C:$C,"Lost") -> 0 | D15: =COUNTIFS(Accounts!$E:$E,'AccountSummary (New)'!D$1,Accounts!$G:$G,'AccountSummary (New)'!D$2,Accounts!$F:$F,'AccountSummary (New)'!D$3,Accounts!$W:$W,1,Accounts!$C:$C,"Lost") -> 0 | E15: =COUNTIFS(Accounts!$E:$E,'AccountSummary (New)'!E$1,Accounts!$G:$G,'AccountSummary (New)'!E$2,Accounts!$F:$F,'AccountSummary (New)'!E$3,Accounts!$W:$W,1,Accounts!$C:$C,"Lost") -> 0 | F15: =COUNTIFS(Accounts!$E:$E,'AccountSummary (New)'!F$1,Accounts!$G:$G,'AccountSummary (New)'!F$2,Accounts!$F:$F,'AccountSummary (New)'!F$3,Accounts!$W:$W,1,Accounts!$C:$C,"Lost") -> 0 | G15: =COUNTIFS(Accounts!$E:$E,'AccountSummary (New)'!G$1,Accounts!$G:$G,'AccountSummary (New)'!G$2,Accounts!$F:$F,'AccountSummary (New)'!G$3,Accounts!$W:$W,1,Accounts!$C:$C,"Lost") -> 0 | H15: =COUNTIFS(Accounts!$E:$E,'AccountSummary (New)'!H$1,Accounts!$G:$G,'AccountSummary (New)'!H$2,Accounts!$F:$F,'AccountSummary (New)'!H$3,Accounts!$W:$W,1,Accounts!$C:$C,"Lost") -> 0 | I15: =SUM(C15:H15) -> 0 | J15: =COUNTIFS(Accounts!$E:$E,'AccountSummary (New)'!J$1,Accounts!$G:$G,'AccountSummary (New)'!J$2,Accounts!$F:$F,'AccountSummary (New)'!J$3,Accounts!$W:$W,1,Accounts!$C:$C,"Lost") -> 0 | K15: =COUNTIFS(Accounts!$E:$E,'AccountSummary (New)'!K$1,Accounts!$G:$G,'AccountSummary (New)'!K$2,Accounts!$F:$F,'AccountSummary (New)'!K$3,Accounts!$W:$W,1,Accounts!$C:$C,"Lost") -> 0 | L15: =COUNTIFS(Accounts!$E:$E,'AccountSummary (New)'!L$1,Accounts!$G:$G,'AccountSummary (New)'!L$2,Accounts!$F:$F,'AccountSummary (New)'!L$3,Accounts!$W:$W,1,Accounts!$C:$C,"Lost") -> 0 | M15: =COUNTIFS(Accounts!$E:$E,'AccountSummary (New)'!M$1,Accounts!$G:$G,'AccountSummary (New)'!M$2,Accounts!$F:$F,'AccountSummary (New)'!M$3,Accounts!$W:$W,1,Accounts!$C:$C,"Lost") -> 0 | N15: =COUNTIFS(Accounts!$E:$E,'AccountSummary (New)'!N$1,Accounts!$G:$G,'AccountSummary (New)'!N$2,Accounts!$F:$F,'AccountSummary (New)'!N$3,Accounts!$W:$W,1,Accounts!$C:$C,"Lost") -> 0 | O15: =COUNTIFS(Accounts!$E:$E,'AccountSummary (New)'!O$1,Accounts!$G:$G,'AccountSummary (New)'!O$2,Accounts!$F:$F,'AccountSummary (New)'!O$3,Accounts!$W:$W,1,Accounts!$C:$C,"Lost") -> 0 | P15: =SUM(J15:O15) -> 0 | Q15: =COUNTIFS(Accounts!$E:$E,'AccountSummary (New)'!Q$1,Accounts!$G:$G,'AccountSummary (New)'!Q$2,Accounts!$F:$F,'AccountSummary (New)'!Q$3,Accounts!$W:$W,1,Accounts!$C:$C,"Lost") -> 0 | R15: =COUNTIFS(Accounts!$E:$E,'AccountSummary (New)'!R$1,Accounts!$G:$G,'AccountSummary (New)'!R$2,Accounts!$F:$F,'AccountSummary (New)'!R$3,Accounts!$W:$W,1,Accounts!$C:$C,"Lost") -> 0 | S15: =COUNTIFS(Accounts!$E:$E,'AccountSummary (New)'!S$1,Accounts!$G:$G,'AccountSummary (New)'!S$2,Accounts!$F:$F,'AccountSummary (New)'!S$3,Accounts!$W:$W,1,Accounts!$C:$C,"Lost") -> 0 | T15: =COUNTIFS(Accounts!$E:$E,'AccountSummary (New)'!T$1,Accounts!$G:$G,'AccountSummary (New)'!T$2,Accounts!$F:$F,'AccountSummary (New)'!T$3,Accounts!$W:$W,1,Accounts!$C:$C,"Lost") -> 0 | U15: =COUNTIFS(Accounts!$E:$E,'AccountSummary (New)'!U$1,Accounts!$G:$G,'AccountSummary (New)'!U$2,Accounts!$F:$F,'AccountSummary (New)'!U$3,Accounts!$W:$W,1,Accounts!$C:$C,"Lost") -> 0 | V15: =COUNTIFS(Accounts!$E:$E,'AccountSummary (New)'!V$1,Accounts!$G:$G,'AccountSummary (New)'!V$2,Accounts!$F:$F,'AccountSummary (New)'!V$3,Accounts!$W:$W,1,Accounts!$C:$C,"Lost") -> 0 | W15: =SUM(Q15:V15) -> 0
A16: Net: Paid, retained EOM | B16: =I16+P16+W16 -> 0 | C16: =C7-C15 -> 0 | D16: =D7-D15 -> 0 | E16: =E7-E15 -> 0 | F16: =F7-F15 -> 0 | G16: =G7-G15 -> 0 | H16: =H7-H15 -> 0 | I16: =SUM(C16:H16) -> 0 | J16: =J7-J15 -> 0 | K16: =K7-K15 -> 0 | L16: =L7-L15 -> 0 | M16: =M7-M15 -> 0 | N16: =N7-N15 -> 0 | O16: =O7-O15 -> 0 | P16: =SUM(J16:O16) -> 0 | Q16: =Q7-Q15 -> 0 | R16: =R7-R15 -> 0 | S16: =S7-S15 -> 0 | T16: =T7-T15 -> 0 | U16: =U7-U15 -> 0 | V16: =V7-V15 -> 0 | W16: =SUM(Q16:V16) -> 0
A18: *Paying Customers*
A19: Starting Count BOM | B19: =I19+P19+W19 -> 1 | C19: =COUNTIFS(Accounts!$E:$E,'AccountSummary (New)'!C$1,Accounts!$G:$G,'AccountSummary (New)'!C$2,Accounts!$F:$F,'AccountSummary (New)'!C$3,Accounts!$B:$B,"Customer") -> 0 | D19: =COUNTIFS(Accounts!$E:$E,'AccountSummary (New)'!D$1,Accounts!$G:$G,'AccountSummary (New)'!D$2,Accounts!$F:$F,'AccountSummary (New)'!D$3,Accounts!$B:$B,"Customer") -> 0 | E19: =COUNTIFS(Accounts!$E:$E,'AccountSummary (New)'!E$1,Accounts!$G:$G,'AccountSummary (New)'!E$2,Accounts!$F:$F,'AccountSummary (New)'!E$3,Accounts!$B:$B,"Customer") -> 0 | F19: =COUNTIFS(Accounts!$E:$E,'AccountSummary (New)'!F$1,Accounts!$G:$G,'AccountSummary (New)'!F$2,Accounts!$F:$F,'AccountSummary (New)'!F$3,Accounts!$B:$B,"Customer") -> 0 | G19: =COUNTIFS(Accounts!$E:$E,'AccountSummary (New)'!G$1,Accounts!$G:$G,'AccountSummary (New)'!G$2,Accounts!$F:$F,'AccountSummary (New)'!G$3,Accounts!$B:$B,"Customer") -> 0 | H19: =COUNTIFS(Accounts!$E:$E,'AccountSummary (New)'!H$1,Accounts!$G:$G,'AccountSummary (New)'!H$2,Accounts!$F:$F,'AccountSummary (New)'!H$3,Accounts!$B:$B,"Customer") -> 0 | I19: =SUM(C19:H19) -> 0 | J19: =COUNTIFS(Accounts!$E:$E,'AccountSummary (New)'!J$1,Accounts!$G:$G,'AccountSummary (New)'!J$2,Accounts!$F:$F,'AccountSummary (New)'!J$3,Accounts!$B:$B,"Customer") -> 0 | K19: =COUNTIFS(Accounts!$E:$E,'AccountSummary (New)'!K$1,Accounts!$G:$G,'AccountSummary (New)'!K$2,Accounts!$F:$F,'AccountSummary (New)'!K$3,Accounts!$B:$B,"Customer") -> 0 | L19: =COUNTIFS(Accounts!$E:$E,'AccountSummary (New)'!L$1,Accounts!$G:$G,'AccountSummary (New)'!L$2,Accounts!$F:$F,'AccountSummary (New)'!L$3,Accounts!$B:$B,"Customer") -> 0 | M19: =COUNTIFS(Accounts!$E:$E,'AccountSummary (New)'!M$1,Accounts!$G:$G,'AccountSummary (New)'!M$2,Accounts!$F:$F,'AccountSummary (New)'!M$3,Accounts!$B:$B,"Customer") -> 0 | N19: =COUNTIFS(Accounts!$E:$E,'AccountSummary (New)'!N$1,Accounts!$G:$G,'AccountSummary (New)'!N$2,Accounts!$F:$F,'AccountSummary (New)'!N$3,Accounts!$B:$B,"Customer") -> 0 | O19: =COUNTIFS(Accounts!$E:$E,'AccountSummary (New)'!O$1,Accounts!$G:$G,'AccountSummary (New)'!O$2,Accounts!$F:$F,'AccountSummary (New)'!O$3,Accounts!$B:$B,"Customer") -> 0 | P19: =SUM(J19:O19) -> 0 | Q19: =COUNTIFS(Accounts!$E:$E,'AccountSummary (New)'!Q$1,Accounts!$G:$G,'AccountSummary (New)'!Q$2,Accounts!$F:$F,'AccountSummary (New)'!Q$3,Accounts!$B:$B,"Customer") -> 0 | R19: =COUNTIFS(Accounts!$E:$E,'AccountSummary (New)'!R$1,Accounts!$G:$G,'AccountSummary (New)'!R$2,Accounts!$F:$F,'AccountSummary (New)'!R$3,Accounts!$B:$B,"Customer") -> 1 | S19: =COUNTIFS(Accounts!$E:$E,'AccountSummary (New)'!S$1,Accounts!$G:$G,'AccountSummary (New)'!S$2,Accounts!$F:$F,'AccountSummary (New)'!S$3,Accounts!$B:$B,"Customer") -> 0 | T19: =COUNTIFS(Accounts!$E:$E,'AccountSummary (New)'!T$1,Accounts!$G:$G,'AccountSummary (New)'!T$2,Accounts!$F:$F,'AccountSummary (New)'!T$3,Accounts!$B:$B,"Customer") -> 0 | U19: =COUNTIFS(Accounts!$E:$E,'AccountSummary (New)'!U$1,Accounts!$G:$G,'AccountSummary (New)'!U$2,Accounts!$F:$F,'AccountSummary (New)'!U$3,Accounts!$B:$B,"Customer") -> 0 | V19: =COUNTIFS(Accounts!$E:$E,'AccountSummary (New)'!V$1,Accounts!$G:$G,'AccountSummary (New)'!V$2,Accounts!$F:$F,'AccountSummary (New)'!V$3,Accounts!$B:$B,"Customer") -> 0 | W19: =SUM(Q19:V19) -> 1
A21: 0-30 day cohort as of BOM
A22: Total % of Paying Customers | B22: =IF(B$19=0,0,(B24+B25)/B$19) -> 0 | C22: =IF(C$19=0,0,(C24+C25)/C$19) -> 0 | D22: =IF(D$19=0,0,(D24+D25)/D$19) -> 0 | E22: =IF(E$19=0,0,(E24+E25)/E$19) -> 0 | F22: =IF(F$19=0,0,(F24+F25)/F$19) -> 0 | G22: =IF(G$19=0,0,(G24+G25)/G$19) -> 0 | H22: =IF(H$19=0,0,(H24+H25)/H$19) -> 0 | I22: =IF(I$19=0,0,(I24+I25)/I$19) -> 0 | ... W22: =IF(W$19=0,0,(W24+W25)/W$19) -> 0
A23: Loss % | B23: =IF((B24+B25)=0,0,B24/(B24+B25)) -> 0 | C23: =IF((C24+C25)=0,0,C24/(C24+C25)) -> 0 | D23: =IF((D24+D25)=0,0,D24/(D24+D25)) -> 0 | E23: =IF((E24+E25)=0,0,E24/(E24+E25)) -> 0 | F23: =IF((F24+F25)=0,0,F24/(F24+F25)) -> 0 | G23: =IF((G24+G25)=0,0,G24/(G24+G25)) -> 0 | H23: =IF((H24+H25)=0,0,H24/(H24+H25)) -> 0 | I23: =IF((I24+I25)=0,0,I24/(I24+I25)) -> 0 | ... W23: =IF((W24+W25)=0,0,W24/(W24+W25)) -> 0
A24: Lost Count | B24: =I24+P24+W24 -> 0 | C24: =COUNTIFS(Accounts!$E:$E,'AccountSummary (New)'!C$1,Accounts!$G:$G,'AccountSummary (New)'!C$2,Accounts!$F:$F,'AccountSummary (New)'!C$3,Accounts!$B:$B,"Customer",Accounts!$C:$C,"Lost",Accounts!$H:$H,"<="&30) -> 0 | D24: =COUNTIFS(Accounts!$E:$E,'AccountSummary (New)'!D$1,Accounts!$G:$G,'AccountSummary (New)'!D$2,Accounts!$F:$F,'AccountSummary (New)'!D$3,Accounts!$B:$B,"Customer",Accounts!$C:$C,"Lost",Accounts!$H:$H,"<="&30) -> 0 | E24: =COUNTIFS(Accounts!$E:$E,'AccountSummary (New)'!E$1,Accounts!$G:$G,'AccountSummary (New)'!E$2,Accounts!$F:$F,'AccountSummary (New)'!E$3,Accounts!$B:$B,"Customer",Accounts!$C:$C,"Lost",Accounts!$H:$H,"<="&30) -> 0 | F24: =COUNTIFS(Accounts!$E:$E,'AccountSummary (New)'!F$1,Accounts!$G:$G,'AccountSummary (New)'!F$2,Accounts!$F:$F,'AccountSummary (New)'!F$3,Accounts!$B:$B,"Customer",Accounts!$C:$C,"Lost",Accounts!$H:$H,"<="&30) -> 0 | G24: =COUNTIFS(Accounts!$E:$E,'AccountSummary (New)'!G$1,Accounts!$G:$G,'AccountSummary (New)'!G$2,Accounts!$F:$F,'AccountSummary (New)'!G$3,Accounts!$B:$B,"Customer",Accounts!$C:$C,"Lost",Accounts!$H:$H,"<="&30) -> 0 | H24: =COUNTIFS(Accounts!$E:$E,'AccountSummary (New)'!H$1,Accounts!$G:$G,'AccountSummary (New)'!H$2,Accounts!$F:$F,'AccountSummary (New)'!H$3,Accounts!$B:$B,"Customer",Accounts!$C:$C,"Lost",Accounts!$H:$H,"<="&30) -> 0 | I24: =SUM(C24:H24) -> 0 | J24: =COUNTIFS(Accounts!$E:$E,'AccountSummary (New)'!J$1,Accounts!$G:$G,'AccountSummary (New)'!J$2,Accounts!$F:$F,'AccountSummary (New)'!J$3,Accounts!$B:$B,"Customer",Accounts!$C:$C,"Lost",Accounts!$H:$H,"<="&30) -> 0 | K24: =COUNTIFS(Accounts!$E:$E,'AccountSummary (New)'!K$1,Accounts!$G:$G,'AccountSummary (New)'!K$2,Accounts!$F:$F,'AccountSummary (New)'!K$3,Accounts!$B:$B,"Customer",Accounts!$C:$C,"Lost",Accounts!$H:$H,"<="&30) -> 0 | L24: =COUNTIFS(Accounts!$E:$E,'AccountSummary (New)'!L$1,Accounts!$G:$G,'AccountSummary (New)'!L$2,Accounts!$F:$F,'AccountSummary (New)'!L$3,Accounts!$B:$B,"Customer",Accounts!$C:$C,"Lost",Accounts!$H:$H,"<="&30) -> 0 | M24: =COUNTIFS(Accounts!$E:$E,'AccountSummary (New)'!M$1,Accounts!$G:$G,'AccountSummary (New)'!M$2,Accounts!$F:$F,'AccountSummary (New)'!M$3,Accounts!$B:$B,"Customer",Accounts!$C:$C,"Lost",Accounts!$H:$H,"<="&30) -> 0 | N24: =COUNTIFS(Accounts!$E:$E,'AccountSummary (New)'!N$1,Accounts!$G:$G,'AccountSummary (New)'!N$2,Accounts!$F:$F,'AccountSummary (New)'!N$3,Accounts!$B:$B,"Customer",Accounts!$C:$C,"Lost",Accounts!$H:$H,"<="&30) -> 0 | O24: =COUNTIFS(Accounts!$E:$E,'AccountSummary (New)'!O$1,Accounts!$G:$G,'AccountSummary (New)'!O$2,Accounts!$F:$F,'AccountSummary (New)'!O$3,Accounts!$B:$B,"Customer",Accounts!$C:$C,"Lost",Accounts!$H:$H,"<="&30) -> 0 | P24: =SUM(J24:O24) -> 0 | Q24: =COUNTIFS(Accounts!$E:$E,'AccountSummary (New)'!Q$1,Accounts!$G:$G,'AccountSummary (New)'!Q$2,Accounts!$F:$F,'AccountSummary (New)'!Q$3,Accounts!$B:$B,"Customer",Accounts!$C:$C,"Lost",Accounts!$H:$H,"<="&30) -> 0 | R24: =COUNTIFS(Accounts!$E:$E,'AccountSummary (New)'!R$1,Accounts!$G:$G,'AccountSummary (New)'!R$2,Accounts!$F:$F,'AccountSummary (New)'!R$3,Accounts!$B:$B,"Customer",Accounts!$C:$C,"Lost",Accounts!$H:$H,"<="&30) -> 0 | S24: =COUNTIFS(Accounts!$E:$E,'AccountSummary (New)'!S$1,Accounts!$G:$G,'AccountSummary (New)'!S$2,Accounts!$F:$F,'AccountSummary (New)'!S$3,Accounts!$B:$B,"Customer",Accounts!$C:$C,"Lost",Accounts!$H:$H,"<="&30) -> 0 | T24: =COUNTIFS(Accounts!$E:$E,'AccountSummary (New)'!T$1,Accounts!$G:$G,'AccountSummary (New)'!T$2,Accounts!$F:$F,'AccountSummary (New)'!T$3,Accounts!$B:$B,"Customer",Accounts!$C:$C,"Lost",Accounts!$H:$H,"<="&30) -> 0 | U24: =COUNTIFS(Accounts!$E:$E,'AccountSummary (New)'!U$1,Accounts!$G:$G,'AccountSummary (New)'!U$2,Accounts!$F:$F,'AccountSummary (New)'!U$3,Accounts!$B:$B,"Customer",Accounts!$C:$C,"Lost",Accounts!$H:$H,"<="&30) -> 0 | V24: =COUNTIFS(Accounts!$E:$E,'AccountSummary (New)'!V$1,Accounts!$G:$G,'AccountSummary (New)'!V$2,Accounts!$F:$F,'AccountSummary (New)'!V$3,Accounts!$B:$B,"Customer",Accounts!$C:$C,"Lost",Accounts!$H:$H,"<="&30) -> 0 | W24: =SUM(Q24:V24) -> 0
A25: Retained Count | B25: =I25+P25+W25 -> 0 | C25: =COUNTIFS(Accounts!$E:$E,'AccountSummary (New)'!C$1,Accounts!$G:$G,'AccountSummary (New)'!C$2,Accounts!$F:$F,'AccountSummary (New)'!C$3,Accounts!$B:$B,"Customer",Accounts!$C:$C,"Customer",Accounts!$H:$H,"<="&30) -> 0 | D25: =COUNTIFS(Accounts!$E:$E,'AccountSummary (New)'!D$1,Accounts!$G:$G,'AccountSummary (New)'!D$2,Accounts!$F:$F,'AccountSummary (New)'!D$3,Accounts!$B:$B,"Customer",Accounts!$C:$C,"Customer",Accounts!$H:$H,"<="&30) -> 0 | E25: =COUNTIFS(Accounts!$E:$E,'AccountSummary (New)'!E$1,Accounts!$G:$G,'AccountSummary (New)'!E$2,Accounts!$F:$F,'AccountSummary (New)'!E$3,Accounts!$B:$B,"Customer",Accounts!$C:$C,"Customer",Accounts!$H:$H,"<="&30) -> 0 | F25: =COUNTIFS(Accounts!$E:$E,'AccountSummary (New)'!F$1,Accounts!$G:$G,'AccountSummary (New)'!F$2,Accounts!$F:$F,'AccountSummary (New)'!F$3,Accounts!$B:$B,"Customer",Accounts!$C:$C,"Customer",Accounts!$H:$H,"<="&30) -> 0 | G25: =COUNTIFS(Accounts!$E:$E,'AccountSummary (New)'!G$1,Accounts!$G:$G,'AccountSummary (New)'!G$2,Accounts!$F:$F,'AccountSummary (New)'!G$3,Accounts!$B:$B,"Customer",Accounts!$C:$C,"Customer",Accounts!$H:$H,"<="&30) -> 0 | H25: =COUNTIFS(Accounts!$E:$E,'AccountSummary (New)'!H$1,Accounts!$G:$G,'AccountSummary (New)'!H$2,Accounts!$F:$F,'AccountSummary (New)'!H$3,Accounts!$B:$B,"Customer",Accounts!$C:$C,"Customer",Accounts!$H:$H,"<="&30) -> 0 | I25: =SUM(C25:H25) -> 0 | J25: =COUNTIFS(Accounts!$E:$E,'AccountSummary (New)'!J$1,Accounts!$G:$G,'AccountSummary (New)'!J$2,Accounts!$F:$F,'AccountSummary (New)'!J$3,Accounts!$B:$B,"Customer",Accounts!$C:$C,"Customer",Accounts!$H:$H,"<="&30) -> 0 | K25: =COUNTIFS(Accounts!$E:$E,'AccountSummary (New)'!K$1,Accounts!$G:$G,'AccountSummary (New)'!K$2,Accounts!$F:$F,'AccountSummary (New)'!K$3,Accounts!$B:$B,"Customer",Accounts!$C:$C,"Customer",Accounts!$H:$H,"<="&30) -> 0 | L25: =COUNTIFS(Accounts!$E:$E,'AccountSummary (New)'!L$1,Accounts!$G:$G,'AccountSummary (New)'!L$2,Accounts!$F:$F,'AccountSummary (New)'!L$3,Accounts!$B:$B,"Customer",Accounts!$C:$C,"Customer",Accounts!$H:$H,"<="&30) -> 0 | M25: =COUNTIFS(Accounts!$E:$E,'AccountSummary (New)'!M$1,Accounts!$G:$G,'AccountSummary (New)'!M$2,Accounts!$F:$F,'AccountSummary (New)'!M$3,Accounts!$B:$B,"Customer",Accounts!$C:$C,"Customer",Accounts!$H:$H,"<="&30) -> 0 | N25: =COUNTIFS(Accounts!$E:$E,'AccountSummary (New)'!N$1,Accounts!$G:$G,'AccountSummary (New)'!N$2,Accounts!$F:$F,'AccountSummary (New)'!N$3,Accounts!$B:$B,"Customer",Accounts!$C:$C,"Customer",Accounts!$H:$H,"<="&30) -> 0 | O25: =COUNTIFS(Accounts!$E:$E,'AccountSummary (New)'!O$1,Accounts!$G:$G,'AccountSummary (New)'!O$2,Accounts!$F:$F,'AccountSummary (New)'!O$3,Accounts!$B:$B,"Customer",Accounts!$C:$C,"Customer",Accounts!$H:$H,"<="&30) -> 0 | P25: =SUM(J25:O25) -> 0 | Q25: =COUNTIFS(Accounts!$E:$E,'AccountSummary (New)'!Q$1,Accounts!$G:$G,'AccountSummary (New)'!Q$2,Accounts!$F:$F,'AccountSummary (New)'!Q$3,Accounts!$B:$B,"Customer",Accounts!$C:$C,"Customer",Accounts!$H:$H,"<="&30) -> 0 | R25: =COUNTIFS(Accounts!$E:$E,'AccountSummary (New)'!R$1,Accounts!$G:$G,'AccountSummary (New)'!R$2,Accounts!$F:$F,'AccountSummary (New)'!R$3,Accounts!$B:$B,"Customer",Accounts!$C:$C,"Customer",Accounts!$H:$H,"<="&30) -> 0 | S25: =COUNTIFS(Accounts!$E:$E,'AccountSummary (New)'!S$1,Accounts!$G:$G,'AccountSummary (New)'!S$2,Accounts!$F:$F,'AccountSummary (New)'!S$3,Accounts!$B:$B,"Customer",Accounts!$C:$C,"Customer",Accounts!$H:$H,"<="&30) -> 0 | T25: =COUNTIFS(Accounts!$E:$E,'AccountSummary (New)'!T$1,Accounts!$G:$G,'AccountSummary (New)'!T$2,Accounts!$F:$F,'AccountSummary (New)'!T$3,Accounts!$B:$B,"Customer",Accounts!$C:$C,"Customer",Accounts!$H:$H,"<="&30) -> 0 | U25: =COUNTIFS(Accounts!$E:$E,'AccountSummary (New)'!U$1,Accounts!$G:$G,'AccountSummary (New)'!U$2,Accounts!$F:$F,'AccountSummary (New)'!U$3,Accounts!$B:$B,"Customer",Accounts!$C:$C,"Customer",Accounts!$H:$H,"<="&30) -> 0 | V25: =COUNTIFS(Accounts!$E:$E,'AccountSummary (New)'!V$1,Accounts!$G:$G,'AccountSummary (New)'!V$2,Accounts!$F:$F,'AccountSummary (New)'!V$3,Accounts!$B:$B,"Customer",Accounts!$C:$C,"Customer",Accounts!$H:$H,"<="&30) -> 0 | W25: =SUM(Q25:V25) -> 0
A26: Packs per Account | B26: =IF(B25=0,0,SUMIFS(Accounts!$L:$L,Accounts!$W:$W,0,Accounts!$C:$C,"Customer",Accounts!$H:$H,"<="&30)/B25) -> 0 | C26: =IF(C25=0,0,SUMIFS(Accounts!$L:$L,Accounts!$E:$E,'AccountSummary (New)'!C$1,Accounts!$G:$G,'AccountSummary (New)'!C$2,Accounts!$F:$F,'AccountSummary (New)'!C$3,Accounts!$W:$W,0,Accounts!$C:$C,"Customer",Accounts!$H:$H,"<="&30)/C25) -> 0 | D26: =IF(D25=0,0,SUMIFS(Accounts!$L:$L,Accounts!$E:$E,'AccountSummary (New)'!D$1,Accounts!$G:$G,'AccountSummary (New)'!D$2,Accounts!$F:$F,'AccountSummary (New)'!D$3,Accounts!$W:$W,0,Accounts!$C:$C,"Customer",Accounts!$H:$H,"<="&30)/D25) -> 0 | E26: =IF(E25=0,0,SUMIFS(Accounts!$L:$L,Accounts!$E:$E,'AccountSummary (New)'!E$1,Accounts!$G:$G,'AccountSummary (New)'!E$2,Accounts!$F:$F,'AccountSummary (New)'!E$3,Accounts!$W:$W,0,Accounts!$C:$C,"Customer",Accounts!$H:$H,"<="&30)/E25) -> 0 | F26: =IF(F25=0,0,SUMIFS(Accounts!$L:$L,Accounts!$E:$E,'AccountSummary (New)'!F$1,Accounts!$G:$G,'AccountSummary (New)'!F$2,Accounts!$F:$F,'AccountSummary (New)'!F$3,Accounts!$W:$W,0,Accounts!$C:$C,"Customer",Accounts!$H:$H,"<="&30)/F25) -> 0 | G26: =IF(G25=0,0,SUMIFS(Accounts!$L:$L,Accounts!$E:$E,'AccountSummary (New)'!G$1,Accounts!$G:$G,'AccountSummary (New)'!G$2,Accounts!$F:$F,'AccountSummary (New)'!G$3,Accounts!$W:$W,0,Accounts!$C:$C,"Customer",Accounts!$H:$H,"<="&30)/G25) -> 0 | H26: =IF(H25=0,0,SUMIFS(Accounts!$L:$L,Accounts!$E:$E,'AccountSummary (New)'!H$1,Accounts!$G:$G,'AccountSummary (New)'!H$2,Accounts!$F:$F,'AccountSummary (New)'!H$3,Accounts!$W:$W,0,Accounts!$C:$C,"Customer",Accounts!$H:$H,"<="&30)/H25) -> 0 | I26: =IF(I25=0,0,SUMIFS(Accounts!$L:$L,Accounts!$F:$F,'AccountSummary (New)'!I$3,Accounts!$W:$W,0,Accounts!$C:$C,"Customer",Accounts!$H:$H,"<="&30)/I25) -> 0 | J26: =IF(J25=0,0,SUMIFS(Accounts!$L:$L,Accounts!$E:$E,'AccountSummary (New)'!J$1,Accounts!$G:$G,'AccountSummary (New)'!J$2,Accounts!$F:$F,'AccountSummary (New)'!J$3,Accounts!$W:$W,0,Accounts!$C:$C,"Customer",Accounts!$H:$H,"<="&30)/J25) -> 0 | K26: =IF(K25=0,0,SUMIFS(Accounts!$L:$L,Accounts!$E:$E,'AccountSummary (New)'!K$1,Accounts!$G:$G,'AccountSummary (New)'!K$2,Accounts!$F:$F,'AccountSummary (New)'!K$3,Accounts!$W:$W,0,Accounts!$C:$C,"Customer",Accounts!$H:$H,"<="&30)/K25) -> 0 | L26: =IF(L25=0,0,SUMIFS(Accounts!$L:$L,Accounts!$E:$E,'AccountSummary (New)'!L$1,Accounts!$G:$G,'AccountSummary (New)'!L$2,Accounts!$F:$F,'AccountSummary (New)'!L$3,Accounts!$W:$W,0,Accounts!$C:$C,"Customer",Accounts!$H:$H,"<="&30)/L25) -> 0 | M26: =IF(M25=0,0,SUMIFS(Accounts!$L:$L,Accounts!$E:$E,'AccountSummary (New)'!M$1,Accounts!$G:$G,'AccountSummary (New)'!M$2,Accounts!$F:$F,'AccountSummary (New)'!M$3,Accounts!$W:$W,0,Accounts!$C:$C,"Customer",Accounts!$H:$H,"<="&30)/M25) -> 0 | N26: =IF(N25=0,0,SUMIFS(Accounts!$L:$L,Accounts!$E:$E,'AccountSummary (New)'!N$1,Accounts!$G:$G,'AccountSummary (New)'!N$2,Accounts!$F:$F,'AccountSummary (New)'!N$3,Accounts!$W:$W,0,Accounts!$C:$C,"Customer",Accounts!$H:$H,"<="&30)/N25) -> 0 | O26: =IF(O25=0,0,SUMIFS(Accounts!$L:$L,Accounts!$E:$E,'AccountSummary (New)'!O$1,Accounts!$G:$G,'AccountSummary (New)'!O$2,Accounts!$F:$F,'AccountSummary (New)'!O$3,Accounts!$W:$W,0,Accounts!$C:$C,"Customer",Accounts!$H:$H,"<="&30)/O25) -> 0 | P26: =IF(P25=0,0,SUMIFS(Accounts!$L:$L,Accounts!$F:$F,'AccountSummary (New)'!P$3,Accounts!$W:$W,0,Accounts!$C:$C,"Customer",Accounts!$H:$H,"<="&30)/P25) -> 0 | Q26: =IF(Q25=0,0,SUMIFS(Accounts!$L:$L,Accounts!$E:$E,'AccountSummary (New)'!Q$1,Accounts!$G:$G,'AccountSummary (New)'!Q$2,Accounts!$F:$F,'AccountSummary (New)'!Q$3,Accounts!$W:$W,0,Accounts!$C:$C,"Customer",Accounts!$H:$H,"<="&30)/Q25) -> 0 | R26: =IF(R25=0,0,SUMIFS(Accounts!$L:$L,Accounts!$E:$E,'AccountSummary (New)'!R$1,Accounts!$G:$G,'AccountSummary (New)'!R$2,Accounts!$F:$F,'AccountSummary (New)'!R$3,Accounts!$W:$W,0,Accounts!$C:$C,"Customer",Accounts!$H:$H,"<="&30)/R25) -> 0 | S26: =IF(S25=0,0,SUMIFS(Accounts!$L:$L,Accounts!$E:$E,'AccountSummary (New)'!S$1,Accounts!$G:$G,'AccountSummary (New)'!S$2,Accounts!$F:$F,'AccountSummary (New)'!S$3,Accounts!$W:$W,0,Accounts!$C:$C,"Customer",Accounts!$H:$H,"<="&30)/S25) -> 0 | T26: =IF(T25=0,0,SUMIFS(Accounts!$L:$L,Accounts!$E:$E,'AccountSummary (New)'!T$1,Accounts!$G:$G,'AccountSummary (New)'!T$2,Accounts!$F:$F,'AccountSummary (New)'!T$3,Accounts!$W:$W,0,Accounts!$C:$C,"Customer",Accounts!$H:$H,"<="&30)/T25) -> 0 | U26: =IF(U25=0,0,SUMIFS(Accounts!$L:$L,Accounts!$E:$E,'AccountSummary (New)'!U$1,Accounts!$G:$G,'AccountSummary (New)'!U$2,Accounts!$F:$F,'AccountSummary (New)'!U$3,Accounts!$W:$W,0,Accounts!$C:$C,"Customer",Accounts!$H:$H,"<="&30)/U25) -> 0 | V26: =IF(V25=0,0,SUMIFS(Accounts!$L:$L,Accounts!$E:$E,'AccountSummary (New)'!V$1,Accounts!$G:$G,'AccountSummary (New)'!V$2,Accounts!$F:$F,'AccountSummary (New)'!V$3,Accounts!$W:$W,0,Accounts!$C:$C,"Customer",Accounts!$H:$H,"<="&30)/V25) -> 0 | W26: =IF(W25=0,0,SUMIFS(Accounts!$L:$L,Accounts!$F:$F,'AccountSummary (New)'!W$3,Accounts!$W:$W,0,Accounts!$C:$C,"Customer",Accounts!$H:$H,"<="&30)/W25) -> 0
A27: Users per Account | B27: =IF(B25=0,0,SUMIFS(Accounts!$M:$M,Accounts!$W:$W,0,Accounts!$C:$C,"Customer",Accounts!$H:$H,"<="&30)/B25) -> 0 | C27: =IF(C25=0,0,SUMIFS(Accounts!$M:$M,Accounts!$E:$E,'AccountSummary (New)'!C$1,Accounts!$G:$G,'AccountSummary (New)'!C$2,Accounts!$F:$F,'AccountSummary (New)'!C$3,Accounts!$W:$W,0,Accounts!$C:$C,"Customer",Accounts!$H:$H,"<="&30)/C25) -> 0 | D27: =IF(D25=0,0,SUMIFS(Accounts!$M:$M,Accounts!$E:$E,'AccountSummary (New)'!D$1,Accounts!$G:$G,'AccountSummary (New)'!D$2,Accounts!$F:$F,'AccountSummary (New)'!D$3,Accounts!$W:$W,0,Accounts!$C:$C,"Customer",Accounts!$H:$H,"<="&30)/D25) -> 0 | E27: =IF(E25=0,0,SUMIFS(Accounts!$M:$M,Accounts!$E:$E,'AccountSummary (New)'!E$1,Accounts!$G:$G,'AccountSummary (New)'!E$2,Accounts!$F:$F,'AccountSummary (New)'!E$3,Accounts!$W:$W,0,Accounts!$C:$C,"Customer",Accounts!$H:$H,"<="&30)/E25) -> 0 | F27: =IF(F25=0,0,SUMIFS(Accounts!$M:$M,Accounts!$E:$E,'AccountSummary (New)'!F$1,Accounts!$G:$G,'AccountSummary (New)'!F$2,Accounts!$F:$F,'AccountSummary (New)'!F$3,Accounts!$W:$W,0,Accounts!$C:$C,"Customer",Accounts!$H:$H,"<="&30)/F25) -> 0 | G27: =IF(G25=0,0,SUMIFS(Accounts!$M:$M,Accounts!$E:$E,'AccountSummary (New)'!G$1,Accounts!$G:$G,'AccountSummary (New)'!G$2,Accounts!$F:$F,'AccountSummary (New)'!G$3,Accounts!$W:$W,0,Accounts!$C:$C,"Customer",Accounts!$H:$H,"<="&30)/G25) -> 0 | H27: =IF(H25=0,0,SUMIFS(Accounts!$M:$M,Accounts!$E:$E,'AccountSummary (New)'!H$1,Accounts!$G:$G,'AccountSummary (New)'!H$2,Accounts!$F:$F,'AccountSummary (New)'!H$3,Accounts!$W:$W,0,Accounts!$C:$C,"Customer",Accounts!$H:$H,"<="&30)/H25) -> 0 | I27: =IF(I25=0,0,SUMIFS(Accounts!$M:$M,Accounts!$F:$F,'AccountSummary (New)'!I$3,Accounts!$W:$W,0,Accounts!$C:$C,"Customer",Accounts!$H:$H,"<="&30)/I25) -> 0 | J27: =IF(J25=0,0,SUMIFS(Accounts!$M:$M,Accounts!$E:$E,'AccountSummary (New)'!J$1,Accounts!$G:$G,'AccountSummary (New)'!J$2,Accounts!$F:$F,'AccountSummary (New)'!J$3,Accounts!$W:$W,0,Accounts!$C:$C,"Customer",Accounts!$H:$H,"<="&30)/J25) -> 0 | K27: =IF(K25=0,0,SUMIFS(Accounts!$M:$M,Accounts!$E:$E,'AccountSummary (New)'!K$1,Accounts!$G:$G,'AccountSummary (New)'!K$2,Accounts!$F:$F,'AccountSummary (New)'!K$3,Accounts!$W:$W,0,Accounts!$C:$C,"Customer",Accounts!$H:$H,"<="&30)/K25) -> 0 | L27: =IF(L25=0,0,SUMIFS(Accounts!$M:$M,Accounts!$E:$E,'AccountSummary (New)'!L$1,Accounts!$G:$G,'AccountSummary (New)'!L$2,Accounts!$F:$F,'AccountSummary (New)'!L$3,Accounts!$W:$W,0,Accounts!$C:$C,"Customer",Accounts!$H:$H,"<="&30)/L25) -> 0 | M27: =IF(M25=0,0,SUMIFS(Accounts!$M:$M,Accounts!$E:$E,'AccountSummary (New)'!M$1,Accounts!$G:$G,'AccountSummary (New)'!M$2,Accounts!$F:$F,'AccountSummary (New)'!M$3,Accounts!$W:$W,0,Accounts!$C:$C,"Customer",Accounts!$H:$H,"<="&30)/M25) -> 0 | N27: =IF(N25=0,0,SUMIFS(Accounts!$M:$M,Accounts!$E:$E,'AccountSummary (New)'!N$1,Accounts!$G:$G,'AccountSummary (New)'!N$2,Accounts!$F:$F,'AccountSummary (New)'!N$3,Accounts!$W:$W,0,Accounts!$C:$C,"Customer",Accounts!$H:$H,"<="&30)/N25) -> 0 | O27: =IF(O25=0,0,SUMIFS(Accounts!$M:$M,Accounts!$E:$E,'AccountSummary (New)'!O$1,Accounts!$G:$G,'AccountSummary (New)'!O$2,Accounts!$F:$F,'AccountSummary (New)'!O$3,Accounts!$W:$W,0,Accounts!$C:$C,"Customer",Accounts!$H:$H,"<="&30)/O25) -> 0 | P27: =IF(P25=0,0,SUMIFS(Accounts!$M:$M,Accounts!$F:$F,'AccountSummary (New)'!P$3,Accounts!$W:$W,0,Accounts!$C:$C,"Customer",Accounts!$H:$H,"<="&30)/P25) -> 0 | Q27: =IF(Q25=0,0,SUMIFS(Accounts!$M:$M,Accounts!$E:$E,'AccountSummary (New)'!Q$1,Accounts!$G:$G,'AccountSummary (New)'!Q$2,Accounts!$F:$F,'AccountSummary (New)'!Q$3,Accounts!$W:$W,0,Accounts!$C:$C,"Customer",Accounts!$H:$H,"<="&30)/Q25) -> 0 | R27: =IF(R25=0,0,SUMIFS(Accounts!$M:$M,Accounts!$E:$E,'AccountSummary (New)'!R$1,Accounts!$G:$G,'AccountSummary (New)'!R$2,Accounts!$F:$F,'AccountSummary (New)'!R$3,Accounts!$W:$W,0,Accounts!$C:$C,"Customer",Accounts!$H:$H,"<="&30)/R25) -> 0 | S27: =IF(S25=0,0,SUMIFS(Accounts!$M:$M,Accounts!$E:$E,'AccountSummary (New)'!S$1,Accounts!$G:$G,'AccountSummary (New)'!S$2,Accounts!$F:$F,'AccountSummary (New)'!S$3,Accounts!$W:$W,0,Accounts!$C:$C,"Customer",Accounts!$H:$H,"<="&30)/S25) -> 0 | T27: =IF(T25=0,0,SUMIFS(Accounts!$M:$M,Accounts!$E:$E,'AccountSummary (New)'!T$1,Accounts!$G:$G,'AccountSummary (New)'!T$2,Accounts!$F:$F,'AccountSummary (New)'!T$3,Accounts!$W:$W,0,Accounts!$C:$C,"Customer",Accounts!$H:$H,"<="&30)/T25) -> 0 | U27: =IF(U25=0,0,SUMIFS(Accounts!$M:$M,Accounts!$E:$E,'AccountSummary (New)'!U$1,Accounts!$G:$G,'AccountSummary (New)'!U$2,Accounts!$F:$F,'AccountSummary (New)'!U$3,Accounts!$W:$W,0,Accounts!$C:$C,"Customer",Accounts!$H:$H,"<="&30)/U25) -> 0 | V27: =IF(V25=0,0,SUMIFS(Accounts!$M:$M,Accounts!$E:$E,'AccountSummary (New)'!V$1,Accounts!$G:$G,'AccountSummary (New)'!V$2,Accounts!$F:$F,'AccountSummary (New)'!V$3,Accounts!$W:$W,0,Accounts!$C:$C,"Customer",Accounts!$H:$H,"<="&30)/V25) -> 0 | W27: =IF(W25=0,0,SUMIFS(Accounts!$M:$M,Accounts!$F:$F,'AccountSummary (New)'!W$3,Accounts!$W:$W,0,Accounts!$C:$C,"Customer",Accounts!$H:$H,"<="&30)/W25) -> 0
A28: ARPC | B28: =IF(B25=0,0,B29/B25) -> 0 | C28: =IF(C25=0,0,C29/C25) -> 0 | D28: =IF(D25=0,0,D29/D25) -> 0 | E28: =IF(E25=0,0,E29/E25) -> 0 | F28: =IF(F25=0,0,F29/F25) -> 0 | G28: =IF(G25=0,0,G29/G25) -> 0 | H28: =IF(H25=0,0,H29/H25) -> 0 | I28: =IF(I25=0,0,I29/I25) -> 0 | ... W28: =IF(W25=0,0,W29/W25) -> 0
A29: SaaS | B29: =I29+P29+W29 -> 0 | C29: =SUMIFS(Accounts!$I:$I,Accounts!$E:$E,'AccountSummary (New)'!C$1,Accounts!$G:$G,'AccountSummary (New)'!C$2,Accounts!$F:$F,'AccountSummary (New)'!C$3,Accounts!$W:$W,0,Accounts!$C:$C,"Customer",Accounts!$H:$H,"<="&30) -> 0 | D29: =SUMIFS(Accounts!$I:$I,Accounts!$E:$E,'AccountSummary (New)'!D$1,Accounts!$G:$G,'AccountSummary (New)'!D$2,Accounts!$F:$F,'AccountSummary (New)'!D$3,Accounts!$W:$W,0,Accounts!$C:$C,"Customer",Accounts!$H:$H,"<="&30) -> 0 | E29: =SUMIFS(Accounts!$I:$I,Accounts!$E:$E,'AccountSummary (New)'!E$1,Accounts!$G:$G,'AccountSummary (New)'!E$2,Accounts!$F:$F,'AccountSummary (New)'!E$3,Accounts!$W:$W,0,Accounts!$C:$C,"Customer",Accounts!$H:$H,"<="&30) -> 0 | F29: =SUMIFS(Accounts!$I:$I,Accounts!$E:$E,'AccountSummary (New)'!F$1,Accounts!$G:$G,'AccountSummary (New)'!F$2,Accounts!$F:$F,'AccountSummary (New)'!F$3,Accounts!$W:$W,0,Accounts!$C:$C,"Customer",Accounts!$H:$H,"<="&30) -> 0 | G29: =SUMIFS(Accounts!$I:$I,Accounts!$E:$E,'AccountSummary (New)'!G$1,Accounts!$G:$G,'AccountSummary (New)'!G$2,Accounts!$F:$F,'AccountSummary (New)'!G$3,Accounts!$W:$W,0,Accounts!$C:$C,"Customer",Accounts!$H:$H,"<="&30) -> 0 | H29: =SUMIFS(Accounts!$I:$I,Accounts!$E:$E,'AccountSummary (New)'!H$1,Accounts!$G:$G,'AccountSummary (New)'!H$2,Accounts!$F:$F,'AccountSummary (New)'!H$3,Accounts!$W:$W,0,Accounts!$C:$C,"Customer",Accounts!$H:$H,"<="&30) -> 0 | I29: =SUM(C29:H29) -> 0 | J29: =SUMIFS(Accounts!$I:$I,Accounts!$E:$E,'AccountSummary (New)'!J$1,Accounts!$G:$G,'AccountSummary (New)'!J$2,Accounts!$F:$F,'AccountSummary (New)'!J$3,Accounts!$W:$W,0,Accounts!$C:$C,"Customer",Accounts!$H:$H,"<="&30) -> 0 | K29: =SUMIFS(Accounts!$I:$I,Accounts!$E:$E,'AccountSummary (New)'!K$1,Accounts!$G:$G,'AccountSummary (New)'!K$2,Accounts!$F:$F,'AccountSummary (New)'!K$3,Accounts!$W:$W,0,Accounts!$C:$C,"Customer",Accounts!$H:$H,"<="&30) -> 0 | L29: =SUMIFS(Accounts!$I:$I,Accounts!$E:$E,'AccountSummary (New)'!L$1,Accounts!$G:$G,'AccountSummary (New)'!L$2,Accounts!$F:$F,'AccountSummary (New)'!L$3,Accounts!$W:$W,0,Accounts!$C:$C,"Customer",Accounts!$H:$H,"<="&30) -> 0 | M29: =SUMIFS(Accounts!$I:$I,Accounts!$E:$E,'AccountSummary (New)'!M$1,Accounts!$G:$G,'AccountSummary (New)'!M$2,Accounts!$F:$F,'AccountSummary (New)'!M$3,Accounts!$W:$W,0,Accounts!$C:$C,"Customer",Accounts!$H:$H,"<="&30) -> 0 | N29: =SUMIFS(Accounts!$I:$I,Accounts!$E:$E,'AccountSummary (New)'!N$1,Accounts!$G:$G,'AccountSummary (New)'!N$2,Accounts!$F:$F,'AccountSummary (New)'!N$3,Accounts!$W:$W,0,Accounts!$C:$C,"Customer",Accounts!$H:$H,"<="&30) -> 0 | O29: =SUMIFS(Accounts!$I:$I,Accounts!$E:$E,'AccountSummary (New)'!O$1,Accounts!$G:$G,'AccountSummary (New)'!O$2,Accounts!$F:$F,'AccountSummary (New)'!O$3,Accounts!$W:$W,0,Accounts!$C:$C,"Customer",Accounts!$H:$H,"<="&30) -> 0 | P29: =SUM(J29:O29) -> 0 | Q29: =SUMIFS(Accounts!$I:$I,Accounts!$E:$E,'AccountSummary (New)'!Q$1,Accounts!$G:$G,'AccountSummary (New)'!Q$2,Accounts!$F:$F,'AccountSummary (New)'!Q$3,Accounts!$W:$W,0,Accounts!$C:$C,"Customer",Accounts!$H:$H,"<="&30) -> 0 | R29: =SUMIFS(Accounts!$I:$I,Accounts!$E:$E,'AccountSummary (New)'!R$1,Accounts!$G:$G,'AccountSummary (New)'!R$2,Accounts!$F:$F,'AccountSummary (New)'!R$3,Accounts!$W:$W,0,Accounts!$C:$C,"Customer",Accounts!$H:$H,"<="&30) -> 0 | S29: =SUMIFS(Accounts!$I:$I,Accounts!$E:$E,'AccountSummary (New)'!S$1,Accounts!$G:$G,'AccountSummary (New)'!S$2,Accounts!$F:$F,'AccountSummary (New)'!S$3,Accounts!$W:$W,0,Accounts!$C:$C,"Customer",Accounts!$H:$H,"<="&30) -> 0 | T29: =SUMIFS(Accounts!$I:$I,Accounts!$E:$E,'AccountSummary (New)'!T$1,Accounts!$G:$G,'AccountSummary (New)'!T$2,Accounts!$F:$F,'AccountSummary (New)'!T$3,Accounts!$W:$W,0,Accounts!$C:$C,"Customer",Accounts!$H:$H,"<="&30) -> 0 | U29: =SUMIFS(Accounts!$I:$I,Accounts!$E:$E,'AccountSummary (New)'!U$1,Accounts!$G:$G,'AccountSummary (New)'!U$2,Accounts!$F:$F,'AccountSummary (New)'!U$3,Accounts!$W:$W,0,Accounts!$C:$C,"Customer",Accounts!$H:$H,"<="&30) -> 0 | V29: =SUMIFS(Accounts!$I:$I,Accounts!$E:$E,'AccountSummary (New)'!V$1,Accounts!$G:$G,'AccountSummary (New)'!V$2,Accounts!$F:$F,'AccountSummary (New)'!V$3,Accounts!$W:$W,0,Accounts!$C:$C,"Customer",Accounts!$H:$H,"<="&30) -> 0 | W29: =SUM(Q29:V29) -> 0
A30: 31-60 day cohort as of BOM
A31: Total % of Paying Customers | B31: =IF(B$19=0,0,(B33+B34)/B$19) -> 0 | C31: =IF(C$19=0,0,(C33+C34)/C$19) -> 0 | D31: =IF(D$19=0,0,(D33+D34)/D$19) -> 0 | E31: =IF(E$19=0,0,(E33+E34)/E$19) -> 0 | F31: =IF(F$19=0,0,(F33+F34)/F$19) -> 0 | G31: =IF(G$19=0,0,(G33+G34)/G$19) -> 0 | H31: =IF(H$19=0,0,(H33+H34)/H$19) -> 0 | I31: =IF(I$19=0,0,(I33+I34)/I$19) -> 0 | ... W31: =IF(W$19=0,0,(W33+W34)/W$19) -> 0
A32: Loss % | B32: =IF((B33+B34)=0,0,B33/(B33+B34)) -> 0 | C32: =IF((C33+C34)=0,0,C33/(C33+C34)) -> 0 | D32: =IF((D33+D34)=0,0,D33/(D33+D34)) -> 0 | E32: =IF((E33+E34)=0,0,E33/(E33+E34)) -> 0 | F32: =IF((F33+F34)=0,0,F33/(F33+F34)) -> 0 | G32: =IF((G33+G34)=0,0,G33/(G33+G34)) -> 0 | H32: =IF((H33+H34)=0,0,H33/(H33+H34)) -> 0 | I32: =IF((I33+I34)=0,0,I33/(I33+I34)) -> 0 | ... W32: =IF((W33+W34)=0,0,W33/(W33+W34)) -> 0
A33: Lost Count | B33: =I33+P33+W33 -> 0 | C33: =COUNTIFS(Accounts!$E:$E,'AccountSummary (New)'!C$1,Accounts!$G:$G,'AccountSummary (New)'!C$2,Accounts!$F:$F,'AccountSummary (New)'!C$3,Accounts!$B:$B,"Customer",Accounts!$C:$C,"Lost",Accounts!$H:$H,">"&30,Accounts!$H:$H,"<="&60) -> 0 | D33: =COUNTIFS(Accounts!$E:$E,'AccountSummary (New)'!D$1,Accounts!$G:$G,'AccountSummary (New)'!D$2,Accounts!$F:$F,'AccountSummary (New)'!D$3,Accounts!$B:$B,"Customer",Accounts!$C:$C,"Lost",Accounts!$H:$H,">"&30,Accounts!$H:$H,"<="&60) -> 0 | E33: =COUNTIFS(Accounts!$E:$E,'AccountSummary (New)'!E$1,Accounts!$G:$G,'AccountSummary (New)'!E$2,Accounts!$F:$F,'AccountSummary (New)'!E$3,Accounts!$B:$B,"Customer",Accounts!$C:$C,"Lost",Accounts!$H:$H,">"&30,Accounts!$H:$H,"<="&60) -> 0 | F33: =COUNTIFS(Accounts!$E:$E,'AccountSummary (New)'!F$1,Accounts!$G:$G,'AccountSummary (New)'!F$2,Accounts!$F:$F,'AccountSummary (New)'!F$3,Accounts!$B:$B,"Customer",Accounts!$C:$C,"Lost",Accounts!$H:$H,">"&30,Accounts!$H:$H,"<="&60) -> 0 | G33: =COUNTIFS(Accounts!$E:$E,'AccountSummary (New)'!G$1,Accounts!$G:$G,'AccountSummary (New)'!G$2,Accounts!$F:$F,'AccountSummary (New)'!G$3,Accounts!$B:$B,"Customer",Accounts!$C:$C,"Lost",Accounts!$H:$H,">"&30,Accounts!$H:$H,"<="&60) -> 0 | H33: =COUNTIFS(Accounts!$E:$E,'AccountSummary (New)'!H$1,Accounts!$G:$G,'AccountSummary (New)'!H$2,Accounts!$F:$F,'AccountSummary (New)'!H$3,Accounts!$B:$B,"Customer",Accounts!$C:$C,"Lost",Accounts!$H:$H,">"&30,Accounts!$H:$H,"<="&60) -> 0 | I33: =SUM(C33:H33) -> 0 | J33: =COUNTIFS(Accounts!$E:$E,'AccountSummary (New)'!J$1,Accounts!$G:$G,'AccountSummary (New)'!J$2,Accounts!$F:$F,'AccountSummary (New)'!J$3,Accounts!$B:$B,"Customer",Accounts!$C:$C,"Lost",Accounts!$H:$H,">"&30,Accounts!$H:$H,"<="&60) -> 0 | K33: =COUNTIFS(Accounts!$E:$E,'AccountSummary (New)'!K$1,Accounts!$G:$G,'AccountSummary (New)'!K$2,Accounts!$F:$F,'AccountSummary (New)'!K$3,Accounts!$B:$B,"Customer",Accounts!$C:$C,"Lost",Accounts!$H:$H,">"&30,Accounts!$H:$H,"<="&60) -> 0 | L33: =COUNTIFS(Accounts!$E:$E,'AccountSummary (New)'!L$1,Accounts!$G:$G,'AccountSummary (New)'!L$2,Accounts!$F:$F,'AccountSummary (New)'!L$3,Accounts!$B:$B,"Customer",Accounts!$C:$C,"Lost",Accounts!$H:$H,">"&30,Accounts!$H:$H,"<="&60) -> 0 | M33: =COUNTIFS(Accounts!$E:$E,'AccountSummary (New)'!M$1,Accounts!$G:$G,'AccountSummary (New)'!M$2,Accounts!$F:$F,'AccountSummary (New)'!M$3,Accounts!$B:$B,"Customer",Accounts!$C:$C,"Lost",Accounts!$H:$H,">"&30,Accounts!$H:$H,"<="&60) -> 0 | N33: =COUNTIFS(Accounts!$E:$E,'AccountSummary (New)'!N$1,Accounts!$G:$G,'AccountSummary (New)'!N$2,Accounts!$F:$F,'AccountSummary (New)'!N$3,Accounts!$B:$B,"Customer",Accounts!$C:$C,"Lost",Accounts!$H:$H,">"&30,Accounts!$H:$H,"<="&60) -> 0 | O33: =COUNTIFS(Accounts!$E:$E,'AccountSummary (New)'!O$1,Accounts!$G:$G,'AccountSummary (New)'!O$2,Accounts!$F:$F,'AccountSummary (New)'!O$3,Accounts!$B:$B,"Customer",Accounts!$C:$C,"Lost",Accounts!$H:$H,">"&30,Accounts!$H:$H,"<="&60) -> 0 | P33: =SUM(J33:O33) -> 0 | Q33: =COUNTIFS(Accounts!$E:$E,'AccountSummary (New)'!Q$1,Accounts!$G:$G,'AccountSummary (New)'!Q$2,Accounts!$F:$F,'AccountSummary (New)'!Q$3,Accounts!$B:$B,"Customer",Accounts!$C:$C,"Lost",Accounts!$H:$H,">"&30,Accounts!$H:$H,"<="&60) -> 0 | R33: =COUNTIFS(Accounts!$E:$E,'AccountSummary (New)'!R$1,Accounts!$G:$G,'AccountSummary (New)'!R$2,Accounts!$F:$F,'AccountSummary (New)'!R$3,Accounts!$B:$B,"Customer",Accounts!$C:$C,"Lost",Accounts!$H:$H,">"&30,Accounts!$H:$H,"<="&60) -> 0 | S33: =COUNTIFS(Accounts!$E:$E,'AccountSummary (New)'!S$1,Accounts!$G:$G,'AccountSummary (New)'!S$2,Accounts!$F:$F,'AccountSummary (New)'!S$3,Accounts!$B:$B,"Customer",Accounts!$C:$C,"Lost",Accounts!$H:$H,">"&30,Accounts!$H:$H,"<="&60) -> 0 | T33: =COUNTIFS(Accounts!$E:$E,'AccountSummary (New)'!T$1,Accounts!$G:$G,'AccountSummary (New)'!T$2,Accounts!$F:$F,'AccountSummary (New)'!T$3,Accounts!$B:$B,"Customer",Accounts!$C:$C,"Lost",Accounts!$H:$H,">"&30,Accounts!$H:$H,"<="&60) -> 0 | U33: =COUNTIFS(Accounts!$E:$E,'AccountSummary (New)'!U$1,Accounts!$G:$G,'AccountSummary (New)'!U$2,Accounts!$F:$F,'AccountSummary (New)'!U$3,Accounts!$B:$B,"Customer",Accounts!$C:$C,"Lost",Accounts!$H:$H,">"&30,Accounts!$H:$H,"<="&60) -> 0 | V33: =COUNTIFS(Accounts!$E:$E,'AccountSummary (New)'!V$1,Accounts!$G:$G,'AccountSummary (New)'!V$2,Accounts!$F:$F,'AccountSummary (New)'!V$3,Accounts!$B:$B,"Customer",Accounts!$C:$C,"Lost",Accounts!$H:$H,">"&30,Accounts!$H:$H,"<="&60) -> 0 | W33: =SUM(Q33:V33) -> 0
A34: Retained Count | B34: =I34+P34+W34 -> 0 | C34: =COUNTIFS(Accounts!$E:$E,'AccountSummary (New)'!C$1,Accounts!$G:$G,'AccountSummary (New)'!C$2,Accounts!$F:$F,'AccountSummary (New)'!C$3,Accounts!$B:$B,"Customer",Accounts!$C:$C,"Customer",Accounts!$H:$H,">"&30,Accounts!$H:$H,"<="&60) -> 0 | D34: =COUNTIFS(Accounts!$E:$E,'AccountSummary (New)'!D$1,Accounts!$G:$G,'AccountSummary (New)'!D$2,Accounts!$F:$F,'AccountSummary (New)'!D$3,Accounts!$B:$B,"Customer",Accounts!$C:$C,"Customer",Accounts!$H:$H,">"&30,Accounts!$H:$H,"<="&60) -> 0 | E34: =COUNTIFS(Accounts!$E:$E,'AccountSummary (New)'!E$1,Accounts!$G:$G,'AccountSummary (New)'!E$2,Accounts!$F:$F,'AccountSummary (New)'!E$3,Accounts!$B:$B,"Customer",Accounts!$C:$C,"Customer",Accounts!$H:$H,">"&30,Accounts!$H:$H,"<="&60) -> 0 | F34: =COUNTIFS(Accounts!$E:$E,'AccountSummary (New)'!F$1,Accounts!$G:$G,'AccountSummary (New)'!F$2,Accounts!$F:$F,'AccountSummary (New)'!F$3,Accounts!$B:$B,"Customer",Accounts!$C:$C,"Customer",Accounts!$H:$H,">"&30,Accounts!$H:$H,"<="&60) -> 0 | G34: =COUNTIFS(Accounts!$E:$E,'AccountSummary (New)'!G$1,Accounts!$G:$G,'AccountSummary (New)'!G$2,Accounts!$F:$F,'AccountSummary (New)'!G$3,Accounts!$B:$B,"Customer",Accounts!$C:$C,"Customer",Accounts!$H:$H,">"&30,Accounts!$H:$H,"<="&60) -> 0 | H34: =COUNTIFS(Accounts!$E:$E,'AccountSummary (New)'!H$1,Accounts!$G:$G,'AccountSummary (New)'!H$2,Accounts!$F:$F,'AccountSummary (New)'!H$3,Accounts!$B:$B,"Customer",Accounts!$C:$C,"Customer",Accounts!$H:$H,">"&30,Accounts!$H:$H,"<="&60) -> 0 | I34: =SUM(C34:H34) -> 0 | J34: =COUNTIFS(Accounts!$E:$E,'AccountSummary (New)'!J$1,Accounts!$G:$G,'AccountSummary (New)'!J$2,Accounts!$F:$F,'AccountSummary (New)'!J$3,Accounts!$B:$B,"Customer",Accounts!$C:$C,"Customer",Accounts!$H:$H,">"&30,Accounts!$H:$H,"<="&60) -> 0 | K34: =COUNTIFS(Accounts!$E:$E,'AccountSummary (New)'!K$1,Accounts!$G:$G,'AccountSummary (New)'!K$2,Accounts!$F:$F,'AccountSummary (New)'!K$3,Accounts!$B:$B,"Customer",Accounts!$C:$C,"Customer",Accounts!$H:$H,">"&30,Accounts!$H:$H,"<="&60) -> 0 | L34: =COUNTIFS(Accounts!$E:$E,'AccountSummary (New)'!L$1,Accounts!$G:$G,'AccountSummary (New)'!L$2,Accounts!$F:$F,'AccountSummary (New)'!L$3,Accounts!$B:$B,"Customer",Accounts!$C:$C,"Customer",Accounts!$H:$H,">"&30,Accounts!$H:$H,"<="&60) -> 0 | M34: =COUNTIFS(Accounts!$E:$E,'AccountSummary (New)'!M$1,Accounts!$G:$G,'AccountSummary (New)'!M$2,Accounts!$F:$F,'AccountSummary (New)'!M$3,Accounts!$B:$B,"Customer",Accounts!$C:$C,"Customer",Accounts!$H:$H,">"&30,Accounts!$H:$H,"<="&60) -> 0 | N34: =COUNTIFS(Accounts!$E:$E,'AccountSummary (New)'!N$1,Accounts!$G:$G,'AccountSummary (New)'!N$2,Accounts!$F:$F,'AccountSummary (New)'!N$3,Accounts!$B:$B,"Customer",Accounts!$C:$C,"Customer",Accounts!$H:$H,">"&30,Accounts!$H:$H,"<="&60) -> 0 | O34: =COUNTIFS(Accounts!$E:$E,'AccountSummary (New)'!O$1,Accounts!$G:$G,'AccountSummary (New)'!O$2,Accounts!$F:$F,'AccountSummary (New)'!O$3,Accounts!$B:$B,"Customer",Accounts!$C:$C,"Customer",Accounts!$H:$H,">"&30,Accounts!$H:$H,"<="&60) -> 0 | P34: =SUM(J34:O34) -> 0 | Q34: =COUNTIFS(Accounts!$E:$E,'AccountSummary (New)'!Q$1,Accounts!$G:$G,'AccountSummary (New)'!Q$2,Accounts!$F:$F,'AccountSummary (New)'!Q$3,Accounts!$B:$B,"Customer",Accounts!$C:$C,"Customer",Accounts!$H:$H,">"&30,Accounts!$H:$H,"<="&60) -> 0 | R34: =COUNTIFS(Accounts!$E:$E,'AccountSummary (New)'!R$1,Accounts!$G:$G,'AccountSummary (New)'!R$2,Accounts!$F:$F,'AccountSummary (New)'!R$3,Accounts!$B:$B,"Customer",Accounts!$C:$C,"Customer",Accounts!$H:$H,">"&30,Accounts!$H:$H,"<="&60) -> 0 | S34: =COUNTIFS(Accounts!$E:$E,'AccountSummary (New)'!S$1,Accounts!$G:$G,'AccountSummary (New)'!S$2,Accounts!$F:$F,'AccountSummary (New)'!S$3,Accounts!$B:$B,"Customer",Accounts!$C:$C,"Customer",Accounts!$H:$H,">"&30,Accounts!$H:$H,"<="&60) -> 0 | T34: =COUNTIFS(Accounts!$E:$E,'AccountSummary (New)'!T$1,Accounts!$G:$G,'AccountSummary (New)'!T$2,Accounts!$F:$F,'AccountSummary (New)'!T$3,Accounts!$B:$B,"Customer",Accounts!$C:$C,"Customer",Accounts!$H:$H,">"&30,Accounts!$H:$H,"<="&60) -> 0 | U34: =COUNTIFS(Accounts!$E:$E,'AccountSummary (New)'!U$1,Accounts!$G:$G,'AccountSummary (New)'!U$2,Accounts!$F:$F,'AccountSummary (New)'!U$3,Accounts!$B:$B,"Customer",Accounts!$C:$C,"Customer",Accounts!$H:$H,">"&30,Accounts!$H:$H,"<="&60) -> 0 | V34: =COUNTIFS(Accounts!$E:$E,'AccountSummary (New)'!V$1,Accounts!$G:$G,'AccountSummary (New)'!V$2,Accounts!$F:$F,'AccountSummary (New)'!V$3,Accounts!$B:$B,"Customer",Accounts!$C:$C,"Customer",Accounts!$H:$H,">"&30,Accounts!$H:$H,"<="&60) -> 0 | W34: =SUM(Q34:V34) -> 0
A35: Packs per Account | B35: =IF(B34=0,0,SUMIFS(Accounts!$L:$L,Accounts!$W:$W,0,Accounts!$C:$C,"Customer",Accounts!$H:$H,">"&30,Accounts!$H:$H,"<="&60)/B34) -> 0 | C35: =IF(C34=0,0,SUMIFS(Accounts!$L:$L,Accounts!$E:$E,'AccountSummary (New)'!C$1,Accounts!$G:$G,'AccountSummary (New)'!C$2,Accounts!$F:$F,'AccountSummary (New)'!C$3,Accounts!$W:$W,0,Accounts!$C:$C,"Customer",Accounts!$H:$H,">"&30,Accounts!$H:$H,"<="&60)/C34) -> 0 | D35: =IF(D34=0,0,SUMIFS(Accounts!$L:$L,Accounts!$E:$E,'AccountSummary (New)'!D$1,Accounts!$G:$G,'AccountSummary (New)'!D$2,Accounts!$F:$F,'AccountSummary (New)'!D$3,Accounts!$W:$W,0,Accounts!$C:$C,"Customer",Accounts!$H:$H,">"&30,Accounts!$H:$H,"<="&60)/D34) -> 0 | E35: =IF(E34=0,0,SUMIFS(Accounts!$L:$L,Accounts!$E:$E,'AccountSummary (New)'!E$1,Accounts!$G:$G,'AccountSummary (New)'!E$2,Accounts!$F:$F,'AccountSummary (New)'!E$3,Accounts!$W:$W,0,Accounts!$C:$C,"Customer",Accounts!$H:$H,">"&30,Accounts!$H:$H,"<="&60)/E34) -> 0 | F35: =IF(F34=0,0,SUMIFS(Accounts!$L:$L,Accounts!$E:$E,'AccountSummary (New)'!F$1,Accounts!$G:$G,'AccountSummary (New)'!F$2,Accounts!$F:$F,'AccountSummary (New)'!F$3,Accounts!$W:$W,0,Accounts!$C:$C,"Customer",Accounts!$H:$H,">"&30,Accounts!$H:$H,"<="&60)/F34) -> 0 | G35: =IF(G34=0,0,SUMIFS(Accounts!$L:$L,Accounts!$E:$E,'AccountSummary (New)'!G$1,Accounts!$G:$G,'AccountSummary (New)'!G$2,Accounts!$F:$F,'AccountSummary (New)'!G$3,Accounts!$W:$W,0,Accounts!$C:$C,"Customer",Accounts!$H:$H,">"&30,Accounts!$H:$H,"<="&60)/G34) -> 0 | H35: =IF(H34=0,0,SUMIFS(Accounts!$L:$L,Accounts!$E:$E,'AccountSummary (New)'!H$1,Accounts!$G:$G,'AccountSummary (New)'!H$2,Accounts!$F:$F,'AccountSummary (New)'!H$3,Accounts!$W:$W,0,Accounts!$C:$C,"Customer",Accounts!$H:$H,">"&30,Accounts!$H:$H,"<="&60)/H34) -> 0 | I35: =IF(I34=0,0,SUMIFS(Accounts!$L:$L,Accounts!$F:$F,'AccountSummary (New)'!I$3,Accounts!$W:$W,0,Accounts!$C:$C,"Customer",Accounts!$H:$H,">"&30,Accounts!$H:$H,"<="&60)/I34) -> 0 | J35: =IF(J34=0,0,SUMIFS(Accounts!$L:$L,Accounts!$E:$E,'AccountSummary (New)'!J$1,Accounts!$G:$G,'AccountSummary (New)'!J$2,Accounts!$F:$F,'AccountSummary (New)'!J$3,Accounts!$W:$W,0,Accounts!$C:$C,"Customer",Accounts!$H:$H,">"&30,Accounts!$H:$H,"<="&60)/J34) -> 0 | K35: =IF(K34=0,0,SUMIFS(Accounts!$L:$L,Accounts!$E:$E,'AccountSummary (New)'!K$1,Accounts!$G:$G,'AccountSummary (New)'!K$2,Accounts!$F:$F,'AccountSummary (New)'!K$3,Accounts!$W:$W,0,Accounts!$C:$C,"Customer",Accounts!$H:$H,">"&30,Accounts!$H:$H,"<="&60)/K34) -> 0 | L35: =IF(L34=0,0,SUMIFS(Accounts!$L:$L,Accounts!$E:$E,'AccountSummary (New)'!L$1,Accounts!$G:$G,'AccountSummary (New)'!L$2,Accounts!$F:$F,'AccountSummary (New)'!L$3,Accounts!$W:$W,0,Accounts!$C:$C,"Customer",Accounts!$H:$H,">"&30,Accounts!$H:$H,"<="&60)/L34) -> 0 | M35: =IF(M34=0,0,SUMIFS(Accounts!$L:$L,Accounts!$E:$E,'AccountSummary (New)'!M$1,Accounts!$G:$G,'AccountSummary (New)'!M$2,Accounts!$F:$F,'AccountSummary (New)'!M$3,Accounts!$W:$W,0,Accounts!$C:$C,"Customer",Accounts!$H:$H,">"&30,Accounts!$H:$H,"<="&60)/M34) -> 0 | N35: =IF(N34=0,0,SUMIFS(Accounts!$L:$L,Accounts!$E:$E,'AccountSummary (New)'!N$1,Accounts!$G:$G,'AccountSummary (New)'!N$2,Accounts!$F:$F,'AccountSummary (New)'!N$3,Accounts!$W:$W,0,Accounts!$C:$C,"Customer",Accounts!$H:$H,">"&30,Accounts!$H:$H,"<="&60)/N34) -> 0 | O35: =IF(O34=0,0,SUMIFS(Accounts!$L:$L,Accounts!$E:$E,'AccountSummary (New)'!O$1,Accounts!$G:$G,'AccountSummary (New)'!O$2,Accounts!$F:$F,'AccountSummary (New)'!O$3,Accounts!$W:$W,0,Accounts!$C:$C,"Customer",Accounts!$H:$H,">"&30,Accounts!$H:$H,"<="&60)/O34) -> 0 | P35: =IF(P34=0,0,SUMIFS(Accounts!$L:$L,Accounts!$F:$F,'AccountSummary (New)'!P$3,Accounts!$W:$W,0,Accounts!$C:$C,"Customer",Accounts!$H:$H,">"&30,Accounts!$H:$H,"<="&60)/P34) -> 0 | Q35: =IF(Q34=0,0,SUMIFS(Accounts!$L:$L,Accounts!$E:$E,'AccountSummary (New)'!Q$1,Accounts!$G:$G,'AccountSummary (New)'!Q$2,Accounts!$F:$F,'AccountSummary (New)'!Q$3,Accounts!$W:$W,0,Accounts!$C:$C,"Customer",Accounts!$H:$H,">"&30,Accounts!$H:$H,"<="&60)/Q34) -> 0 | R35: =IF(R34=0,0,SUMIFS(Accounts!$L:$L,Accounts!$E:$E,'AccountSummary (New)'!R$1,Accounts!$G:$G,'AccountSummary (New)'!R$2,Accounts!$F:$F,'AccountSummary (New)'!R$3,Accounts!$W:$W,0,Accounts!$C:$C,"Customer",Accounts!$H:$H,">"&30,Accounts!$H:$H,"<="&60)/R34) -> 0 | S35: =IF(S34=0,0,SUMIFS(Accounts!$L:$L,Accounts!$E:$E,'AccountSummary (New)'!S$1,Accounts!$G:$G,'AccountSummary (New)'!S$2,Accounts!$F:$F,'AccountSummary (New)'!S$3,Accounts!$W:$W,0,Accounts!$C:$C,"Customer",Accounts!$H:$H,">"&30,Accounts!$H:$H,"<="&60)/S34) -> 0 | T35: =IF(T34=0,0,SUMIFS(Accounts!$L:$L,Accounts!$E:$E,'AccountSummary (New)'!T$1,Accounts!$G:$G,'AccountSummary (New)'!T$2,Accounts!$F:$F,'AccountSummary (New)'!T$3,Accounts!$W:$W,0,Accounts!$C:$C,"Customer",Accounts!$H:$H,">"&30,Accounts!$H:$H,"<="&60)/T34) -> 0 | U35: =IF(U34=0,0,SUMIFS(Accounts!$L:$L,Accounts!$E:$E,'AccountSummary (New)'!U$1,Accounts!$G:$G,'AccountSummary (New)'!U$2,Accounts!$F:$F,'AccountSummary (New)'!U$3,Accounts!$W:$W,0,Accounts!$C:$C,"Customer",Accounts!$H:$H,">"&30,Accounts!$H:$H,"<="&60)/U34) -> 0 | V35: =IF(V34=0,0,SUMIFS(Accounts!$L:$L,Accounts!$E:$E,'AccountSummary (New)'!V$1,Accounts!$G:$G,'AccountSummary (New)'!V$2,Accounts!$F:$F,'AccountSummary (New)'!V$3,Accounts!$W:$W,0,Accounts!$C:$C,"Customer",Accounts!$H:$H,">"&30,Accounts!$H:$H,"<="&60)/V34) -> 0 | W35: =IF(W34=0,0,SUMIFS(Accounts!$L:$L,Accounts!$F:$F,'AccountSummary (New)'!W$3,Accounts!$W:$W,0,Accounts!$C:$C,"Customer",Accounts!$H:$H,">"&30,Accounts!$H:$H,"<="&60)/W34) -> 0
A36: Users per Account | B36: =IF(B34=0,0,SUMIFS(Accounts!$M:$M,Accounts!$W:$W,0,Accounts!$C:$C,"Customer",Accounts!$H:$H,">"&30,Accounts!$H:$H,"<="&60)/B34) -> 0 | C36: =IF(C34=0,0,SUMIFS(Accounts!$M:$M,Accounts!$E:$E,'AccountSummary (New)'!C$1,Accounts!$G:$G,'AccountSummary (New)'!C$2,Accounts!$F:$F,'AccountSummary (New)'!C$3,Accounts!$W:$W,0,Accounts!$C:$C,"Customer",Accounts!$H:$H,">"&30,Accounts!$H:$H,"<="&60)/C34) -> 0 | D36: =IF(D34=0,0,SUMIFS(Accounts!$M:$M,Accounts!$E:$E,'AccountSummary (New)'!D$1,Accounts!$G:$G,'AccountSummary (New)'!D$2,Accounts!$F:$F,'AccountSummary (New)'!D$3,Accounts!$W:$W,0,Accounts!$C:$C,"Customer",Accounts!$H:$H,">"&30,Accounts!$H:$H,"<="&60)/D34) -> 0 | E36: =IF(E34=0,0,SUMIFS(Accounts!$M:$M,Accounts!$E:$E,'AccountSummary (New)'!E$1,Accounts!$G:$G,'AccountSummary (New)'!E$2,Accounts!$F:$F,'AccountSummary (New)'!E$3,Accounts!$W:$W,0,Accounts!$C:$C,"Customer",Accounts!$H:$H,">"&30,Accounts!$H:$H,"<="&60)/E34) -> 0 | F36: =IF(F34=0,0,SUMIFS(Accounts!$M:$M,Accounts!$E:$E,'AccountSummary (New)'!F$1,Accounts!$G:$G,'AccountSummary (New)'!F$2,Accounts!$F:$F,'AccountSummary (New)'!F$3,Accounts!$W:$W,0,Accounts!$C:$C,"Customer",Accounts!$H:$H,">"&30,Accounts!$H:$H,"<="&60)/F34) -> 0 | G36: =IF(G34=0,0,SUMIFS(Accounts!$M:$M,Accounts!$E:$E,'AccountSummary (New)'!G$1,Accounts!$G:$G,'AccountSummary (New)'!G$2,Accounts!$F:$F,'AccountSummary (New)'!G$3,Accounts!$W:$W,0,Accounts!$C:$C,"Customer",Accounts!$H:$H,">"&30,Accounts!$H:$H,"<="&60)/G34) -> 0 | H36: =IF(H34=0,0,SUMIFS(Accounts!$M:$M,Accounts!$E:$E,'AccountSummary (New)'!H$1,Accounts!$G:$G,'AccountSummary (New)'!H$2,Accounts!$F:$F,'AccountSummary (New)'!H$3,Accounts!$W:$W,0,Accounts!$C:$C,"Customer",Accounts!$H:$H,">"&30,Accounts!$H:$H,"<="&60)/H34) -> 0 | I36: =IF(I34=0,0,SUMIFS(Accounts!$M:$M,Accounts!$F:$F,'AccountSummary (New)'!I$3,Accounts!$W:$W,0,Accounts!$C:$C,"Customer",Accounts!$H:$H,">"&30,Accounts!$H:$H,"<="&60)/I34) -> 0 | J36: =IF(J34=0,0,SUMIFS(Accounts!$M:$M,Accounts!$E:$E,'AccountSummary (New)'!J$1,Accounts!$G:$G,'AccountSummary (New)'!J$2,Accounts!$F:$F,'AccountSummary (New)'!J$3,Accounts!$W:$W,0,Accounts!$C:$C,"Customer",Accounts!$H:$H,">"&30,Accounts!$H:$H,"<="&60)/J34) -> 0 | K36: =IF(K34=0,0,SUMIFS(Accounts!$M:$M,Accounts!$E:$E,'AccountSummary (New)'!K$1,Accounts!$G:$G,'AccountSummary (New)'!K$2,Accounts!$F:$F,'AccountSummary (New)'!K$3,Accounts!$W:$W,0,Accounts!$C:$C,"Customer",Accounts!$H:$H,">"&30,Accounts!$H:$H,"<="&60)/K34) -> 0 | L36: =IF(L34=0,0,SUMIFS(Accounts!$M:$M,Accounts!$E:$E,'AccountSummary (New)'!L$1,Accounts!$G:$G,'AccountSummary (New)'!L$2,Accounts!$F:$F,'AccountSummary (New)'!L$3,Accounts!$W:$W,0,Accounts!$C:$C,"Customer",Accounts!$H:$H,">"&30,Accounts!$H:$H,"<="&60)/L34) -> 0 | M36: =IF(M34=0,0,SUMIFS(Accounts!$M:$M,Accounts!$E:$E,'AccountSummary (New)'!M$1,Accounts!$G:$G,'AccountSummary (New)'!M$2,Accounts!$F:$F,'AccountSummary (New)'!M$3,Accounts!$W:$W,0,Accounts!$C:$C,"Customer",Accounts!$H:$H,">"&30,Accounts!$H:$H,"<="&60)/M34) -> 0 | N36: =IF(N34=0,0,SUMIFS(Accounts!$M:$M,Accounts!$E:$E,'AccountSummary (New)'!N$1,Accounts!$G:$G,'AccountSummary (New)'!N$2,Accounts!$F:$F,'AccountSummary (New)'!N$3,Accounts!$W:$W,0,Accounts!$C:$C,"Customer",Accounts!$H:$H,">"&30,Accounts!$H:$H,"<="&60)/N34) -> 0 | O36: =IF(O34=0,0,SUMIFS(Accounts!$M:$M,Accounts!$E:$E,'AccountSummary (New)'!O$1,Accounts!$G:$G,'AccountSummary (New)'!O$2,Accounts!$F:$F,'AccountSummary (New)'!O$3,Accounts!$W:$W,0,Accounts!$C:$C,"Customer",Accounts!$H:$H,">"&30,Accounts!$H:$H,"<="&60)/O34) -> 0 | P36: =IF(P34=0,0,SUMIFS(Accounts!$M:$M,Accounts!$F:$F,'AccountSummary (New)'!P$3,Accounts!$W:$W,0,Accounts!$C:$C,"Customer",Accounts!$H:$H,">"&30,Accounts!$H:$H,"<="&60)/P34) -> 0 | Q36: =IF(Q34=0,0,SUMIFS(Accounts!$M:$M,Accounts!$E:$E,'AccountSummary (New)'!Q$1,Accounts!$G:$G,'AccountSummary (New)'!Q$2,Accounts!$F:$F,'AccountSummary (New)'!Q$3,Accounts!$W:$W,0,Accounts!$C:$C,"Customer",Accounts!$H:$H,">"&30,Accounts!$H:$H,"<="&60)/Q34) -> 0 | R36: =IF(R34=0,0,SUMIFS(Accounts!$M:$M,Accounts!$E:$E,'AccountSummary (New)'!R$1,Accounts!$G:$G,'AccountSummary (New)'!R$2,Accounts!$F:$F,'AccountSummary (New)'!R$3,Accounts!$W:$W,0,Accounts!$C:$C,"Customer",Accounts!$H:$H,">"&30,Accounts!$H:$H,"<="&60)/R34) -> 0 | S36: =IF(S34=0,0,SUMIFS(Accounts!$M:$M,Accounts!$E:$E,'AccountSummary (New)'!S$1,Accounts!$G:$G,'AccountSummary (New)'!S$2,Accounts!$F:$F,'AccountSummary (New)'!S$3,Accounts!$W:$W,0,Accounts!$C:$C,"Customer",Accounts!$H:$H,">"&30,Accounts!$H:$H,"<="&60)/S34) -> 0 | T36: =IF(T34=0,0,SUMIFS(Accounts!$M:$M,Accounts!$E:$E,'AccountSummary (New)'!T$1,Accounts!$G:$G,'AccountSummary (New)'!T$2,Accounts!$F:$F,'AccountSummary (New)'!T$3,Accounts!$W:$W,0,Accounts!$C:$C,"Customer",Accounts!$H:$H,">"&30,Accounts!$H:$H,"<="&60)/T34) -> 0 | U36: =IF(U34=0,0,SUMIFS(Accounts!$M:$M,Accounts!$E:$E,'AccountSummary (New)'!U$1,Accounts!$G:$G,'AccountSummary (New)'!U$2,Accounts!$F:$F,'AccountSummary (New)'!U$3,Accounts!$W:$W,0,Accounts!$C:$C,"Customer",Accounts!$H:$H,">"&30,Accounts!$H:$H,"<="&60)/U34) -> 0 | V36: =IF(V34=0,0,SUMIFS(Accounts!$M:$M,Accounts!$E:$E,'AccountSummary (New)'!V$1,Accounts!$G:$G,'AccountSummary (New)'!V$2,Accounts!$F:$F,'AccountSummary (New)'!V$3,Accounts!$W:$W,0,Accounts!$C:$C,"Customer",Accounts!$H:$H,">"&30,Accounts!$H:$H,"<="&60)/V34) -> 0 | W36: =IF(W34=0,0,SUMIFS(Accounts!$M:$M,Accounts!$F:$F,'AccountSummary (New)'!W$3,Accounts!$W:$W,0,Accounts!$C:$C,"Customer",Accounts!$H:$H,">"&30,Accounts!$H:$H,"<="&60)/W34) -> 0
A37: ARPC | B37: =IF(B34=0,0,B38/B34) -> 0 | C37: =IF(C34=0,0,C38/C34) -> 0 | D37: =IF(D34=0,0,D38/D34) -> 0 | E37: =IF(E34=0,0,E38/E34) -> 0 | F37: =IF(F34=0,0,F38/F34) -> 0 | G37: =IF(G34=0,0,G38/G34) -> 0 | H37: =IF(H34=0,0,H38/H34) -> 0 | I37: =IF(I34=0,0,I38/I34) -> 0 | ... W37: =IF(W34=0,0,W38/W34) -> 0
A38: SaaS | B38: =I38+P38+W38 -> 0 | C38: =SUMIFS(Accounts!$I:$I,Accounts!$E:$E,'AccountSummary (New)'!C$1,Accounts!$G:$G,'AccountSummary (New)'!C$2,Accounts!$F:$F,'AccountSummary (New)'!C$3,Accounts!$W:$W,0,Accounts!$C:$C,"Customer",Accounts!$H:$H,">"&30,Accounts!$H:$H,"<="&60) -> 0 | D38: =SUMIFS(Accounts!$I:$I,Accounts!$E:$E,'AccountSummary (New)'!D$1,Accounts!$G:$G,'AccountSummary (New)'!D$2,Accounts!$F:$F,'AccountSummary (New)'!D$3,Accounts!$W:$W,0,Accounts!$C:$C,"Customer",Accounts!$H:$H,">"&30,Accounts!$H:$H,"<="&60) -> 0 | E38: =SUMIFS(Accounts!$I:$I,Accounts!$E:$E,'AccountSummary (New)'!E$1,Accounts!$G:$G,'AccountSummary (New)'!E$2,Accounts!$F:$F,'AccountSummary (New)'!E$3,Accounts!$W:$W,0,Accounts!$C:$C,"Customer",Accounts!$H:$H,">"&30,Accounts!$H:$H,"<="&60) -> 0 | F38: =SUMIFS(Accounts!$I:$I,Accounts!$E:$E,'AccountSummary (New)'!F$1,Accounts!$G:$G,'AccountSummary (New)'!F$2,Accounts!$F:$F,'AccountSummary (New)'!F$3,Accounts!$W:$W,0,Accounts!$C:$C,"Customer",Accounts!$H:$H,">"&30,Accounts!$H:$H,"<="&60) -> 0 | G38: =SUMIFS(Accounts!$I:$I,Accounts!$E:$E,'AccountSummary (New)'!G$1,Accounts!$G:$G,'AccountSummary (New)'!G$2,Accounts!$F:$F,'AccountSummary (New)'!G$3,Accounts!$W:$W,0,Accounts!$C:$C,"Customer",Accounts!$H:$H,">"&30,Accounts!$H:$H,"<="&60) -> 0 | H38: =SUMIFS(Accounts!$I:$I,Accounts!$E:$E,'AccountSummary (New)'!H$1,Accounts!$G:$G,'AccountSummary (New)'!H$2,Accounts!$F:$F,'AccountSummary (New)'!H$3,Accounts!$W:$W,0,Accounts!$C:$C,"Customer",Accounts!$H:$H,">"&30,Accounts!$H:$H,"<="&60) -> 0 | I38: =SUM(C38:H38) -> 0 | J38: =SUMIFS(Accounts!$I:$I,Accounts!$E:$E,'AccountSummary (New)'!J$1,Accounts!$G:$G,'AccountSummary (New)'!J$2,Accounts!$F:$F,'AccountSummary (New)'!J$3,Accounts!$W:$W,0,Accounts!$C:$C,"Customer",Accounts!$H:$H,">"&30,Accounts!$H:$H,"<="&60) -> 0 | K38: =SUMIFS(Accounts!$I:$I,Accounts!$E:$E,'AccountSummary (New)'!K$1,Accounts!$G:$G,'AccountSummary (New)'!K$2,Accounts!$F:$F,'AccountSummary (New)'!K$3,Accounts!$W:$W,0,Accounts!$C:$C,"Customer",Accounts!$H:$H,">"&30,Accounts!$H:$H,"<="&60) -> 0 | L38: =SUMIFS(Accounts!$I:$I,Accounts!$E:$E,'AccountSummary (New)'!L$1,Accounts!$G:$G,'AccountSummary (New)'!L$2,Accounts!$F:$F,'AccountSummary (New)'!L$3,Accounts!$W:$W,0,Accounts!$C:$C,"Customer",Accounts!$H:$H,">"&30,Accounts!$H:$H,"<="&60) -> 0 | M38: =SUMIFS(Accounts!$I:$I,Accounts!$E:$E,'AccountSummary (New)'!M$1,Accounts!$G:$G,'AccountSummary (New)'!M$2,Accounts!$F:$F,'AccountSummary (New)'!M$3,Accounts!$W:$W,0,Accounts!$C:$C,"Customer",Accounts!$H:$H,">"&30,Accounts!$H:$H,"<="&60) -> 0 | N38: =SUMIFS(Accounts!$I:$I,Accounts!$E:$E,'AccountSummary (New)'!N$1,Accounts!$G:$G,'AccountSummary (New)'!N$2,Accounts!$F:$F,'AccountSummary (New)'!N$3,Accounts!$W:$W,0,Accounts!$C:$C,"Customer",Accounts!$H:$H,">"&30,Accounts!$H:$H,"<="&60) -> 0 | O38: =SUMIFS(Accounts!$I:$I,Accounts!$E:$E,'AccountSummary (New)'!O$1,Accounts!$G:$G,'AccountSummary (New)'!O$2,Accounts!$F:$F,'AccountSummary (New)'!O$3,Accounts!$W:$W,0,Accounts!$C:$C,"Customer",Accounts!$H:$H,">"&30,Accounts!$H:$H,"<="&60) -> 0 | P38: =SUM(J38:O38) -> 0 | Q38: =SUMIFS(Accounts!$I:$I,Accounts!$E:$E,'AccountSummary (New)'!Q$1,Accounts!$G:$G,'AccountSummary (New)'!Q$2,Accounts!$F:$F,'AccountSummary (New)'!Q$3,Accounts!$W:$W,0,Accounts!$C:$C,"Customer",Accounts!$H:$H,">"&30,Accounts!$H:$H,"<="&60) -> 0 | R38: =SUMIFS(Accounts!$I:$I,Accounts!$E:$E,'AccountSummary (New)'!R$1,Accounts!$G:$G,'AccountSummary (New)'!R$2,Accounts!$F:$F,'AccountSummary (New)'!R$3,Accounts!$W:$W,0,Accounts!$C:$C,"Customer",Accounts!$H:$H,">"&30,Accounts!$H:$H,"<="&60) -> 0 | S38: =SUMIFS(Accounts!$I:$I,Accounts!$E:$E,'AccountSummary (New)'!S$1,Accounts!$G:$G,'AccountSummary (New)'!S$2,Accounts!$F:$F,'AccountSummary (New)'!S$3,Accounts!$W:$W,0,Accounts!$C:$C,"Customer",Accounts!$H:$H,">"&30,Accounts!$H:$H,"<="&60) -> 0 | T38: =SUMIFS(Accounts!$I:$I,Accounts!$E:$E,'AccountSummary (New)'!T$1,Accounts!$G:$G,'AccountSummary (New)'!T$2,Accounts!$F:$F,'AccountSummary (New)'!T$3,Accounts!$W:$W,0,Accounts!$C:$C,"Customer",Accounts!$H:$H,">"&30,Accounts!$H:$H,"<="&60) -> 0 | U38: =SUMIFS(Accounts!$I:$I,Accounts!$E:$E,'AccountSummary (New)'!U$1,Accounts!$G:$G,'AccountSummary (New)'!U$2,Accounts!$F:$F,'AccountSummary (New)'!U$3,Accounts!$W:$W,0,Accounts!$C:$C,"Customer",Accounts!$H:$H,">"&30,Accounts!$H:$H,"<="&60) -> 0 | V38: =SUMIFS(Accounts!$I:$I,Accounts!$E:$E,'AccountSummary (New)'!V$1,Accounts!$G:$G,'AccountSummary (New)'!V$2,Accounts!$F:$F,'AccountSummary (New)'!V$3,Accounts!$W:$W,0,Accounts!$C:$C,"Customer",Accounts!$H:$H,">"&30,Accounts!$H:$H,"<="&60) -> 0 | W38: =SUM(Q38:V38) -> 0
A39: 61-90 day cohort as of BOM
A40: Total % of Paying Customers | B40: =IF(B$19=0,0,(B42+B43)/B$19) -> 0 | C40: =IF(C$19=0,0,(C42+C43)/C$19) -> 0 | D40: =IF(D$19=0,0,(D42+D43)/D$19) -> 0 | E40: =IF(E$19=0,0,(E42+E43)/E$19) -> 0 | F40: =IF(F$19=0,0,(F42+F43)/F$19) -> 0 | G40: =IF(G$19=0,0,(G42+G43)/G$19) -> 0 | H40: =IF(H$19=0,0,(H42+H43)/H$19) -> 0 | I40: =IF(I$19=0,0,(I42+I43)/I$19) -> 0 | ... W40: =IF(W$19=0,0,(W42+W43)/W$19) -> 0
A41: Loss % | B41: =IF((B42+B43)=0,0,B42/(B42+B43)) -> 0 | C41: =IF((C42+C43)=0,0,C42/(C42+C43)) -> 0 | D41: =IF((D42+D43)=0,0,D42/(D42+D43)) -> 0 | E41: =IF((E42+E43)=0,0,E42/(E42+E43)) -> 0 | F41: =IF((F42+F43)=0,0,F42/(F42+F43)) -> 0 | G41: =IF((G42+G43)=0,0,G42/(G42+G43)) -> 0 | H41: =IF((H42+H43)=0,0,H42/(H42+H43)) -> 0 | I41: =IF((I42+I43)=0,0,I42/(I42+I43)) -> 0 | ... W41: =IF((W42+W43)=0,0,W42/(W42+W43)) -> 0
A42: Lost Count | B42: =I42+P42+W42 -> 0 | C42: =COUNTIFS(Accounts!$E:$E,'AccountSummary (New)'!C$1,Accounts!$G:$G,'AccountSummary (New)'!C$2,Accounts!$F:$F,'AccountSummary (New)'!C$3,Accounts!$B:$B,"Customer",Accounts!$C:$C,"Lost",Accounts!$H:$H,">"&60,Accounts!$H:$H,"<="&90) -> 0 | D42: =COUNTIFS(Accounts!$E:$E,'AccountSummary (New)'!D$1,Accounts!$G:$G,'AccountSummary (New)'!D$2,Accounts!$F:$F,'AccountSummary (New)'!D$3,Accounts!$B:$B,"Customer",Accounts!$C:$C,"Lost",Accounts!$H:$H,">"&60,Accounts!$H:$H,"<="&90) -> 0 | E42: =COUNTIFS(Accounts!$E:$E,'AccountSummary (New)'!E$1,Accounts!$G:$G,'AccountSummary (New)'!E$2,Accounts!$F:$F,'AccountSummary (New)'!E$3,Accounts!$B:$B,"Customer",Accounts!$C:$C,"Lost",Accounts!$H:$H,">"&60,Accounts!$H:$H,"<="&90) -> 0 | F42: =COUNTIFS(Accounts!$E:$E,'AccountSummary (New)'!F$1,Accounts!$G:$G,'AccountSummary (New)'!F$2,Accounts!$F:$F,'AccountSummary (New)'!F$3,Accounts!$B:$B,"Customer",Accounts!$C:$C,"Lost",Accounts!$H:$H,">"&60,Accounts!$H:$H,"<="&90) -> 0 | G42: =COUNTIFS(Accounts!$E:$E,'AccountSummary (New)'!G$1,Accounts!$G:$G,'AccountSummary (New)'!G$2,Accounts!$F:$F,'AccountSummary (New)'!G$3,Accounts!$B:$B,"Customer",Accounts!$C:$C,"Lost",Accounts!$H:$H,">"&60,Accounts!$H:$H,"<="&90) -> 0 | H42: =COUNTIFS(Accounts!$E:$E,'AccountSummary (New)'!H$1,Accounts!$G:$G,'AccountSummary (New)'!H$2,Accounts!$F:$F,'AccountSummary (New)'!H$3,Accounts!$B:$B,"Customer",Accounts!$C:$C,"Lost",Accounts!$H:$H,">"&60,Accounts!$H:$H,"<="&90) -> 0 | I42: =SUM(C42:H42) -> 0 | J42: =COUNTIFS(Accounts!$E:$E,'AccountSummary (New)'!J$1,Accounts!$G:$G,'AccountSummary (New)'!J$2,Accounts!$F:$F,'AccountSummary (New)'!J$3,Accounts!$B:$B,"Customer",Accounts!$C:$C,"Lost",Accounts!$H:$H,">"&60,Accounts!$H:$H,"<="&90) -> 0 | K42: =COUNTIFS(Accounts!$E:$E,'AccountSummary (New)'!K$1,Accounts!$G:$G,'AccountSummary (New)'!K$2,Accounts!$F:$F,'AccountSummary (New)'!K$3,Accounts!$B:$B,"Customer",Accounts!$C:$C,"Lost",Accounts!$H:$H,">"&60,Accounts!$H:$H,"<="&90) -> 0 | L42: =COUNTIFS(Accounts!$E:$E,'AccountSummary (New)'!L$1,Accounts!$G:$G,'AccountSummary (New)'!L$2,Accounts!$F:$F,'AccountSummary (New)'!L$3,Accounts!$B:$B,"Customer",Accounts!$C:$C,"Lost",Accounts!$H:$H,">"&60,Accounts!$H:$H,"<="&90) -> 0 | M42: =COUNTIFS(Accounts!$E:$E,'AccountSummary (New)'!M$1,Accounts!$G:$G,'AccountSummary (New)'!M$2,Accounts!$F:$F,'AccountSummary (New)'!M$3,Accounts!$B:$B,"Customer",Accounts!$C:$C,"Lost",Accounts!$H:$H,">"&60,Accounts!$H:$H,"<="&90) -> 0 | N42: =COUNTIFS(Accounts!$E:$E,'AccountSummary (New)'!N$1,Accounts!$G:$G,'AccountSummary (New)'!N$2,Accounts!$F:$F,'AccountSummary (New)'!N$3,Accounts!$B:$B,"Customer",Accounts!$C:$C,"Lost",Accounts!$H:$H,">"&60,Accounts!$H:$H,"<="&90) -> 0 | O42: =COUNTIFS(Accounts!$E:$E,'AccountSummary (New)'!O$1,Accounts!$G:$G,'AccountSummary (New)'!O$2,Accounts!$F:$F,'AccountSummary (New)'!O$3,Accounts!$B:$B,"Customer",Accounts!$C:$C,"Lost",Accounts!$H:$H,">"&60,Accounts!$H:$H,"<="&90) -> 0 | P42: =SUM(J42:O42) -> 0 | Q42: =COUNTIFS(Accounts!$E:$E,'AccountSummary (New)'!Q$1,Accounts!$G:$G,'AccountSummary (New)'!Q$2,Accounts!$F:$F,'AccountSummary (New)'!Q$3,Accounts!$B:$B,"Customer",Accounts!$C:$C,"Lost",Accounts!$H:$H,">"&60,Accounts!$H:$H,"<="&90) -> 0 | R42: =COUNTIFS(Accounts!$E:$E,'AccountSummary (New)'!R$1,Accounts!$G:$G,'AccountSummary (New)'!R$2,Accounts!$F:$F,'AccountSummary (New)'!R$3,Accounts!$B:$B,"Customer",Accounts!$C:$C,"Lost",Accounts!$H:$H,">"&60,Accounts!$H:$H,"<="&90) -> 0 | S42: =COUNTIFS(Accounts!$E:$E,'AccountSummary (New)'!S$1,Accounts!$G:$G,'AccountSummary (New)'!S$2,Accounts!$F:$F,'AccountSummary (New)'!S$3,Accounts!$B:$B,"Customer",Accounts!$C:$C,"Lost",Accounts!$H:$H,">"&60,Accounts!$H:$H,"<="&90) -> 0 | T42: =COUNTIFS(Accounts!$E:$E,'AccountSummary (New)'!T$1,Accounts!$G:$G,'AccountSummary (New)'!T$2,Accounts!$F:$F,'AccountSummary (New)'!T$3,Accounts!$B:$B,"Customer",Accounts!$C:$C,"Lost",Accounts!$H:$H,">"&60,Accounts!$H:$H,"<="&90) -> 0 | U42: =COUNTIFS(Accounts!$E:$E,'AccountSummary (New)'!U$1,Accounts!$G:$G,'AccountSummary (New)'!U$2,Accounts!$F:$F,'AccountSummary (New)'!U$3,Accounts!$B:$B,"Customer",Accounts!$C:$C,"Lost",Accounts!$H:$H,">"&60,Accounts!$H:$H,"<="&90) -> 0 | V42: =COUNTIFS(Accounts!$E:$E,'AccountSummary (New)'!V$1,Accounts!$G:$G,'AccountSummary (New)'!V$2,Accounts!$F:$F,'AccountSummary (New)'!V$3,Accounts!$B:$B,"Customer",Accounts!$C:$C,"Lost",Accounts!$H:$H,">"&60,Accounts!$H:$H,"<="&90) -> 0 | W42: =SUM(Q42:V42) -> 0
A43: Retained Count | B43: =I43+P43+W43 -> 0 | C43: =COUNTIFS(Accounts!$E:$E,'AccountSummary (New)'!C$1,Accounts!$G:$G,'AccountSummary (New)'!C$2,Accounts!$F:$F,'AccountSummary (New)'!C$3,Accounts!$B:$B,"Customer",Accounts!$C:$C,"Customer",Accounts!$H:$H,">"&60,Accounts!$H:$H,"<="&90) -> 0 | D43: =COUNTIFS(Accounts!$E:$E,'AccountSummary (New)'!D$1,Accounts!$G:$G,'AccountSummary (New)'!D$2,Accounts!$F:$F,'AccountSummary (New)'!D$3,Accounts!$B:$B,"Customer",Accounts!$C:$C,"Customer",Accounts!$H:$H,">"&60,Accounts!$H:$H,"<="&90) -> 0 | E43: =COUNTIFS(Accounts!$E:$E,'AccountSummary (New)'!E$1,Accounts!$G:$G,'AccountSummary (New)'!E$2,Accounts!$F:$F,'AccountSummary (New)'!E$3,Accounts!$B:$B,"Customer",Accounts!$C:$C,"Customer",Accounts!$H:$H,">"&60,Accounts!$H:$H,"<="&90) -> 0 | F43: =COUNTIFS(Accounts!$E:$E,'AccountSummary (New)'!F$1,Accounts!$G:$G,'AccountSummary (New)'!F$2,Accounts!$F:$F,'AccountSummary (New)'!F$3,Accounts!$B:$B,"Customer",Accounts!$C:$C,"Customer",Accounts!$H:$H,">"&60,Accounts!$H:$H,"<="&90) -> 0 | G43: =COUNTIFS(Accounts!$E:$E,'AccountSummary (New)'!G$1,Accounts!$G:$G,'AccountSummary (New)'!G$2,Accounts!$F:$F,'AccountSummary (New)'!G$3,Accounts!$B:$B,"Customer",Accounts!$C:$C,"Customer",Accounts!$H:$H,">"&60,Accounts!$H:$H,"<="&90) -> 0 | H43: =COUNTIFS(Accounts!$E:$E,'AccountSummary (New)'!H$1,Accounts!$G:$G,'AccountSummary (New)'!H$2,Accounts!$F:$F,'AccountSummary (New)'!H$3,Accounts!$B:$B,"Customer",Accounts!$C:$C,"Customer",Accounts!$H:$H,">"&60,Accounts!$H:$H,"<="&90) -> 0 | I43: =SUM(C43:H43) -> 0 | J43: =COUNTIFS(Accounts!$E:$E,'AccountSummary (New)'!J$1,Accounts!$G:$G,'AccountSummary (New)'!J$2,Accounts!$F:$F,'AccountSummary (New)'!J$3,Accounts!$B:$B,"Customer",Accounts!$C:$C,"Customer",Accounts!$H:$H,">"&60,Accounts!$H:$H,"<="&90) -> 0 | K43: =COUNTIFS(Accounts!$E:$E,'AccountSummary (New)'!K$1,Accounts!$G:$G,'AccountSummary (New)'!K$2,Accounts!$F:$F,'AccountSummary (New)'!K$3,Accounts!$B:$B,"Customer",Accounts!$C:$C,"Customer",Accounts!$H:$H,">"&60,Accounts!$H:$H,"<="&90) -> 0 | L43: =COUNTIFS(Accounts!$E:$E,'AccountSummary (New)'!L$1,Accounts!$G:$G,'AccountSummary (New)'!L$2,Accounts!$F:$F,'AccountSummary (New)'!L$3,Accounts!$B:$B,"Customer",Accounts!$C:$C,"Customer",Accounts!$H:$H,">"&60,Accounts!$H:$H,"<="&90) -> 0 | M43: =COUNTIFS(Accounts!$E:$E,'AccountSummary (New)'!M$1,Accounts!$G:$G,'AccountSummary (New)'!M$2,Accounts!$F:$F,'AccountSummary (New)'!M$3,Accounts!$B:$B,"Customer",Accounts!$C:$C,"Customer",Accounts!$H:$H,">"&60,Accounts!$H:$H,"<="&90) -> 0 | N43: =COUNTIFS(Accounts!$E:$E,'AccountSummary (New)'!N$1,Accounts!$G:$G,'AccountSummary (New)'!N$2,Accounts!$F:$F,'AccountSummary (New)'!N$3,Accounts!$B:$B,"Customer",Accounts!$C:$C,"Customer",Accounts!$H:$H,">"&60,Accounts!$H:$H,"<="&90) -> 0 | O43: =COUNTIFS(Accounts!$E:$E,'AccountSummary (New)'!O$1,Accounts!$G:$G,'AccountSummary (New)'!O$2,Accounts!$F:$F,'AccountSummary (New)'!O$3,Accounts!$B:$B,"Customer",Accounts!$C:$C,"Customer",Accounts!$H:$H,">"&60,Accounts!$H:$H,"<="&90) -> 0 | P43: =SUM(J43:O43) -> 0 | Q43: =COUNTIFS(Accounts!$E:$E,'AccountSummary (New)'!Q$1,Accounts!$G:$G,'AccountSummary (New)'!Q$2,Accounts!$F:$F,'AccountSummary (New)'!Q$3,Accounts!$B:$B,"Customer",Accounts!$C:$C,"Customer",Accounts!$H:$H,">"&60,Accounts!$H:$H,"<="&90) -> 0 | R43: =COUNTIFS(Accounts!$E:$E,'AccountSummary (New)'!R$1,Accounts!$G:$G,'AccountSummary (New)'!R$2,Accounts!$F:$F,'AccountSummary (New)'!R$3,Accounts!$B:$B,"Customer",Accounts!$C:$C,"Customer",Accounts!$H:$H,">"&60,Accounts!$H:$H,"<="&90) -> 0 | S43: =COUNTIFS(Accounts!$E:$E,'AccountSummary (New)'!S$1,Accounts!$G:$G,'AccountSummary (New)'!S$2,Accounts!$F:$F,'AccountSummary (New)'!S$3,Accounts!$B:$B,"Customer",Accounts!$C:$C,"Customer",Accounts!$H:$H,">"&60,Accounts!$H:$H,"<="&90) -> 0 | T43: =COUNTIFS(Accounts!$E:$E,'AccountSummary (New)'!T$1,Accounts!$G:$G,'AccountSummary (New)'!T$2,Accounts!$F:$F,'AccountSummary (New)'!T$3,Accounts!$B:$B,"Customer",Accounts!$C:$C,"Customer",Accounts!$H:$H,">"&60,Accounts!$H:$H,"<="&90) -> 0 | U43: =COUNTIFS(Accounts!$E:$E,'AccountSummary (New)'!U$1,Accounts!$G:$G,'AccountSummary (New)'!U$2,Accounts!$F:$F,'AccountSummary (New)'!U$3,Accounts!$B:$B,"Customer",Accounts!$C:$C,"Customer",Accounts!$H:$H,">"&60,Accounts!$H:$H,"<="&90) -> 0 | V43: =COUNTIFS(Accounts!$E:$E,'AccountSummary (New)'!V$1,Accounts!$G:$G,'AccountSummary (New)'!V$2,Accounts!$F:$F,'AccountSummary (New)'!V$3,Accounts!$B:$B,"Customer",Accounts!$C:$C,"Customer",Accounts!$H:$H,">"&60,Accounts!$H:$H,"<="&90) -> 0 | W43: =SUM(Q43:V43) -> 0
A44: Packs per Account | B44: =IF(B43=0,0,SUMIFS(Accounts!$L:$L,Accounts!$W:$W,0,Accounts!$C:$C,"Customer",Accounts!$H:$H,">"&60,Accounts!$H:$H,"<="&90)/B43) -> 0 | C44: =IF(C43=0,0,SUMIFS(Accounts!$L:$L,Accounts!$E:$E,'AccountSummary (New)'!C$1,Accounts!$G:$G,'AccountSummary (New)'!C$2,Accounts!$F:$F,'AccountSummary (New)'!C$3,Accounts!$W:$W,0,Accounts!$C:$C,"Customer",Accounts!$H:$H,">"&60,Accounts!$H:$H,"<="&90)/C43) -> 0 | D44: =IF(D43=0,0,SUMIFS(Accounts!$L:$L,Accounts!$E:$E,'AccountSummary (New)'!D$1,Accounts!$G:$G,'AccountSummary (New)'!D$2,Accounts!$F:$F,'AccountSummary (New)'!D$3,Accounts!$W:$W,0,Accounts!$C:$C,"Customer",Accounts!$H:$H,">"&60,Accounts!$H:$H,"<="&90)/D43) -> 0 | E44: =IF(E43=0,0,SUMIFS(Accounts!$L:$L,Accounts!$E:$E,'AccountSummary (New)'!E$1,Accounts!$G:$G,'AccountSummary (New)'!E$2,Accounts!$F:$F,'AccountSummary (New)'!E$3,Accounts!$W:$W,0,Accounts!$C:$C,"Customer",Accounts!$H:$H,">"&60,Accounts!$H:$H,"<="&90)/E43) -> 0 | F44: =IF(F43=0,0,SUMIFS(Accounts!$L:$L,Accounts!$E:$E,'AccountSummary (New)'!F$1,Accounts!$G:$G,'AccountSummary (New)'!F$2,Accounts!$F:$F,'AccountSummary (New)'!F$3,Accounts!$W:$W,0,Accounts!$C:$C,"Customer",Accounts!$H:$H,">"&60,Accounts!$H:$H,"<="&90)/F43) -> 0 | G44: =IF(G43=0,0,SUMIFS(Accounts!$L:$L,Accounts!$E:$E,'AccountSummary (New)'!G$1,Accounts!$G:$G,'AccountSummary (New)'!G$2,Accounts!$F:$F,'AccountSummary (New)'!G$3,Accounts!$W:$W,0,Accounts!$C:$C,"Customer",Accounts!$H:$H,">"&60,Accounts!$H:$H,"<="&90)/G43) -> 0 | H44: =IF(H43=0,0,SUMIFS(Accounts!$L:$L,Accounts!$E:$E,'AccountSummary (New)'!H$1,Accounts!$G:$G,'AccountSummary (New)'!H$2,Accounts!$F:$F,'AccountSummary (New)'!H$3,Accounts!$W:$W,0,Accounts!$C:$C,"Customer",Accounts!$H:$H,">"&60,Accounts!$H:$H,"<="&90)/H43) -> 0 | I44: =IF(I43=0,0,SUMIFS(Accounts!$L:$L,Accounts!$F:$F,'AccountSummary (New)'!I$3,Accounts!$W:$W,0,Accounts!$C:$C,"Customer",Accounts!$H:$H,">"&60,Accounts!$H:$H,"<="&90)/I43) -> 0 | J44: =IF(J43=0,0,SUMIFS(Accounts!$L:$L,Accounts!$E:$E,'AccountSummary (New)'!J$1,Accounts!$G:$G,'AccountSummary (New)'!J$2,Accounts!$F:$F,'AccountSummary (New)'!J$3,Accounts!$W:$W,0,Accounts!$C:$C,"Customer",Accounts!$H:$H,">"&60,Accounts!$H:$H,"<="&90)/J43) -> 0 | K44: =IF(K43=0,0,SUMIFS(Accounts!$L:$L,Accounts!$E:$E,'AccountSummary (New)'!K$1,Accounts!$G:$G,'AccountSummary (New)'!K$2,Accounts!$F:$F,'AccountSummary (New)'!K$3,Accounts!$W:$W,0,Accounts!$C:$C,"Customer",Accounts!$H:$H,">"&60,Accounts!$H:$H,"<="&90)/K43) -> 0 | L44: =IF(L43=0,0,SUMIFS(Accounts!$L:$L,Accounts!$E:$E,'AccountSummary (New)'!L$1,Accounts!$G:$G,'AccountSummary (New)'!L$2,Accounts!$F:$F,'AccountSummary (New)'!L$3,Accounts!$W:$W,0,Accounts!$C:$C,"Customer",Accounts!$H:$H,">"&60,Accounts!$H:$H,"<="&90)/L43) -> 0 | M44: =IF(M43=0,0,SUMIFS(Accounts!$L:$L,Accounts!$E:$E,'AccountSummary (New)'!M$1,Accounts!$G:$G,'AccountSummary (New)'!M$2,Accounts!$F:$F,'AccountSummary (New)'!M$3,Accounts!$W:$W,0,Accounts!$C:$C,"Customer",Accounts!$H:$H,">"&60,Accounts!$H:$H,"<="&90)/M43) -> 0 | N44: =IF(N43=0,0,SUMIFS(Accounts!$L:$L,Accounts!$E:$E,'AccountSummary (New)'!N$1,Accounts!$G:$G,'AccountSummary (New)'!N$2,Accounts!$F:$F,'AccountSummary (New)'!N$3,Accounts!$W:$W,0,Accounts!$C:$C,"Customer",Accounts!$H:$H,">"&60,Accounts!$H:$H,"<="&90)/N43) -> 0 | O44: =IF(O43=0,0,SUMIFS(Accounts!$L:$L,Accounts!$E:$E,'AccountSummary (New)'!O$1,Accounts!$G:$G,'AccountSummary (New)'!O$2,Accounts!$F:$F,'AccountSummary (New)'!O$3,Accounts!$W:$W,0,Accounts!$C:$C,"Customer",Accounts!$H:$H,">"&60,Accounts!$H:$H,"<="&90)/O43) -> 0 | P44: =IF(P43=0,0,SUMIFS(Accounts!$L:$L,Accounts!$F:$F,'AccountSummary (New)'!P$3,Accounts!$W:$W,0,Accounts!$C:$C,"Customer",Accounts!$H:$H,">"&60,Accounts!$H:$H,"<="&90)/P43) -> 0 | Q44: =IF(Q43=0,0,SUMIFS(Accounts!$L:$L,Accounts!$E:$E,'AccountSummary (New)'!Q$1,Accounts!$G:$G,'AccountSummary (New)'!Q$2,Accounts!$F:$F,'AccountSummary (New)'!Q$3,Accounts!$W:$W,0,Accounts!$C:$C,"Customer",Accounts!$H:$H,">"&60,Accounts!$H:$H,"<="&90)/Q43) -> 0 | R44: =IF(R43=0,0,SUMIFS(Accounts!$L:$L,Accounts!$E:$E,'AccountSummary (New)'!R$1,Accounts!$G:$G,'AccountSummary (New)'!R$2,Accounts!$F:$F,'AccountSummary (New)'!R$3,Accounts!$W:$W,0,Accounts!$C:$C,"Customer",Accounts!$H:$H,">"&60,Accounts!$H:$H,"<="&90)/R43) -> 0 | S44: =IF(S43=0,0,SUMIFS(Accounts!$L:$L,Accounts!$E:$E,'AccountSummary (New)'!S$1,Accounts!$G:$G,'AccountSummary (New)'!S$2,Accounts!$F:$F,'AccountSummary (New)'!S$3,Accounts!$W:$W,0,Accounts!$C:$C,"Customer",Accounts!$H:$H,">"&60,Accounts!$H:$H,"<="&90)/S43) -> 0 | T44: =IF(T43=0,0,SUMIFS(Accounts!$L:$L,Accounts!$E:$E,'AccountSummary (New)'!T$1,Accounts!$G:$G,'AccountSummary (New)'!T$2,Accounts!$F:$F,'AccountSummary (New)'!T$3,Accounts!$W:$W,0,Accounts!$C:$C,"Customer",Accounts!$H:$H,">"&60,Accounts!$H:$H,"<="&90)/T43) -> 0 | U44: =IF(U43=0,0,SUMIFS(Accounts!$L:$L,Accounts!$E:$E,'AccountSummary (New)'!U$1,Accounts!$G:$G,'AccountSummary (New)'!U$2,Accounts!$F:$F,'AccountSummary (New)'!U$3,Accounts!$W:$W,0,Accounts!$C:$C,"Customer",Accounts!$H:$H,">"&60,Accounts!$H:$H,"<="&90)/U43) -> 0 | V44: =IF(V43=0,0,SUMIFS(Accounts!$L:$L,Accounts!$E:$E,'AccountSummary (New)'!V$1,Accounts!$G:$G,'AccountSummary (New)'!V$2,Accounts!$F:$F,'AccountSummary (New)'!V$3,Accounts!$W:$W,0,Accounts!$C:$C,"Customer",Accounts!$H:$H,">"&60,Accounts!$H:$H,"<="&90)/V43) -> 0 | W44: =IF(W43=0,0,SUMIFS(Accounts!$L:$L,Accounts!$F:$F,'AccountSummary (New)'!W$3,Accounts!$W:$W,0,Accounts!$C:$C,"Customer",Accounts!$H:$H,">"&60,Accounts!$H:$H,"<="&90)/W43) -> 0
A45: Users per Account | B45: =IF(B43=0,0,SUMIFS(Accounts!$M:$M,Accounts!$W:$W,0,Accounts!$C:$C,"Customer",Accounts!$H:$H,">"&60,Accounts!$H:$H,"<="&90)/B43) -> 0 | C45: =IF(C43=0,0,SUMIFS(Accounts!$M:$M,Accounts!$E:$E,'AccountSummary (New)'!C$1,Accounts!$G:$G,'AccountSummary (New)'!C$2,Accounts!$F:$F,'AccountSummary (New)'!C$3,Accounts!$W:$W,0,Accounts!$C:$C,"Customer",Accounts!$H:$H,">"&60,Accounts!$H:$H,"<="&90)/C43) -> 0 | D45: =IF(D43=0,0,SUMIFS(Accounts!$M:$M,Accounts!$E:$E,'AccountSummary (New)'!D$1,Accounts!$G:$G,'AccountSummary (New)'!D$2,Accounts!$F:$F,'AccountSummary (New)'!D$3,Accounts!$W:$W,0,Accounts!$C:$C,"Customer",Accounts!$H:$H,">"&60,Accounts!$H:$H,"<="&90)/D43) -> 0 | E45: =IF(E43=0,0,SUMIFS(Accounts!$M:$M,Accounts!$E:$E,'AccountSummary (New)'!E$1,Accounts!$G:$G,'AccountSummary (New)'!E$2,Accounts!$F:$F,'AccountSummary (New)'!E$3,Accounts!$W:$W,0,Accounts!$C:$C,"Customer",Accounts!$H:$H,">"&60,Accounts!$H:$H,"<="&90)/E43) -> 0 | F45: =IF(F43=0,0,SUMIFS(Accounts!$M:$M,Accounts!$E:$E,'AccountSummary (New)'!F$1,Accounts!$G:$G,'AccountSummary (New)'!F$2,Accounts!$F:$F,'AccountSummary (New)'!F$3,Accounts!$W:$W,0,Accounts!$C:$C,"Customer",Accounts!$H:$H,">"&60,Accounts!$H:$H,"<="&90)/F43) -> 0 | G45: =IF(G43=0,0,SUMIFS(Accounts!$M:$M,Accounts!$E:$E,'AccountSummary (New)'!G$1,Accounts!$G:$G,'AccountSummary (New)'!G$2,Accounts!$F:$F,'AccountSummary (New)'!G$3,Accounts!$W:$W,0,Accounts!$C:$C,"Customer",Accounts!$H:$H,">"&60,Accounts!$H:$H,"<="&90)/G43) -> 0 | H45: =IF(H43=0,0,SUMIFS(Accounts!$M:$M,Accounts!$E:$E,'AccountSummary (New)'!H$1,Accounts!$G:$G,'AccountSummary (New)'!H$2,Accounts!$F:$F,'AccountSummary (New)'!H$3,Accounts!$W:$W,0,Accounts!$C:$C,"Customer",Accounts!$H:$H,">"&60,Accounts!$H:$H,"<="&90)/H43) -> 0 | I45: =IF(I43=0,0,SUMIFS(Accounts!$M:$M,Accounts!$F:$F,'AccountSummary (New)'!I$3,Accounts!$W:$W,0,Accounts!$C:$C,"Customer",Accounts!$H:$H,">"&60,Accounts!$H:$H,"<="&90)/I43) -> 0 | J45: =IF(J43=0,0,SUMIFS(Accounts!$M:$M,Accounts!$E:$E,'AccountSummary (New)'!J$1,Accounts!$G:$G,'AccountSummary (New)'!J$2,Accounts!$F:$F,'AccountSummary (New)'!J$3,Accounts!$W:$W,0,Accounts!$C:$C,"Customer",Accounts!$H:$H,">"&60,Accounts!$H:$H,"<="&90)/J43) -> 0 | K45: =IF(K43=0,0,SUMIFS(Accounts!$M:$M,Accounts!$E:$E,'AccountSummary (New)'!K$1,Accounts!$G:$G,'AccountSummary (New)'!K$2,Accounts!$F:$F,'AccountSummary (New)'!K$3,Accounts!$W:$W,0,Accounts!$C:$C,"Customer",Accounts!$H:$H,">"&60,Accounts!$H:$H,"<="&90)/K43) -> 0 | L45: =IF(L43=0,0,SUMIFS(Accounts!$M:$M,Accounts!$E:$E,'AccountSummary (New)'!L$1,Accounts!$G:$G,'AccountSummary (New)'!L$2,Accounts!$F:$F,'AccountSummary (New)'!L$3,Accounts!$W:$W,0,Accounts!$C:$C,"Customer",Accounts!$H:$H,">"&60,Accounts!$H:$H,"<="&90)/L43) -> 0 | M45: =IF(M43=0,0,SUMIFS(Accounts!$M:$M,Accounts!$E:$E,'AccountSummary (New)'!M$1,Accounts!$G:$G,'AccountSummary (New)'!M$2,Accounts!$F:$F,'AccountSummary (New)'!M$3,Accounts!$W:$W,0,Accounts!$C:$C,"Customer",Accounts!$H:$H,">"&60,Accounts!$H:$H,"<="&90)/M43) -> 0 | N45: =IF(N43=0,0,SUMIFS(Accounts!$M:$M,Accounts!$E:$E,'AccountSummary (New)'!N$1,Accounts!$G:$G,'AccountSummary (New)'!N$2,Accounts!$F:$F,'AccountSummary (New)'!N$3,Accounts!$W:$W,0,Accounts!$C:$C,"Customer",Accounts!$H:$H,">"&60,Accounts!$H:$H,"<="&90)/N43) -> 0 | O45: =IF(O43=0,0,SUMIFS(Accounts!$M:$M,Accounts!$E:$E,'AccountSummary (New)'!O$1,Accounts!$G:$G,'AccountSummary (New)'!O$2,Accounts!$F:$F,'AccountSummary (New)'!O$3,Accounts!$W:$W,0,Accounts!$C:$C,"Customer",Accounts!$H:$H,">"&60,Accounts!$H:$H,"<="&90)/O43) -> 0 | P45: =IF(P43=0,0,SUMIFS(Accounts!$M:$M,Accounts!$F:$F,'AccountSummary (New)'!P$3,Accounts!$W:$W,0,Accounts!$C:$C,"Customer",Accounts!$H:$H,">"&60,Accounts!$H:$H,"<="&90)/P43) -> 0 | Q45: =IF(Q43=0,0,SUMIFS(Accounts!$M:$M,Accounts!$E:$E,'AccountSummary (New)'!Q$1,Accounts!$G:$G,'AccountSummary (New)'!Q$2,Accounts!$F:$F,'AccountSummary (New)'!Q$3,Accounts!$W:$W,0,Accounts!$C:$C,"Customer",Accounts!$H:$H,">"&60,Accounts!$H:$H,"<="&90)/Q43) -> 0 | R45: =IF(R43=0,0,SUMIFS(Accounts!$M:$M,Accounts!$E:$E,'AccountSummary (New)'!R$1,Accounts!$G:$G,'AccountSummary (New)'!R$2,Accounts!$F:$F,'AccountSummary (New)'!R$3,Accounts!$W:$W,0,Accounts!$C:$C,"Customer",Accounts!$H:$H,">"&60,Accounts!$H:$H,"<="&90)/R43) -> 0 | S45: =IF(S43=0,0,SUMIFS(Accounts!$M:$M,Accounts!$E:$E,'AccountSummary (New)'!S$1,Accounts!$G:$G,'AccountSummary (New)'!S$2,Accounts!$F:$F,'AccountSummary (New)'!S$3,Accounts!$W:$W,0,Accounts!$C:$C,"Customer",Accounts!$H:$H,">"&60,Accounts!$H:$H,"<="&90)/S43) -> 0 | T45: =IF(T43=0,0,SUMIFS(Accounts!$M:$M,Accounts!$E:$E,'AccountSummary (New)'!T$1,Accounts!$G:$G,'AccountSummary (New)'!T$2,Accounts!$F:$F,'AccountSummary (New)'!T$3,Accounts!$W:$W,0,Accounts!$C:$C,"Customer",Accounts!$H:$H,">"&60,Accounts!$H:$H,"<="&90)/T43) -> 0 | U45: =IF(U43=0,0,SUMIFS(Accounts!$M:$M,Accounts!$E:$E,'AccountSummary (New)'!U$1,Accounts!$G:$G,'AccountSummary (New)'!U$2,Accounts!$F:$F,'AccountSummary (New)'!U$3,Accounts!$W:$W,0,Accounts!$C:$C,"Customer",Accounts!$H:$H,">"&60,Accounts!$H:$H,"<="&90)/U43) -> 0 | V45: =IF(V43=0,0,SUMIFS(Accounts!$M:$M,Accounts!$E:$E,'AccountSummary (New)'!V$1,Accounts!$G:$G,'AccountSummary (New)'!V$2,Accounts!$F:$F,'AccountSummary (New)'!V$3,Accounts!$W:$W,0,Accounts!$C:$C,"Customer",Accounts!$H:$H,">"&60,Accounts!$H:$H,"<="&90)/V43) -> 0 | W45: =IF(W43=0,0,SUMIFS(Accounts!$M:$M,Accounts!$F:$F,'AccountSummary (New)'!W$3,Accounts!$W:$W,0,Accounts!$C:$C,"Customer",Accounts!$H:$H,">"&60,Accounts!$H:$H,"<="&90)/W43) -> 0
A46: ARPC | B46: =IF(B43=0,0,B47/B43) -> 0 | C46: =IF(C43=0,0,C47/C43) -> 0 | D46: =IF(D43=0,0,D47/D43) -> 0 | E46: =IF(E43=0,0,E47/E43) -> 0 | F46: =IF(F43=0,0,F47/F43) -> 0 | G46: =IF(G43=0,0,G47/G43) -> 0 | H46: =IF(H43=0,0,H47/H43) -> 0 | I46: =IF(I43=0,0,I47/I43) -> 0 | ... W46: =IF(W43=0,0,W47/W43) -> 0
A47: SaaS | B47: =I47+P47+W47 -> 0 | C47: =SUMIFS(Accounts!$I:$I,Accounts!$E:$E,'AccountSummary (New)'!C$1,Accounts!$G:$G,'AccountSummary (New)'!C$2,Accounts!$F:$F,'AccountSummary (New)'!C$3,Accounts!$W:$W,0,Accounts!$C:$C,"Customer",Accounts!$H:$H,">"&60,Accounts!$H:$H,"<="&90) -> 0 | D47: =SUMIFS(Accounts!$I:$I,Accounts!$E:$E,'AccountSummary (New)'!D$1,Accounts!$G:$G,'AccountSummary (New)'!D$2,Accounts!$F:$F,'AccountSummary (New)'!D$3,Accounts!$W:$W,0,Accounts!$C:$C,"Customer",Accounts!$H:$H,">"&60,Accounts!$H:$H,"<="&90) -> 0 | E47: =SUMIFS(Accounts!$I:$I,Accounts!$E:$E,'AccountSummary (New)'!E$1,Accounts!$G:$G,'AccountSummary (New)'!E$2,Accounts!$F:$F,'AccountSummary (New)'!E$3,Accounts!$W:$W,0,Accounts!$C:$C,"Customer",Accounts!$H:$H,">"&60,Accounts!$H:$H,"<="&90) -> 0 | F47: =SUMIFS(Accounts!$I:$I,Accounts!$E:$E,'AccountSummary (New)'!F$1,Accounts!$G:$G,'AccountSummary (New)'!F$2,Accounts!$F:$F,'AccountSummary (New)'!F$3,Accounts!$W:$W,0,Accounts!$C:$C,"Customer",Accounts!$H:$H,">"&60,Accounts!$H:$H,"<="&90) -> 0 | G47: =SUMIFS(Accounts!$I:$I,Accounts!$E:$E,'AccountSummary (New)'!G$1,Accounts!$G:$G,'AccountSummary (New)'!G$2,Accounts!$F:$F,'AccountSummary (New)'!G$3,Accounts!$W:$W,0,Accounts!$C:$C,"Customer",Accounts!$H:$H,">"&60,Accounts!$H:$H,"<="&90) -> 0 | H47: =SUMIFS(Accounts!$I:$I,Accounts!$E:$E,'AccountSummary (New)'!H$1,Accounts!$G:$G,'AccountSummary (New)'!H$2,Accounts!$F:$F,'AccountSummary (New)'!H$3,Accounts!$W:$W,0,Accounts!$C:$C,"Customer",Accounts!$H:$H,">"&60,Accounts!$H:$H,"<="&90) -> 0 | I47: =SUM(C47:H47) -> 0 | J47: =SUMIFS(Accounts!$I:$I,Accounts!$E:$E,'AccountSummary (New)'!J$1,Accounts!$G:$G,'AccountSummary (New)'!J$2,Accounts!$F:$F,'AccountSummary (New)'!J$3,Accounts!$W:$W,0,Accounts!$C:$C,"Customer",Accounts!$H:$H,">"&60,Accounts!$H:$H,"<="&90) -> 0 | K47: =SUMIFS(Accounts!$I:$I,Accounts!$E:$E,'AccountSummary (New)'!K$1,Accounts!$G:$G,'AccountSummary (New)'!K$2,Accounts!$F:$F,'AccountSummary (New)'!K$3,Accounts!$W:$W,0,Accounts!$C:$C,"Customer",Accounts!$H:$H,">"&60,Accounts!$H:$H,"<="&90) -> 0 | L47: =SUMIFS(Accounts!$I:$I,Accounts!$E:$E,'AccountSummary (New)'!L$1,Accounts!$G:$G,'AccountSummary (New)'!L$2,Accounts!$F:$F,'AccountSummary (New)'!L$3,Accounts!$W:$W,0,Accounts!$C:$C,"Customer",Accounts!$H:$H,">"&60,Accounts!$H:$H,"<="&90) -> 0 | M47: =SUMIFS(Accounts!$I:$I,Accounts!$E:$E,'AccountSummary (New)'!M$1,Accounts!$G:$G,'AccountSummary (New)'!M$2,Accounts!$F:$F,'AccountSummary (New)'!M$3,Accounts!$W:$W,0,Accounts!$C:$C,"Customer",Accounts!$H:$H,">"&60,Accounts!$H:$H,"<="&90) -> 0 | N47: =SUMIFS(Accounts!$I:$I,Accounts!$E:$E,'AccountSummary (New)'!N$1,Accounts!$G:$G,'AccountSummary (New)'!N$2,Accounts!$F:$F,'AccountSummary (New)'!N$3,Accounts!$W:$W,0,Accounts!$C:$C,"Customer",Accounts!$H:$H,">"&60,Accounts!$H:$H,"<="&90) -> 0 | O47: =SUMIFS(Accounts!$I:$I,Accounts!$E:$E,'AccountSummary (New)'!O$1,Accounts!$G:$G,'AccountSummary (New)'!O$2,Accounts!$F:$F,'AccountSummary (New)'!O$3,Accounts!$W:$W,0,Accounts!$C:$C,"Customer",Accounts!$H:$H,">"&60,Accounts!$H:$H,"<="&90) -> 0 | P47: =SUM(J47:O47) -> 0 | Q47: =SUMIFS(Accounts!$I:$I,Accounts!$E:$E,'AccountSummary (New)'!Q$1,Accounts!$G:$G,'AccountSummary (New)'!Q$2,Accounts!$F:$F,'AccountSummary (New)'!Q$3,Accounts!$W:$W,0,Accounts!$C:$C,"Customer",Accounts!$H:$H,">"&60,Accounts!$H:$H,"<="&90) -> 0 | R47: =SUMIFS(Accounts!$I:$I,Accounts!$E:$E,'AccountSummary (New)'!R$1,Accounts!$G:$G,'AccountSummary (New)'!R$2,Accounts!$F:$F,'AccountSummary (New)'!R$3,Accounts!$W:$W,0,Accounts!$C:$C,"Customer",Accounts!$H:$H,">"&60,Accounts!$H:$H,"<="&90) -> 0 | S47: =SUMIFS(Accounts!$I:$I,Accounts!$E:$E,'AccountSummary (New)'!S$1,Accounts!$G:$G,'AccountSummary (New)'!S$2,Accounts!$F:$F,'AccountSummary (New)'!S$3,Accounts!$W:$W,0,Accounts!$C:$C,"Customer",Accounts!$H:$H,">"&60,Accounts!$H:$H,"<="&90) -> 0 | T47: =SUMIFS(Accounts!$I:$I,Accounts!$E:$E,'AccountSummary (New)'!T$1,Accounts!$G:$G,'AccountSummary (New)'!T$2,Accounts!$F:$F,'AccountSummary (New)'!T$3,Accounts!$W:$W,0,Accounts!$C:$C,"Customer",Accounts!$H:$H,">"&60,Accounts!$H:$H,"<="&90) -> 0 | U47: =SUMIFS(Accounts!$I:$I,Accounts!$E:$E,'AccountSummary (New)'!U$1,Accounts!$G:$G,'AccountSummary (New)'!U$2,Accounts!$F:$F,'AccountSummary (New)'!U$3,Accounts!$W:$W,0,Accounts!$C:$C,"Customer",Accounts!$H:$H,">"&60,Accounts!$H:$H,"<="&90) -> 0 | V47: =SUMIFS(Accounts!$I:$I,Accounts!$E:$E,'AccountSummary (New)'!V$1,Accounts!$G:$G,'AccountSummary (New)'!V$2,Accounts!$F:$F,'AccountSummary (New)'!V$3,Accounts!$W:$W,0,Accounts!$C:$C,"Customer",Accounts!$H:$H,">"&60,Accounts!$H:$H,"<="&90) -> 0 | W47: =SUM(Q47:V47) -> 0
A48: 91-180 day cohort as of BOM
A49: Total % of Paying Customers | B49: =IF(B$19=0,0,(B51+B52)/B$19) -> 0 | C49: =IF(C$19=0,0,(C51+C52)/C$19) -> 0 | D49: =IF(D$19=0,0,(D51+D52)/D$19) -> 0 | E49: =IF(E$19=0,0,(E51+E52)/E$19) -> 0 | F49: =IF(F$19=0,0,(F51+F52)/F$19) -> 0 | G49: =IF(G$19=0,0,(G51+G52)/G$19) -> 0 | H49: =IF(H$19=0,0,(H51+H52)/H$19) -> 0 | I49: =IF(I$19=0,0,(I51+I52)/I$19) -> 0 | ... W49: =IF(W$19=0,0,(W51+W52)/W$19) -> 0
A50: Loss % | B50: =IF((B51+B52)=0,0,B51/(B51+B52)) -> 0 | C50: =IF((C51+C52)=0,0,C51/(C51+C52)) -> 0 | D50: =IF((D51+D52)=0,0,D51/(D51+D52)) -> 0 | E50: =IF((E51+E52)=0,0,E51/(E51+E52)) -> 0 | F50: =IF((F51+F52)=0,0,F51/(F51+F52)) -> 0 | G50: =IF((G51+G52)=0,0,G51/(G51+G52)) -> 0 | H50: =IF((H51+H52)=0,0,H51/(H51+H52)) -> 0 | I50: =IF((I51+I52)=0,0,I51/(I51+I52)) -> 0 | ... W50: =IF((W51+W52)=0,0,W51/(W51+W52)) -> 0
A51: Lost Count | B51: =I51+P51+W51 -> 0 | C51: =COUNTIFS(Accounts!$E:$E,'AccountSummary (New)'!C$1,Accounts!$G:$G,'AccountSummary (New)'!C$2,Accounts!$F:$F,'AccountSummary (New)'!C$3,Accounts!$B:$B,"Customer",Accounts!$C:$C,"Lost",Accounts!$H:$H,">"&90,Accounts!$H:$H,"<="&180) -> 0 | D51: =COUNTIFS(Accounts!$E:$E,'AccountSummary (New)'!D$1,Accounts!$G:$G,'AccountSummary (New)'!D$2,Accounts!$F:$F,'AccountSummary (New)'!D$3,Accounts!$B:$B,"Customer",Accounts!$C:$C,"Lost",Accounts!$H:$H,">"&90,Accounts!$H:$H,"<="&180) -> 0 | E51: =COUNTIFS(Accounts!$E:$E,'AccountSummary (New)'!E$1,Accounts!$G:$G,'AccountSummary (New)'!E$2,Accounts!$F:$F,'AccountSummary (New)'!E$3,Accounts!$B:$B,"Customer",Accounts!$C:$C,"Lost",Accounts!$H:$H,">"&90,Accounts!$H:$H,"<="&180) -> 0 | F51: =COUNTIFS(Accounts!$E:$E,'AccountSummary (New)'!F$1,Accounts!$G:$G,'AccountSummary (New)'!F$2,Accounts!$F:$F,'AccountSummary (New)'!F$3,Accounts!$B:$B,"Customer",Accounts!$C:$C,"Lost",Accounts!$H:$H,">"&90,Accounts!$H:$H,"<="&180) -> 0 | G51: =COUNTIFS(Accounts!$E:$E,'AccountSummary (New)'!G$1,Accounts!$G:$G,'AccountSummary (New)'!G$2,Accounts!$F:$F,'AccountSummary (New)'!G$3,Accounts!$B:$B,"Customer",Accounts!$C:$C,"Lost",Accounts!$H:$H,">"&90,Accounts!$H:$H,"<="&180) -> 0 | H51: =COUNTIFS(Accounts!$E:$E,'AccountSummary (New)'!H$1,Accounts!$G:$G,'AccountSummary (New)'!H$2,Accounts!$F:$F,'AccountSummary (New)'!H$3,Accounts!$B:$B,"Customer",Accounts!$C:$C,"Lost",Accounts!$H:$H,">"&90,Accounts!$H:$H,"<="&180) -> 0 | I51: =SUM(C51:H51) -> 0 | J51: =COUNTIFS(Accounts!$E:$E,'AccountSummary (New)'!J$1,Accounts!$G:$G,'AccountSummary (New)'!J$2,Accounts!$F:$F,'AccountSummary (New)'!J$3,Accounts!$B:$B,"Customer",Accounts!$C:$C,"Lost",Accounts!$H:$H,">"&90,Accounts!$H:$H,"<="&180) -> 0 | K51: =COUNTIFS(Accounts!$E:$E,'AccountSummary (New)'!K$1,Accounts!$G:$G,'AccountSummary (New)'!K$2,Accounts!$F:$F,'AccountSummary (New)'!K$3,Accounts!$B:$B,"Customer",Accounts!$C:$C,"Lost",Accounts!$H:$H,">"&90,Accounts!$H:$H,"<="&180) -> 0 | L51: =COUNTIFS(Accounts!$E:$E,'AccountSummary (New)'!L$1,Accounts!$G:$G,'AccountSummary (New)'!L$2,Accounts!$F:$F,'AccountSummary (New)'!L$3,Accounts!$B:$B,"Customer",Accounts!$C:$C,"Lost",Accounts!$H:$H,">"&90,Accounts!$H:$H,"<="&180) -> 0 | M51: =COUNTIFS(Accounts!$E:$E,'AccountSummary (New)'!M$1,Accounts!$G:$G,'AccountSummary (New)'!M$2,Accounts!$F:$F,'AccountSummary (New)'!M$3,Accounts!$B:$B,"Customer",Accounts!$C:$C,"Lost",Accounts!$H:$H,">"&90,Accounts!$H:$H,"<="&180) -> 0 | N51: =COUNTIFS(Accounts!$E:$E,'AccountSummary (New)'!N$1,Accounts!$G:$G,'AccountSummary (New)'!N$2,Accounts!$F:$F,'AccountSummary (New)'!N$3,Accounts!$B:$B,"Customer",Accounts!$C:$C,"Lost",Accounts!$H:$H,">"&90,Accounts!$H:$H,"<="&180) -> 0 | O51: =COUNTIFS(Accounts!$E:$E,'AccountSummary (New)'!O$1,Accounts!$G:$G,'AccountSummary (New)'!O$2,Accounts!$F:$F,'AccountSummary (New)'!O$3,Accounts!$B:$B,"Customer",Accounts!$C:$C,"Lost",Accounts!$H:$H,">"&90,Accounts!$H:$H,"<="&180) -> 0 | P51: =SUM(J51:O51) -> 0 | Q51: =COUNTIFS(Accounts!$E:$E,'AccountSummary (New)'!Q$1,Accounts!$G:$G,'AccountSummary (New)'!Q$2,Accounts!$F:$F,'AccountSummary (New)'!Q$3,Accounts!$B:$B,"Customer",Accounts!$C:$C,"Lost",Accounts!$H:$H,">"&90,Accounts!$H:$H,"<="&180) -> 0 | R51: =COUNTIFS(Accounts!$E:$E,'AccountSummary (New)'!R$1,Accounts!$G:$G,'AccountSummary (New)'!R$2,Accounts!$F:$F,'AccountSummary (New)'!R$3,Accounts!$B:$B,"Customer",Accounts!$C:$C,"Lost",Accounts!$H:$H,">"&90,Accounts!$H:$H,"<="&180) -> 0 | S51: =COUNTIFS(Accounts!$E:$E,'AccountSummary (New)'!S$1,Accounts!$G:$G,'AccountSummary (New)'!S$2,Accounts!$F:$F,'AccountSummary (New)'!S$3,Accounts!$B:$B,"Customer",Accounts!$C:$C,"Lost",Accounts!$H:$H,">"&90,Accounts!$H:$H,"<="&180) -> 0 | T51: =COUNTIFS(Accounts!$E:$E,'AccountSummary (New)'!T$1,Accounts!$G:$G,'AccountSummary (New)'!T$2,Accounts!$F:$F,'AccountSummary (New)'!T$3,Accounts!$B:$B,"Customer",Accounts!$C:$C,"Lost",Accounts!$H:$H,">"&90,Accounts!$H:$H,"<="&180) -> 0 | U51: =COUNTIFS(Accounts!$E:$E,'AccountSummary (New)'!U$1,Accounts!$G:$G,'AccountSummary (New)'!U$2,Accounts!$F:$F,'AccountSummary (New)'!U$3,Accounts!$B:$B,"Customer",Accounts!$C:$C,"Lost",Accounts!$H:$H,">"&90,Accounts!$H:$H,"<="&180) -> 0 | V51: =COUNTIFS(Accounts!$E:$E,'AccountSummary (New)'!V$1,Accounts!$G:$G,'AccountSummary (New)'!V$2,Accounts!$F:$F,'AccountSummary (New)'!V$3,Accounts!$B:$B,"Customer",Accounts!$C:$C,"Lost",Accounts!$H:$H,">"&90,Accounts!$H:$H,"<="&180) -> 0 | W51: =SUM(Q51:V51) -> 0
A52: Retained Count | B52: =I52+P52+W52 -> 0 | C52: =COUNTIFS(Accounts!$E:$E,'AccountSummary (New)'!C$1,Accounts!$G:$G,'AccountSummary (New)'!C$2,Accounts!$F:$F,'AccountSummary (New)'!C$3,Accounts!$B:$B,"Customer",Accounts!$C:$C,"Customer",Accounts!$H:$H,">"&90,Accounts!$H:$H,"<="&180) -> 0 | D52: =COUNTIFS(Accounts!$E:$E,'AccountSummary (New)'!D$1,Accounts!$G:$G,'AccountSummary (New)'!D$2,Accounts!$F:$F,'AccountSummary (New)'!D$3,Accounts!$B:$B,"Customer",Accounts!$C:$C,"Customer",Accounts!$H:$H,">"&90,Accounts!$H:$H,"<="&180) -> 0 | E52: =COUNTIFS(Accounts!$E:$E,'AccountSummary (New)'!E$1,Accounts!$G:$G,'AccountSummary (New)'!E$2,Accounts!$F:$F,'AccountSummary (New)'!E$3,Accounts!$B:$B,"Customer",Accounts!$C:$C,"Customer",Accounts!$H:$H,">"&90,Accounts!$H:$H,"<="&180) -> 0 | F52: =COUNTIFS(Accounts!$E:$E,'AccountSummary (New)'!F$1,Accounts!$G:$G,'AccountSummary (New)'!F$2,Accounts!$F:$F,'AccountSummary (New)'!F$3,Accounts!$B:$B,"Customer",Accounts!$C:$C,"Customer",Accounts!$H:$H,">"&90,Accounts!$H:$H,"<="&180) -> 0 | G52: =COUNTIFS(Accounts!$E:$E,'AccountSummary (New)'!G$1,Accounts!$G:$G,'AccountSummary (New)'!G$2,Accounts!$F:$F,'AccountSummary (New)'!G$3,Accounts!$B:$B,"Customer",Accounts!$C:$C,"Customer",Accounts!$H:$H,">"&90,Accounts!$H:$H,"<="&180) -> 0 | H52: =COUNTIFS(Accounts!$E:$E,'AccountSummary (New)'!H$1,Accounts!$G:$G,'AccountSummary (New)'!H$2,Accounts!$F:$F,'AccountSummary (New)'!H$3,Accounts!$B:$B,"Customer",Accounts!$C:$C,"Customer",Accounts!$H:$H,">"&90,Accounts!$H:$H,"<="&180) -> 0 | I52: =SUM(C52:H52) -> 0 | J52: =COUNTIFS(Accounts!$E:$E,'AccountSummary (New)'!J$1,Accounts!$G:$G,'AccountSummary (New)'!J$2,Accounts!$F:$F,'AccountSummary (New)'!J$3,Accounts!$B:$B,"Customer",Accounts!$C:$C,"Customer",Accounts!$H:$H,">"&90,Accounts!$H:$H,"<="&180) -> 0 | K52: =COUNTIFS(Accounts!$E:$E,'AccountSummary (New)'!K$1,Accounts!$G:$G,'AccountSummary (New)'!K$2,Accounts!$F:$F,'AccountSummary (New)'!K$3,Accounts!$B:$B,"Customer",Accounts!$C:$C,"Customer",Accounts!$H:$H,">"&90,Accounts!$H:$H,"<="&180) -> 0 | L52: =COUNTIFS(Accounts!$E:$E,'AccountSummary (New)'!L$1,Accounts!$G:$G,'AccountSummary (New)'!L$2,Accounts!$F:$F,'AccountSummary (New)'!L$3,Accounts!$B:$B,"Customer",Accounts!$C:$C,"Customer",Accounts!$H:$H,">"&90,Accounts!$H:$H,"<="&180) -> 0 | M52: =COUNTIFS(Accounts!$E:$E,'AccountSummary (New)'!M$1,Accounts!$G:$G,'AccountSummary (New)'!M$2,Accounts!$F:$F,'AccountSummary (New)'!M$3,Accounts!$B:$B,"Customer",Accounts!$C:$C,"Customer",Accounts!$H:$H,">"&90,Accounts!$H:$H,"<="&180) -> 0 | N52: =COUNTIFS(Accounts!$E:$E,'AccountSummary (New)'!N$1,Accounts!$G:$G,'AccountSummary (New)'!N$2,Accounts!$F:$F,'AccountSummary (New)'!N$3,Accounts!$B:$B,"Customer",Accounts!$C:$C,"Customer",Accounts!$H:$H,">"&90,Accounts!$H:$H,"<="&180) -> 0 | O52: =COUNTIFS(Accounts!$E:$E,'AccountSummary (New)'!O$1,Accounts!$G:$G,'AccountSummary (New)'!O$2,Accounts!$F:$F,'AccountSummary (New)'!O$3,Accounts!$B:$B,"Customer",Accounts!$C:$C,"Customer",Accounts!$H:$H,">"&90,Accounts!$H:$H,"<="&180) -> 0 | P52: =SUM(J52:O52) -> 0 | Q52: =COUNTIFS(Accounts!$E:$E,'AccountSummary (New)'!Q$1,Accounts!$G:$G,'AccountSummary (New)'!Q$2,Accounts!$F:$F,'AccountSummary (New)'!Q$3,Accounts!$B:$B,"Customer",Accounts!$C:$C,"Customer",Accounts!$H:$H,">"&90,Accounts!$H:$H,"<="&180) -> 0 | R52: =COUNTIFS(Accounts!$E:$E,'AccountSummary (New)'!R$1,Accounts!$G:$G,'AccountSummary (New)'!R$2,Accounts!$F:$F,'AccountSummary (New)'!R$3,Accounts!$B:$B,"Customer",Accounts!$C:$C,"Customer",Accounts!$H:$H,">"&90,Accounts!$H:$H,"<="&180) -> 0 | S52: =COUNTIFS(Accounts!$E:$E,'AccountSummary (New)'!S$1,Accounts!$G:$G,'AccountSummary (New)'!S$2,Accounts!$F:$F,'AccountSummary (New)'!S$3,Accounts!$B:$B,"Customer",Accounts!$C:$C,"Customer",Accounts!$H:$H,">"&90,Accounts!$H:$H,"<="&180) -> 0 | T52: =COUNTIFS(Accounts!$E:$E,'AccountSummary (New)'!T$1,Accounts!$G:$G,'AccountSummary (New)'!T$2,Accounts!$F:$F,'AccountSummary (New)'!T$3,Accounts!$B:$B,"Customer",Accounts!$C:$C,"Customer",Accounts!$H:$H,">"&90,Accounts!$H:$H,"<="&180) -> 0 | U52: =COUNTIFS(Accounts!$E:$E,'AccountSummary (New)'!U$1,Accounts!$G:$G,'AccountSummary (New)'!U$2,Accounts!$F:$F,'AccountSummary (New)'!U$3,Accounts!$B:$B,"Customer",Accounts!$C:$C,"Customer",Accounts!$H:$H,">"&90,Accounts!$H:$H,"<="&180) -> 0 | V52: =COUNTIFS(Accounts!$E:$E,'AccountSummary (New)'!V$1,Accounts!$G:$G,'AccountSummary (New)'!V$2,Accounts!$F:$F,'AccountSummary (New)'!V$3,Accounts!$B:$B,"Customer",Accounts!$C:$C,"Customer",Accounts!$H:$H,">"&90,Accounts!$H:$H,"<="&180) -> 0 | W52: =SUM(Q52:V52) -> 0
A53: Packs per Account | B53: =IF(B52=0,0,SUMIFS(Accounts!$L:$L,Accounts!$W:$W,0,Accounts!$C:$C,"Customer",Accounts!$H:$H,">"&60,Accounts!$H:$H,"<="&90)/B52) -> 0 | C53: =IF(C52=0,0,SUMIFS(Accounts!$L:$L,Accounts!$E:$E,'AccountSummary (New)'!C$1,Accounts!$G:$G,'AccountSummary (New)'!C$2,Accounts!$F:$F,'AccountSummary (New)'!C$3,Accounts!$W:$W,0,Accounts!$C:$C,"Customer",Accounts!$H:$H,">"&90,Accounts!$H:$H,"<="&180)/C52) -> 0 | D53: =IF(D52=0,0,SUMIFS(Accounts!$L:$L,Accounts!$E:$E,'AccountSummary (New)'!D$1,Accounts!$G:$G,'AccountSummary (New)'!D$2,Accounts!$F:$F,'AccountSummary (New)'!D$3,Accounts!$W:$W,0,Accounts!$C:$C,"Customer",Accounts!$H:$H,">"&90,Accounts!$H:$H,"<="&180)/D52) -> 0 | E53: =IF(E52=0,0,SUMIFS(Accounts!$L:$L,Accounts!$E:$E,'AccountSummary (New)'!E$1,Accounts!$G:$G,'AccountSummary (New)'!E$2,Accounts!$F:$F,'AccountSummary (New)'!E$3,Accounts!$W:$W,0,Accounts!$C:$C,"Customer",Accounts!$H:$H,">"&90,Accounts!$H:$H,"<="&180)/E52) -> 0 | F53: =IF(F52=0,0,SUMIFS(Accounts!$L:$L,Accounts!$E:$E,'AccountSummary (New)'!F$1,Accounts!$G:$G,'AccountSummary (New)'!F$2,Accounts!$F:$F,'AccountSummary (New)'!F$3,Accounts!$W:$W,0,Accounts!$C:$C,"Customer",Accounts!$H:$H,">"&90,Accounts!$H:$H,"<="&180)/F52) -> 0 | G53: =IF(G52=0,0,SUMIFS(Accounts!$L:$L,Accounts!$E:$E,'AccountSummary (New)'!G$1,Accounts!$G:$G,'AccountSummary (New)'!G$2,Accounts!$F:$F,'AccountSummary (New)'!G$3,Accounts!$W:$W,0,Accounts!$C:$C,"Customer",Accounts!$H:$H,">"&90,Accounts!$H:$H,"<="&180)/G52) -> 0 | H53: =IF(H52=0,0,SUMIFS(Accounts!$L:$L,Accounts!$E:$E,'AccountSummary (New)'!H$1,Accounts!$G:$G,'AccountSummary (New)'!H$2,Accounts!$F:$F,'AccountSummary (New)'!H$3,Accounts!$W:$W,0,Accounts!$C:$C,"Customer",Accounts!$H:$H,">"&90,Accounts!$H:$H,"<="&180)/H52) -> 0 | I53: =IF(I52=0,0,SUMIFS(Accounts!$L:$L,Accounts!$F:$F,'AccountSummary (New)'!I$3,Accounts!$W:$W,0,Accounts!$C:$C,"Customer",Accounts!$H:$H,">"&90,Accounts!$H:$H,"<="&180)/I52) -> 0 | J53: =IF(J52=0,0,SUMIFS(Accounts!$L:$L,Accounts!$E:$E,'AccountSummary (New)'!J$1,Accounts!$G:$G,'AccountSummary (New)'!J$2,Accounts!$F:$F,'AccountSummary (New)'!J$3,Accounts!$W:$W,0,Accounts!$C:$C,"Customer",Accounts!$H:$H,">"&90,Accounts!$H:$H,"<="&180)/J52) -> 0 | K53: =IF(K52=0,0,SUMIFS(Accounts!$L:$L,Accounts!$E:$E,'AccountSummary (New)'!K$1,Accounts!$G:$G,'AccountSummary (New)'!K$2,Accounts!$F:$F,'AccountSummary (New)'!K$3,Accounts!$W:$W,0,Accounts!$C:$C,"Customer",Accounts!$H:$H,">"&90,Accounts!$H:$H,"<="&180)/K52) -> 0 | L53: =IF(L52=0,0,SUMIFS(Accounts!$L:$L,Accounts!$E:$E,'AccountSummary (New)'!L$1,Accounts!$G:$G,'AccountSummary (New)'!L$2,Accounts!$F:$F,'AccountSummary (New)'!L$3,Accounts!$W:$W,0,Accounts!$C:$C,"Customer",Accounts!$H:$H,">"&90,Accounts!$H:$H,"<="&180)/L52) -> 0 | M53: =IF(M52=0,0,SUMIFS(Accounts!$L:$L,Accounts!$E:$E,'AccountSummary (New)'!M$1,Accounts!$G:$G,'AccountSummary (New)'!M$2,Accounts!$F:$F,'AccountSummary (New)'!M$3,Accounts!$W:$W,0,Accounts!$C:$C,"Customer",Accounts!$H:$H,">"&90,Accounts!$H:$H,"<="&180)/M52) -> 0 | N53: =IF(N52=0,0,SUMIFS(Accounts!$L:$L,Accounts!$E:$E,'AccountSummary (New)'!N$1,Accounts!$G:$G,'AccountSummary (New)'!N$2,Accounts!$F:$F,'AccountSummary (New)'!N$3,Accounts!$W:$W,0,Accounts!$C:$C,"Customer",Accounts!$H:$H,">"&90,Accounts!$H:$H,"<="&180)/N52) -> 0 | O53: =IF(O52=0,0,SUMIFS(Accounts!$L:$L,Accounts!$E:$E,'AccountSummary (New)'!O$1,Accounts!$G:$G,'AccountSummary (New)'!O$2,Accounts!$F:$F,'AccountSummary (New)'!O$3,Accounts!$W:$W,0,Accounts!$C:$C,"Customer",Accounts!$H:$H,">"&90,Accounts!$H:$H,"<="&180)/O52) -> 0 | P53: =IF(P52=0,0,SUMIFS(Accounts!$L:$L,Accounts!$F:$F,'AccountSummary (New)'!P$3,Accounts!$W:$W,0,Accounts!$C:$C,"Customer",Accounts!$H:$H,">"&90,Accounts!$H:$H,"<="&180)/P52) -> 0 | Q53: =IF(Q52=0,0,SUMIFS(Accounts!$L:$L,Accounts!$E:$E,'AccountSummary (New)'!Q$1,Accounts!$G:$G,'AccountSummary (New)'!Q$2,Accounts!$F:$F,'AccountSummary (New)'!Q$3,Accounts!$W:$W,0,Accounts!$C:$C,"Customer",Accounts!$H:$H,">"&90,Accounts!$H:$H,"<="&180)/Q52) -> 0 | R53: =IF(R52=0,0,SUMIFS(Accounts!$L:$L,Accounts!$E:$E,'AccountSummary (New)'!R$1,Accounts!$G:$G,'AccountSummary (New)'!R$2,Accounts!$F:$F,'AccountSummary (New)'!R$3,Accounts!$W:$W,0,Accounts!$C:$C,"Customer",Accounts!$H:$H,">"&90,Accounts!$H:$H,"<="&180)/R52) -> 0 | S53: =IF(S52=0,0,SUMIFS(Accounts!$L:$L,Accounts!$E:$E,'AccountSummary (New)'!S$1,Accounts!$G:$G,'AccountSummary (New)'!S$2,Accounts!$F:$F,'AccountSummary (New)'!S$3,Accounts!$W:$W,0,Accounts!$C:$C,"Customer",Accounts!$H:$H,">"&90,Accounts!$H:$H,"<="&180)/S52) -> 0 | T53: =IF(T52=0,0,SUMIFS(Accounts!$L:$L,Accounts!$E:$E,'AccountSummary (New)'!T$1,Accounts!$G:$G,'AccountSummary (New)'!T$2,Accounts!$F:$F,'AccountSummary (New)'!T$3,Accounts!$W:$W,0,Accounts!$C:$C,"Customer",Accounts!$H:$H,">"&90,Accounts!$H:$H,"<="&180)/T52) -> 0 | U53: =IF(U52=0,0,SUMIFS(Accounts!$L:$L,Accounts!$E:$E,'AccountSummary (New)'!U$1,Accounts!$G:$G,'AccountSummary (New)'!U$2,Accounts!$F:$F,'AccountSummary (New)'!U$3,Accounts!$W:$W,0,Accounts!$C:$C,"Customer",Accounts!$H:$H,">"&90,Accounts!$H:$H,"<="&180)/U52) -> 0 | V53: =IF(V52=0,0,SUMIFS(Accounts!$L:$L,Accounts!$E:$E,'AccountSummary (New)'!V$1,Accounts!$G:$G,'AccountSummary (New)'!V$2,Accounts!$F:$F,'AccountSummary (New)'!V$3,Accounts!$W:$W,0,Accounts!$C:$C,"Customer",Accounts!$H:$H,">"&90,Accounts!$H:$H,"<="&180)/V52) -> 0 | W53: =IF(W52=0,0,SUMIFS(Accounts!$L:$L,Accounts!$F:$F,'AccountSummary (New)'!W$3,Accounts!$W:$W,0,Accounts!$C:$C,"Customer",Accounts!$H:$H,">"&90,Accounts!$H:$H,"<="&180)/W52) -> 0
A54: Users per Account | B54: =IF(B52=0,0,SUMIFS(Accounts!$M:$M,Accounts!$W:$W,0,Accounts!$C:$C,"Customer",Accounts!$H:$H,">"&60,Accounts!$H:$H,"<="&90)/B52) -> 0 | C54: =IF(C52=0,0,SUMIFS(Accounts!$M:$M,Accounts!$E:$E,'AccountSummary (New)'!C$1,Accounts!$G:$G,'AccountSummary (New)'!C$2,Accounts!$F:$F,'AccountSummary (New)'!C$3,Accounts!$W:$W,0,Accounts!$C:$C,"Customer",Accounts!$H:$H,">"&90,Accounts!$H:$H,"<="&180)/C52) -> 0 | D54: =IF(D52=0,0,SUMIFS(Accounts!$M:$M,Accounts!$E:$E,'AccountSummary (New)'!D$1,Accounts!$G:$G,'AccountSummary (New)'!D$2,Accounts!$F:$F,'AccountSummary (New)'!D$3,Accounts!$W:$W,0,Accounts!$C:$C,"Customer",Accounts!$H:$H,">"&90,Accounts!$H:$H,"<="&180)/D52) -> 0 | E54: =IF(E52=0,0,SUMIFS(Accounts!$M:$M,Accounts!$E:$E,'AccountSummary (New)'!E$1,Accounts!$G:$G,'AccountSummary (New)'!E$2,Accounts!$F:$F,'AccountSummary (New)'!E$3,Accounts!$W:$W,0,Accounts!$C:$C,"Customer",Accounts!$H:$H,">"&90,Accounts!$H:$H,"<="&180)/E52) -> 0 | F54: =IF(F52=0,0,SUMIFS(Accounts!$M:$M,Accounts!$E:$E,'AccountSummary (New)'!F$1,Accounts!$G:$G,'AccountSummary (New)'!F$2,Accounts!$F:$F,'AccountSummary (New)'!F$3,Accounts!$W:$W,0,Accounts!$C:$C,"Customer",Accounts!$H:$H,">"&90,Accounts!$H:$H,"<="&180)/F52) -> 0 | G54: =IF(G52=0,0,SUMIFS(Accounts!$M:$M,Accounts!$E:$E,'AccountSummary (New)'!G$1,Accounts!$G:$G,'AccountSummary (New)'!G$2,Accounts!$F:$F,'AccountSummary (New)'!G$3,Accounts!$W:$W,0,Accounts!$C:$C,"Customer",Accounts!$H:$H,">"&90,Accounts!$H:$H,"<="&180)/G52) -> 0 | H54: =IF(H52=0,0,SUMIFS(Accounts!$M:$M,Accounts!$E:$E,'AccountSummary (New)'!H$1,Accounts!$G:$G,'AccountSummary (New)'!H$2,Accounts!$F:$F,'AccountSummary (New)'!H$3,Accounts!$W:$W,0,Accounts!$C:$C,"Customer",Accounts!$H:$H,">"&90,Accounts!$H:$H,"<="&180)/H52) -> 0 | I54: =IF(I52=0,0,SUMIFS(Accounts!$M:$M,Accounts!$F:$F,'AccountSummary (New)'!I$3,Accounts!$W:$W,0,Accounts!$C:$C,"Customer",Accounts!$H:$H,">"&90,Accounts!$H:$H,"<="&180)/I52) -> 0 | J54: =IF(J52=0,0,SUMIFS(Accounts!$M:$M,Accounts!$E:$E,'AccountSummary (New)'!J$1,Accounts!$G:$G,'AccountSummary (New)'!J$2,Accounts!$F:$F,'AccountSummary (New)'!J$3,Accounts!$W:$W,0,Accounts!$C:$C,"Customer",Accounts!$H:$H,">"&90,Accounts!$H:$H,"<="&180)/J52) -> 0 | K54: =IF(K52=0,0,SUMIFS(Accounts!$M:$M,Accounts!$E:$E,'AccountSummary (New)'!K$1,Accounts!$G:$G,'AccountSummary (New)'!K$2,Accounts!$F:$F,'AccountSummary (New)'!K$3,Accounts!$W:$W,0,Accounts!$C:$C,"Customer",Accounts!$H:$H,">"&90,Accounts!$H:$H,"<="&180)/K52) -> 0 | L54: =IF(L52=0,0,SUMIFS(Accounts!$M:$M,Accounts!$E:$E,'AccountSummary (New)'!L$1,Accounts!$G:$G,'AccountSummary (New)'!L$2,Accounts!$F:$F,'AccountSummary (New)'!L$3,Accounts!$W:$W,0,Accounts!$C:$C,"Customer",Accounts!$H:$H,">"&90,Accounts!$H:$H,"<="&180)/L52) -> 0 | M54: =IF(M52=0,0,SUMIFS(Accounts!$M:$M,Accounts!$E:$E,'AccountSummary (New)'!M$1,Accounts!$G:$G,'AccountSummary (New)'!M$2,Accounts!$F:$F,'AccountSummary (New)'!M$3,Accounts!$W:$W,0,Accounts!$C:$C,"Customer",Accounts!$H:$H,">"&90,Accounts!$H:$H,"<="&180)/M52) -> 0 | N54: =IF(N52=0,0,SUMIFS(Accounts!$M:$M,Accounts!$E:$E,'AccountSummary (New)'!N$1,Accounts!$G:$G,'AccountSummary (New)'!N$2,Accounts!$F:$F,'AccountSummary (New)'!N$3,Accounts!$W:$W,0,Accounts!$C:$C,"Customer",Accounts!$H:$H,">"&90,Accounts!$H:$H,"<="&180)/N52) -> 0 | O54: =IF(O52=0,0,SUMIFS(Accounts!$M:$M,Accounts!$E:$E,'AccountSummary (New)'!O$1,Accounts!$G:$G,'AccountSummary (New)'!O$2,Accounts!$F:$F,'AccountSummary (New)'!O$3,Accounts!$W:$W,0,Accounts!$C:$C,"Customer",Accounts!$H:$H,">"&90,Accounts!$H:$H,"<="&180)/O52) -> 0 | P54: =IF(P52=0,0,SUMIFS(Accounts!$M:$M,Accounts!$F:$F,'AccountSummary (New)'!P$3,Accounts!$W:$W,0,Accounts!$C:$C,"Customer",Accounts!$H:$H,">"&90,Accounts!$H:$H,"<="&180)/P52) -> 0 | Q54: =IF(Q52=0,0,SUMIFS(Accounts!$M:$M,Accounts!$E:$E,'AccountSummary (New)'!Q$1,Accounts!$G:$G,'AccountSummary (New)'!Q$2,Accounts!$F:$F,'AccountSummary (New)'!Q$3,Accounts!$W:$W,0,Accounts!$C:$C,"Customer",Accounts!$H:$H,">"&90,Accounts!$H:$H,"<="&180)/Q52) -> 0 | R54: =IF(R52=0,0,SUMIFS(Accounts!$M:$M,Accounts!$E:$E,'AccountSummary (New)'!R$1,Accounts!$G:$G,'AccountSummary (New)'!R$2,Accounts!$F:$F,'AccountSummary (New)'!R$3,Accounts!$W:$W,0,Accounts!$C:$C,"Customer",Accounts!$H:$H,">"&90,Accounts!$H:$H,"<="&180)/R52) -> 0 | S54: =IF(S52=0,0,SUMIFS(Accounts!$M:$M,Accounts!$E:$E,'AccountSummary (New)'!S$1,Accounts!$G:$G,'AccountSummary (New)'!S$2,Accounts!$F:$F,'AccountSummary (New)'!S$3,Accounts!$W:$W,0,Accounts!$C:$C,"Customer",Accounts!$H:$H,">"&90,Accounts!$H:$H,"<="&180)/S52) -> 0 | T54: =IF(T52=0,0,SUMIFS(Accounts!$M:$M,Accounts!$E:$E,'AccountSummary (New)'!T$1,Accounts!$G:$G,'AccountSummary (New)'!T$2,Accounts!$F:$F,'AccountSummary (New)'!T$3,Accounts!$W:$W,0,Accounts!$C:$C,"Customer",Accounts!$H:$H,">"&90,Accounts!$H:$H,"<="&180)/T52) -> 0 | U54: =IF(U52=0,0,SUMIFS(Accounts!$M:$M,Accounts!$E:$E,'AccountSummary (New)'!U$1,Accounts!$G:$G,'AccountSummary (New)'!U$2,Accounts!$F:$F,'AccountSummary (New)'!U$3,Accounts!$W:$W,0,Accounts!$C:$C,"Customer",Accounts!$H:$H,">"&90,Accounts!$H:$H,"<="&180)/U52) -> 0 | V54: =IF(V52=0,0,SUMIFS(Accounts!$M:$M,Accounts!$E:$E,'AccountSummary (New)'!V$1,Accounts!$G:$G,'AccountSummary (New)'!V$2,Accounts!$F:$F,'AccountSummary (New)'!V$3,Accounts!$W:$W,0,Accounts!$C:$C,"Customer",Accounts!$H:$H,">"&90,Accounts!$H:$H,"<="&180)/V52) -> 0 | W54: =IF(W52=0,0,SUMIFS(Accounts!$M:$M,Accounts!$F:$F,'AccountSummary (New)'!W$3,Accounts!$W:$W,0,Accounts!$C:$C,"Customer",Accounts!$H:$H,">"&90,Accounts!$H:$H,"<="&180)/W52) -> 0
A55: ARPC | B55: =IF(B52=0,0,B56/B52) -> 0 | C55: =IF(C52=0,0,C56/C52) -> 0 | D55: =IF(D52=0,0,D56/D52) -> 0 | E55: =IF(E52=0,0,E56/E52) -> 0 | F55: =IF(F52=0,0,F56/F52) -> 0 | G55: =IF(G52=0,0,G56/G52) -> 0 | H55: =IF(H52=0,0,H56/H52) -> 0 | I55: =IF(I52=0,0,I56/I52) -> 0 | ... W55: =IF(W52=0,0,W56/W52) -> 0
A56: SaaS | B56: =I56+P56+W56 -> 0 | C56: =SUMIFS(Accounts!$I:$I,Accounts!$E:$E,'AccountSummary (New)'!C$1,Accounts!$G:$G,'AccountSummary (New)'!C$2,Accounts!$F:$F,'AccountSummary (New)'!C$3,Accounts!$W:$W,0,Accounts!$C:$C,"Customer",Accounts!$H:$H,">"&90,Accounts!$H:$H,"<="&180) -> 0 | D56: =SUMIFS(Accounts!$I:$I,Accounts!$E:$E,'AccountSummary (New)'!D$1,Accounts!$G:$G,'AccountSummary (New)'!D$2,Accounts!$F:$F,'AccountSummary (New)'!D$3,Accounts!$W:$W,0,Accounts!$C:$C,"Customer",Accounts!$H:$H,">"&90,Accounts!$H:$H,"<="&180) -> 0 | E56: =SUMIFS(Accounts!$I:$I,Accounts!$E:$E,'AccountSummary (New)'!E$1,Accounts!$G:$G,'AccountSummary (New)'!E$2,Accounts!$F:$F,'AccountSummary (New)'!E$3,Accounts!$W:$W,0,Accounts!$C:$C,"Customer",Accounts!$H:$H,">"&90,Accounts!$H:$H,"<="&180) -> 0 | F56: =SUMIFS(Accounts!$I:$I,Accounts!$E:$E,'AccountSummary (New)'!F$1,Accounts!$G:$G,'AccountSummary (New)'!F$2,Accounts!$F:$F,'AccountSummary (New)'!F$3,Accounts!$W:$W,0,Accounts!$C:$C,"Customer",Accounts!$H:$H,">"&90,Accounts!$H:$H,"<="&180) -> 0 | G56: =SUMIFS(Accounts!$I:$I,Accounts!$E:$E,'AccountSummary (New)'!G$1,Accounts!$G:$G,'AccountSummary (New)'!G$2,Accounts!$F:$F,'AccountSummary (New)'!G$3,Accounts!$W:$W,0,Accounts!$C:$C,"Customer",Accounts!$H:$H,">"&90,Accounts!$H:$H,"<="&180) -> 0 | H56: =SUMIFS(Accounts!$I:$I,Accounts!$E:$E,'AccountSummary (New)'!H$1,Accounts!$G:$G,'AccountSummary (New)'!H$2,Accounts!$F:$F,'AccountSummary (New)'!H$3,Accounts!$W:$W,0,Accounts!$C:$C,"Customer",Accounts!$H:$H,">"&90,Accounts!$H:$H,"<="&180) -> 0 | I56: =SUM(C56:H56) -> 0 | J56: =SUMIFS(Accounts!$I:$I,Accounts!$E:$E,'AccountSummary (New)'!J$1,Accounts!$G:$G,'AccountSummary (New)'!J$2,Accounts!$F:$F,'AccountSummary (New)'!J$3,Accounts!$W:$W,0,Accounts!$C:$C,"Customer",Accounts!$H:$H,">"&90,Accounts!$H:$H,"<="&180) -> 0 | K56: =SUMIFS(Accounts!$I:$I,Accounts!$E:$E,'AccountSummary (New)'!K$1,Accounts!$G:$G,'AccountSummary (New)'!K$2,Accounts!$F:$F,'AccountSummary (New)'!K$3,Accounts!$W:$W,0,Accounts!$C:$C,"Customer",Accounts!$H:$H,">"&90,Accounts!$H:$H,"<="&180) -> 0 | L56: =SUMIFS(Accounts!$I:$I,Accounts!$E:$E,'AccountSummary (New)'!L$1,Accounts!$G:$G,'AccountSummary (New)'!L$2,Accounts!$F:$F,'AccountSummary (New)'!L$3,Accounts!$W:$W,0,Accounts!$C:$C,"Customer",Accounts!$H:$H,">"&90,Accounts!$H:$H,"<="&180) -> 0 | M56: =SUMIFS(Accounts!$I:$I,Accounts!$E:$E,'AccountSummary (New)'!M$1,Accounts!$G:$G,'AccountSummary (New)'!M$2,Accounts!$F:$F,'AccountSummary (New)'!M$3,Accounts!$W:$W,0,Accounts!$C:$C,"Customer",Accounts!$H:$H,">"&90,Accounts!$H:$H,"<="&180) -> 0 | N56: =SUMIFS(Accounts!$I:$I,Accounts!$E:$E,'AccountSummary (New)'!N$1,Accounts!$G:$G,'AccountSummary (New)'!N$2,Accounts!$F:$F,'AccountSummary (New)'!N$3,Accounts!$W:$W,0,Accounts!$C:$C,"Customer",Accounts!$H:$H,">"&90,Accounts!$H:$H,"<="&180) -> 0 | O56: =SUMIFS(Accounts!$I:$I,Accounts!$E:$E,'AccountSummary (New)'!O$1,Accounts!$G:$G,'AccountSummary (New)'!O$2,Accounts!$F:$F,'AccountSummary (New)'!O$3,Accounts!$W:$W,0,Accounts!$C:$C,"Customer",Accounts!$H:$H,">"&90,Accounts!$H:$H,"<="&180) -> 0 | P56: =SUM(J56:O56) -> 0 | Q56: =SUMIFS(Accounts!$I:$I,Accounts!$E:$E,'AccountSummary (New)'!Q$1,Accounts!$G:$G,'AccountSummary (New)'!Q$2,Accounts!$F:$F,'AccountSummary (New)'!Q$3,Accounts!$W:$W,0,Accounts!$C:$C,"Customer",Accounts!$H:$H,">"&90,Accounts!$H:$H,"<="&180) -> 0 | R56: =SUMIFS(Accounts!$I:$I,Accounts!$E:$E,'AccountSummary (New)'!R$1,Accounts!$G:$G,'AccountSummary (New)'!R$2,Accounts!$F:$F,'AccountSummary (New)'!R$3,Accounts!$W:$W,0,Accounts!$C:$C,"Customer",Accounts!$H:$H,">"&90,Accounts!$H:$H,"<="&180) -> 0 | S56: =SUMIFS(Accounts!$I:$I,Accounts!$E:$E,'AccountSummary (New)'!S$1,Accounts!$G:$G,'AccountSummary (New)'!S$2,Accounts!$F:$F,'AccountSummary (New)'!S$3,Accounts!$W:$W,0,Accounts!$C:$C,"Customer",Accounts!$H:$H,">"&90,Accounts!$H:$H,"<="&180) -> 0 | T56: =SUMIFS(Accounts!$I:$I,Accounts!$E:$E,'AccountSummary (New)'!T$1,Accounts!$G:$G,'AccountSummary (New)'!T$2,Accounts!$F:$F,'AccountSummary (New)'!T$3,Accounts!$W:$W,0,Accounts!$C:$C,"Customer",Accounts!$H:$H,">"&90,Accounts!$H:$H,"<="&180) -> 0 | U56: =SUMIFS(Accounts!$I:$I,Accounts!$E:$E,'AccountSummary (New)'!U$1,Accounts!$G:$G,'AccountSummary (New)'!U$2,Accounts!$F:$F,'AccountSummary (New)'!U$3,Accounts!$W:$W,0,Accounts!$C:$C,"Customer",Accounts!$H:$H,">"&90,Accounts!$H:$H,"<="&180) -> 0 | V56: =SUMIFS(Accounts!$I:$I,Accounts!$E:$E,'AccountSummary (New)'!V$1,Accounts!$G:$G,'AccountSummary (New)'!V$2,Accounts!$F:$F,'AccountSummary (New)'!V$3,Accounts!$W:$W,0,Accounts!$C:$C,"Customer",Accounts!$H:$H,">"&90,Accounts!$H:$H,"<="&180) -> 0 | W56: =SUM(Q56:V56) -> 0
A57: 180+ day cohort as of BOM
A58: Total % of Paying Customers | B58: =IF(B$19=0,0,(B60+B61)/B$19) -> 1 | C58: =IF(C$19=0,0,(C60+C61)/C$19) -> 0 | D58: =IF(D$19=0,0,(D60+D61)/D$19) -> 0 | E58: =IF(E$19=0,0,(E60+E61)/E$19) -> 0 | F58: =IF(F$19=0,0,(F60+F61)/F$19) -> 0 | G58: =IF(G$19=0,0,(G60+G61)/G$19) -> 0 | H58: =IF(H$19=0,0,(H60+H61)/H$19) -> 0 | I58: =IF(I$19=0,0,(I60+I61)/I$19) -> 0 | ... W58: =IF(W$19=0,0,(W60+W61)/W$19) -> 1
A59: Loss % | B59: =IF((B60+B61)=0,0,B60/(B60+B61)) -> 0 | C59: =IF((C60+C61)=0,0,C60/(C60+C61)) -> 0 | D59: =IF((D60+D61)=0,0,D60/(D60+D61)) -> 0 | E59: =IF((E60+E61)=0,0,E60/(E60+E61)) -> 0 | F59: =IF((F60+F61)=0,0,F60/(F60+F61)) -> 0 | G59: =IF((G60+G61)=0,0,G60/(G60+G61)) -> 0 | H59: =IF((H60+H61)=0,0,H60/(H60+H61)) -> 0 | I59: =IF((I60+I61)=0,0,I60/(I60+I61)) -> 0 | ... W59: =IF((W60+W61)=0,0,W60/(W60+W61)) -> 0
A60: Lost Count | B60: =I60+P60+W60 -> 0 | C60: =COUNTIFS(Accounts!$E:$E,'AccountSummary (New)'!C$1,Accounts!$G:$G,'AccountSummary (New)'!C$2,Accounts!$F:$F,'AccountSummary (New)'!C$3,Accounts!$B:$B,"Customer",Accounts!$C:$C,"Lost",Accounts!$H:$H,">"&180) -> 0 | D60: =COUNTIFS(Accounts!$E:$E,'AccountSummary (New)'!D$1,Accounts!$G:$G,'AccountSummary (New)'!D$2,Accounts!$F:$F,'AccountSummary (New)'!D$3,Accounts!$B:$B,"Customer",Accounts!$C:$C,"Lost",Accounts!$H:$H,">"&180) -> 0 | E60: =COUNTIFS(Accounts!$E:$E,'AccountSummary (New)'!E$1,Accounts!$G:$G,'AccountSummary (New)'!E$2,Accounts!$F:$F,'AccountSummary (New)'!E$3,Accounts!$B:$B,"Customer",Accounts!$C:$C,"Lost",Accounts!$H:$H,">"&180) -> 0 | F60: =COUNTIFS(Accounts!$E:$E,'AccountSummary (New)'!F$1,Accounts!$G:$G,'AccountSummary (New)'!F$2,Accounts!$F:$F,'AccountSummary (New)'!F$3,Accounts!$B:$B,"Customer",Accounts!$C:$C,"Lost",Accounts!$H:$H,">"&180) -> 0 | G60: =COUNTIFS(Accounts!$E:$E,'AccountSummary (New)'!G$1,Accounts!$G:$G,'AccountSummary (New)'!G$2,Accounts!$F:$F,'AccountSummary (New)'!G$3,Accounts!$B:$B,"Customer",Accounts!$C:$C,"Lost",Accounts!$H:$H,">"&180) -> 0 | H60: =COUNTIFS(Accounts!$E:$E,'AccountSummary (New)'!H$1,Accounts!$G:$G,'AccountSummary (New)'!H$2,Accounts!$F:$F,'AccountSummary (New)'!H$3,Accounts!$B:$B,"Customer",Accounts!$C:$C,"Lost",Accounts!$H:$H,">"&180) -> 0 | I60: =SUM(C60:H60) -> 0 | J60: =COUNTIFS(Accounts!$E:$E,'AccountSummary (New)'!J$1,Accounts!$G:$G,'AccountSummary (New)'!J$2,Accounts!$F:$F,'AccountSummary (New)'!J$3,Accounts!$B:$B,"Customer",Accounts!$C:$C,"Lost",Accounts!$H:$H,">"&180) -> 0 | K60: =COUNTIFS(Accounts!$E:$E,'AccountSummary (New)'!K$1,Accounts!$G:$G,'AccountSummary (New)'!K$2,Accounts!$F:$F,'AccountSummary (New)'!K$3,Accounts!$B:$B,"Customer",Accounts!$C:$C,"Lost",Accounts!$H:$H,">"&180) -> 0 | L60: =COUNTIFS(Accounts!$E:$E,'AccountSummary (New)'!L$1,Accounts!$G:$G,'AccountSummary (New)'!L$2,Accounts!$F:$F,'AccountSummary (New)'!L$3,Accounts!$B:$B,"Customer",Accounts!$C:$C,"Lost",Accounts!$H:$H,">"&180) -> 0 | M60: =COUNTIFS(Accounts!$E:$E,'AccountSummary (New)'!M$1,Accounts!$G:$G,'AccountSummary (New)'!M$2,Accounts!$F:$F,'AccountSummary (New)'!M$3,Accounts!$B:$B,"Customer",Accounts!$C:$C,"Lost",Accounts!$H:$H,">"&180) -> 0 | N60: =COUNTIFS(Accounts!$E:$E,'AccountSummary (New)'!N$1,Accounts!$G:$G,'AccountSummary (New)'!N$2,Accounts!$F:$F,'AccountSummary (New)'!N$3,Accounts!$B:$B,"Customer",Accounts!$C:$C,"Lost",Accounts!$H:$H,">"&180) -> 0 | O60: =COUNTIFS(Accounts!$E:$E,'AccountSummary (New)'!O$1,Accounts!$G:$G,'AccountSummary (New)'!O$2,Accounts!$F:$F,'AccountSummary (New)'!O$3,Accounts!$B:$B,"Customer",Accounts!$C:$C,"Lost",Accounts!$H:$H,">"&180) -> 0 | P60: =SUM(J60:O60) -> 0 | Q60: =COUNTIFS(Accounts!$E:$E,'AccountSummary (New)'!Q$1,Accounts!$G:$G,'AccountSummary (New)'!Q$2,Accounts!$F:$F,'AccountSummary (New)'!Q$3,Accounts!$B:$B,"Customer",Accounts!$C:$C,"Lost",Accounts!$H:$H,">"&180) -> 0 | R60: =COUNTIFS(Accounts!$E:$E,'AccountSummary (New)'!R$1,Accounts!$G:$G,'AccountSummary (New)'!R$2,Accounts!$F:$F,'AccountSummary (New)'!R$3,Accounts!$B:$B,"Customer",Accounts!$C:$C,"Lost",Accounts!$H:$H,">"&180) -> 0 | S60: =COUNTIFS(Accounts!$E:$E,'AccountSummary (New)'!S$1,Accounts!$G:$G,'AccountSummary (New)'!S$2,Accounts!$F:$F,'AccountSummary (New)'!S$3,Accounts!$B:$B,"Customer",Accounts!$C:$C,"Lost",Accounts!$H:$H,">"&180) -> 0 | T60: =COUNTIFS(Accounts!$E:$E,'AccountSummary (New)'!T$1,Accounts!$G:$G,'AccountSummary (New)'!T$2,Accounts!$F:$F,'AccountSummary (New)'!T$3,Accounts!$B:$B,"Customer",Accounts!$C:$C,"Lost",Accounts!$H:$H,">"&180) -> 0 | U60: =COUNTIFS(Accounts!$E:$E,'AccountSummary (New)'!U$1,Accounts!$G:$G,'AccountSummary (New)'!U$2,Accounts!$F:$F,'AccountSummary (New)'!U$3,Accounts!$B:$B,"Customer",Accounts!$C:$C,"Lost",Accounts!$H:$H,">"&180) -> 0 | V60: =COUNTIFS(Accounts!$E:$E,'AccountSummary (New)'!V$1,Accounts!$G:$G,'AccountSummary (New)'!V$2,Accounts!$F:$F,'AccountSummary (New)'!V$3,Accounts!$B:$B,"Customer",Accounts!$C:$C,"Lost",Accounts!$H:$H,">"&180) -> 0 | W60: =SUM(Q60:V60) -> 0
A61: Retained Count | B61: =I61+P61+W61 -> 1 | C61: =COUNTIFS(Accounts!$E:$E,'AccountSummary (New)'!C$1,Accounts!$G:$G,'AccountSummary (New)'!C$2,Accounts!$F:$F,'AccountSummary (New)'!C$3,Accounts!$B:$B,"Customer",Accounts!$C:$C,"Customer",Accounts!$H:$H,">"&180) -> 0 | D61: =COUNTIFS(Accounts!$E:$E,'AccountSummary (New)'!D$1,Accounts!$G:$G,'AccountSummary (New)'!D$2,Accounts!$F:$F,'AccountSummary (New)'!D$3,Accounts!$B:$B,"Customer",Accounts!$C:$C,"Customer",Accounts!$H:$H,">"&180) -> 0 | E61: =COUNTIFS(Accounts!$E:$E,'AccountSummary (New)'!E$1,Accounts!$G:$G,'AccountSummary (New)'!E$2,Accounts!$F:$F,'AccountSummary (New)'!E$3,Accounts!$B:$B,"Customer",Accounts!$C:$C,"Customer",Accounts!$H:$H,">"&180) -> 0 | F61: =COUNTIFS(Accounts!$E:$E,'AccountSummary (New)'!F$1,Accounts!$G:$G,'AccountSummary (New)'!F$2,Accounts!$F:$F,'AccountSummary (New)'!F$3,Accounts!$B:$B,"Customer",Accounts!$C:$C,"Customer",Accounts!$H:$H,">"&180) -> 0 | G61: =COUNTIFS(Accounts!$E:$E,'AccountSummary (New)'!G$1,Accounts!$G:$G,'AccountSummary (New)'!G$2,Accounts!$F:$F,'AccountSummary (New)'!G$3,Accounts!$B:$B,"Customer",Accounts!$C:$C,"Customer",Accounts!$H:$H,">"&180) -> 0 | H61: =COUNTIFS(Accounts!$E:$E,'AccountSummary (New)'!H$1,Accounts!$G:$G,'AccountSummary (New)'!H$2,Accounts!$F:$F,'AccountSummary (New)'!H$3,Accounts!$B:$B,"Customer",Accounts!$C:$C,"Customer",Accounts!$H:$H,">"&180) -> 0 | I61: =SUM(C61:H61) -> 0 | J61: =COUNTIFS(Accounts!$E:$E,'AccountSummary (New)'!J$1,Accounts!$G:$G,'AccountSummary (New)'!J$2,Accounts!$F:$F,'AccountSummary (New)'!J$3,Accounts!$B:$B,"Customer",Accounts!$C:$C,"Customer",Accounts!$H:$H,">"&180) -> 0 | K61: =COUNTIFS(Accounts!$E:$E,'AccountSummary (New)'!K$1,Accounts!$G:$G,'AccountSummary (New)'!K$2,Accounts!$F:$F,'AccountSummary (New)'!K$3,Accounts!$B:$B,"Customer",Accounts!$C:$C,"Customer",Accounts!$H:$H,">"&180) -> 0 | L61: =COUNTIFS(Accounts!$E:$E,'AccountSummary (New)'!L$1,Accounts!$G:$G,'AccountSummary (New)'!L$2,Accounts!$F:$F,'AccountSummary (New)'!L$3,Accounts!$B:$B,"Customer",Accounts!$C:$C,"Customer",Accounts!$H:$H,">"&180) -> 0 | M61: =COUNTIFS(Accounts!$E:$E,'AccountSummary (New)'!M$1,Accounts!$G:$G,'AccountSummary (New)'!M$2,Accounts!$F:$F,'AccountSummary (New)'!M$3,Accounts!$B:$B,"Customer",Accounts!$C:$C,"Customer",Accounts!$H:$H,">"&180) -> 0 | N61: =COUNTIFS(Accounts!$E:$E,'AccountSummary (New)'!N$1,Accounts!$G:$G,'AccountSummary (New)'!N$2,Accounts!$F:$F,'AccountSummary (New)'!N$3,Accounts!$B:$B,"Customer",Accounts!$C:$C,"Customer",Accounts!$H:$H,">"&180) -> 0 | O61: =COUNTIFS(Accounts!$E:$E,'AccountSummary (New)'!O$1,Accounts!$G:$G,'AccountSummary (New)'!O$2,Accounts!$F:$F,'AccountSummary (New)'!O$3,Accounts!$B:$B,"Customer",Accounts!$C:$C,"Customer",Accounts!$H:$H,">"&180) -> 0 | P61: =SUM(J61:O61) -> 0 | Q61: =COUNTIFS(Accounts!$E:$E,'AccountSummary (New)'!Q$1,Accounts!$G:$G,'AccountSummary (New)'!Q$2,Accounts!$F:$F,'AccountSummary (New)'!Q$3,Accounts!$B:$B,"Customer",Accounts!$C:$C,"Customer",Accounts!$H:$H,">"&180) -> 0 | R61: =COUNTIFS(Accounts!$E:$E,'AccountSummary (New)'!R$1,Accounts!$G:$G,'AccountSummary (New)'!R$2,Accounts!$F:$F,'AccountSummary (New)'!R$3,Accounts!$B:$B,"Customer",Accounts!$C:$C,"Customer",Accounts!$H:$H,">"&180) -> 1 | S61: =COUNTIFS(Accounts!$E:$E,'AccountSummary (New)'!S$1,Accounts!$G:$G,'AccountSummary (New)'!S$2,Accounts!$F:$F,'AccountSummary (New)'!S$3,Accounts!$B:$B,"Customer",Accounts!$C:$C,"Customer",Accounts!$H:$H,">"&180) -> 0 | T61: =COUNTIFS(Accounts!$E:$E,'AccountSummary (New)'!T$1,Accounts!$G:$G,'AccountSummary (New)'!T$2,Accounts!$F:$F,'AccountSummary (New)'!T$3,Accounts!$B:$B,"Customer",Accounts!$C:$C,"Customer",Accounts!$H:$H,">"&180) -> 0 | U61: =COUNTIFS(Accounts!$E:$E,'AccountSummary (New)'!U$1,Accounts!$G:$G,'AccountSummary (New)'!U$2,Accounts!$F:$F,'AccountSummary (New)'!U$3,Accounts!$B:$B,"Customer",Accounts!$C:$C,"Customer",Accounts!$H:$H,">"&180) -> 0 | V61: =COUNTIFS(Accounts!$E:$E,'AccountSummary (New)'!V$1,Accounts!$G:$G,'AccountSummary (New)'!V$2,Accounts!$F:$F,'AccountSummary (New)'!V$3,Accounts!$B:$B,"Customer",Accounts!$C:$C,"Customer",Accounts!$H:$H,">"&180) -> 0 | W61: =SUM(Q61:V61) -> 1
A62: Packs per Account | B62: =IF(B61=0,0,SUMIFS(Accounts!$L:$L,Accounts!$W:$W,0,Accounts!$C:$C,"Customer",Accounts!$H:$H,">"&180)/B61) -> 3 | C62: =IF(C61=0,0,SUMIFS(Accounts!$L:$L,Accounts!$E:$E,'AccountSummary (New)'!C$1,Accounts!$G:$G,'AccountSummary (New)'!C$2,Accounts!$F:$F,'AccountSummary (New)'!C$3,Accounts!$W:$W,0,Accounts!$C:$C,"Customer",Accounts!$H:$H,">"&180)/C61) -> 0 | D62: =IF(D61=0,0,SUMIFS(Accounts!$L:$L,Accounts!$E:$E,'AccountSummary (New)'!D$1,Accounts!$G:$G,'AccountSummary (New)'!D$2,Accounts!$F:$F,'AccountSummary (New)'!D$3,Accounts!$W:$W,0,Accounts!$C:$C,"Customer",Accounts!$H:$H,">"&180)/D61) -> 0 | E62: =IF(E61=0,0,SUMIFS(Accounts!$L:$L,Accounts!$E:$E,'AccountSummary (New)'!E$1,Accounts!$G:$G,'AccountSummary (New)'!E$2,Accounts!$F:$F,'AccountSummary (New)'!E$3,Accounts!$W:$W,0,Accounts!$C:$C,"Customer",Accounts!$H:$H,">"&180)/E61) -> 0 | F62: =IF(F61=0,0,SUMIFS(Accounts!$L:$L,Accounts!$E:$E,'AccountSummary (New)'!F$1,Accounts!$G:$G,'AccountSummary (New)'!F$2,Accounts!$F:$F,'AccountSummary (New)'!F$3,Accounts!$W:$W,0,Accounts!$C:$C,"Customer",Accounts!$H:$H,">"&180)/F61) -> 0 | G62: =IF(G61=0,0,SUMIFS(Accounts!$L:$L,Accounts!$E:$E,'AccountSummary (New)'!G$1,Accounts!$G:$G,'AccountSummary (New)'!G$2,Accounts!$F:$F,'AccountSummary (New)'!G$3,Accounts!$W:$W,0,Accounts!$C:$C,"Customer",Accounts!$H:$H,">"&180)/G61) -> 0 | H62: =IF(H61=0,0,SUMIFS(Accounts!$L:$L,Accounts!$E:$E,'AccountSummary (New)'!H$1,Accounts!$G:$G,'AccountSummary (New)'!H$2,Accounts!$F:$F,'AccountSummary (New)'!H$3,Accounts!$W:$W,0,Accounts!$C:$C,"Customer",Accounts!$H:$H,">"&180)/H61) -> 0 | I62: =IF(I61=0,0,SUMIFS(Accounts!$L:$L,Accounts!$F:$F,'AccountSummary (New)'!I$3,Accounts!$W:$W,0,Accounts!$C:$C,"Customer",Accounts!$H:$H,">"&60,Accounts!$H:$H,"<="&180)/I61) -> 0 | J62: =IF(J61=0,0,SUMIFS(Accounts!$L:$L,Accounts!$E:$E,'AccountSummary (New)'!J$1,Accounts!$G:$G,'AccountSummary (New)'!J$2,Accounts!$F:$F,'AccountSummary (New)'!J$3,Accounts!$W:$W,0,Accounts!$C:$C,"Customer",Accounts!$H:$H,">"&180)/J61) -> 0 | K62: =IF(K61=0,0,SUMIFS(Accounts!$L:$L,Accounts!$E:$E,'AccountSummary (New)'!K$1,Accounts!$G:$G,'AccountSummary (New)'!K$2,Accounts!$F:$F,'AccountSummary (New)'!K$3,Accounts!$W:$W,0,Accounts!$C:$C,"Customer",Accounts!$H:$H,">"&180)/K61) -> 0 | L62: =IF(L61=0,0,SUMIFS(Accounts!$L:$L,Accounts!$E:$E,'AccountSummary (New)'!L$1,Accounts!$G:$G,'AccountSummary (New)'!L$2,Accounts!$F:$F,'AccountSummary (New)'!L$3,Accounts!$W:$W,0,Accounts!$C:$C,"Customer",Accounts!$H:$H,">"&180)/L61) -> 0 | M62: =IF(M61=0,0,SUMIFS(Accounts!$L:$L,Accounts!$E:$E,'AccountSummary (New)'!M$1,Accounts!$G:$G,'AccountSummary (New)'!M$2,Accounts!$F:$F,'AccountSummary (New)'!M$3,Accounts!$W:$W,0,Accounts!$C:$C,"Customer",Accounts!$H:$H,">"&180)/M61) -> 0 | N62: =IF(N61=0,0,SUMIFS(Accounts!$L:$L,Accounts!$E:$E,'AccountSummary (New)'!N$1,Accounts!$G:$G,'AccountSummary (New)'!N$2,Accounts!$F:$F,'AccountSummary (New)'!N$3,Accounts!$W:$W,0,Accounts!$C:$C,"Customer",Accounts!$H:$H,">"&180)/N61) -> 0 | O62: =IF(O61=0,0,SUMIFS(Accounts!$L:$L,Accounts!$E:$E,'AccountSummary (New)'!O$1,Accounts!$G:$G,'AccountSummary (New)'!O$2,Accounts!$F:$F,'AccountSummary (New)'!O$3,Accounts!$W:$W,0,Accounts!$C:$C,"Customer",Accounts!$H:$H,">"&180)/O61) -> 0 | P62: =IF(P61=0,0,SUMIFS(Accounts!$L:$L,Accounts!$F:$F,'AccountSummary (New)'!P$3,Accounts!$W:$W,0,Accounts!$C:$C,"Customer",Accounts!$H:$H,">"&60,Accounts!$H:$H,"<="&180)/P61) -> 0 | Q62: =IF(Q61=0,0,SUMIFS(Accounts!$L:$L,Accounts!$E:$E,'AccountSummary (New)'!Q$1,Accounts!$G:$G,'AccountSummary (New)'!Q$2,Accounts!$F:$F,'AccountSummary (New)'!Q$3,Accounts!$W:$W,0,Accounts!$C:$C,"Customer",Accounts!$H:$H,">"&180)/Q61) -> 0 | R62: =IF(R61=0,0,SUMIFS(Accounts!$L:$L,Accounts!$E:$E,'AccountSummary (New)'!R$1,Accounts!$G:$G,'AccountSummary (New)'!R$2,Accounts!$F:$F,'AccountSummary (New)'!R$3,Accounts!$W:$W,0,Accounts!$C:$C,"Customer",Accounts!$H:$H,">"&180)/R61) -> 3 | S62: =IF(S61=0,0,SUMIFS(Accounts!$L:$L,Accounts!$E:$E,'AccountSummary (New)'!S$1,Accounts!$G:$G,'AccountSummary (New)'!S$2,Accounts!$F:$F,'AccountSummary (New)'!S$3,Accounts!$W:$W,0,Accounts!$C:$C,"Customer",Accounts!$H:$H,">"&180)/S61) -> 0 | T62: =IF(T61=0,0,SUMIFS(Accounts!$L:$L,Accounts!$E:$E,'AccountSummary (New)'!T$1,Accounts!$G:$G,'AccountSummary (New)'!T$2,Accounts!$F:$F,'AccountSummary (New)'!T$3,Accounts!$W:$W,0,Accounts!$C:$C,"Customer",Accounts!$H:$H,">"&180)/T61) -> 0 | U62: =IF(U61=0,0,SUMIFS(Accounts!$L:$L,Accounts!$E:$E,'AccountSummary (New)'!U$1,Accounts!$G:$G,'AccountSummary (New)'!U$2,Accounts!$F:$F,'AccountSummary (New)'!U$3,Accounts!$W:$W,0,Accounts!$C:$C,"Customer",Accounts!$H:$H,">"&180)/U61) -> 0 | V62: =IF(V61=0,0,SUMIFS(Accounts!$L:$L,Accounts!$E:$E,'AccountSummary (New)'!V$1,Accounts!$G:$G,'AccountSummary (New)'!V$2,Accounts!$F:$F,'AccountSummary (New)'!V$3,Accounts!$W:$W,0,Accounts!$C:$C,"Customer",Accounts!$H:$H,">"&180)/V61) -> 0 | W62: =IF(W61=0,0,SUMIFS(Accounts!$L:$L,Accounts!$F:$F,'AccountSummary (New)'!W$3,Accounts!$W:$W,0,Accounts!$C:$C,"Customer",Accounts!$H:$H,">"&60,Accounts!$H:$H,"<="&180)/W61) -> 0
A63: Users per Account | B63: =IF(B61=0,0,SUMIFS(Accounts!$M:$M,Accounts!$W:$W,0,Accounts!$C:$C,"Customer",Accounts!$H:$H,">"&180)/B61) -> 2 | C63: =IF(C61=0,0,SUMIFS(Accounts!$M:$M,Accounts!$E:$E,'AccountSummary (New)'!C$1,Accounts!$G:$G,'AccountSummary (New)'!C$2,Accounts!$F:$F,'AccountSummary (New)'!C$3,Accounts!$W:$W,0,Accounts!$C:$C,"Customer",Accounts!$H:$H,">"&180)/C61) -> 0 | D63: =IF(D61=0,0,SUMIFS(Accounts!$M:$M,Accounts!$E:$E,'AccountSummary (New)'!D$1,Accounts!$G:$G,'AccountSummary (New)'!D$2,Accounts!$F:$F,'AccountSummary (New)'!D$3,Accounts!$W:$W,0,Accounts!$C:$C,"Customer",Accounts!$H:$H,">"&180)/D61) -> 0 | E63: =IF(E61=0,0,SUMIFS(Accounts!$M:$M,Accounts!$E:$E,'AccountSummary (New)'!E$1,Accounts!$G:$G,'AccountSummary (New)'!E$2,Accounts!$F:$F,'AccountSummary (New)'!E$3,Accounts!$W:$W,0,Accounts!$C:$C,"Customer",Accounts!$H:$H,">"&180)/E61) -> 0 | F63: =IF(F61=0,0,SUMIFS(Accounts!$M:$M,Accounts!$E:$E,'AccountSummary (New)'!F$1,Accounts!$G:$G,'AccountSummary (New)'!F$2,Accounts!$F:$F,'AccountSummary (New)'!F$3,Accounts!$W:$W,0,Accounts!$C:$C,"Customer",Accounts!$H:$H,">"&180)/F61) -> 0 | G63: =IF(G61=0,0,SUMIFS(Accounts!$M:$M,Accounts!$E:$E,'AccountSummary (New)'!G$1,Accounts!$G:$G,'AccountSummary (New)'!G$2,Accounts!$F:$F,'AccountSummary (New)'!G$3,Accounts!$W:$W,0,Accounts!$C:$C,"Customer",Accounts!$H:$H,">"&180)/G61) -> 0 | H63: =IF(H61=0,0,SUMIFS(Accounts!$M:$M,Accounts!$E:$E,'AccountSummary (New)'!H$1,Accounts!$G:$G,'AccountSummary (New)'!H$2,Accounts!$F:$F,'AccountSummary (New)'!H$3,Accounts!$W:$W,0,Accounts!$C:$C,"Customer",Accounts!$H:$H,">"&180)/H61) -> 0 | I63: =IF(I61=0,0,SUMIFS(Accounts!$M:$M,Accounts!$F:$F,'AccountSummary (New)'!I$3,Accounts!$W:$W,0,Accounts!$C:$C,"Customer",Accounts!$H:$H,">"&60,Accounts!$H:$H,"<="&180)/I61) -> 0 | J63: =IF(J61=0,0,SUMIFS(Accounts!$M:$M,Accounts!$E:$E,'AccountSummary (New)'!J$1,Accounts!$G:$G,'AccountSummary (New)'!J$2,Accounts!$F:$F,'AccountSummary (New)'!J$3,Accounts!$W:$W,0,Accounts!$C:$C,"Customer",Accounts!$H:$H,">"&180)/J61) -> 0 | K63: =IF(K61=0,0,SUMIFS(Accounts!$M:$M,Accounts!$E:$E,'AccountSummary (New)'!K$1,Accounts!$G:$G,'AccountSummary (New)'!K$2,Accounts!$F:$F,'AccountSummary (New)'!K$3,Accounts!$W:$W,0,Accounts!$C:$C,"Customer",Accounts!$H:$H,">"&180)/K61) -> 0 | L63: =IF(L61=0,0,SUMIFS(Accounts!$M:$M,Accounts!$E:$E,'AccountSummary (New)'!L$1,Accounts!$G:$G,'AccountSummary (New)'!L$2,Accounts!$F:$F,'AccountSummary (New)'!L$3,Accounts!$W:$W,0,Accounts!$C:$C,"Customer",Accounts!$H:$H,">"&180)/L61) -> 0 | M63: =IF(M61=0,0,SUMIFS(Accounts!$M:$M,Accounts!$E:$E,'AccountSummary (New)'!M$1,Accounts!$G:$G,'AccountSummary (New)'!M$2,Accounts!$F:$F,'AccountSummary (New)'!M$3,Accounts!$W:$W,0,Accounts!$C:$C,"Customer",Accounts!$H:$H,">"&180)/M61) -> 0 | N63: =IF(N61=0,0,SUMIFS(Accounts!$M:$M,Accounts!$E:$E,'AccountSummary (New)'!N$1,Accounts!$G:$G,'AccountSummary (New)'!N$2,Accounts!$F:$F,'AccountSummary (New)'!N$3,Accounts!$W:$W,0,Accounts!$C:$C,"Customer",Accounts!$H:$H,">"&180)/N61) -> 0 | O63: =IF(O61=0,0,SUMIFS(Accounts!$M:$M,Accounts!$E:$E,'AccountSummary (New)'!O$1,Accounts!$G:$G,'AccountSummary (New)'!O$2,Accounts!$F:$F,'AccountSummary (New)'!O$3,Accounts!$W:$W,0,Accounts!$C:$C,"Customer",Accounts!$H:$H,">"&180)/O61) -> 0 | P63: =IF(P61=0,0,SUMIFS(Accounts!$M:$M,Accounts!$F:$F,'AccountSummary (New)'!P$3,Accounts!$W:$W,0,Accounts!$C:$C,"Customer",Accounts!$H:$H,">"&60,Accounts!$H:$H,"<="&180)/P61) -> 0 | Q63: =IF(Q61=0,0,SUMIFS(Accounts!$M:$M,Accounts!$E:$E,'AccountSummary (New)'!Q$1,Accounts!$G:$G,'AccountSummary (New)'!Q$2,Accounts!$F:$F,'AccountSummary (New)'!Q$3,Accounts!$W:$W,0,Accounts!$C:$C,"Customer",Accounts!$H:$H,">"&180)/Q61) -> 0 | R63: =IF(R61=0,0,SUMIFS(Accounts!$M:$M,Accounts!$E:$E,'AccountSummary (New)'!R$1,Accounts!$G:$G,'AccountSummary (New)'!R$2,Accounts!$F:$F,'AccountSummary (New)'!R$3,Accounts!$W:$W,0,Accounts!$C:$C,"Customer",Accounts!$H:$H,">"&180)/R61) -> 2 | S63: =IF(S61=0,0,SUMIFS(Accounts!$M:$M,Accounts!$E:$E,'AccountSummary (New)'!S$1,Accounts!$G:$G,'AccountSummary (New)'!S$2,Accounts!$F:$F,'AccountSummary (New)'!S$3,Accounts!$W:$W,0,Accounts!$C:$C,"Customer",Accounts!$H:$H,">"&180)/S61) -> 0 | T63: =IF(T61=0,0,SUMIFS(Accounts!$M:$M,Accounts!$E:$E,'AccountSummary (New)'!T$1,Accounts!$G:$G,'AccountSummary (New)'!T$2,Accounts!$F:$F,'AccountSummary (New)'!T$3,Accounts!$W:$W,0,Accounts!$C:$C,"Customer",Accounts!$H:$H,">"&180)/T61) -> 0 | U63: =IF(U61=0,0,SUMIFS(Accounts!$M:$M,Accounts!$E:$E,'AccountSummary (New)'!U$1,Accounts!$G:$G,'AccountSummary (New)'!U$2,Accounts!$F:$F,'AccountSummary (New)'!U$3,Accounts!$W:$W,0,Accounts!$C:$C,"Customer",Accounts!$H:$H,">"&180)/U61) -> 0 | V63: =IF(V61=0,0,SUMIFS(Accounts!$M:$M,Accounts!$E:$E,'AccountSummary (New)'!V$1,Accounts!$G:$G,'AccountSummary (New)'!V$2,Accounts!$F:$F,'AccountSummary (New)'!V$3,Accounts!$W:$W,0,Accounts!$C:$C,"Customer",Accounts!$H:$H,">"&180)/V61) -> 0 | W63: =IF(W61=0,0,SUMIFS(Accounts!$M:$M,Accounts!$F:$F,'AccountSummary (New)'!W$3,Accounts!$W:$W,0,Accounts!$C:$C,"Customer",Accounts!$H:$H,">"&60,Accounts!$H:$H,"<="&180)/W61) -> 0
A64: ARPC | B64: =IF(B61=0,0,B65/B61) -> 0 | C64: =IF(C61=0,0,C65/C61) -> 0 | D64: =IF(D61=0,0,D65/D61) -> 0 | E64: =IF(E61=0,0,E65/E61) -> 0 | F64: =IF(F61=0,0,F65/F61) -> 0 | G64: =IF(G61=0,0,G65/G61) -> 0 | H64: =IF(H61=0,0,H65/H61) -> 0 | I64: =IF(I61=0,0,I65/I61) -> 0 | ... W64: =IF(W61=0,0,W65/W61) -> 0
A65: SaaS | B65: =I65+P65+W65 -> 0 | C65: =SUMIFS(Accounts!$I:$I,Accounts!$E:$E,'AccountSummary (New)'!C$1,Accounts!$G:$G,'AccountSummary (New)'!C$2,Accounts!$F:$F,'AccountSummary (New)'!C$3,Accounts!$W:$W,0,Accounts!$C:$C,"Customer",Accounts!$C:$C,"Customer",Accounts!$H:$H,">"&180) -> 0 | D65: =SUMIFS(Accounts!$I:$I,Accounts!$E:$E,'AccountSummary (New)'!D$1,Accounts!$G:$G,'AccountSummary (New)'!D$2,Accounts!$F:$F,'AccountSummary (New)'!D$3,Accounts!$W:$W,0,Accounts!$C:$C,"Customer",Accounts!$C:$C,"Customer",Accounts!$H:$H,">"&180) -> 0 | E65: =SUMIFS(Accounts!$I:$I,Accounts!$E:$E,'AccountSummary (New)'!E$1,Accounts!$G:$G,'AccountSummary (New)'!E$2,Accounts!$F:$F,'AccountSummary (New)'!E$3,Accounts!$W:$W,0,Accounts!$C:$C,"Customer",Accounts!$C:$C,"Customer",Accounts!$H:$H,">"&180) -> 0 | F65: =SUMIFS(Accounts!$I:$I,Accounts!$E:$E,'AccountSummary (New)'!F$1,Accounts!$G:$G,'AccountSummary (New)'!F$2,Accounts!$F:$F,'AccountSummary (New)'!F$3,Accounts!$W:$W,0,Accounts!$C:$C,"Customer",Accounts!$C:$C,"Customer",Accounts!$H:$H,">"&180) -> 0 | G65: =SUMIFS(Accounts!$I:$I,Accounts!$E:$E,'AccountSummary (New)'!G$1,Accounts!$G:$G,'AccountSummary (New)'!G$2,Accounts!$F:$F,'AccountSummary (New)'!G$3,Accounts!$W:$W,0,Accounts!$C:$C,"Customer",Accounts!$C:$C,"Customer",Accounts!$H:$H,">"&180) -> 0 | H65: =SUMIFS(Accounts!$I:$I,Accounts!$E:$E,'AccountSummary (New)'!H$1,Accounts!$G:$G,'AccountSummary (New)'!H$2,Accounts!$F:$F,'AccountSummary (New)'!H$3,Accounts!$W:$W,0,Accounts!$C:$C,"Customer",Accounts!$C:$C,"Customer",Accounts!$H:$H,">"&180) -> 0 | I65: =SUM(C65:H65) -> 0 | J65: =SUMIFS(Accounts!$I:$I,Accounts!$E:$E,'AccountSummary (New)'!J$1,Accounts!$G:$G,'AccountSummary (New)'!J$2,Accounts!$F:$F,'AccountSummary (New)'!J$3,Accounts!$W:$W,0,Accounts!$C:$C,"Customer",Accounts!$C:$C,"Customer",Accounts!$H:$H,">"&180) -> 0 | K65: =SUMIFS(Accounts!$I:$I,Accounts!$E:$E,'AccountSummary (New)'!K$1,Accounts!$G:$G,'AccountSummary (New)'!K$2,Accounts!$F:$F,'AccountSummary (New)'!K$3,Accounts!$W:$W,0,Accounts!$C:$C,"Customer",Accounts!$C:$C,"Customer",Accounts!$H:$H,">"&180) -> 0 | L65: =SUMIFS(Accounts!$I:$I,Accounts!$E:$E,'AccountSummary (New)'!L$1,Accounts!$G:$G,'AccountSummary (New)'!L$2,Accounts!$F:$F,'AccountSummary (New)'!L$3,Accounts!$W:$W,0,Accounts!$C:$C,"Customer",Accounts!$C:$C,"Customer",Accounts!$H:$H,">"&180) -> 0 | M65: =SUMIFS(Accounts!$I:$I,Accounts!$E:$E,'AccountSummary (New)'!M$1,Accounts!$G:$G,'AccountSummary (New)'!M$2,Accounts!$F:$F,'AccountSummary (New)'!M$3,Accounts!$W:$W,0,Accounts!$C:$C,"Customer",Accounts!$C:$C,"Customer",Accounts!$H:$H,">"&180) -> 0 | N65: =SUMIFS(Accounts!$I:$I,Accounts!$E:$E,'AccountSummary (New)'!N$1,Accounts!$G:$G,'AccountSummary (New)'!N$2,Accounts!$F:$F,'AccountSummary (New)'!N$3,Accounts!$W:$W,0,Accounts!$C:$C,"Customer",Accounts!$C:$C,"Customer",Accounts!$H:$H,">"&180) -> 0 | O65: =SUMIFS(Accounts!$I:$I,Accounts!$E:$E,'AccountSummary (New)'!O$1,Accounts!$G:$G,'AccountSummary (New)'!O$2,Accounts!$F:$F,'AccountSummary (New)'!O$3,Accounts!$W:$W,0,Accounts!$C:$C,"Customer",Accounts!$C:$C,"Customer",Accounts!$H:$H,">"&180) -> 0 | P65: =SUM(J65:O65) -> 0 | Q65: =SUMIFS(Accounts!$I:$I,Accounts!$E:$E,'AccountSummary (New)'!Q$1,Accounts!$G:$G,'AccountSummary (New)'!Q$2,Accounts!$F:$F,'AccountSummary (New)'!Q$3,Accounts!$W:$W,0,Accounts!$C:$C,"Customer",Accounts!$C:$C,"Customer",Accounts!$H:$H,">"&180) -> 0 | R65: =SUMIFS(Accounts!$I:$I,Accounts!$E:$E,'AccountSummary (New)'!R$1,Accounts!$G:$G,'AccountSummary (New)'!R$2,Accounts!$F:$F,'AccountSummary (New)'!R$3,Accounts!$W:$W,0,Accounts!$C:$C,"Customer",Accounts!$C:$C,"Customer",Accounts!$H:$H,">"&180) -> 0 | S65: =SUMIFS(Accounts!$I:$I,Accounts!$E:$E,'AccountSummary (New)'!S$1,Accounts!$G:$G,'AccountSummary (New)'!S$2,Accounts!$F:$F,'AccountSummary (New)'!S$3,Accounts!$W:$W,0,Accounts!$C:$C,"Customer",Accounts!$C:$C,"Customer",Accounts!$H:$H,">"&180) -> 0 | T65: =SUMIFS(Accounts!$I:$I,Accounts!$E:$E,'AccountSummary (New)'!T$1,Accounts!$G:$G,'AccountSummary (New)'!T$2,Accounts!$F:$F,'AccountSummary (New)'!T$3,Accounts!$W:$W,0,Accounts!$C:$C,"Customer",Accounts!$C:$C,"Customer",Accounts!$H:$H,">"&180) -> 0 | U65: =SUMIFS(Accounts!$I:$I,Accounts!$E:$E,'AccountSummary (New)'!U$1,Accounts!$G:$G,'AccountSummary (New)'!U$2,Accounts!$F:$F,'AccountSummary (New)'!U$3,Accounts!$W:$W,0,Accounts!$C:$C,"Customer",Accounts!$C:$C,"Customer",Accounts!$H:$H,">"&180) -> 0 | V65: =SUMIFS(Accounts!$I:$I,Accounts!$E:$E,'AccountSummary (New)'!V$1,Accounts!$G:$G,'AccountSummary (New)'!V$2,Accounts!$F:$F,'AccountSummary (New)'!V$3,Accounts!$W:$W,0,Accounts!$C:$C,"Customer",Accounts!$C:$C,"Customer",Accounts!$H:$H,">"&180) -> 0 | W65: =SUM(Q65:V65) -> 0
A66: Total Lost Count | B66: =I66+P66+W66 -> 0 | C66: =C24+C33+C42+C51+C60 -> 0 | D66: =D24+D33+D42+D51+D60 -> 0 | E66: =E24+E33+E42+E51+E60 -> 0 | F66: =F24+F33+F42+F51+F60 -> 0 | G66: =G24+G33+G42+G51+G60 -> 0 | H66: =H24+H33+H42+H51+H60 -> 0 | I66: =SUM(C66:H66) -> 0 | J66: =J24+J33+J42+J51+J60 -> 0 | K66: =K24+K33+K42+K51+K60 -> 0 | L66: =L24+L33+L42+L60 -> 0 | M66: =M24+M33+M42+M51+M60 -> 0 | N66: =N24+N33+N42+N51+N60 -> 0 | O66: =O24+O33+O42+O51+O60 -> 0 | P66: =SUM(J66:O66) -> 0 | Q66: =Q24+Q33+Q42+Q51+Q60 -> 0 | R66: =R24+R33+R42+R51+R60 -> 0 | S66: =S24+S33+S42+S51+S60 -> 0 | T66: =T24+T33+T42+T51+T60 -> 0 | U66: =U24+U33+U42+U51+U60 -> 0 | V66: =V24+V33+V42+V51+V60 -> 0 | W66: =SUM(Q66:V66) -> 0
A67: Total Retained Count | B67: =I67+P67+W67 -> 1 | C67: =C25+C34+C43+C52+C61 -> 0 | D67: =D25+D34+D43+D52+D61 -> 0 | E67: =E25+E34+E43+E52+E61 -> 0 | F67: =F25+F34+F43+F52+F61 -> 0 | G67: =G25+G34+G43+G52+G61 -> 0 | H67: =H25+H34+H43+H52+H61 -> 0 | I67: =SUM(C67:H67) -> 0 | J67: =J25+J34+J43+J52+J61 -> 0 | K67: =K25+K34+K43+K52+K61 -> 0 | L67: =L25+L34+L43+L52+L61 -> 0 | M67: =M25+M34+M43+M52+M61 -> 0 | N67: =N25+N34+N43+N52+N61 -> 0 | O67: =O25+O34+O43+O52+O61 -> 0 | P67: =SUM(J67:O67) -> 0 | Q67: =Q25+Q34+Q43+Q52+Q61 -> 0 | R67: =R25+R34+R43+R52+R61 -> 1 | S67: =S25+S34+S43+S52+S61 -> 0 | T67: =T25+T34+T43+T52+T61 -> 0 | U67: =U25+U34+U43+U52+U61 -> 0 | V67: =V25+V34+V43+V52+V61 -> 0 | W67: =SUM(Q67:V67) -> 1
A68: SaaS from Retained Customers | B68: =I68+P68+W68 -> 0 | C68: =C29+C38+C47+C56+C65 -> 0 | D68: =D29+D38+D47+D56+D65 -> 0 | E68: =E29+E38+E47+E56+E65 -> 0 | F68: =F29+F38+F47+F56+F65 -> 0 | G68: =G29+G38+G47+G56+G65 -> 0 | H68: =H29+H38+H47+H56+H65 -> 0 | I68: =SUM(C68:H68) -> 0 | J68: =J29+J38+J47+J56+J65 -> 0 | K68: =K29+K38+K47+K56+K65 -> 0 | L68: =L29+L38+L47+L56+L65 -> 0 | M68: =M29+M38+M47+M56+M65 -> 0 | N68: =N29+N38+N47+N56+N65 -> 0 | O68: =O29+O38+O47+O56+O65 -> 0 | P68: =SUM(J68:O68) -> 0 | Q68: =Q29+Q38+Q47+Q56+Q65 -> 0 | R68: =R29+R38+R47+R56+R65 -> 0 | S68: =S29+S38+S47+S56+S65 -> 0 | T68: =T29+T38+T47+T56+T65 -> 0 | U68: =U29+U38+U47+U56+U65 -> 0 | V68: =V29+V38+V47+V56+V65 -> 0 | W68: =SUM(Q68:V68) -> 0
A70: Prepay % of Paying Customers | B70: =IF(B19=0,0,B71/B19) -> 0 | C70: =IF(C19=0,0,C71/C19) -> 0 | D70: =IF(D19=0,0,D71/D19) -> 0 | E70: =IF(E19=0,0,E71/E19) -> 0 | F70: =IF(F19=0,0,F71/F19) -> 0 | G70: =IF(G19=0,0,G71/G19) -> 0 | H70: =IF(H19=0,0,H71/H19) -> 0 | I70: =IF(I19=0,0,I71/I19) -> 0 | J70: =IF(J19=0,0,J71/J19) -> 0 | K70: =IF(K18=0,0,K71/K19) -> 0 | L70: =IF(L19=0,0,L71/L19) -> 0 | M70: =IF(M19=0,0,M71/M19) -> 0 | N70: =IF(N19=0,0,N71/N19) -> 0 | O70: =IF(O19=0,0,O71/O19) -> 0 | P70: =IF(P19=0,0,P71/P19) -> 0 | Q70: =IF(Q19=0,0,Q71/Q19) -> 0 | R70: =IF(R19=0,0,R71/R19) -> 0 | S70: =IF(S19=0,0,S71/S19) -> 0 | ... W70: =IF(W19=0,0,W71/W19) -> 0
A71: Prepay Starting Count BOM | B71: =I71+P71+W71 -> 0 | C71: =COUNTIFS(Accounts!$E:$E,'AccountSummary (New)'!C$1,Accounts!$G:$G,'AccountSummary (New)'!C$2,Accounts!$F:$F,'AccountSummary (New)'!C$3,Accounts!$B:$B,"Customer",Accounts!$D:$D,"Prepay") -> 0 | D71: =COUNTIFS(Accounts!$E:$E,'AccountSummary (New)'!D$1,Accounts!$G:$G,'AccountSummary (New)'!D$2,Accounts!$F:$F,'AccountSummary (New)'!D$3,Accounts!$B:$B,"Customer",Accounts!$D:$D,"Prepay") -> 0 | E71: =COUNTIFS(Accounts!$E:$E,'AccountSummary (New)'!E$1,Accounts!$G:$G,'AccountSummary (New)'!E$2,Accounts!$F:$F,'AccountSummary (New)'!E$3,Accounts!$B:$B,"Customer",Accounts!$D:$D,"Prepay") -> 0 | F71: =COUNTIFS(Accounts!$E:$E,'AccountSummary (New)'!F$1,Accounts!$G:$G,'AccountSummary (New)'!F$2,Accounts!$F:$F,'AccountSummary (New)'!F$3,Accounts!$B:$B,"Customer",Accounts!$D:$D,"Prepay") -> 0 | G71: =COUNTIFS(Accounts!$E:$E,'AccountSummary (New)'!G$1,Accounts!$G:$G,'AccountSummary (New)'!G$2,Accounts!$F:$F,'AccountSummary (New)'!G$3,Accounts!$B:$B,"Customer",Accounts!$D:$D,"Prepay") -> 0 | H71: =COUNTIFS(Accounts!$E:$E,'AccountSummary (New)'!H$1,Accounts!$G:$G,'AccountSummary (New)'!H$2,Accounts!$F:$F,'AccountSummary (New)'!H$3,Accounts!$B:$B,"Customer",Accounts!$D:$D,"Prepay") -> 0 | I71: =SUM(C71:H71) -> 0 | J71: =COUNTIFS(Accounts!$E:$E,'AccountSummary (New)'!J$1,Accounts!$G:$G,'AccountSummary (New)'!J$2,Accounts!$F:$F,'AccountSummary (New)'!J$3,Accounts!$B:$B,"Customer",Accounts!$D:$D,"Prepay") -> 0 | K71: =COUNTIFS(Accounts!$E:$E,'AccountSummary (New)'!K$1,Accounts!$G:$G,'AccountSummary (New)'!K$2,Accounts!$F:$F,'AccountSummary (New)'!K$3,Accounts!$B:$B,"Customer",Accounts!$D:$D,"Prepay") -> 0 | L71: =COUNTIFS(Accounts!$E:$E,'AccountSummary (New)'!L$1,Accounts!$G:$G,'AccountSummary (New)'!L$2,Accounts!$F:$F,'AccountSummary (New)'!L$3,Accounts!$B:$B,"Customer",Accounts!$D:$D,"Prepay") -> 0 | M71: =COUNTIFS(Accounts!$E:$E,'AccountSummary (New)'!M$1,Accounts!$G:$G,'AccountSummary (New)'!M$2,Accounts!$F:$F,'AccountSummary (New)'!M$3,Accounts!$B:$B,"Customer",Accounts!$D:$D,"Prepay") -> 0 | N71: =COUNTIFS(Accounts!$E:$E,'AccountSummary (New)'!N$1,Accounts!$G:$G,'AccountSummary (New)'!N$2,Accounts!$F:$F,'AccountSummary (New)'!N$3,Accounts!$B:$B,"Customer",Accounts!$D:$D,"Prepay") -> 0 | O71: =COUNTIFS(Accounts!$E:$E,'AccountSummary (New)'!O$1,Accounts!$G:$G,'AccountSummary (New)'!O$2,Accounts!$F:$F,'AccountSummary (New)'!O$3,Accounts!$B:$B,"Customer",Accounts!$D:$D,"Prepay") -> 0 | P71: =SUM(J71:O71) -> 0 | Q71: =COUNTIFS(Accounts!$E:$E,'AccountSummary (New)'!Q$1,Accounts!$G:$G,'AccountSummary (New)'!Q$2,Accounts!$F:$F,'AccountSummary (New)'!Q$3,Accounts!$B:$B,"Customer",Accounts!$D:$D,"Prepay") -> 0 | R71: =COUNTIFS(Accounts!$E:$E,'AccountSummary (New)'!R$1,Accounts!$G:$G,'AccountSummary (New)'!R$2,Accounts!$F:$F,'AccountSummary (New)'!R$3,Accounts!$B:$B,"Customer",Accounts!$D:$D,"Prepay") -> 0 | S71: =COUNTIFS(Accounts!$E:$E,'AccountSummary (New)'!S$1,Accounts!$G:$G,'AccountSummary (New)'!S$2,Accounts!$F:$F,'AccountSummary (New)'!S$3,Accounts!$B:$B,"Customer",Accounts!$D:$D,"Prepay") -> 0 | T71: =COUNTIFS(Accounts!$E:$E,'AccountSummary (New)'!T$1,Accounts!$G:$G,'AccountSummary (New)'!T$2,Accounts!$F:$F,'AccountSummary (New)'!T$3,Accounts!$B:$B,"Customer",Accounts!$D:$D,"Prepay") -> 0 | U71: =COUNTIFS(Accounts!$E:$E,'AccountSummary (New)'!U$1,Accounts!$G:$G,'AccountSummary (New)'!U$2,Accounts!$F:$F,'AccountSummary (New)'!U$3,Accounts!$B:$B,"Customer",Accounts!$D:$D,"Prepay") -> 0 | V71: =COUNTIFS(Accounts!$E:$E,'AccountSummary (New)'!V$1,Accounts!$G:$G,'AccountSummary (New)'!V$2,Accounts!$F:$F,'AccountSummary (New)'!V$3,Accounts!$B:$B,"Customer",Accounts!$D:$D,"Prepay") -> 0 | W71: =SUM(Q71:V71) -> 0
A72: Prepay Loss % | B72: =IF(B71=0,0,B73/B71) -> 0 | C72: =IF(C71=0,0,C73/C71) -> 0 | D72: =IF(D71=0,0,D73/D71) -> 0 | E72: =IF(E71=0,0,E73/E71) -> 0 | F72: =IF(F71=0,0,F73/F71) -> 0 | G72: =IF(G71=0,0,G73/G71) -> 0 | H72: =IF(H71=0,0,H73/H71) -> 0 | I72: =IF(I71=0,0,I73/I71) -> 0 | ... W72: =IF(W71=0,0,W73/W71) -> 0
A73: Prepay Total Lost | B73: =I73+P73+W73 -> 0 | C73: =COUNTIFS(Accounts!$E:$E,'AccountSummary (New)'!C$1,Accounts!$G:$G,'AccountSummary (New)'!C$2,Accounts!$F:$F,'AccountSummary (New)'!C$3,Accounts!$B:$B,"Customer",Accounts!$D:$D,"Prepay",Accounts!$C:$C,"Lost") -> 0 | D73: =COUNTIFS(Accounts!$E:$E,'AccountSummary (New)'!D$1,Accounts!$G:$G,'AccountSummary (New)'!D$2,Accounts!$F:$F,'AccountSummary (New)'!D$3,Accounts!$B:$B,"Customer",Accounts!$D:$D,"Prepay",Accounts!$C:$C,"Lost") -> 0 | E73: =COUNTIFS(Accounts!$E:$E,'AccountSummary (New)'!E$1,Accounts!$G:$G,'AccountSummary (New)'!E$2,Accounts!$F:$F,'AccountSummary (New)'!E$3,Accounts!$B:$B,"Customer",Accounts!$D:$D,"Prepay",Accounts!$C:$C,"Lost") -> 0 | F73: =COUNTIFS(Accounts!$E:$E,'AccountSummary (New)'!F$1,Accounts!$G:$G,'AccountSummary (New)'!F$2,Accounts!$F:$F,'AccountSummary (New)'!F$3,Accounts!$B:$B,"Customer",Accounts!$D:$D,"Prepay",Accounts!$C:$C,"Lost") -> 0 | G73: =COUNTIFS(Accounts!$E:$E,'AccountSummary (New)'!G$1,Accounts!$G:$G,'AccountSummary (New)'!G$2,Accounts!$F:$F,'AccountSummary (New)'!G$3,Accounts!$B:$B,"Customer",Accounts!$D:$D,"Prepay",Accounts!$C:$C,"Lost") -> 0 | H73: =COUNTIFS(Accounts!$E:$E,'AccountSummary (New)'!H$1,Accounts!$G:$G,'AccountSummary (New)'!H$2,Accounts!$F:$F,'AccountSummary (New)'!H$3,Accounts!$B:$B,"Customer",Accounts!$D:$D,"Prepay",Accounts!$C:$C,"Lost") -> 0 | I73: =SUM(C73:H73) -> 0 | J73: =COUNTIFS(Accounts!$E:$E,'AccountSummary (New)'!J$1,Accounts!$G:$G,'AccountSummary (New)'!J$2,Accounts!$F:$F,'AccountSummary (New)'!J$3,Accounts!$B:$B,"Customer",Accounts!$D:$D,"Prepay",Accounts!$C:$C,"Lost") -> 0 | K73: =COUNTIFS(Accounts!$E:$E,'AccountSummary (New)'!K$1,Accounts!$G:$G,'AccountSummary (New)'!K$2,Accounts!$F:$F,'AccountSummary (New)'!K$3,Accounts!$B:$B,"Customer",Accounts!$D:$D,"Prepay",Accounts!$C:$C,"Lost") -> 0 | L73: =COUNTIFS(Accounts!$E:$E,'AccountSummary (New)'!L$1,Accounts!$G:$G,'AccountSummary (New)'!L$2,Accounts!$F:$F,'AccountSummary (New)'!L$3,Accounts!$B:$B,"Customer",Accounts!$D:$D,"Prepay",Accounts!$C:$C,"Lost") -> 0 | M73: =COUNTIFS(Accounts!$E:$E,'AccountSummary (New)'!M$1,Accounts!$G:$G,'AccountSummary (New)'!M$2,Accounts!$F:$F,'AccountSummary (New)'!M$3,Accounts!$B:$B,"Customer",Accounts!$D:$D,"Prepay",Accounts!$C:$C,"Lost") -> 0 | N73: =COUNTIFS(Accounts!$E:$E,'AccountSummary (New)'!N$1,Accounts!$G:$G,'AccountSummary (New)'!N$2,Accounts!$F:$F,'AccountSummary (New)'!N$3,Accounts!$B:$B,"Customer",Accounts!$D:$D,"Prepay",Accounts!$C:$C,"Lost") -> 0 | O73: =COUNTIFS(Accounts!$E:$E,'AccountSummary (New)'!O$1,Accounts!$G:$G,'AccountSummary (New)'!O$2,Accounts!$F:$F,'AccountSummary (New)'!O$3,Accounts!$B:$B,"Customer",Accounts!$D:$D,"Prepay",Accounts!$C:$C,"Lost") -> 0 | P73: =SUM(J73:O73) -> 0 | Q73: =COUNTIFS(Accounts!$E:$E,'AccountSummary (New)'!Q$1,Accounts!$G:$G,'AccountSummary (New)'!Q$2,Accounts!$F:$F,'AccountSummary (New)'!Q$3,Accounts!$B:$B,"Customer",Accounts!$D:$D,"Prepay",Accounts!$C:$C,"Lost") -> 0 | R73: =COUNTIFS(Accounts!$E:$E,'AccountSummary (New)'!R$1,Accounts!$G:$G,'AccountSummary (New)'!R$2,Accounts!$F:$F,'AccountSummary (New)'!R$3,Accounts!$B:$B,"Customer",Accounts!$D:$D,"Prepay",Accounts!$C:$C,"Lost") -> 0 | S73: =COUNTIFS(Accounts!$E:$E,'AccountSummary (New)'!S$1,Accounts!$G:$G,'AccountSummary (New)'!S$2,Accounts!$F:$F,'AccountSummary (New)'!S$3,Accounts!$B:$B,"Customer",Accounts!$D:$D,"Prepay",Accounts!$C:$C,"Lost") -> 0 | T73: =COUNTIFS(Accounts!$E:$E,'AccountSummary (New)'!T$1,Accounts!$G:$G,'AccountSummary (New)'!T$2,Accounts!$F:$F,'AccountSummary (New)'!T$3,Accounts!$B:$B,"Customer",Accounts!$D:$D,"Prepay",Accounts!$C:$C,"Lost") -> 0 | U73: =COUNTIFS(Accounts!$E:$E,'AccountSummary (New)'!U$1,Accounts!$G:$G,'AccountSummary (New)'!U$2,Accounts!$F:$F,'AccountSummary (New)'!U$3,Accounts!$B:$B,"Customer",Accounts!$D:$D,"Prepay",Accounts!$C:$C,"Lost") -> 0 | V73: =COUNTIFS(Accounts!$E:$E,'AccountSummary (New)'!V$1,Accounts!$G:$G,'AccountSummary (New)'!V$2,Accounts!$F:$F,'AccountSummary (New)'!V$3,Accounts!$B:$B,"Customer",Accounts!$D:$D,"Prepay",Accounts!$C:$C,"Lost") -> 0 | W73: =SUM(Q73:V73) -> 0
A74: Prepay Retained | B74: =I74+P74+W74 -> 0 | C74: =COUNTIFS(Accounts!$E:$E,'AccountSummary (New)'!C$1,Accounts!$G:$G,'AccountSummary (New)'!C$2,Accounts!$F:$F,'AccountSummary (New)'!C$3,Accounts!$B:$B,"Customer",Accounts!$D:$D,"Prepay",Accounts!$C:$C,"Customer") -> 0 | D74: =COUNTIFS(Accounts!$E:$E,'AccountSummary (New)'!D$1,Accounts!$G:$G,'AccountSummary (New)'!D$2,Accounts!$F:$F,'AccountSummary (New)'!D$3,Accounts!$B:$B,"Customer",Accounts!$D:$D,"Prepay",Accounts!$C:$C,"Customer") -> 0 | E74: =COUNTIFS(Accounts!$E:$E,'AccountSummary (New)'!E$1,Accounts!$G:$G,'AccountSummary (New)'!E$2,Accounts!$F:$F,'AccountSummary (New)'!E$3,Accounts!$B:$B,"Customer",Accounts!$D:$D,"Prepay",Accounts!$C:$C,"Customer") -> 0 | F74: =COUNTIFS(Accounts!$E:$E,'AccountSummary (New)'!F$1,Accounts!$G:$G,'AccountSummary (New)'!F$2,Accounts!$F:$F,'AccountSummary (New)'!F$3,Accounts!$B:$B,"Customer",Accounts!$D:$D,"Prepay",Accounts!$C:$C,"Customer") -> 0 | G74: =COUNTIFS(Accounts!$E:$E,'AccountSummary (New)'!G$1,Accounts!$G:$G,'AccountSummary (New)'!G$2,Accounts!$F:$F,'AccountSummary (New)'!G$3,Accounts!$B:$B,"Customer",Accounts!$D:$D,"Prepay",Accounts!$C:$C,"Customer") -> 0 | H74: =COUNTIFS(Accounts!$E:$E,'AccountSummary (New)'!H$1,Accounts!$G:$G,'AccountSummary (New)'!H$2,Accounts!$F:$F,'AccountSummary (New)'!H$3,Accounts!$B:$B,"Customer",Accounts!$D:$D,"Prepay",Accounts!$C:$C,"Customer") -> 0 | I74: =SUM(C74:H74) -> 0 | J74: =COUNTIFS(Accounts!$E:$E,'AccountSummary (New)'!J$1,Accounts!$G:$G,'AccountSummary (New)'!J$2,Accounts!$F:$F,'AccountSummary (New)'!J$3,Accounts!$B:$B,"Customer",Accounts!$D:$D,"Prepay",Accounts!$C:$C,"Customer") -> 0 | K74: =COUNTIFS(Accounts!$E:$E,'AccountSummary (New)'!K$1,Accounts!$G:$G,'AccountSummary (New)'!K$2,Accounts!$F:$F,'AccountSummary (New)'!K$3,Accounts!$B:$B,"Customer",Accounts!$D:$D,"Prepay",Accounts!$C:$C,"Customer") -> 0 | L74: =COUNTIFS(Accounts!$E:$E,'AccountSummary (New)'!L$1,Accounts!$G:$G,'AccountSummary (New)'!L$2,Accounts!$F:$F,'AccountSummary (New)'!L$3,Accounts!$B:$B,"Customer",Accounts!$D:$D,"Prepay",Accounts!$C:$C,"Customer") -> 0 | M74: =COUNTIFS(Accounts!$E:$E,'AccountSummary (New)'!M$1,Accounts!$G:$G,'AccountSummary (New)'!M$2,Accounts!$F:$F,'AccountSummary (New)'!M$3,Accounts!$B:$B,"Customer",Accounts!$D:$D,"Prepay",Accounts!$C:$C,"Customer") -> 0 | N74: =COUNTIFS(Accounts!$E:$E,'AccountSummary (New)'!N$1,Accounts!$G:$G,'AccountSummary (New)'!N$2,Accounts!$F:$F,'AccountSummary (New)'!N$3,Accounts!$B:$B,"Customer",Accounts!$D:$D,"Prepay",Accounts!$C:$C,"Customer") -> 0 | O74: =COUNTIFS(Accounts!$E:$E,'AccountSummary (New)'!O$1,Accounts!$G:$G,'AccountSummary (New)'!O$2,Accounts!$F:$F,'AccountSummary (New)'!O$3,Accounts!$B:$B,"Customer",Accounts!$D:$D,"Prepay",Accounts!$C:$C,"Customer") -> 0 | P74: =SUM(J74:O74) -> 0 | Q74: =COUNTIFS(Accounts!$E:$E,'AccountSummary (New)'!Q$1,Accounts!$G:$G,'AccountSummary (New)'!Q$2,Accounts!$F:$F,'AccountSummary (New)'!Q$3,Accounts!$B:$B,"Customer",Accounts!$D:$D,"Prepay",Accounts!$C:$C,"Customer") -> 0 | R74: =COUNTIFS(Accounts!$E:$E,'AccountSummary (New)'!R$1,Accounts!$G:$G,'AccountSummary (New)'!R$2,Accounts!$F:$F,'AccountSummary (New)'!R$3,Accounts!$B:$B,"Customer",Accounts!$D:$D,"Prepay",Accounts!$C:$C,"Customer") -> 0 | S74: =COUNTIFS(Accounts!$E:$E,'AccountSummary (New)'!S$1,Accounts!$G:$G,'AccountSummary (New)'!S$2,Accounts!$F:$F,'AccountSummary (New)'!S$3,Accounts!$B:$B,"Customer",Accounts!$D:$D,"Prepay",Accounts!$C:$C,"Customer") -> 0 | T74: =COUNTIFS(Accounts!$E:$E,'AccountSummary (New)'!T$1,Accounts!$G:$G,'AccountSummary (New)'!T$2,Accounts!$F:$F,'AccountSummary (New)'!T$3,Accounts!$B:$B,"Customer",Accounts!$D:$D,"Prepay",Accounts!$C:$C,"Customer") -> 0 | U74: =COUNTIFS(Accounts!$E:$E,'AccountSummary (New)'!U$1,Accounts!$G:$G,'AccountSummary (New)'!U$2,Accounts!$F:$F,'AccountSummary (New)'!U$3,Accounts!$B:$B,"Customer",Accounts!$D:$D,"Prepay",Accounts!$C:$C,"Customer") -> 0 | V74: =COUNTIFS(Accounts!$E:$E,'AccountSummary (New)'!V$1,Accounts!$G:$G,'AccountSummary (New)'!V$2,Accounts!$F:$F,'AccountSummary (New)'!V$3,Accounts!$B:$B,"Customer",Accounts!$D:$D,"Prepay",Accounts!$C:$C,"Customer") -> 0 | W74: =SUM(Q74:V74) -> 0
A75: Packs per Account | B75: =IF(B74=0,0,SUMIFS(Accounts!$L:$L,Accounts!$W:$W,0,Accounts!$C:$C,"Customer",Accounts!$D:$D,"Prepay")/B74) -> 0 | C75: =IF(C74=0,0,SUMIFS(Accounts!$L:$L,Accounts!$E:$E,'AccountSummary (New)'!C$1,Accounts!$G:$G,'AccountSummary (New)'!C$2,Accounts!$F:$F,'AccountSummary (New)'!C$3,Accounts!$W:$W,0,Accounts!$C:$C,"Customer",Accounts!$D:$D,"Prepay")/C74) -> 0 | D75: =IF(D74=0,0,SUMIFS(Accounts!$L:$L,Accounts!$E:$E,'AccountSummary (New)'!D$1,Accounts!$G:$G,'AccountSummary (New)'!D$2,Accounts!$F:$F,'AccountSummary (New)'!D$3,Accounts!$W:$W,0,Accounts!$C:$C,"Customer",Accounts!$D:$D,"Prepay")/D74) -> 0 | E75: =IF(E74=0,0,SUMIFS(Accounts!$L:$L,Accounts!$E:$E,'AccountSummary (New)'!E$1,Accounts!$G:$G,'AccountSummary (New)'!E$2,Accounts!$F:$F,'AccountSummary (New)'!E$3,Accounts!$W:$W,0,Accounts!$C:$C,"Customer",Accounts!$D:$D,"Prepay")/E74) -> 0 | F75: =IF(F74=0,0,SUMIFS(Accounts!$L:$L,Accounts!$E:$E,'AccountSummary (New)'!F$1,Accounts!$G:$G,'AccountSummary (New)'!F$2,Accounts!$F:$F,'AccountSummary (New)'!F$3,Accounts!$W:$W,0,Accounts!$C:$C,"Customer",Accounts!$D:$D,"Prepay")/F74) -> 0 | G75: =IF(G74=0,0,SUMIFS(Accounts!$L:$L,Accounts!$E:$E,'AccountSummary (New)'!G$1,Accounts!$G:$G,'AccountSummary (New)'!G$2,Accounts!$F:$F,'AccountSummary (New)'!G$3,Accounts!$W:$W,0,Accounts!$C:$C,"Customer",Accounts!$D:$D,"Prepay")/G74) -> 0 | H75: =IF(H74=0,0,SUMIFS(Accounts!$L:$L,Accounts!$E:$E,'AccountSummary (New)'!H$1,Accounts!$G:$G,'AccountSummary (New)'!H$2,Accounts!$F:$F,'AccountSummary (New)'!H$3,Accounts!$W:$W,0,Accounts!$C:$C,"Customer",Accounts!$D:$D,"Prepay")/H74) -> 0 | I75: =IF(I74=0,0,SUMIFS(Accounts!$L:$L,Accounts!$F:$F,'AccountSummary (New)'!I$3,Accounts!$W:$W,0,Accounts!$C:$C,"Customer",Accounts!$D:$D,"Prepay")/I74) -> 0 | J75: =IF(J74=0,0,SUMIFS(Accounts!$L:$L,Accounts!$E:$E,'AccountSummary (New)'!J$1,Accounts!$G:$G,'AccountSummary (New)'!J$2,Accounts!$F:$F,'AccountSummary (New)'!J$3,Accounts!$W:$W,0,Accounts!$C:$C,"Customer",Accounts!$D:$D,"Prepay")/J74) -> 0 | K75: =IF(K74=0,0,SUMIFS(Accounts!$L:$L,Accounts!$E:$E,'AccountSummary (New)'!K$1,Accounts!$G:$G,'AccountSummary (New)'!K$2,Accounts!$F:$F,'AccountSummary (New)'!K$3,Accounts!$W:$W,0,Accounts!$C:$C,"Customer",Accounts!$D:$D,"Prepay")/K74) -> 0 | L75: =IF(L74=0,0,SUMIFS(Accounts!$L:$L,Accounts!$E:$E,'AccountSummary (New)'!L$1,Accounts!$G:$G,'AccountSummary (New)'!L$2,Accounts!$F:$F,'AccountSummary (New)'!L$3,Accounts!$W:$W,0,Accounts!$C:$C,"Customer",Accounts!$D:$D,"Prepay")/L74) -> 0 | M75: =IF(M74=0,0,SUMIFS(Accounts!$L:$L,Accounts!$E:$E,'AccountSummary (New)'!M$1,Accounts!$G:$G,'AccountSummary (New)'!M$2,Accounts!$F:$F,'AccountSummary (New)'!M$3,Accounts!$W:$W,0,Accounts!$C:$C,"Customer",Accounts!$D:$D,"Prepay")/M74) -> 0 | N75: =IF(N74=0,0,SUMIFS(Accounts!$L:$L,Accounts!$E:$E,'AccountSummary (New)'!N$1,Accounts!$G:$G,'AccountSummary (New)'!N$2,Accounts!$F:$F,'AccountSummary (New)'!N$3,Accounts!$W:$W,0,Accounts!$C:$C,"Customer",Accounts!$D:$D,"Prepay")/N74) -> 0 | O75: =IF(O74=0,0,SUMIFS(Accounts!$L:$L,Accounts!$E:$E,'AccountSummary (New)'!O$1,Accounts!$G:$G,'AccountSummary (New)'!O$2,Accounts!$F:$F,'AccountSummary (New)'!O$3,Accounts!$W:$W,0,Accounts!$C:$C,"Customer",Accounts!$D:$D,"Prepay")/O74) -> 0 | P75: =IF(P74=0,0,SUMIFS(Accounts!$L:$L,Accounts!$F:$F,'AccountSummary (New)'!P$3,Accounts!$W:$W,0,Accounts!$C:$C,"Customer",Accounts!$D:$D,"Prepay")/P74) -> 0 | Q75: =IF(Q74=0,0,SUMIFS(Accounts!$L:$L,Accounts!$E:$E,'AccountSummary (New)'!Q$1,Accounts!$G:$G,'AccountSummary (New)'!Q$2,Accounts!$F:$F,'AccountSummary (New)'!Q$3,Accounts!$W:$W,0,Accounts!$C:$C,"Customer",Accounts!$D:$D,"Prepay")/Q74) -> 0 | R75: =IF(R74=0,0,SUMIFS(Accounts!$L:$L,Accounts!$E:$E,'AccountSummary (New)'!R$1,Accounts!$G:$G,'AccountSummary (New)'!R$2,Accounts!$F:$F,'AccountSummary (New)'!R$3,Accounts!$W:$W,0,Accounts!$C:$C,"Customer",Accounts!$D:$D,"Prepay")/R74) -> 0 | S75: =IF(S74=0,0,SUMIFS(Accounts!$L:$L,Accounts!$E:$E,'AccountSummary (New)'!S$1,Accounts!$G:$G,'AccountSummary (New)'!S$2,Accounts!$F:$F,'AccountSummary (New)'!S$3,Accounts!$W:$W,0,Accounts!$C:$C,"Customer",Accounts!$D:$D,"Prepay")/S74) -> 0 | T75: =IF(T74=0,0,SUMIFS(Accounts!$L:$L,Accounts!$E:$E,'AccountSummary (New)'!T$1,Accounts!$G:$G,'AccountSummary (New)'!T$2,Accounts!$F:$F,'AccountSummary (New)'!T$3,Accounts!$W:$W,0,Accounts!$C:$C,"Customer",Accounts!$D:$D,"Prepay")/T74) -> 0 | U75: =IF(U74=0,0,SUMIFS(Accounts!$L:$L,Accounts!$E:$E,'AccountSummary (New)'!U$1,Accounts!$G:$G,'AccountSummary (New)'!U$2,Accounts!$F:$F,'AccountSummary (New)'!U$3,Accounts!$W:$W,0,Accounts!$C:$C,"Customer",Accounts!$D:$D,"Prepay")/U74) -> 0 | V75: =IF(V74=0,0,SUMIFS(Accounts!$L:$L,Accounts!$E:$E,'AccountSummary (New)'!V$1,Accounts!$G:$G,'AccountSummary (New)'!V$2,Accounts!$F:$F,'AccountSummary (New)'!V$3,Accounts!$W:$W,0,Accounts!$C:$C,"Customer",Accounts!$D:$D,"Prepay")/V74) -> 0 | W75: =IF(W74=0,0,SUMIFS(Accounts!$L:$L,Accounts!$F:$F,'AccountSummary (New)'!W$3,Accounts!$W:$W,0,Accounts!$C:$C,"Customer",Accounts!$D:$D,"Prepay")/W74) -> 0
A76: Users per Account | B76: =IF(B74=0,0,SUMIFS(Accounts!$M:$M,Accounts!$W:$W,0,Accounts!$C:$C,"Customer",Accounts!$D:$D,"Prepay")/B74) -> 0 | C76: =IF(C74=0,0,SUMIFS(Accounts!$M:$M,Accounts!$E:$E,'AccountSummary (New)'!C$1,Accounts!$G:$G,'AccountSummary (New)'!C$2,Accounts!$F:$F,'AccountSummary (New)'!C$3,Accounts!$W:$W,0,Accounts!$C:$C,"Customer",Accounts!$D:$D,"Prepay")/C74) -> 0 | D76: =IF(D74=0,0,SUMIFS(Accounts!$M:$M,Accounts!$E:$E,'AccountSummary (New)'!D$1,Accounts!$G:$G,'AccountSummary (New)'!D$2,Accounts!$F:$F,'AccountSummary (New)'!D$3,Accounts!$W:$W,0,Accounts!$C:$C,"Customer",Accounts!$D:$D,"Prepay")/D74) -> 0 | E76: =IF(E74=0,0,SUMIFS(Accounts!$M:$M,Accounts!$E:$E,'AccountSummary (New)'!E$1,Accounts!$G:$G,'AccountSummary (New)'!E$2,Accounts!$F:$F,'AccountSummary (New)'!E$3,Accounts!$W:$W,0,Accounts!$C:$C,"Customer",Accounts!$D:$D,"Prepay")/E74) -> 0 | F76: =IF(F74=0,0,SUMIFS(Accounts!$M:$M,Accounts!$E:$E,'AccountSummary (New)'!F$1,Accounts!$G:$G,'AccountSummary (New)'!F$2,Accounts!$F:$F,'AccountSummary (New)'!F$3,Accounts!$W:$W,0,Accounts!$C:$C,"Customer",Accounts!$D:$D,"Prepay")/F74) -> 0 | G76: =IF(G74=0,0,SUMIFS(Accounts!$M:$M,Accounts!$E:$E,'AccountSummary (New)'!G$1,Accounts!$G:$G,'AccountSummary (New)'!G$2,Accounts!$F:$F,'AccountSummary (New)'!G$3,Accounts!$W:$W,0,Accounts!$C:$C,"Customer",Accounts!$D:$D,"Prepay")/G74) -> 0 | H76: =IF(H74=0,0,SUMIFS(Accounts!$M:$M,Accounts!$E:$E,'AccountSummary (New)'!H$1,Accounts!$G:$G,'AccountSummary (New)'!H$2,Accounts!$F:$F,'AccountSummary (New)'!H$3,Accounts!$W:$W,0,Accounts!$C:$C,"Customer",Accounts!$D:$D,"Prepay")/H74) -> 0 | I76: =IF(I74=0,0,SUMIFS(Accounts!$M:$M,Accounts!$F:$F,'AccountSummary (New)'!I$3,Accounts!$W:$W,0,Accounts!$C:$C,"Customer",Accounts!$D:$D,"Prepay")/I74) -> 0 | J76: =IF(J74=0,0,SUMIFS(Accounts!$M:$M,Accounts!$E:$E,'AccountSummary (New)'!J$1,Accounts!$G:$G,'AccountSummary (New)'!J$2,Accounts!$F:$F,'AccountSummary (New)'!J$3,Accounts!$W:$W,0,Accounts!$C:$C,"Customer",Accounts!$D:$D,"Prepay")/J74) -> 0 | K76: =IF(K74=0,0,SUMIFS(Accounts!$M:$M,Accounts!$E:$E,'AccountSummary (New)'!K$1,Accounts!$G:$G,'AccountSummary (New)'!K$2,Accounts!$F:$F,'AccountSummary (New)'!K$3,Accounts!$W:$W,0,Accounts!$C:$C,"Customer",Accounts!$D:$D,"Prepay")/K74) -> 0 | L76: =IF(L74=0,0,SUMIFS(Accounts!$M:$M,Accounts!$E:$E,'AccountSummary (New)'!L$1,Accounts!$G:$G,'AccountSummary (New)'!L$2,Accounts!$F:$F,'AccountSummary (New)'!L$3,Accounts!$W:$W,0,Accounts!$C:$C,"Customer",Accounts!$D:$D,"Prepay")/L74) -> 0 | M76: =IF(M74=0,0,SUMIFS(Accounts!$M:$M,Accounts!$E:$E,'AccountSummary (New)'!M$1,Accounts!$G:$G,'AccountSummary (New)'!M$2,Accounts!$F:$F,'AccountSummary (New)'!M$3,Accounts!$W:$W,0,Accounts!$C:$C,"Customer",Accounts!$D:$D,"Prepay")/M74) -> 0 | N76: =IF(N74=0,0,SUMIFS(Accounts!$M:$M,Accounts!$E:$E,'AccountSummary (New)'!N$1,Accounts!$G:$G,'AccountSummary (New)'!N$2,Accounts!$F:$F,'AccountSummary (New)'!N$3,Accounts!$W:$W,0,Accounts!$C:$C,"Customer",Accounts!$D:$D,"Prepay")/N74) -> 0 | O76: =IF(O74=0,0,SUMIFS(Accounts!$M:$M,Accounts!$E:$E,'AccountSummary (New)'!O$1,Accounts!$G:$G,'AccountSummary (New)'!O$2,Accounts!$F:$F,'AccountSummary (New)'!O$3,Accounts!$W:$W,0,Accounts!$C:$C,"Customer",Accounts!$D:$D,"Prepay")/O74) -> 0 | P76: =IF(P74=0,0,SUMIFS(Accounts!$M:$M,Accounts!$F:$F,'AccountSummary (New)'!P$3,Accounts!$W:$W,0,Accounts!$C:$C,"Customer",Accounts!$D:$D,"Prepay")/P74) -> 0 | Q76: =IF(Q74=0,0,SUMIFS(Accounts!$M:$M,Accounts!$E:$E,'AccountSummary (New)'!Q$1,Accounts!$G:$G,'AccountSummary (New)'!Q$2,Accounts!$F:$F,'AccountSummary (New)'!Q$3,Accounts!$W:$W,0,Accounts!$C:$C,"Customer",Accounts!$D:$D,"Prepay")/Q74) -> 0 | R76: =IF(R74=0,0,SUMIFS(Accounts!$M:$M,Accounts!$E:$E,'AccountSummary (New)'!R$1,Accounts!$G:$G,'AccountSummary (New)'!R$2,Accounts!$F:$F,'AccountSummary (New)'!R$3,Accounts!$W:$W,0,Accounts!$C:$C,"Customer",Accounts!$D:$D,"Prepay")/R74) -> 0 | S76: =IF(S74=0,0,SUMIFS(Accounts!$M:$M,Accounts!$E:$E,'AccountSummary (New)'!S$1,Accounts!$G:$G,'AccountSummary (New)'!S$2,Accounts!$F:$F,'AccountSummary (New)'!S$3,Accounts!$W:$W,0,Accounts!$C:$C,"Customer",Accounts!$D:$D,"Prepay")/S74) -> 0 | T76: =IF(T74=0,0,SUMIFS(Accounts!$M:$M,Accounts!$E:$E,'AccountSummary (New)'!T$1,Accounts!$G:$G,'AccountSummary (New)'!T$2,Accounts!$F:$F,'AccountSummary (New)'!T$3,Accounts!$W:$W,0,Accounts!$C:$C,"Customer",Accounts!$D:$D,"Prepay")/T74) -> 0 | U76: =IF(U74=0,0,SUMIFS(Accounts!$M:$M,Accounts!$E:$E,'AccountSummary (New)'!U$1,Accounts!$G:$G,'AccountSummary (New)'!U$2,Accounts!$F:$F,'AccountSummary (New)'!U$3,Accounts!$W:$W,0,Accounts!$C:$C,"Customer",Accounts!$D:$D,"Prepay")/U74) -> 0 | V76: =IF(V74=0,0,SUMIFS(Accounts!$M:$M,Accounts!$E:$E,'AccountSummary (New)'!V$1,Accounts!$G:$G,'AccountSummary (New)'!V$2,Accounts!$F:$F,'AccountSummary (New)'!V$3,Accounts!$W:$W,0,Accounts!$C:$C,"Customer",Accounts!$D:$D,"Prepay")/V74) -> 0 | W76: =IF(W74=0,0,SUMIFS(Accounts!$M:$M,Accounts!$F:$F,'AccountSummary (New)'!W$3,Accounts!$W:$W,0,Accounts!$C:$C,"Customer",Accounts!$D:$D,"Prepay")/W74) -> 0
A77: ARPC Prepay | B77: =IF(B74=0,0,B78/B74) -> 0 | C77: =IF(C74=0,0,C78/C74) -> 0 | D77: =IF(D74=0,0,D78/D74) -> 0 | E77: =IF(E74=0,0,E78/E74) -> 0 | F77: =IF(F74=0,0,F78/F74) -> 0 | G77: =IF(G74=0,0,G78/G74) -> 0 | H77: =IF(H74=0,0,H78/H74) -> 0 | I77: =IF(I74=0,0,I78/I74) -> 0 | ... W77: =IF(W74=0,0,W78/W74) -> 0
A78: SaaS from Retained Prepay Customers | B78: =I78+P78+W78 -> 0 | C78: =SUMIFS(Accounts!$I:$I,Accounts!$E:$E,'AccountSummary (New)'!C$1,Accounts!$G:$G,'AccountSummary (New)'!C$2,Accounts!$F:$F,'AccountSummary (New)'!C$3,Accounts!$W:$W,0,Accounts!$C:$C,"Customer",Accounts!$D:$D,"Prepay") -> 0 | D78: =SUMIFS(Accounts!$I:$I,Accounts!$E:$E,'AccountSummary (New)'!D$1,Accounts!$G:$G,'AccountSummary (New)'!D$2,Accounts!$F:$F,'AccountSummary (New)'!D$3,Accounts!$W:$W,0,Accounts!$C:$C,"Customer",Accounts!$D:$D,"Prepay") -> 0 | E78: =SUMIFS(Accounts!$I:$I,Accounts!$E:$E,'AccountSummary (New)'!E$1,Accounts!$G:$G,'AccountSummary (New)'!E$2,Accounts!$F:$F,'AccountSummary (New)'!E$3,Accounts!$W:$W,0,Accounts!$C:$C,"Customer",Accounts!$D:$D,"Prepay") -> 0 | F78: =SUMIFS(Accounts!$I:$I,Accounts!$E:$E,'AccountSummary (New)'!F$1,Accounts!$G:$G,'AccountSummary (New)'!F$2,Accounts!$F:$F,'AccountSummary (New)'!F$3,Accounts!$W:$W,0,Accounts!$C:$C,"Customer",Accounts!$D:$D,"Prepay") -> 0 | G78: =SUMIFS(Accounts!$I:$I,Accounts!$E:$E,'AccountSummary (New)'!G$1,Accounts!$G:$G,'AccountSummary (New)'!G$2,Accounts!$F:$F,'AccountSummary (New)'!G$3,Accounts!$W:$W,0,Accounts!$C:$C,"Customer",Accounts!$D:$D,"Prepay") -> 0 | H78: =SUMIFS(Accounts!$I:$I,Accounts!$E:$E,'AccountSummary (New)'!H$1,Accounts!$G:$G,'AccountSummary (New)'!H$2,Accounts!$F:$F,'AccountSummary (New)'!H$3,Accounts!$W:$W,0,Accounts!$C:$C,"Customer",Accounts!$D:$D,"Prepay") -> 0 | I78: =SUM(C78:H78) -> 0 | J78: =SUMIFS(Accounts!$I:$I,Accounts!$E:$E,'AccountSummary (New)'!J$1,Accounts!$G:$G,'AccountSummary (New)'!J$2,Accounts!$F:$F,'AccountSummary (New)'!J$3,Accounts!$W:$W,0,Accounts!$C:$C,"Customer",Accounts!$D:$D,"Prepay") -> 0 | K78: =SUMIFS(Accounts!$I:$I,Accounts!$E:$E,'AccountSummary (New)'!K$1,Accounts!$G:$G,'AccountSummary (New)'!K$2,Accounts!$F:$F,'AccountSummary (New)'!K$3,Accounts!$W:$W,0,Accounts!$C:$C,"Customer",Accounts!$D:$D,"Prepay") -> 0 | L78: =SUMIFS(Accounts!$I:$I,Accounts!$E:$E,'AccountSummary (New)'!L$1,Accounts!$G:$G,'AccountSummary (New)'!L$2,Accounts!$F:$F,'AccountSummary (New)'!L$3,Accounts!$W:$W,0,Accounts!$C:$C,"Customer",Accounts!$D:$D,"Prepay") -> 0 | M78: =SUMIFS(Accounts!$I:$I,Accounts!$E:$E,'AccountSummary (New)'!M$1,Accounts!$G:$G,'AccountSummary (New)'!M$2,Accounts!$F:$F,'AccountSummary (New)'!M$3,Accounts!$W:$W,0,Accounts!$C:$C,"Customer",Accounts!$D:$D,"Prepay") -> 0 | N78: =SUMIFS(Accounts!$I:$I,Accounts!$E:$E,'AccountSummary (New)'!N$1,Accounts!$G:$G,'AccountSummary (New)'!N$2,Accounts!$F:$F,'AccountSummary (New)'!N$3,Accounts!$W:$W,0,Accounts!$C:$C,"Customer",Accounts!$D:$D,"Prepay") -> 0 | O78: =SUMIFS(Accounts!$I:$I,Accounts!$E:$E,'AccountSummary (New)'!O$1,Accounts!$G:$G,'AccountSummary (New)'!O$2,Accounts!$F:$F,'AccountSummary (New)'!O$3,Accounts!$W:$W,0,Accounts!$C:$C,"Customer",Accounts!$D:$D,"Prepay") -> 0 | P78: =SUM(J78:O78) -> 0 | Q78: =SUMIFS(Accounts!$I:$I,Accounts!$E:$E,'AccountSummary (New)'!Q$1,Accounts!$G:$G,'AccountSummary (New)'!Q$2,Accounts!$F:$F,'AccountSummary (New)'!Q$3,Accounts!$W:$W,0,Accounts!$C:$C,"Customer",Accounts!$D:$D,"Prepay") -> 0 | R78: =SUMIFS(Accounts!$I:$I,Accounts!$E:$E,'AccountSummary (New)'!R$1,Accounts!$G:$G,'AccountSummary (New)'!R$2,Accounts!$F:$F,'AccountSummary (New)'!R$3,Accounts!$W:$W,0,Accounts!$C:$C,"Customer",Accounts!$D:$D,"Prepay") -> 0 | S78: =SUMIFS(Accounts!$I:$I,Accounts!$E:$E,'AccountSummary (New)'!S$1,Accounts!$G:$G,'AccountSummary (New)'!S$2,Accounts!$F:$F,'AccountSummary (New)'!S$3,Accounts!$W:$W,0,Accounts!$C:$C,"Customer",Accounts!$D:$D,"Prepay") -> 0 | T78: =SUMIFS(Accounts!$I:$I,Accounts!$E:$E,'AccountSummary (New)'!T$1,Accounts!$G:$G,'AccountSummary (New)'!T$2,Accounts!$F:$F,'AccountSummary (New)'!T$3,Accounts!$W:$W,0,Accounts!$C:$C,"Customer",Accounts!$D:$D,"Prepay") -> 0 | U78: =SUMIFS(Accounts!$I:$I,Accounts!$E:$E,'AccountSummary (New)'!U$1,Accounts!$G:$G,'AccountSummary (New)'!U$2,Accounts!$F:$F,'AccountSummary (New)'!U$3,Accounts!$W:$W,0,Accounts!$C:$C,"Customer",Accounts!$D:$D,"Prepay") -> 0 | V78: =SUMIFS(Accounts!$I:$I,Accounts!$E:$E,'AccountSummary (New)'!V$1,Accounts!$G:$G,'AccountSummary (New)'!V$2,Accounts!$F:$F,'AccountSummary (New)'!V$3,Accounts!$W:$W,0,Accounts!$C:$C,"Customer",Accounts!$D:$D,"Prepay") -> 0 | W78: =SUM(Q78:V78) -> 0
A79: SaaS from Retained Prepay % of Total | B79: =B78/B68 -> #DIV/0! | C79: =C78/C68 -> #DIV/0! | D79: =D78/D68 -> #DIV/0! | E79: =E78/E68 -> #DIV/0! | F79: =F78/F68 -> #DIV/0! | G79: =G78/G68 -> #DIV/0! | H79: =H78/H68 -> #DIV/0! | I79: =I78/I68 -> #DIV/0! | ... W79: =W78/W68 -> #DIV/0!
A81: Total Paying Customers Lost | B81: =I81+P81+W81 -> 0 | C81: =COUNTIFS(Accounts!$E:$E,'AccountSummary (New)'!C$1,Accounts!$G:$G,'AccountSummary (New)'!C$2,Accounts!$F:$F,'AccountSummary (New)'!C$3,Accounts!$C:$C,"Lost",Accounts!$BG:$BG,FALSE) -> 0 | D81: =COUNTIFS(Accounts!$E:$E,'AccountSummary (New)'!D$1,Accounts!$G:$G,'AccountSummary (New)'!D$2,Accounts!$F:$F,'AccountSummary (New)'!D$3,Accounts!$C:$C,"Lost",Accounts!$BG:$BG,FALSE) -> 0 | E81: =COUNTIFS(Accounts!$E:$E,'AccountSummary (New)'!E$1,Accounts!$G:$G,'AccountSummary (New)'!E$2,Accounts!$F:$F,'AccountSummary (New)'!E$3,Accounts!$C:$C,"Lost",Accounts!$BG:$BG,FALSE) -> 0 | F81: =COUNTIFS(Accounts!$E:$E,'AccountSummary (New)'!F$1,Accounts!$G:$G,'AccountSummary (New)'!F$2,Accounts!$F:$F,'AccountSummary (New)'!F$3,Accounts!$C:$C,"Lost",Accounts!$BG:$BG,FALSE) -> 0 | G81: =COUNTIFS(Accounts!$E:$E,'AccountSummary (New)'!G$1,Accounts!$G:$G,'AccountSummary (New)'!G$2,Accounts!$F:$F,'AccountSummary (New)'!G$3,Accounts!$C:$C,"Lost",Accounts!$BG:$BG,FALSE) -> 0 | H81: =COUNTIFS(Accounts!$E:$E,'AccountSummary (New)'!H$1,Accounts!$G:$G,'AccountSummary (New)'!H$2,Accounts!$F:$F,'AccountSummary (New)'!H$3,Accounts!$C:$C,"Lost",Accounts!$BG:$BG,FALSE) -> 0 | I81: =SUM(C81:H81) -> 0 | J81: =COUNTIFS(Accounts!$E:$E,'AccountSummary (New)'!J$1,Accounts!$G:$G,'AccountSummary (New)'!J$2,Accounts!$F:$F,'AccountSummary (New)'!J$3,Accounts!$C:$C,"Lost",Accounts!$BG:$BG,FALSE) -> 0 | K81: =COUNTIFS(Accounts!$E:$E,'AccountSummary (New)'!K$1,Accounts!$G:$G,'AccountSummary (New)'!K$2,Accounts!$F:$F,'AccountSummary (New)'!K$3,Accounts!$C:$C,"Lost",Accounts!$BG:$BG,FALSE) -> 0 | L81: =COUNTIFS(Accounts!$E:$E,'AccountSummary (New)'!L$1,Accounts!$G:$G,'AccountSummary (New)'!L$2,Accounts!$F:$F,'AccountSummary (New)'!L$3,Accounts!$C:$C,"Lost",Accounts!$BG:$BG,FALSE) -> 0 | M81: =COUNTIFS(Accounts!$E:$E,'AccountSummary (New)'!M$1,Accounts!$G:$G,'AccountSummary (New)'!M$2,Accounts!$F:$F,'AccountSummary (New)'!M$3,Accounts!$C:$C,"Lost",Accounts!$BG:$BG,FALSE) -> 0 | N81: =COUNTIFS(Accounts!$E:$E,'AccountSummary (New)'!N$1,Accounts!$G:$G,'AccountSummary (New)'!N$2,Accounts!$F:$F,'AccountSummary (New)'!N$3,Accounts!$C:$C,"Lost",Accounts!$BG:$BG,FALSE) -> 0 | O81: =COUNTIFS(Accounts!$E:$E,'AccountSummary (New)'!O$1,Accounts!$G:$G,'AccountSummary (New)'!O$2,Accounts!$F:$F,'AccountSummary (New)'!O$3,Accounts!$C:$C,"Lost",Accounts!$BG:$BG,FALSE) -> 0 | P81: =SUM(J81:O81) -> 0 | Q81: =COUNTIFS(Accounts!$E:$E,'AccountSummary (New)'!Q$1,Accounts!$G:$G,'AccountSummary (New)'!Q$2,Accounts!$F:$F,'AccountSummary (New)'!Q$3,Accounts!$C:$C,"Lost",Accounts!$BG:$BG,FALSE) -> 0 | R81: =COUNTIFS(Accounts!$E:$E,'AccountSummary (New)'!R$1,Accounts!$G:$G,'AccountSummary (New)'!R$2,Accounts!$F:$F,'AccountSummary (New)'!R$3,Accounts!$C:$C,"Lost",Accounts!$BG:$BG,FALSE) -> 0 | S81: =COUNTIFS(Accounts!$E:$E,'AccountSummary (New)'!S$1,Accounts!$G:$G,'AccountSummary (New)'!S$2,Accounts!$F:$F,'AccountSummary (New)'!S$3,Accounts!$C:$C,"Lost",Accounts!$BG:$BG,FALSE) -> 0 | T81: =COUNTIFS(Accounts!$E:$E,'AccountSummary (New)'!T$1,Accounts!$G:$G,'AccountSummary (New)'!T$2,Accounts!$F:$F,'AccountSummary (New)'!T$3,Accounts!$C:$C,"Lost",Accounts!$BG:$BG,FALSE) -> 0 | U81: =COUNTIFS(Accounts!$E:$E,'AccountSummary (New)'!U$1,Accounts!$G:$G,'AccountSummary (New)'!U$2,Accounts!$F:$F,'AccountSummary (New)'!U$3,Accounts!$C:$C,"Lost",Accounts!$BG:$BG,FALSE) -> 0 | V81: =COUNTIFS(Accounts!$E:$E,'AccountSummary (New)'!V$1,Accounts!$G:$G,'AccountSummary (New)'!V$2,Accounts!$F:$F,'AccountSummary (New)'!V$3,Accounts!$C:$C,"Lost",Accounts!$BG:$BG,FALSE) -> 0 | W81: =SUM(Q81:V81) -> 0
A82: Lost who paid % | B82: =IF(B81=0,0,B83/B81) -> 0 | C82: =IF(C81=0,0,C83/C81) -> 0 | D82: =IF(D81=0,0,D83/D81) -> 0 | E82: =IF(E81=0,0,E83/E81) -> 0 | F82: =IF(F81=0,0,F83/F81) -> 0 | G82: =IF(G81=0,0,G83/G81) -> 0 | H82: =IF(H81=0,0,H83/H81) -> 0 | I82: =IF(I81=0,0,I83/I81) -> 0 | ... W82: =IF(W81=0,0,W83/W81) -> 0
A83: Lost who paid Count | B83: =I83+P83+W83 -> 0 | C83: =COUNTIFS(Accounts!$E:$E,'AccountSummary (New)'!C$1,Accounts!$G:$G,'AccountSummary (New)'!C$2,Accounts!$F:$F,'AccountSummary (New)'!C$3,Accounts!$B:$B,"Customer",Accounts!$C:$C,"Lost",Accounts!$I:$I,">"&0) -> 0 | D83: =COUNTIFS(Accounts!$E:$E,'AccountSummary (New)'!D$1,Accounts!$G:$G,'AccountSummary (New)'!D$2,Accounts!$F:$F,'AccountSummary (New)'!D$3,Accounts!$B:$B,"Customer",Accounts!$C:$C,"Lost",Accounts!$I:$I,">"&0) -> 0 | E83: =COUNTIFS(Accounts!$E:$E,'AccountSummary (New)'!E$1,Accounts!$G:$G,'AccountSummary (New)'!E$2,Accounts!$F:$F,'AccountSummary (New)'!E$3,Accounts!$B:$B,"Customer",Accounts!$C:$C,"Lost",Accounts!$I:$I,">"&0) -> 0 | F83: =COUNTIFS(Accounts!$E:$E,'AccountSummary (New)'!F$1,Accounts!$G:$G,'AccountSummary (New)'!F$2,Accounts!$F:$F,'AccountSummary (New)'!F$3,Accounts!$B:$B,"Customer",Accounts!$C:$C,"Lost",Accounts!$I:$I,">"&0) -> 0 | G83: =COUNTIFS(Accounts!$E:$E,'AccountSummary (New)'!G$1,Accounts!$G:$G,'AccountSummary (New)'!G$2,Accounts!$F:$F,'AccountSummary (New)'!G$3,Accounts!$B:$B,"Customer",Accounts!$C:$C,"Lost",Accounts!$I:$I,">"&0) -> 0 | H83: =COUNTIFS(Accounts!$E:$E,'AccountSummary (New)'!H$1,Accounts!$G:$G,'AccountSummary (New)'!H$2,Accounts!$F:$F,'AccountSummary (New)'!H$3,Accounts!$B:$B,"Customer",Accounts!$C:$C,"Lost",Accounts!$I:$I,">"&0) -> 0 | I83: =SUM(C83:H83) -> 0 | J83: =COUNTIFS(Accounts!$E:$E,'AccountSummary (New)'!J$1,Accounts!$G:$G,'AccountSummary (New)'!J$2,Accounts!$F:$F,'AccountSummary (New)'!J$3,Accounts!$B:$B,"Customer",Accounts!$C:$C,"Lost",Accounts!$I:$I,">"&0) -> 0 | K83: =COUNTIFS(Accounts!$E:$E,'AccountSummary (New)'!K$1,Accounts!$G:$G,'AccountSummary (New)'!K$2,Accounts!$F:$F,'AccountSummary (New)'!K$3,Accounts!$B:$B,"Customer",Accounts!$C:$C,"Lost",Accounts!$I:$I,">"&0) -> 0 | L83: =COUNTIFS(Accounts!$E:$E,'AccountSummary (New)'!L$1,Accounts!$G:$G,'AccountSummary (New)'!L$2,Accounts!$F:$F,'AccountSummary (New)'!L$3,Accounts!$B:$B,"Customer",Accounts!$C:$C,"Lost",Accounts!$I:$I,">"&0) -> 0 | M83: =COUNTIFS(Accounts!$E:$E,'AccountSummary (New)'!M$1,Accounts!$G:$G,'AccountSummary (New)'!M$2,Accounts!$F:$F,'AccountSummary (New)'!M$3,Accounts!$B:$B,"Customer",Accounts!$C:$C,"Lost",Accounts!$I:$I,">"&0) -> 0 | N83: =COUNTIFS(Accounts!$E:$E,'AccountSummary (New)'!N$1,Accounts!$G:$G,'AccountSummary (New)'!N$2,Accounts!$F:$F,'AccountSummary (New)'!N$3,Accounts!$B:$B,"Customer",Accounts!$C:$C,"Lost",Accounts!$I:$I,">"&0) -> 0 | O83: =COUNTIFS(Accounts!$E:$E,'AccountSummary (New)'!O$1,Accounts!$G:$G,'AccountSummary (New)'!O$2,Accounts!$F:$F,'AccountSummary (New)'!O$3,Accounts!$B:$B,"Customer",Accounts!$C:$C,"Lost",Accounts!$I:$I,">"&0) -> 0 | P83: =SUM(J83:O83) -> 0 | Q83: =COUNTIFS(Accounts!$E:$E,'AccountSummary (New)'!Q$1,Accounts!$G:$G,'AccountSummary (New)'!Q$2,Accounts!$F:$F,'AccountSummary (New)'!Q$3,Accounts!$B:$B,"Customer",Accounts!$C:$C,"Lost",Accounts!$I:$I,">"&0) -> 0 | R83: =COUNTIFS(Accounts!$E:$E,'AccountSummary (New)'!R$1,Accounts!$G:$G,'AccountSummary (New)'!R$2,Accounts!$F:$F,'AccountSummary (New)'!R$3,Accounts!$B:$B,"Customer",Accounts!$C:$C,"Lost",Accounts!$I:$I,">"&0) -> 0 | S83: =COUNTIFS(Accounts!$E:$E,'AccountSummary (New)'!S$1,Accounts!$G:$G,'AccountSummary (New)'!S$2,Accounts!$F:$F,'AccountSummary (New)'!S$3,Accounts!$B:$B,"Customer",Accounts!$C:$C,"Lost",Accounts!$I:$I,">"&0) -> 0 | T83: =COUNTIFS(Accounts!$E:$E,'AccountSummary (New)'!T$1,Accounts!$G:$G,'AccountSummary (New)'!T$2,Accounts!$F:$F,'AccountSummary (New)'!T$3,Accounts!$B:$B,"Customer",Accounts!$C:$C,"Lost",Accounts!$I:$I,">"&0) -> 0 | U83: =COUNTIFS(Accounts!$E:$E,'AccountSummary (New)'!U$1,Accounts!$G:$G,'AccountSummary (New)'!U$2,Accounts!$F:$F,'AccountSummary (New)'!U$3,Accounts!$B:$B,"Customer",Accounts!$C:$C,"Lost",Accounts!$I:$I,">"&0) -> 0 | V83: =COUNTIFS(Accounts!$E:$E,'AccountSummary (New)'!V$1,Accounts!$G:$G,'AccountSummary (New)'!V$2,Accounts!$F:$F,'AccountSummary (New)'!V$3,Accounts!$B:$B,"Customer",Accounts!$C:$C,"Lost",Accounts!$I:$I,">"&0) -> 0 | W83: =SUM(Q83:V83) -> 0
A84: ARPC lost who paid | B84: =IF(B83=0,0,B85/B83) -> 0 | C84: =IF(C81=0,0,C85/C81) -> 0 | D84: =IF(D81=0,0,D85/D81) -> 0 | E84: =IF(E81=0,0,E85/E81) -> 0 | F84: =IF(F81=0,0,F85/F81) -> 0 | G84: =IF(G81=0,0,G85/G81) -> 0 | H84: =IF(H81=0,0,H85/H81) -> 0 | I84: =IF(I83=0,0,I85/I83) -> 0 | J84: =IF(J81=0,0,J85/J81) -> 0 | K84: =IF(K81=0,0,K85/K81) -> 0 | L84: =IF(L81=0,0,L85/L81) -> 0 | M84: =IF(M81=0,0,M85/M81) -> 0 | N84: =IF(N81=0,0,N85/N81) -> 0 | O84: =IF(O81=0,0,O85/O81) -> 0 | P84: =IF(P83=0,0,P85/P83) -> 0 | Q84: =IF(Q81=0,0,Q85/Q81) -> 0 | R84: =IF(R81=0,0,R85/R81) -> 0 | S84: =IF(S81=0,0,S85/S81) -> 0 | T84: =IF(T81=0,0,T85/T81) -> 0 | U84: =IF(U81=0,0,U85/U81) -> 0 | V84: =IF(V81=0,0,V85/V81) -> 0 | W84: =IF(W83=0,0,W85/W83) -> 0
A85: SaaS from Lost Customers | B85: =I85+P85+W85 -> 0 | C85: =SUMIFS(Accounts!$I:$I,Accounts!$E:$E,'AccountSummary (New)'!C$1,Accounts!$G:$G,'AccountSummary (New)'!C$2,Accounts!$F:$F,'AccountSummary (New)'!C$3,Accounts!$W:$W,0,Accounts!$C:$C,"Lost") -> 0 | D85: =SUMIFS(Accounts!$I:$I,Accounts!$E:$E,'AccountSummary (New)'!D$1,Accounts!$G:$G,'AccountSummary (New)'!D$2,Accounts!$F:$F,'AccountSummary (New)'!D$3,Accounts!$W:$W,0,Accounts!$C:$C,"Lost") -> 0 | E85: =SUMIFS(Accounts!$I:$I,Accounts!$E:$E,'AccountSummary (New)'!E$1,Accounts!$G:$G,'AccountSummary (New)'!E$2,Accounts!$F:$F,'AccountSummary (New)'!E$3,Accounts!$W:$W,0,Accounts!$C:$C,"Lost") -> 0 | F85: =SUMIFS(Accounts!$I:$I,Accounts!$E:$E,'AccountSummary (New)'!F$1,Accounts!$G:$G,'AccountSummary (New)'!F$2,Accounts!$F:$F,'AccountSummary (New)'!F$3,Accounts!$W:$W,0,Accounts!$C:$C,"Lost") -> 0 | G85: =SUMIFS(Accounts!$I:$I,Accounts!$E:$E,'AccountSummary (New)'!G$1,Accounts!$G:$G,'AccountSummary (New)'!G$2,Accounts!$F:$F,'AccountSummary (New)'!G$3,Accounts!$W:$W,0,Accounts!$C:$C,"Lost") -> 0 | H85: =SUMIFS(Accounts!$I:$I,Accounts!$E:$E,'AccountSummary (New)'!H$1,Accounts!$G:$G,'AccountSummary (New)'!H$2,Accounts!$F:$F,'AccountSummary (New)'!H$3,Accounts!$W:$W,0,Accounts!$C:$C,"Lost") -> 0 | I85: =SUM(C85:H85) -> 0 | J85: =SUMIFS(Accounts!$I:$I,Accounts!$E:$E,'AccountSummary (New)'!J$1,Accounts!$G:$G,'AccountSummary (New)'!J$2,Accounts!$F:$F,'AccountSummary (New)'!J$3,Accounts!$W:$W,0,Accounts!$C:$C,"Lost") -> 0 | K85: =SUMIFS(Accounts!$I:$I,Accounts!$E:$E,'AccountSummary (New)'!K$1,Accounts!$G:$G,'AccountSummary (New)'!K$2,Accounts!$F:$F,'AccountSummary (New)'!K$3,Accounts!$W:$W,0,Accounts!$C:$C,"Lost") -> 0 | L85: =SUMIFS(Accounts!$I:$I,Accounts!$E:$E,'AccountSummary (New)'!L$1,Accounts!$G:$G,'AccountSummary (New)'!L$2,Accounts!$F:$F,'AccountSummary (New)'!L$3,Accounts!$W:$W,0,Accounts!$C:$C,"Lost") -> 0 | M85: =SUMIFS(Accounts!$I:$I,Accounts!$E:$E,'AccountSummary (New)'!M$1,Accounts!$G:$G,'AccountSummary (New)'!M$2,Accounts!$F:$F,'AccountSummary (New)'!M$3,Accounts!$W:$W,0,Accounts!$C:$C,"Lost") -> 0 | N85: =SUMIFS(Accounts!$I:$I,Accounts!$E:$E,'AccountSummary (New)'!N$1,Accounts!$G:$G,'AccountSummary (New)'!N$2,Accounts!$F:$F,'AccountSummary (New)'!N$3,Accounts!$W:$W,0,Accounts!$C:$C,"Lost") -> 0 | O85: =SUMIFS(Accounts!$I:$I,Accounts!$E:$E,'AccountSummary (New)'!O$1,Accounts!$G:$G,'AccountSummary (New)'!O$2,Accounts!$F:$F,'AccountSummary (New)'!O$3,Accounts!$W:$W,0,Accounts!$C:$C,"Lost") -> 0 | P85: =SUM(J85:O85) -> 0 | Q85: =SUMIFS(Accounts!$I:$I,Accounts!$E:$E,'AccountSummary (New)'!Q$1,Accounts!$G:$G,'AccountSummary (New)'!Q$2,Accounts!$F:$F,'AccountSummary (New)'!Q$3,Accounts!$W:$W,0,Accounts!$C:$C,"Lost") -> 0 | R85: =SUMIFS(Accounts!$I:$I,Accounts!$E:$E,'AccountSummary (New)'!R$1,Accounts!$G:$G,'AccountSummary (New)'!R$2,Accounts!$F:$F,'AccountSummary (New)'!R$3,Accounts!$W:$W,0,Accounts!$C:$C,"Lost") -> 0 | S85: =SUMIFS(Accounts!$I:$I,Accounts!$E:$E,'AccountSummary (New)'!S$1,Accounts!$G:$G,'AccountSummary (New)'!S$2,Accounts!$F:$F,'AccountSummary (New)'!S$3,Accounts!$W:$W,0,Accounts!$C:$C,"Lost") -> 0 | T85: =SUMIFS(Accounts!$I:$I,Accounts!$E:$E,'AccountSummary (New)'!T$1,Accounts!$G:$G,'AccountSummary (New)'!T$2,Accounts!$F:$F,'AccountSummary (New)'!T$3,Accounts!$W:$W,0,Accounts!$C:$C,"Lost") -> 0 | U85: =SUMIFS(Accounts!$I:$I,Accounts!$E:$E,'AccountSummary (New)'!U$1,Accounts!$G:$G,'AccountSummary (New)'!U$2,Accounts!$F:$F,'AccountSummary (New)'!U$3,Accounts!$W:$W,0,Accounts!$C:$C,"Lost") -> 0 | V85: =SUMIFS(Accounts!$I:$I,Accounts!$E:$E,'AccountSummary (New)'!V$1,Accounts!$G:$G,'AccountSummary (New)'!V$2,Accounts!$F:$F,'AccountSummary (New)'!V$3,Accounts!$W:$W,0,Accounts!$C:$C,"Lost") -> 0 | W85: =SUM(Q85:V85) -> 0
A87: SaaS from Trialers | B87: =I87+P87+W87 -> 0 | C87: =C11 -> 0 | D87: =D11 -> 0 | E87: =E11 -> 0 | F87: =F11 -> 0 | G87: =G11 -> 0 | H87: =H11 -> 0 | I87: =SUM(C87:H87) -> 0 | J87: =J11 -> 0 | K87: =K11 -> 0 | L87: =L11 -> 0 | M87: =M11 -> 0 | N87: =N11 -> 0 | O87: =O11 -> 0 | P87: =SUM(J87:O87) -> 0 | Q87: =Q11 -> 0 | R87: =R11 -> 0 | S87: =S11 -> 0 | T87: =T11 -> 0 | U87: =U11 -> 0 | V87: =V11 -> 0 | W87: =SUM(Q87:V87) -> 0
A88: SaaS from Retained Customers | B88: =I88+P88+W88 -> 0 | C88: =C68 -> 0 | D88: =D68 -> 0 | E88: =E68 -> 0 | F88: =F68 -> 0 | G88: =G68 -> 0 | H88: =H68 -> 0 | I88: =SUM(C88:H88) -> 0 | J88: =J68 -> 0 | K88: =K68 -> 0 | L88: =L68 -> 0 | M88: =M68 -> 0 | N88: =N68 -> 0 | O88: =O68 -> 0 | P88: =SUM(J88:O88) -> 0 | Q88: =Q68 -> 0 | R88: =R68 -> 0 | S88: =S68 -> 0 | T88: =T68 -> 0 | U88: =U68 -> 0 | V88: =V68 -> 0 | W88: =SUM(Q88:V88) -> 0
A89: SaaS from Lost Customers | B89: =I89+P89+W89 -> 0 | C89: =C85 -> 0 | D89: =D85 -> 0 | E89: =E85 -> 0 | F89: =F85 -> 0 | G89: =G85 -> 0 | H89: =H85 -> 0 | I89: =SUM(C89:H89) -> 0 | J89: =J85 -> 0 | K89: =K85 -> 0 | L89: =L85 -> 0 | M89: =M85 -> 0 | N89: =N85 -> 0 | O89: =O85 -> 0 | P89: =SUM(J89:O89) -> 0 | Q89: =Q85 -> 0 | R89: =R85 -> 0 | S89: =S85 -> 0 | T89: =T85 -> 0 | U89: =U85 -> 0 | V89: =V85 -> 0 | W89: =SUM(Q89:V89) -> 0
A91: Total Saas (Gross) | B91: =I91+P91+W91 -> 0 | C91: =C87+C88+C89 -> 0 | D91: =D87+D88+D89 -> 0 | E91: =E87+E88+E89 -> 0 | F91: =F87+F88+F89 -> 0 | G91: =G87+G88+G89 -> 0 | H91: =H87+H88+H89 -> 0 | I91: =SUM(C91:H91) -> 0 | J91: =J87+J88+J89 -> 0 | K91: =K87+K88+K89 -> 0 | L91: =L87+L88+L89 -> 0 | M91: =M87+M88+M89 -> 0 | N91: =N87+N88+N89 -> 0 | O91: =O87+O88+O89 -> 0 | P91: =SUM(J91:O91) -> 0 | Q91: =Q87+Q88+Q89 -> 0 | R91: =R87+R88+R89 -> 0 | S91: =S87+S88+S89 -> 0 | T91: =T87+T88+T89 -> 0 | U91: =U87+U88+U89 -> 0 | V91: =V87+V88+V89 -> 0 | W91: =SUM(Q91:V91) -> 0

Sheet AccountSummary
A1: SyncType | B1: All | C1: QBDT | D1: QBDT | E1: QBO | F1: QBO | G1: Xero | H1: none | I1: All | J1: QBDT | K1: QBDT | L1: QBO | M1: QBO | N1: Xero | O1: none | P1: All | Q1: QBDT | R1: QBDT | S1: QBO | T1: QBO | U1: Xero | V1: none | W1: All
A2: Platform | B2: All | C2: Classic | D2: New | E2: Classic | F2: New | G2: New | H2: New | I2: All | J2: Classic | K2: New | L2: Classic | M2: New | N2: New | O2: New | P2: All | Q2: Classic | R2: New | S2: Classic | T2: New | U2: New | V2: New | W2: All
A3: Channel | B3: All | C3: Referred | D3: Referred | E3: Referred | F3: Referred | G3: Referred | H3: Referred | I3: Referred | J3: Managed | K3: Managed | L3: Managed | M3: Managed | N3: Managed | O3: Managed | P3: Managed | Q3: Direct | R3: Direct | S3: Direct | T3: Direct | U3: Direct | V3: Direct | W3: Direct
A4: *Trialers*
